Workbook

Sheet LABOR PRODUCTIVITY
A1: ACTIVITIES | C1: OUTPUT PER HOUR | I1: MANHOUR EQUIVALENT
I2: ='MANHOUR EQUIVALENT'!F15 -> 58.680556 | J2: =CONCATENATE("per hour in area of ",'MANHOUR EQUIVALENT'!D10) -> per hour in area of CAR
I3: EQUIVALENT LABOR COST
A4: ITEM NO. | B4: WORK DESCRIPTION | C4: 3 WORKER PRODUCTIVITY RATE
C5: SLOW | D5: UNIT | E5: AVERAGE | F5: UNIT | G5: FAST | H5: UNIT | I5: =C5 -> SLOW | J5: PESOS PER | K5: AVERAGE | L5: PESOS PER | M5: =G5 -> FAST | N5: PESOS PER
A7: A. | B7: FORM WORKS INSTALLATION
B8: WALL ON THE GROUND | C8: =IFERROR(1/CALCULATIONS!U8,0) -> 0.25 | D8: =CONCATENATE(CALCULATIONS!T8,CALCULATIONS!X8) -> SQ.M.per hour | E8: =IFERROR(1/CALCULATIONS!V8,0) -> 0.5 | F8: =CONCATENATE(CALCULATIONS!T8,CALCULATIONS!X8) -> SQ.M.per hour | G8: =IFERROR(1/CALCULATIONS!W8,0) -> 0.625 | H8: =CONCATENATE(CALCULATIONS!T8,CALCULATIONS!X8) -> SQ.M.per hour | I8: =CALCULATIONS!U8*$I$2 -> 234.72222 | J8: =CONCATENATE(CALCULATIONS!Y8,CALCULATIONS!T8) -> per SQ.M. | K8: =CALCULATIONS!V8*$I$2 -> 117.36111 | L8: =CONCATENATE(CALCULATIONS!Y8,CALCULATIONS!T8) -> per SQ.M. | M8: =CALCULATIONS!W8*$I$2 -> 93.888889 | N8: =CONCATENATE(CALCULATIONS!Y8,CALCULATIONS!T8) -> per SQ.M.
B9: WALL ABOVER GROUND | C9: =IFERROR(1/CALCULATIONS!U9,0) -> 0.21276596 | D9: =CONCATENATE(CALCULATIONS!T9,CALCULATIONS!X9) -> SQ.M.per hour | E9: =IFERROR(1/CALCULATIONS!V9,0) -> 0.42553191 | F9: =CONCATENATE(CALCULATIONS!T9,CALCULATIONS!X9) -> SQ.M.per hour | G9: =IFERROR(1/CALCULATIONS!W9,0) -> 0.53191489 | H9: =CONCATENATE(CALCULATIONS!T9,CALCULATIONS!X9) -> SQ.M.per hour | I9: =CALCULATIONS!U9*$I$2 -> 275.79861 | J9: =CONCATENATE(CALCULATIONS!Y9,CALCULATIONS!T9) -> per SQ.M. | K9: =CALCULATIONS!V9*$I$2 -> 137.89931 | L9: =CONCATENATE(CALCULATIONS!Y9,CALCULATIONS!T9) -> per SQ.M. | M9: =CALCULATIONS!W9*$I$2 -> 110.31944 | N9: =CONCATENATE(CALCULATIONS!Y9,CALCULATIONS!T9) -> per SQ.M.
B10: BEAMS | C10: =IFERROR(1/CALCULATIONS!U10,0) -> 0.16233766 | D10: =CONCATENATE(CALCULATIONS!T10,CALCULATIONS!X10) -> SQ.M.per hour | E10: =IFERROR(1/CALCULATIONS!V10,0) -> 0.32467532 | F10: =CONCATENATE(CALCULATIONS!T10,CALCULATIONS!X10) -> SQ.M.per hour | G10: =IFERROR(1/CALCULATIONS!W10,0) -> 0.40650407 | H10: =CONCATENATE(CALCULATIONS!T10,CALCULATIONS!X10) -> SQ.M.per hour | I10: =CALCULATIONS!U10*$I$2 -> 361.47222 | J10: =CONCATENATE(CALCULATIONS!Y10,CALCULATIONS!T10) -> per SQ.M. | K10: =CALCULATIONS!V10*$I$2 -> 180.73611 | L10: =CONCATENATE(CALCULATIONS!Y10,CALCULATIONS!T10) -> per SQ.M. | M10: =CALCULATIONS!W10*$I$2 -> 144.35417 | N10: =CONCATENATE(CALCULATIONS!Y10,CALCULATIONS!T10) -> per SQ.M.
B11: COLUMN | C11: =IFERROR(1/CALCULATIONS!U11,0) -> 0.21276596 | D11: =CONCATENATE(CALCULATIONS!T11,CALCULATIONS!X11) -> SQ.M.per hour | E11: =IFERROR(1/CALCULATIONS!V11,0) -> 0.42553191 | F11: =CONCATENATE(CALCULATIONS!T11,CALCULATIONS!X11) -> SQ.M.per hour | G11: =IFERROR(1/CALCULATIONS!W11,0) -> 0.53191489 | H11: =CONCATENATE(CALCULATIONS!T11,CALCULATIONS!X11) -> SQ.M.per hour | I11: =CALCULATIONS!U11*$I$2 -> 275.79861 | J11: =CONCATENATE(CALCULATIONS!Y11,CALCULATIONS!T11) -> per SQ.M. | K11: =CALCULATIONS!V11*$I$2 -> 137.89931 | L11: =CONCATENATE(CALCULATIONS!Y11,CALCULATIONS!T11) -> per SQ.M. | M11: =CALCULATIONS!W11*$I$2 -> 110.31944 | N11: =CONCATENATE(CALCULATIONS!Y11,CALCULATIONS!T11) -> per SQ.M.
B12: SUSPENDED SLAB | C12: =IFERROR(1/CALCULATIONS!U12,0) -> 0 | D12: =CONCATENATE(CALCULATIONS!T12,CALCULATIONS!X12) | E12: =IFERROR(1/CALCULATIONS!V12,0) -> 0 | F12: =CONCATENATE(CALCULATIONS!T12,CALCULATIONS!X12) | G12: =IFERROR(1/CALCULATIONS!W12,0) -> 0 | H12: =CONCATENATE(CALCULATIONS!T12,CALCULATIONS!X12) | I12: =CALCULATIONS!U12*$I$2 -> 0 | J12: =CONCATENATE(CALCULATIONS!Y12,CALCULATIONS!T12) | K12: =CALCULATIONS!V12*$I$2 -> 0 | L12: =CONCATENATE(CALCULATIONS!Y12,CALCULATIONS!T12) | M12: =CALCULATIONS!W12*$I$2 -> 0 | N12: =CONCATENATE(CALCULATIONS!Y12,CALCULATIONS!T12)
B13: 0 TO 18' | C13: =IFERROR(1/CALCULATIONS!U13,0) -> 0.2994012 | D13: =CONCATENATE(CALCULATIONS!T13,CALCULATIONS!X13) -> SQ.M.per hour | E13: =IFERROR(1/CALCULATIONS!V13,0) -> 0.5988024 | F13: =CONCATENATE(CALCULATIONS!T13,CALCULATIONS!X13) -> SQ.M.per hour | G13: =IFERROR(1/CALCULATIONS!W13,0) -> 0.74626866 | H13: =CONCATENATE(CALCULATIONS!T13,CALCULATIONS!X13) -> SQ.M.per hour | I13: =CALCULATIONS!U13*$I$2 -> 195.99306 | J13: =CONCATENATE(CALCULATIONS!Y13,CALCULATIONS!T13) -> per SQ.M. | K13: =CALCULATIONS!V13*$I$2 -> 97.996528 | L13: =CONCATENATE(CALCULATIONS!Y13,CALCULATIONS!T13) -> per SQ.M. | M13: =CALCULATIONS!W13*$I$2 -> 78.631944 | N13: =CONCATENATE(CALCULATIONS!Y13,CALCULATIONS!T13) -> per SQ.M.
B14: 18' TO 36' UP | C14: =IFERROR(1/CALCULATIONS!U14,0) -> 0.15015015 | D14: =CONCATENATE(CALCULATIONS!T14,CALCULATIONS!X14) -> SQ.M.per hour | E14: =IFERROR(1/CALCULATIONS!V14,0) -> 0.3003003 | F14: =CONCATENATE(CALCULATIONS!T14,CALCULATIONS!X14) -> SQ.M.per hour | G14: =IFERROR(1/CALCULATIONS!W14,0) -> 0.37593985 | H14: =CONCATENATE(CALCULATIONS!T14,CALCULATIONS!X14) -> SQ.M.per hour | I14: =CALCULATIONS!U14*$I$2 -> 390.8125 | J14: =CONCATENATE(CALCULATIONS!Y14,CALCULATIONS!T14) -> per SQ.M. | K14: =CALCULATIONS!V14*$I$2 -> 195.40625 | L14: =CONCATENATE(CALCULATIONS!Y14,CALCULATIONS!T14) -> per SQ.M. | M14: =CALCULATIONS!W14*$I$2 -> 156.09028 | N14: =CONCATENATE(CALCULATIONS!Y14,CALCULATIONS!T14) -> per SQ.M.
B15: ELEVATED AND SHORED SLAB FORMING | C15: =IFERROR(1/CALCULATIONS!U15,0) -> 0 | D15: =CONCATENATE(CALCULATIONS!T15,CALCULATIONS!X15) | E15: =IFERROR(1/CALCULATIONS!V15,0) -> 0 | F15: =CONCATENATE(CALCULATIONS!T15,CALCULATIONS!X15) | G15: =IFERROR(1/CALCULATIONS!W15,0) -> 0 | H15: =CONCATENATE(CALCULATIONS!T15,CALCULATIONS!X15) | I15: =CALCULATIONS!U15*$I$2 -> 0 | J15: =CONCATENATE(CALCULATIONS!Y15,CALCULATIONS!T15) | K15: =CALCULATIONS!V15*$I$2 -> 0 | L15: =CONCATENATE(CALCULATIONS!Y15,CALCULATIONS!T15) | M15: =CALCULATIONS!W15*$I$2 -> 0 | N15: =CONCATENATE(CALCULATIONS!Y15,CALCULATIONS!T15)
B16: FORMING ONLY | C16: =IFERROR(1/CALCULATIONS!U16,0) -> 0.058139535 | D16: =CONCATENATE(CALCULATIONS!T16,CALCULATIONS!X16) -> SQ.M.per hour | E16: =IFERROR(1/CALCULATIONS!V16,0) -> 0.11111111 | F16: =CONCATENATE(CALCULATIONS!T16,CALCULATIONS!X16) -> SQ.M.per hour | G16: =IFERROR(1/CALCULATIONS!W16,0) -> 0.14534884 | H16: =CONCATENATE(CALCULATIONS!T16,CALCULATIONS!X16) -> SQ.M.per hour | I16: =CALCULATIONS!U16*$I$2 -> 1009.3056 | J16: =CONCATENATE(CALCULATIONS!Y16,CALCULATIONS!T16) -> per SQ.M. | K16: =CALCULATIONS!V16*$I$2 -> 528.125 | L16: =CONCATENATE(CALCULATIONS!Y16,CALCULATIONS!T16) -> per SQ.M. | M16: =CALCULATIONS!W16*$I$2 -> 403.72222 | N16: =CONCATENATE(CALCULATIONS!Y16,CALCULATIONS!T16) -> per SQ.M.
B17: FORMING AND SHORING | C17: =IFERROR(1/CALCULATIONS!U17,0) -> 0.045454545 | D17: =CONCATENATE(CALCULATIONS!T17,CALCULATIONS!X17) -> SQ.M.per hour | E17: =IFERROR(1/CALCULATIONS!V17,0) -> 0.090909091 | F17: =CONCATENATE(CALCULATIONS!T17,CALCULATIONS!X17) -> SQ.M.per hour | G17: =IFERROR(1/CALCULATIONS!W17,0) -> 0.11363636 | H17: =CONCATENATE(CALCULATIONS!T17,CALCULATIONS!X17) -> SQ.M.per hour | I17: =CALCULATIONS!U17*$I$2 -> 1290.9722 | J17: =CONCATENATE(CALCULATIONS!Y17,CALCULATIONS!T17) -> per SQ.M. | K17: =CALCULATIONS!V17*$I$2 -> 645.48611 | L17: =CONCATENATE(CALCULATIONS!Y17,CALCULATIONS!T17) -> per SQ.M. | M17: =CALCULATIONS!W17*$I$2 -> 516.38889 | N17: =CONCATENATE(CALCULATIONS!Y17,CALCULATIONS!T17) -> per SQ.M.
B18: WOOD WALL AND PARTITION | C18: =IFERROR(1/CALCULATIONS!U18,0) -> 1 | D18: =CONCATENATE(CALCULATIONS!T18,CALCULATIONS!X18) -> SQ.M.per hour | E18: =IFERROR(1/CALCULATIONS!V18,0) -> 1.6666667 | F18: =CONCATENATE(CALCULATIONS!T18,CALCULATIONS!X18) -> SQ.M.per hour | G18: =IFERROR(1/CALCULATIONS!W18,0) -> 2.5 | H18: =CONCATENATE(CALCULATIONS!T18,CALCULATIONS!X18) -> SQ.M.per hour | I18: =CALCULATIONS!U18*$I$2 -> 58.680556 | J18: =CONCATENATE(CALCULATIONS!Y18,CALCULATIONS!T18) -> per SQ.M. | K18: =CALCULATIONS!V18*$I$2 -> 35.208333 | L18: =CONCATENATE(CALCULATIONS!Y18,CALCULATIONS!T18) -> per SQ.M. | M18: =CALCULATIONS!W18*$I$2 -> 23.472222 | N18: =CONCATENATE(CALCULATIONS!Y18,CALCULATIONS!T18) -> per SQ.M.
C19: =IFERROR(1/CALCULATIONS!U19,0) -> 0 | D19: =CONCATENATE(CALCULATIONS!T19,CALCULATIONS!X19) | E19: =IFERROR(1/CALCULATIONS!V19,0) -> 0 | F19: =CONCATENATE(CALCULATIONS!T19,CALCULATIONS!X19) | G19: =IFERROR(1/CALCULATIONS!W19,0) -> 0 | H19: =CONCATENATE(CALCULATIONS!T19,CALCULATIONS!X19) | I19: =CALCULATIONS!U19*$I$2 -> 0 | J19: =CONCATENATE(CALCULATIONS!Y19,CALCULATIONS!T19) | K19: =CALCULATIONS!V19*$I$2 -> 0 | L19: =CONCATENATE(CALCULATIONS!Y19,CALCULATIONS!T19) | M19: =CALCULATIONS!W19*$I$2 -> 0 | N19: =CONCATENATE(CALCULATIONS!Y19,CALCULATIONS!T19)
A20: B. | B20: FORMWORKS FABRICATION | C20: =IFERROR(1/CALCULATIONS!U20,0) -> 0.46511628 | D20: =CONCATENATE(CALCULATIONS!T20,CALCULATIONS!X20) -> SQ.M.per hour | E20: =IFERROR(1/CALCULATIONS!V20,0) -> 0.92592593 | F20: =CONCATENATE(CALCULATIONS!T20,CALCULATIONS!X20) -> SQ.M.per hour | G20: =IFERROR(1/CALCULATIONS!W20,0) -> 1.1627907 | H20: =CONCATENATE(CALCULATIONS!T20,CALCULATIONS!X20) -> SQ.M.per hour | I20: =CALCULATIONS!U20*$I$2 -> 126.16319 | J20: =CONCATENATE(CALCULATIONS!Y20,CALCULATIONS!T20) -> per SQ.M. | K20: =CALCULATIONS!V20*$I$2 -> 63.375 | L20: =CONCATENATE(CALCULATIONS!Y20,CALCULATIONS!T20) -> per SQ.M. | M20: =CALCULATIONS!W20*$I$2 -> 50.465278 | N20: =CONCATENATE(CALCULATIONS!Y20,CALCULATIONS!T20) -> per SQ.M.
C21: =IFERROR(1/CALCULATIONS!U21,0) -> 0 | D21: =CONCATENATE(CALCULATIONS!T21,CALCULATIONS!X21) | E21: =IFERROR(1/CALCULATIONS!V21,0) -> 0 | F21: =CONCATENATE(CALCULATIONS!T21,CALCULATIONS!X21) | G21: =IFERROR(1/CALCULATIONS!W21,0) -> 0 | H21: =CONCATENATE(CALCULATIONS!T21,CALCULATIONS!X21) | I21: =CALCULATIONS!U21*$I$2 -> 0 | J21: =CONCATENATE(CALCULATIONS!Y21,CALCULATIONS!T21) | K21: =CALCULATIONS!V21*$I$2 -> 0 | L21: =CONCATENATE(CALCULATIONS!Y21,CALCULATIONS!T21) | M21: =CALCULATIONS!W21*$I$2 -> 0 | N21: =CONCATENATE(CALCULATIONS!Y21,CALCULATIONS!T21)
A22: C. | B22: STRIPPING OF FORMS | C22: =IFERROR(1/CALCULATIONS!U22,0) -> 0 | D22: =CONCATENATE(CALCULATIONS!T22,CALCULATIONS!X22) | E22: =IFERROR(1/CALCULATIONS!V22,0) -> 0 | F22: =CONCATENATE(CALCULATIONS!T22,CALCULATIONS!X22) | G22: =IFERROR(1/CALCULATIONS!W22,0) -> 0 | H22: =CONCATENATE(CALCULATIONS!T22,CALCULATIONS!X22) | I22: =CALCULATIONS!U22*$I$2 -> 0 | J22: =CONCATENATE(CALCULATIONS!Y22,CALCULATIONS!T22) | K22: =CALCULATIONS!V22*$I$2 -> 0 | L22: =CONCATENATE(CALCULATIONS!Y22,CALCULATIONS!T22) | M22: =CALCULATIONS!W22*$I$2 -> 0 | N22: =CONCATENATE(CALCULATIONS!Y22,CALCULATIONS!T22)
B23: WALL ON GROUND | C23: =IFERROR(1/CALCULATIONS!U23,0) -> 2 | D23: =CONCATENATE(CALCULATIONS!T23,CALCULATIONS!X23) -> SQ.M.per hour | E23: =IFERROR(1/CALCULATIONS!V23,0) -> 4 | F23: =CONCATENATE(CALCULATIONS!T23,CALCULATIONS!X23) -> SQ.M.per hour | G23: =IFERROR(1/CALCULATIONS!W23,0) -> 5 | H23: =CONCATENATE(CALCULATIONS!T23,CALCULATIONS!X23) -> SQ.M.per hour | I23: =CALCULATIONS!U23*$I$2 -> 29.340278 | J23: =CONCATENATE(CALCULATIONS!Y23,CALCULATIONS!T23) -> per SQ.M. | K23: =CALCULATIONS!V23*$I$2 -> 14.670139 | L23: =CONCATENATE(CALCULATIONS!Y23,CALCULATIONS!T23) -> per SQ.M. | M23: =CALCULATIONS!W23*$I$2 -> 11.736111 | N23: =CONCATENATE(CALCULATIONS!Y23,CALCULATIONS!T23) -> per SQ.M.
B24: WALL ABOVE 10' | C24: =IFERROR(1/CALCULATIONS!U24,0) -> 0.3875969 | D24: =CONCATENATE(CALCULATIONS!T24,CALCULATIONS!X24) -> SQ.M.per hour | E24: =IFERROR(1/CALCULATIONS!V24,0) -> 0.7751938 | F24: =CONCATENATE(CALCULATIONS!T24,CALCULATIONS!X24) -> SQ.M.per hour | G24: =IFERROR(1/CALCULATIONS!W24,0) -> 0.97087379 | H24: =CONCATENATE(CALCULATIONS!T24,CALCULATIONS!X24) -> SQ.M.per hour | I24: =CALCULATIONS!U24*$I$2 -> 151.39583 | J24: =CONCATENATE(CALCULATIONS!Y24,CALCULATIONS!T24) -> per SQ.M. | K24: =CALCULATIONS!V24*$I$2 -> 75.697917 | L24: =CONCATENATE(CALCULATIONS!Y24,CALCULATIONS!T24) -> per SQ.M. | M24: =CALCULATIONS!W24*$I$2 -> 60.440972 | N24: =CONCATENATE(CALCULATIONS!Y24,CALCULATIONS!T24) -> per SQ.M.
B25: BEAMS | C25: =IFERROR(1/CALCULATIONS!U25,0) -> 0.48543689 | D25: =CONCATENATE(CALCULATIONS!T25,CALCULATIONS!X25) -> SQ.M.per hour | E25: =IFERROR(1/CALCULATIONS!V25,0) -> 0.97087379 | F25: =CONCATENATE(CALCULATIONS!T25,CALCULATIONS!X25) -> SQ.M.per hour | G25: =IFERROR(1/CALCULATIONS!W25,0) -> 1.2195122 | H25: =CONCATENATE(CALCULATIONS!T25,CALCULATIONS!X25) -> SQ.M.per hour | I25: =CALCULATIONS!U25*$I$2 -> 120.88194 | J25: =CONCATENATE(CALCULATIONS!Y25,CALCULATIONS!T25) -> per SQ.M. | K25: =CALCULATIONS!V25*$I$2 -> 60.440972 | L25: =CONCATENATE(CALCULATIONS!Y25,CALCULATIONS!T25) -> per SQ.M. | M25: =CALCULATIONS!W25*$I$2 -> 48.118056 | N25: =CONCATENATE(CALCULATIONS!Y25,CALCULATIONS!T25) -> per SQ.M.
B26: COLUMNS | C26: =IFERROR(1/CALCULATIONS!U26,0) -> 0.58823529 | D26: =CONCATENATE(CALCULATIONS!T26,CALCULATIONS!X26) -> SQ.M.per hour | E26: =IFERROR(1/CALCULATIONS!V26,0) -> 1.1764706 | F26: =CONCATENATE(CALCULATIONS!T26,CALCULATIONS!X26) -> SQ.M.per hour | G26: =IFERROR(1/CALCULATIONS!W26,0) -> 1.4705882 | H26: =CONCATENATE(CALCULATIONS!T26,CALCULATIONS!X26) -> SQ.M.per hour | I26: =CALCULATIONS!U26*$I$2 -> 99.756944 | J26: =CONCATENATE(CALCULATIONS!Y26,CALCULATIONS!T26) -> per SQ.M. | K26: =CALCULATIONS!V26*$I$2 -> 49.878472 | L26: =CONCATENATE(CALCULATIONS!Y26,CALCULATIONS!T26) -> per SQ.M. | M26: =CALCULATIONS!W26*$I$2 -> 39.902778 | N26: =CONCATENATE(CALCULATIONS!Y26,CALCULATIONS!T26) -> per SQ.M.
B27: SUSPENDED SLAB | C27: =IFERROR(1/CALCULATIONS!U27,0) -> 0 | D27: =CONCATENATE(CALCULATIONS!T27,CALCULATIONS!X27) -> SQ.M.per hour | E27: =IFERROR(1/CALCULATIONS!V27,0) -> 0 | F27: =CONCATENATE(CALCULATIONS!T27,CALCULATIONS!X27) -> SQ.M.per hour | G27: =IFERROR(1/CALCULATIONS!W27,0) -> 0 | H27: =CONCATENATE(CALCULATIONS!T27,CALCULATIONS!X27) -> SQ.M.per hour | I27: =CALCULATIONS!U27*$I$2 -> 0 | J27: =CONCATENATE(CALCULATIONS!Y27,CALCULATIONS!T27) -> per SQ.M. | K27: =CALCULATIONS!V27*$I$2 -> 0 | L27: =CONCATENATE(CALCULATIONS!Y27,CALCULATIONS!T27) -> per SQ.M. | M27: =CALCULATIONS!W27*$I$2 -> 0 | N27: =CONCATENATE(CALCULATIONS!Y27,CALCULATIONS!T27) -> per SQ.M.
B28: 0 TO 18' | C28: =IFERROR(1/CALCULATIONS!U28,0) -> 0.5988024 | D28: =CONCATENATE(CALCULATIONS!T28,CALCULATIONS!X28) -> SQ.M.per hour | E28: =IFERROR(1/CALCULATIONS!V28,0) -> 1.2048193 | F28: =CONCATENATE(CALCULATIONS!T28,CALCULATIONS!X28) -> SQ.M.per hour | G28: =IFERROR(1/CALCULATIONS!W28,0) -> 1.4925373 | H28: =CONCATENATE(CALCULATIONS!T28,CALCULATIONS!X28) -> SQ.M.per hour | I28: =CALCULATIONS!U28*$I$2 -> 97.996528 | J28: =CONCATENATE(CALCULATIONS!Y28,CALCULATIONS!T28) -> per SQ.M. | K28: =CALCULATIONS!V28*$I$2 -> 48.704861 | L28: =CONCATENATE(CALCULATIONS!Y28,CALCULATIONS!T28) -> per SQ.M. | M28: =CALCULATIONS!W28*$I$2 -> 39.315972 | N28: =CONCATENATE(CALCULATIONS!Y28,CALCULATIONS!T28) -> per SQ.M.
B29: 18' TO 36' UP | C29: =IFERROR(1/CALCULATIONS!U29,0) -> 0.46296296 | D29: =CONCATENATE(CALCULATIONS!T29,CALCULATIONS!X29) -> SQ.M.per hour | E29: =IFERROR(1/CALCULATIONS!V29,0) -> 0.92592593 | F29: =CONCATENATE(CALCULATIONS!T29,CALCULATIONS!X29) -> SQ.M.per hour | G29: =IFERROR(1/CALCULATIONS!W29,0) -> 1.1627907 | H29: =CONCATENATE(CALCULATIONS!T29,CALCULATIONS!X29) -> SQ.M.per hour | I29: =CALCULATIONS!U29*$I$2 -> 126.75 | J29: =CONCATENATE(CALCULATIONS!Y29,CALCULATIONS!T29) -> per SQ.M. | K29: =CALCULATIONS!V29*$I$2 -> 63.375 | L29: =CONCATENATE(CALCULATIONS!Y29,CALCULATIONS!T29) -> per SQ.M. | M29: =CALCULATIONS!W29*$I$2 -> 50.465278 | N29: =CONCATENATE(CALCULATIONS!Y29,CALCULATIONS!T29) -> per SQ.M.
B30: ELEVATED AND SHORED SLAB FORMING | C30: =IFERROR(1/CALCULATIONS!U30,0) -> 0 | D30: =CONCATENATE(CALCULATIONS!T30,CALCULATIONS!X30) -> SQ.M.per hour | E30: =IFERROR(1/CALCULATIONS!V30,0) -> 0 | F30: =CONCATENATE(CALCULATIONS!T30,CALCULATIONS!X30) -> SQ.M.per hour | G30: =IFERROR(1/CALCULATIONS!W30,0) -> 0 | H30: =CONCATENATE(CALCULATIONS!T30,CALCULATIONS!X30) -> SQ.M.per hour | I30: =CALCULATIONS!U30*$I$2 -> 0 | J30: =CONCATENATE(CALCULATIONS!Y30,CALCULATIONS!T30) -> per SQ.M. | K30: =CALCULATIONS!V30*$I$2 -> 0 | L30: =CONCATENATE(CALCULATIONS!Y30,CALCULATIONS!T30) -> per SQ.M. | M30: =CALCULATIONS!W30*$I$2 -> 0 | N30: =CONCATENATE(CALCULATIONS!Y30,CALCULATIONS!T30) -> per SQ.M.
B31: STRIP OF FORMS | C31: =IFERROR(1/CALCULATIONS!U31,0) -> 0.14285714 | D31: =CONCATENATE(CALCULATIONS!T31,CALCULATIONS!X31) -> SQ.M.per hour | E31: =IFERROR(1/CALCULATIONS!V31,0) -> 0.28571429 | F31: =CONCATENATE(CALCULATIONS!T31,CALCULATIONS!X31) -> SQ.M.per hour | G31: =IFERROR(1/CALCULATIONS!W31,0) -> 0.35714286 | H31: =CONCATENATE(CALCULATIONS!T31,CALCULATIONS!X31) -> SQ.M.per hour | I31: =CALCULATIONS!U31*$I$2 -> 410.76389 | J31: =CONCATENATE(CALCULATIONS!Y31,CALCULATIONS!T31) -> per SQ.M. | K31: =CALCULATIONS!V31*$I$2 -> 205.38194 | L31: =CONCATENATE(CALCULATIONS!Y31,CALCULATIONS!T31) -> per SQ.M. | M31: =CALCULATIONS!W31*$I$2 -> 164.30556 | N31: =CONCATENATE(CALCULATIONS!Y31,CALCULATIONS!T31) -> per SQ.M.
B32: FLOOR SLAB AT GRADE STRIP OF FORMS | C32: =IFERROR(1/CALCULATIONS!U32,0) -> 0.17857143 | D32: =CONCATENATE(CALCULATIONS!T32,CALCULATIONS!X32) -> SQ.M.per hour | E32: =IFERROR(1/CALCULATIONS!V32,0) -> 0.35714286 | F32: =CONCATENATE(CALCULATIONS!T32,CALCULATIONS!X32) -> SQ.M.per hour | G32: =IFERROR(1/CALCULATIONS!W32,0) -> 0.44642857 | H32: =CONCATENATE(CALCULATIONS!T32,CALCULATIONS!X32) -> SQ.M.per hour | I32: =CALCULATIONS!U32*$I$2 -> 328.61111 | J32: =CONCATENATE(CALCULATIONS!Y32,CALCULATIONS!T32) -> per SQ.M. | K32: =CALCULATIONS!V32*$I$2 -> 164.30556 | L32: =CONCATENATE(CALCULATIONS!Y32,CALCULATIONS!T32) -> per SQ.M. | N32: =CONCATENATE(CALCULATIONS!Y32,CALCULATIONS!T32) -> per SQ.M.
C33: =IFERROR(1/CALCULATIONS!U33,0) -> 0 | D33: =CONCATENATE(CALCULATIONS!T33,CALCULATIONS!X33) | E33: =IFERROR(1/CALCULATIONS!V33,0) -> 0 | F33: =CONCATENATE(CALCULATIONS!T33,CALCULATIONS!X33) | G33: =IFERROR(1/CALCULATIONS!W33,0) -> 0 | H33: =CONCATENATE(CALCULATIONS!T33,CALCULATIONS!X33) | I33: =CALCULATIONS!U33*$I$2 -> 0 | J33: =CONCATENATE(CALCULATIONS!Y33,CALCULATIONS!T33) | K33: =CALCULATIONS!V33*$I$2 -> 0 | L33: =CONCATENATE(CALCULATIONS!Y33,CALCULATIONS!T33) | M33: =CALCULATIONS!W33*$I$2 -> 0 | N33: =CONCATENATE(CALCULATIONS!Y33,CALCULATIONS!T33)
A34: D | B34: INSTALLION OF CARPENTRY WORKS | C34: =IFERROR(1/CALCULATIONS!U34,0) -> 0 | D34: =CONCATENATE(CALCULATIONS!T34,CALCULATIONS!X34) | E34: =IFERROR(1/CALCULATIONS!V34,0) -> 0 | F34: =CONCATENATE(CALCULATIONS!T34,CALCULATIONS!X34) | G34: =IFERROR(1/CALCULATIONS!W34,0) -> 0 | H34: =CONCATENATE(CALCULATIONS!T34,CALCULATIONS!X34) | I34: =CALCULATIONS!U34*$I$2 -> 0 | J34: =CONCATENATE(CALCULATIONS!Y34,CALCULATIONS!T34) | K34: =CALCULATIONS!V34*$I$2 -> 0 | L34: =CONCATENATE(CALCULATIONS!Y34,CALCULATIONS!T34) | M34: =CALCULATIONS!W34*$I$2 -> 0 | N34: =CONCATENATE(CALCULATIONS!Y34,CALCULATIONS!T34)
B35: PLYWOOD PARTITION | C35: =IFERROR(1/CALCULATIONS!U35,0) -> 0.5 | D35: =CONCATENATE(CALCULATIONS!T35,CALCULATIONS!X35) -> PCper hour | E35: =IFERROR(1/CALCULATIONS!V35,0) -> 1 | F35: =CONCATENATE(CALCULATIONS!T35,CALCULATIONS!X35) -> PCper hour | G35: =IFERROR(1/CALCULATIONS!W35,0) -> 1.25 | H35: =CONCATENATE(CALCULATIONS!T35,CALCULATIONS!X35) -> PCper hour | I35: =CALCULATIONS!U35*$I$2 -> 117.36111 | J35: =CONCATENATE(CALCULATIONS!Y35,CALCULATIONS!T35) -> per PC | K35: =CALCULATIONS!V35*$I$2 -> 58.680556 | L35: =CONCATENATE(CALCULATIONS!Y35,CALCULATIONS!T35) -> per PC | M35: =CALCULATIONS!W35*$I$2 -> 46.944444 | N35: =CONCATENATE(CALCULATIONS!Y35,CALCULATIONS!T35) -> per PC
B36: T & G FLOORING AND SHORING | C36: =IFERROR(1/CALCULATIONS!U36,0) -> 3.4482759 | D36: =CONCATENATE(CALCULATIONS!T36,CALCULATIONS!X36) -> B.F.per hour | E36: =IFERROR(1/CALCULATIONS!V36,0) -> 7.1428571 | F36: =CONCATENATE(CALCULATIONS!T36,CALCULATIONS!X36) -> B.F.per hour | G36: =IFERROR(1/CALCULATIONS!W36,0) -> 9.0909091 | H36: =CONCATENATE(CALCULATIONS!T36,CALCULATIONS!X36) -> B.F.per hour | I36: =CALCULATIONS!U36*$I$2 -> 17.017361 | J36: =CONCATENATE(CALCULATIONS!Y36,CALCULATIONS!T36) -> per B.F. | K36: =CALCULATIONS!V36*$I$2 -> 8.2152778 | L36: =CONCATENATE(CALCULATIONS!Y36,CALCULATIONS!T36) -> per B.F. | M36: =CALCULATIONS!W36*$I$2 -> 6.4548611 | N36: =CONCATENATE(CALCULATIONS!Y36,CALCULATIONS!T36) -> per B.F.
B37: CEILING FRAME | C37: =IFERROR(1/CALCULATIONS!U37,0) -> 3.3333333 | D37: =CONCATENATE(CALCULATIONS!T37,CALCULATIONS!X37) -> B.F.per hour | E37: =IFERROR(1/CALCULATIONS!V37,0) -> 2.7777778 | F37: =CONCATENATE(CALCULATIONS!T37,CALCULATIONS!X37) -> B.F.per hour | G37: =IFERROR(1/CALCULATIONS!W37,0) -> 3.4482759 | H37: =CONCATENATE(CALCULATIONS!T37,CALCULATIONS!X37) -> B.F.per hour | I37: =CALCULATIONS!U37*$I$2 -> 17.604167 | J37: =CONCATENATE(CALCULATIONS!Y37,CALCULATIONS!T37) -> per B.F. | K37: =CALCULATIONS!V37*$I$2 -> 21.125 | L37: =CONCATENATE(CALCULATIONS!Y37,CALCULATIONS!T37) -> per B.F. | M37: =CALCULATIONS!W37*$I$2 -> 17.017361 | N37: =CONCATENATE(CALCULATIONS!Y37,CALCULATIONS!T37) -> per B.F.
B38: SIDING FRAME | C38: =IFERROR(1/CALCULATIONS!U38,0) -> 1.8867925 | D38: =CONCATENATE(CALCULATIONS!T38,CALCULATIONS!X38) -> B.F.per hour | E38: =IFERROR(1/CALCULATIONS!V38,0) -> 3.7037037 | F38: =CONCATENATE(CALCULATIONS!T38,CALCULATIONS!X38) -> B.F.per hour | G38: =IFERROR(1/CALCULATIONS!W38,0) -> 4.7619048 | H38: =CONCATENATE(CALCULATIONS!T38,CALCULATIONS!X38) -> B.F.per hour | I38: =CALCULATIONS!U38*$I$2 -> 31.100694 | J38: =CONCATENATE(CALCULATIONS!Y38,CALCULATIONS!T38) -> per B.F. | K38: =CALCULATIONS!V38*$I$2 -> 15.84375 | L38: =CONCATENATE(CALCULATIONS!Y38,CALCULATIONS!T38) -> per B.F. | M38: =CALCULATIONS!W38*$I$2 -> 12.322917 | N38: =CONCATENATE(CALCULATIONS!Y38,CALCULATIONS!T38) -> per B.F.
B39: FLOORING FRAME | C39: =IFERROR(1/CALCULATIONS!U39,0) -> 0.51546392 | D39: =CONCATENATE(CALCULATIONS!T39,CALCULATIONS!X39) -> B.F.per hour | E39: =IFERROR(1/CALCULATIONS!V39,0) -> 1.0309278 | F39: =CONCATENATE(CALCULATIONS!T39,CALCULATIONS!X39) -> B.F.per hour | G39: =IFERROR(1/CALCULATIONS!W39,0) -> 1.2987013 | H39: =CONCATENATE(CALCULATIONS!T39,CALCULATIONS!X39) -> B.F.per hour | I39: =CALCULATIONS!U39*$I$2 -> 113.84028 | J39: =CONCATENATE(CALCULATIONS!Y39,CALCULATIONS!T39) -> per B.F. | K39: =CALCULATIONS!V39*$I$2 -> 56.920139 | L39: =CONCATENATE(CALCULATIONS!Y39,CALCULATIONS!T39) -> per B.F. | M39: =CALCULATIONS!W39*$I$2 -> 45.184028 | N39: =CONCATENATE(CALCULATIONS!Y39,CALCULATIONS!T39) -> per B.F.
B40: WOODEN POSS ERECTION | C40: =IFERROR(1/CALCULATIONS!U40,0) -> 1.1764706 | D40: =CONCATENATE(CALCULATIONS!T40,CALCULATIONS!X40) -> B.F.per hour | E40: =IFERROR(1/CALCULATIONS!V40,0) -> 2.3255814 | F40: =CONCATENATE(CALCULATIONS!T40,CALCULATIONS!X40) -> B.F.per hour | G40: =IFERROR(1/CALCULATIONS!W40,0) -> 2.9411765 | H40: =CONCATENATE(CALCULATIONS!T40,CALCULATIONS!X40) -> B.F.per hour | I40: =CALCULATIONS!U40*$I$2 -> 49.878472 | J40: =CONCATENATE(CALCULATIONS!Y40,CALCULATIONS!T40) -> per B.F. | K40: =CALCULATIONS!V40*$I$2 -> 25.232639 | L40: =CONCATENATE(CALCULATIONS!Y40,CALCULATIONS!T40) -> per B.F. | M40: =CALCULATIONS!W40*$I$2 -> 19.951389 | N40: =CONCATENATE(CALCULATIONS!Y40,CALCULATIONS!T40) -> per B.F.
B41: TRUSS FABRICATION | C41: =IFERROR(1/CALCULATIONS!U41,0) -> 1.4285714 | D41: =CONCATENATE(CALCULATIONS!T41,CALCULATIONS!X41) -> B.F.per hour | E41: =IFERROR(1/CALCULATIONS!V41,0) -> 2.8571429 | F41: =CONCATENATE(CALCULATIONS!T41,CALCULATIONS!X41) -> B.F.per hour | G41: =IFERROR(1/CALCULATIONS!W41,0) -> 3.5714286 | H41: =CONCATENATE(CALCULATIONS!T41,CALCULATIONS!X41) -> B.F.per hour | I41: =CALCULATIONS!U41*$I$2 -> 41.076389 | J41: =CONCATENATE(CALCULATIONS!Y41,CALCULATIONS!T41) -> per B.F. | K41: =CALCULATIONS!V41*$I$2 -> 20.538194 | L41: =CONCATENATE(CALCULATIONS!Y41,CALCULATIONS!T41) -> per B.F. | M41: =CALCULATIONS!W41*$I$2 -> 16.430556 | N41: =CONCATENATE(CALCULATIONS!Y41,CALCULATIONS!T41) -> per B.F.
B42: TRUSS INSTALLATION | C42: =IFERROR(1/CALCULATIONS!U42,0) -> 0.625 | D42: =CONCATENATE(CALCULATIONS!T42,CALCULATIONS!X42) -> B.F.per hour | E42: =IFERROR(1/CALCULATIONS!V42,0) -> 1.25 | F42: =CONCATENATE(CALCULATIONS!T42,CALCULATIONS!X42) -> B.F.per hour | G42: =IFERROR(1/CALCULATIONS!W42,0) -> 1.5625 | H42: =CONCATENATE(CALCULATIONS!T42,CALCULATIONS!X42) -> B.F.per hour | I42: =CALCULATIONS!U42*$I$2 -> 93.888889 | J42: =CONCATENATE(CALCULATIONS!Y42,CALCULATIONS!T42) -> per B.F. | K42: =CALCULATIONS!V42*$I$2 -> 46.944444 | L42: =CONCATENATE(CALCULATIONS!Y42,CALCULATIONS!T42) -> per B.F. | M42: =CALCULATIONS!W42*$I$2 -> 37.555556 | N42: =CONCATENATE(CALCULATIONS!Y42,CALCULATIONS!T42) -> per B.F.
B43: GIRTS INSTALLTION | C43: =IFERROR(1/CALCULATIONS!U43,0) -> 2.3255814 | D43: =CONCATENATE(CALCULATIONS!T43,CALCULATIONS!X43) -> B.F.per hour | E43: =IFERROR(1/CALCULATIONS!V43,0) -> 4.7619048 | F43: =CONCATENATE(CALCULATIONS!T43,CALCULATIONS!X43) -> B.F.per hour | G43: =IFERROR(1/CALCULATIONS!W43,0) -> 5.8823529 | H43: =CONCATENATE(CALCULATIONS!T43,CALCULATIONS!X43) -> B.F.per hour | I43: =CALCULATIONS!U43*$I$2 -> 25.232639 | J43: =CONCATENATE(CALCULATIONS!Y43,CALCULATIONS!T43) -> per B.F. | K43: =CALCULATIONS!V43*$I$2 -> 12.322917 | L43: =CONCATENATE(CALCULATIONS!Y43,CALCULATIONS!T43) -> per B.F. | M43: =CALCULATIONS!W43*$I$2 -> 9.9756944 | N43: =CONCATENATE(CALCULATIONS!Y43,CALCULATIONS!T43) -> per B.F.
B44: PLATES INSTALLATION | C44: =IFERROR(1/CALCULATIONS!U44,0) -> 3.7037037 | D44: =CONCATENATE(CALCULATIONS!T44,CALCULATIONS!X44) -> B.F.per hour | E44: =IFERROR(1/CALCULATIONS!V44,0) -> 7.6923077 | F44: =CONCATENATE(CALCULATIONS!T44,CALCULATIONS!X44) -> B.F.per hour | G44: =IFERROR(1/CALCULATIONS!W44,0) -> 9.0909091 | H44: =CONCATENATE(CALCULATIONS!T44,CALCULATIONS!X44) -> B.F.per hour | I44: =CALCULATIONS!U44*$I$2 -> 15.84375 | J44: =CONCATENATE(CALCULATIONS!Y44,CALCULATIONS!T44) -> per B.F. | K44: =CALCULATIONS!V44*$I$2 -> 7.6284722 | L44: =CONCATENATE(CALCULATIONS!Y44,CALCULATIONS!T44) -> per B.F. | M44: =CALCULATIONS!W44*$I$2 -> 6.4548611 | N44: =CONCATENATE(CALCULATIONS!Y44,CALCULATIONS!T44) -> per B.F.
B45: PURLINS INSTALLATION | C45: =IFERROR(1/CALCULATIONS!U45,0) -> 1.8867925 | D45: =CONCATENATE(CALCULATIONS!T45,CALCULATIONS!X45) -> B.F.per hour | E45: =IFERROR(1/CALCULATIONS!V45,0) -> 3.7037037 | F45: =CONCATENATE(CALCULATIONS!T45,CALCULATIONS!X45) -> B.F.per hour | G45: =IFERROR(1/CALCULATIONS!W45,0) -> 10 | H45: =CONCATENATE(CALCULATIONS!T45,CALCULATIONS!X45) -> B.F.per hour | I45: =CALCULATIONS!U45*$I$2 -> 31.100694 | J45: =CONCATENATE(CALCULATIONS!Y45,CALCULATIONS!T45) -> per B.F. | K45: =CALCULATIONS!V45*$I$2 -> 15.84375 | L45: =CONCATENATE(CALCULATIONS!Y45,CALCULATIONS!T45) -> per B.F. | M45: =CALCULATIONS!W45*$I$2 -> 5.8680556 | N45: =CONCATENATE(CALCULATIONS!Y45,CALCULATIONS!T45) -> per B.F.
B46: FASCIA BOARD INSTALLATION | C46: =IFERROR(1/CALCULATIONS!U46,0) -> 1.0989011 | D46: =CONCATENATE(CALCULATIONS!T46,CALCULATIONS!X46) -> B.F.per hour | E46: =IFERROR(1/CALCULATIONS!V46,0) -> 2.173913 | F46: =CONCATENATE(CALCULATIONS!T46,CALCULATIONS!X46) -> B.F.per hour | G46: =IFERROR(1/CALCULATIONS!W46,0) -> 2.7777778 | H46: =CONCATENATE(CALCULATIONS!T46,CALCULATIONS!X46) -> B.F.per hour | I46: =CALCULATIONS!U46*$I$2 -> 53.399306 | J46: =CONCATENATE(CALCULATIONS!Y46,CALCULATIONS!T46) -> per B.F. | K46: =CALCULATIONS!V46*$I$2 -> 26.993056 | L46: =CONCATENATE(CALCULATIONS!Y46,CALCULATIONS!T46) -> per B.F. | M46: =CALCULATIONS!W46*$I$2 -> 21.125 | N46: =CONCATENATE(CALCULATIONS!Y46,CALCULATIONS!T46) -> per B.F.
... B58: WET FORMING | C58: =IFERROR(1/CALCULATIONS!U58,0) -> 0.14285714 | D58: =CONCATENATE(CALCULATIONS!T58,CALCULATIONS!X58) -> SQ.M.per hour | E58: =IFERROR(1/CALCULATIONS!V58,0) -> 0.28571429 | F58: =CONCATENATE(CALCULATIONS!T58,CALCULATIONS!X58) -> SQ.M.per hour | G58: =IFERROR(1/CALCULATIONS!W58,0) -> 0.35714286 | H58: =CONCATENATE(CALCULATIONS!T58,CALCULATIONS!X58) -> SQ.M.per hour | I58: =CALCULATIONS!U58*$I$2 -> 410.76389 | J58: =CONCATENATE(CALCULATIONS!Y58,CALCULATIONS!T58) -> per SQ.M. | K58: =CALCULATIONS!V58*$I$2 -> 205.38194 | L58: =CONCATENATE(CALCULATIONS!Y58,CALCULATIONS!T58) -> per SQ.M. | M58: =CALCULATIONS!W58*$I$2 -> 164.30556 | N58: =CONCATENATE(CALCULATIONS!Y58,CALCULATIONS!T58) -> per SQ.M.
C59: =IFERROR(1/CALCULATIONS!U59,0) -> 0 | D59: =CONCATENATE(CALCULATIONS!T59,CALCULATIONS!X59) | E59: =IFERROR(1/CALCULATIONS!V59,0) -> 0 | F59: =CONCATENATE(CALCULATIONS!T59,CALCULATIONS!X59) | G59: =IFERROR(1/CALCULATIONS!W59,0) -> 0 | H59: =CONCATENATE(CALCULATIONS!T59,CALCULATIONS!X59) | I59: =CALCULATIONS!U59*$I$2 -> 0 | J59: =CONCATENATE(CALCULATIONS!Y59,CALCULATIONS!T59) | K59: =CALCULATIONS!V59*$I$2 -> 0 | L59: =CONCATENATE(CALCULATIONS!Y59,CALCULATIONS!T59) | M59: =CALCULATIONS!W59*$I$2 -> 0 | N59: =CONCATENATE(CALCULATIONS!Y59,CALCULATIONS!T59)
A60: E. | B60: DOORS AND WINDOWS | C60: =IFERROR(1/CALCULATIONS!U60,0) -> 0 | D60: =CONCATENATE(CALCULATIONS!T60,CALCULATIONS!X60) | E60: =IFERROR(1/CALCULATIONS!V60,0) -> 0 | F60: =CONCATENATE(CALCULATIONS!T60,CALCULATIONS!X60) | G60: =IFERROR(1/CALCULATIONS!W60,0) -> 0 | H60: =CONCATENATE(CALCULATIONS!T60,CALCULATIONS!X60) | I60: =CALCULATIONS!U60*$I$2 -> 0 | J60: =CONCATENATE(CALCULATIONS!Y60,CALCULATIONS!T60) | K60: =CALCULATIONS!V60*$I$2 -> 0 | L60: =CONCATENATE(CALCULATIONS!Y60,CALCULATIONS!T60) | M60: =CALCULATIONS!W60*$I$2 -> 0 | N60: =CONCATENATE(CALCULATIONS!Y60,CALCULATIONS!T60)
B61: W-PANEL INSTALLATION | C61: =IFERROR(1/CALCULATIONS!U61,0) -> 1.25 | D61: =CONCATENATE(CALCULATIONS!T61,CALCULATIONS!X61) -> PC.per hour | E61: =IFERROR(1/CALCULATIONS!V61,0) -> 2.5 | F61: =CONCATENATE(CALCULATIONS!T61,CALCULATIONS!X61) -> PC.per hour | G61: =IFERROR(1/CALCULATIONS!W61,0) -> 3.125 | H61: =CONCATENATE(CALCULATIONS!T61,CALCULATIONS!X61) -> PC.per hour | I61: =CALCULATIONS!U61*$I$2 -> 46.944444 | J61: =CONCATENATE(CALCULATIONS!Y61,CALCULATIONS!T61) -> per PC. | K61: =CALCULATIONS!V61*$I$2 -> 23.472222 | L61: =CONCATENATE(CALCULATIONS!Y61,CALCULATIONS!T61) -> per PC. | M61: =CALCULATIONS!W61*$I$2 -> 18.777778 | N61: =CONCATENATE(CALCULATIONS!Y61,CALCULATIONS!T61) -> per PC.
B62: STEEL WINDOWS INSTALLATION | C62: =IFERROR(1/CALCULATIONS!U62,0) -> 0.25 | D62: =CONCATENATE(CALCULATIONS!T62,CALCULATIONS!X62) -> PC.per hour | E62: =IFERROR(1/CALCULATIONS!V62,0) -> 0.5 | F62: =CONCATENATE(CALCULATIONS!T62,CALCULATIONS!X62) -> PC.per hour | G62: =IFERROR(1/CALCULATIONS!W62,0) -> 0.625 | H62: =CONCATENATE(CALCULATIONS!T62,CALCULATIONS!X62) -> PC.per hour | I62: =CALCULATIONS!U62*$I$2 -> 234.72222 | J62: =CONCATENATE(CALCULATIONS!Y62,CALCULATIONS!T62) -> per PC. | K62: =CALCULATIONS!V62*$I$2 -> 117.36111 | L62: =CONCATENATE(CALCULATIONS!Y62,CALCULATIONS!T62) -> per PC. | M62: =CALCULATIONS!W62*$I$2 -> 93.888889 | N62: =CONCATENATE(CALCULATIONS!Y62,CALCULATIONS!T62) -> per PC.
B63: LOUVER WINDOWS INSTALLATION: | C63: =IFERROR(1/CALCULATIONS!U63,0) -> 0 | D63: =CONCATENATE(CALCULATIONS!T63,CALCULATIONS!X63) | E63: =IFERROR(1/CALCULATIONS!V63,0) -> 0 | F63: =CONCATENATE(CALCULATIONS!T63,CALCULATIONS!X63) | G63: =IFERROR(1/CALCULATIONS!W63,0) -> 0 | H63: =CONCATENATE(CALCULATIONS!T63,CALCULATIONS!X63) | I63: =CALCULATIONS!U63*$I$2 -> 0 | J63: =CONCATENATE(CALCULATIONS!Y63,CALCULATIONS!T63) | K63: =CALCULATIONS!V63*$I$2 -> 0 | L63: =CONCATENATE(CALCULATIONS!Y63,CALCULATIONS!T63) | M63: =CALCULATIONS!W63*$I$2 -> 0 | N63: =CONCATENATE(CALCULATIONS!Y63,CALCULATIONS!T63)
B64: FIXED ASBESTOS | C64: =IFERROR(1/CALCULATIONS!U64,0) -> 0.10799136 | D64: =CONCATENATE(CALCULATIONS!T64,CALCULATIONS!X64) -> SQ.M.per hour | E64: =IFERROR(1/CALCULATIONS!V64,0) -> 0.21598272 | F64: =CONCATENATE(CALCULATIONS!T64,CALCULATIONS!X64) -> SQ.M.per hour | G64: =IFERROR(1/CALCULATIONS!W64,0) -> 0.27027027 | H64: =CONCATENATE(CALCULATIONS!T64,CALCULATIONS!X64) -> SQ.M.per hour | I64: =CALCULATIONS!U64*$I$2 -> 543.38194 | J64: =CONCATENATE(CALCULATIONS!Y64,CALCULATIONS!T64) -> per SQ.M. | K64: =CALCULATIONS!V64*$I$2 -> 271.69097 | L64: =CONCATENATE(CALCULATIONS!Y64,CALCULATIONS!T64) -> per SQ.M. | M64: =CALCULATIONS!W64*$I$2 -> 217.11806 | N64: =CONCATENATE(CALCULATIONS!Y64,CALCULATIONS!T64) -> per SQ.M.
B65: FIXED METAL LOUVERS | C65: =IFERROR(1/CALCULATIONS!U65,0) -> 0.16025641 | D65: =CONCATENATE(CALCULATIONS!T65,CALCULATIONS!X65) -> SQ.M.per hour | E65: =IFERROR(1/CALCULATIONS!V65,0) -> 0.32051282 | F65: =CONCATENATE(CALCULATIONS!T65,CALCULATIONS!X65) -> SQ.M.per hour | G65: =IFERROR(1/CALCULATIONS!W65,0) -> 0.4 | H65: =CONCATENATE(CALCULATIONS!T65,CALCULATIONS!X65) -> SQ.M.per hour | I65: =CALCULATIONS!U65*$I$2 -> 366.16667 | J65: =CONCATENATE(CALCULATIONS!Y65,CALCULATIONS!T65) -> per SQ.M. | K65: =CALCULATIONS!V65*$I$2 -> 183.08333 | L65: =CONCATENATE(CALCULATIONS!Y65,CALCULATIONS!T65) -> per SQ.M. | M65: =CALCULATIONS!W65*$I$2 -> 146.70139 | N65: =CONCATENATE(CALCULATIONS!Y65,CALCULATIONS!T65) -> per SQ.M.
B66: FIXED GI SHEETS | C66: =IFERROR(1/CALCULATIONS!U66,0) -> 0.10799136 | D66: =CONCATENATE(CALCULATIONS!T66,CALCULATIONS!X66) -> SQ.M.per hour | E66: =IFERROR(1/CALCULATIONS!V66,0) -> 0.21598272 | F66: =CONCATENATE(CALCULATIONS!T66,CALCULATIONS!X66) -> SQ.M.per hour | G66: =IFERROR(1/CALCULATIONS!W66,0) -> 0.27027027 | H66: =CONCATENATE(CALCULATIONS!T66,CALCULATIONS!X66) -> SQ.M.per hour | I66: =CALCULATIONS!U66*$I$2 -> 543.38194 | J66: =CONCATENATE(CALCULATIONS!Y66,CALCULATIONS!T66) -> per SQ.M. | K66: =CALCULATIONS!V66*$I$2 -> 271.69097 | L66: =CONCATENATE(CALCULATIONS!Y66,CALCULATIONS!T66) -> per SQ.M. | M66: =CALCULATIONS!W66*$I$2 -> 217.11806 | N66: =CONCATENATE(CALCULATIONS!Y66,CALCULATIONS!T66) -> per SQ.M.
B67: FIXED GLASS | C67: =IFERROR(1/CALCULATIONS!U67,0) -> 0.15772871 | D67: =CONCATENATE(CALCULATIONS!T67,CALCULATIONS!X67) -> SQ.M.per hour | E67: =IFERROR(1/CALCULATIONS!V67,0) -> 0.32051282 | F67: =CONCATENATE(CALCULATIONS!T67,CALCULATIONS!X67) -> SQ.M.per hour | G67: =IFERROR(1/CALCULATIONS!W67,0) -> 0.4 | H67: =CONCATENATE(CALCULATIONS!T67,CALCULATIONS!X67) -> SQ.M.per hour | I67: =CALCULATIONS!U67*$I$2 -> 372.03472 | J67: =CONCATENATE(CALCULATIONS!Y67,CALCULATIONS!T67) -> per SQ.M. | K67: =CALCULATIONS!V67*$I$2 -> 183.08333 | L67: =CONCATENATE(CALCULATIONS!Y67,CALCULATIONS!T67) -> per SQ.M. | M67: =CALCULATIONS!W67*$I$2 -> 146.70139 | N67: =CONCATENATE(CALCULATIONS!Y67,CALCULATIONS!T67) -> per SQ.M.
B68: FIXED WOODEN | C68: =IFERROR(1/CALCULATIONS!U68,0) -> 0.14792899 | D68: =CONCATENATE(CALCULATIONS!T68,CALCULATIONS!X68) -> SQ.M.per hour | E68: =IFERROR(1/CALCULATIONS!V68,0) -> 0.29585799 | F68: =CONCATENATE(CALCULATIONS!T68,CALCULATIONS!X68) -> SQ.M.per hour | G68: =IFERROR(1/CALCULATIONS!W68,0) -> 0.37037037 | H68: =CONCATENATE(CALCULATIONS!T68,CALCULATIONS!X68) -> SQ.M.per hour | I68: =CALCULATIONS!U68*$I$2 -> 396.68056 | J68: =CONCATENATE(CALCULATIONS!Y68,CALCULATIONS!T68) -> per SQ.M. | K68: =CALCULATIONS!V68*$I$2 -> 198.34028 | L68: =CONCATENATE(CALCULATIONS!Y68,CALCULATIONS!T68) -> per SQ.M. | M68: =CALCULATIONS!W68*$I$2 -> 158.4375 | N68: =CONCATENATE(CALCULATIONS!Y68,CALCULATIONS!T68) -> per SQ.M.
B69: ALUMINUM FRAME WINDOWS | C69: =IFERROR(1/CALCULATIONS!U69,0) -> 0.05 | D69: =CONCATENATE(CALCULATIONS!T69,CALCULATIONS!X69) -> EACHper hour | E69: =IFERROR(1/CALCULATIONS!V69,0) -> 0.1 | F69: =CONCATENATE(CALCULATIONS!T69,CALCULATIONS!X69) -> EACHper hour | G69: =IFERROR(1/CALCULATIONS!W69,0) -> 0.125 | H69: =CONCATENATE(CALCULATIONS!T69,CALCULATIONS!X69) -> EACHper hour | I69: =CALCULATIONS!U69*$I$2 -> 1173.6111 | J69: =CONCATENATE(CALCULATIONS!Y69,CALCULATIONS!T69) -> per EACH | K69: =CALCULATIONS!V69*$I$2 -> 586.80556 | L69: =CONCATENATE(CALCULATIONS!Y69,CALCULATIONS!T69) -> per EACH | M69: =CALCULATIONS!W69*$I$2 -> 469.44444 | N69: =CONCATENATE(CALCULATIONS!Y69,CALCULATIONS!T69) -> per EACH
B70: SLIDING GLASS DOOR | C70: =IFERROR(1/CALCULATIONS!U70,0) -> 0.041666667 | D70: =CONCATENATE(CALCULATIONS!T70,CALCULATIONS!X70) -> EACHper hour | E70: =IFERROR(1/CALCULATIONS!V70,0) -> 0.083333333 | F70: =CONCATENATE(CALCULATIONS!T70,CALCULATIONS!X70) -> EACHper hour | G70: =IFERROR(1/CALCULATIONS!W70,0) -> 0.10416667 | H70: =CONCATENATE(CALCULATIONS!T70,CALCULATIONS!X70) -> EACHper hour | I70: =CALCULATIONS!U70*$I$2 -> 1408.3333 | J70: =CONCATENATE(CALCULATIONS!Y70,CALCULATIONS!T70) -> per EACH | K70: =CALCULATIONS!V70*$I$2 -> 704.16667 | L70: =CONCATENATE(CALCULATIONS!Y70,CALCULATIONS!T70) -> per EACH | M70: =CALCULATIONS!W70*$I$2 -> 563.33333 | N70: =CONCATENATE(CALCULATIONS!Y70,CALCULATIONS!T70) -> per EACH
B71: HOLLOW METAL DOOR | C71: =IFERROR(1/CALCULATIONS!U71,0) -> 0.05 | D71: =CONCATENATE(CALCULATIONS!T71,CALCULATIONS!X71) -> EACHper hour | E71: =IFERROR(1/CALCULATIONS!V71,0) -> 0.1 | F71: =CONCATENATE(CALCULATIONS!T71,CALCULATIONS!X71) -> EACHper hour | G71: =IFERROR(1/CALCULATIONS!W71,0) -> 0.125 | H71: =CONCATENATE(CALCULATIONS!T71,CALCULATIONS!X71) -> EACHper hour | I71: =CALCULATIONS!U71*$I$2 -> 1173.6111 | J71: =CONCATENATE(CALCULATIONS!Y71,CALCULATIONS!T71) -> per EACH | K71: =CALCULATIONS!V71*$I$2 -> 586.80556 | L71: =CONCATENATE(CALCULATIONS!Y71,CALCULATIONS!T71) -> per EACH | M71: =CALCULATIONS!W71*$I$2 -> 469.44444 | N71: =CONCATENATE(CALCULATIONS!Y71,CALCULATIONS!T71) -> per EACH
B72: ROLLING DOORS | C72: =IFERROR(1/CALCULATIONS!U72,0) -> 0.02 | D72: =CONCATENATE(CALCULATIONS!T72,CALCULATIONS!X72) -> EACHper hour | E72: =IFERROR(1/CALCULATIONS!V72,0) -> 0.04 | F72: =CONCATENATE(CALCULATIONS!T72,CALCULATIONS!X72) -> EACHper hour | G72: =IFERROR(1/CALCULATIONS!W72,0) -> 0.05 | H72: =CONCATENATE(CALCULATIONS!T72,CALCULATIONS!X72) -> EACHper hour | I72: =CALCULATIONS!U72*$I$2 -> 2934.0278 | J72: =CONCATENATE(CALCULATIONS!Y72,CALCULATIONS!T72) -> per EACH | K72: =CALCULATIONS!V72*$I$2 -> 1467.0139 | L72: =CONCATENATE(CALCULATIONS!Y72,CALCULATIONS!T72) -> per EACH | M72: =CALCULATIONS!W72*$I$2 -> 1173.6111 | N72: =CONCATENATE(CALCULATIONS!Y72,CALCULATIONS!T72) -> per EACH
... B77: CYCLONE WIRE INSTALLATION | C77: =IFERROR(1/CALCULATIONS!U77,0) -> 0.16025641 | D77: =CONCATENATE(CALCULATIONS!T77,CALCULATIONS!X77) -> SQ.M.per hour | E77: =IFERROR(1/CALCULATIONS!V77,0) -> 0.32051282 | F77: =CONCATENATE(CALCULATIONS!T77,CALCULATIONS!X77) -> SQ.M.per hour | G77: =IFERROR(1/CALCULATIONS!W77,0) -> 0.4 | H77: =CONCATENATE(CALCULATIONS!T77,CALCULATIONS!X77) -> SQ.M.per hour | I77: =CALCULATIONS!U77*$I$2 -> 366.16667 | J77: =CONCATENATE(CALCULATIONS!Y77,CALCULATIONS!T77) -> per SQ.M. | K77: =CALCULATIONS!V77*$I$2 -> 183.08333 | L77: =CONCATENATE(CALCULATIONS!Y77,CALCULATIONS!T77) -> per SQ.M. | M77: =CALCULATIONS!W77*$I$2 -> 146.70139 | N77: =CONCATENATE(CALCULATIONS!Y77,CALCULATIONS!T77) -> per SQ.M.
C78: =IFERROR(1/CALCULATIONS!U78,0) -> 0 | D78: =CONCATENATE(CALCULATIONS!T78,CALCULATIONS!X78) | E78: =IFERROR(1/CALCULATIONS!V78,0) -> 0 | F78: =CONCATENATE(CALCULATIONS!T78,CALCULATIONS!X78) | G78: =IFERROR(1/CALCULATIONS!W78,0) -> 0 | H78: =CONCATENATE(CALCULATIONS!T78,CALCULATIONS!X78) | I78: =CALCULATIONS!U78*$I$2 -> 0 | J78: =CONCATENATE(CALCULATIONS!Y78,CALCULATIONS!T78) | K78: =CALCULATIONS!V78*$I$2 -> 0 | L78: =CONCATENATE(CALCULATIONS!Y78,CALCULATIONS!T78) | M78: =CALCULATIONS!W78*$I$2 -> 0 | N78: =CONCATENATE(CALCULATIONS!Y78,CALCULATIONS!T78)
A79: F. | B79: TRADE MASONRY WORKS | C79: =IFERROR(1/CALCULATIONS!U79,0) -> 0 | D79: =CONCATENATE(CALCULATIONS!T79,CALCULATIONS!X79) | E79: =IFERROR(1/CALCULATIONS!V79,0) -> 0 | F79: =CONCATENATE(CALCULATIONS!T79,CALCULATIONS!X79) | G79: =IFERROR(1/CALCULATIONS!W79,0) -> 0 | H79: =CONCATENATE(CALCULATIONS!T79,CALCULATIONS!X79) | I79: =CALCULATIONS!U79*$I$2 -> 0 | J79: =CONCATENATE(CALCULATIONS!Y79,CALCULATIONS!T79) | K79: =CALCULATIONS!V79*$I$2 -> 0 | L79: =CONCATENATE(CALCULATIONS!Y79,CALCULATIONS!T79) | M79: =CALCULATIONS!W79*$I$2 -> 0 | N79: =CONCATENATE(CALCULATIONS!Y79,CALCULATIONS!T79)
B80: GROUTING and TOL PLASTERING | C80: =IFERROR(1/CALCULATIONS!U80,0) -> 0.2994012 | D80: =CONCATENATE(CALCULATIONS!T80,CALCULATIONS!X80) -> SQ.M.per hour | E80: =IFERROR(1/CALCULATIONS!V80,0) -> 0.5988024 | F80: =CONCATENATE(CALCULATIONS!T80,CALCULATIONS!X80) -> SQ.M.per hour | G80: =IFERROR(1/CALCULATIONS!W80,0) -> 0.74626866 | H80: =CONCATENATE(CALCULATIONS!T80,CALCULATIONS!X80) -> SQ.M.per hour | I80: =CALCULATIONS!U80*$I$2 -> 195.99306 | J80: =CONCATENATE(CALCULATIONS!Y80,CALCULATIONS!T80) -> per SQ.M. | K80: =CALCULATIONS!V80*$I$2 -> 97.996528 | L80: =CONCATENATE(CALCULATIONS!Y80,CALCULATIONS!T80) -> per SQ.M. | M80: =CALCULATIONS!W80*$I$2 -> 78.631944 | N80: =CONCATENATE(CALCULATIONS!Y80,CALCULATIONS!T80) -> per SQ.M.
B81: PEBBLE FINISHED | C81: =IFERROR(1/CALCULATIONS!U81,0) -> 0.34965035 | D81: =CONCATENATE(CALCULATIONS!T81,CALCULATIONS!X81) -> SQ.M.per hour | E81: =IFERROR(1/CALCULATIONS!V81,0) -> 0.6993007 | F81: =CONCATENATE(CALCULATIONS!T81,CALCULATIONS!X81) -> SQ.M.per hour | G81: =IFERROR(1/CALCULATIONS!W81,0) -> 0.74626866 | H81: =CONCATENATE(CALCULATIONS!T81,CALCULATIONS!X81) -> SQ.M.per hour | I81: =CALCULATIONS!U81*$I$2 -> 167.82639 | J81: =CONCATENATE(CALCULATIONS!Y81,CALCULATIONS!T81) -> per SQ.M. | K81: =CALCULATIONS!V81*$I$2 -> 83.913194 | L81: =CONCATENATE(CALCULATIONS!Y81,CALCULATIONS!T81) -> per SQ.M. | M81: =CALCULATIONS!W81*$I$2 -> 78.631944 | N81: =CONCATENATE(CALCULATIONS!Y81,CALCULATIONS!T81) -> per SQ.M.
B82: MABLE INSTALLATION | C82: =IFERROR(1/CALCULATIONS!U82,0) -> 0.25 | D82: =CONCATENATE(CALCULATIONS!T82,CALCULATIONS!X82) -> SQ.M.per hour | E82: =IFERROR(1/CALCULATIONS!V82,0) -> 0.5 | F82: =CONCATENATE(CALCULATIONS!T82,CALCULATIONS!X82) -> SQ.M.per hour | G82: =IFERROR(1/CALCULATIONS!W82,0) -> 0.625 | H82: =CONCATENATE(CALCULATIONS!T82,CALCULATIONS!X82) -> SQ.M.per hour | I82: =CALCULATIONS!U82*$I$2 -> 234.72222 | J82: =CONCATENATE(CALCULATIONS!Y82,CALCULATIONS!T82) -> per SQ.M. | K82: =CALCULATIONS!V82*$I$2 -> 117.36111 | L82: =CONCATENATE(CALCULATIONS!Y82,CALCULATIONS!T82) -> per SQ.M. | M82: =CALCULATIONS!W82*$I$2 -> 93.888889 | N82: =CONCATENATE(CALCULATIONS!Y82,CALCULATIONS!T82) -> per SQ.M.
B83: 1/4" x 2' x 8" RED BRICKS | C83: =IFERROR(1/CALCULATIONS!U83,0) -> 0.1 | D83: =CONCATENATE(CALCULATIONS!T83,CALCULATIONS!X83) -> SQ.M.per hour | E83: =IFERROR(1/CALCULATIONS!V83,0) -> 0.2 | F83: =CONCATENATE(CALCULATIONS!T83,CALCULATIONS!X83) -> SQ.M.per hour | G83: =IFERROR(1/CALCULATIONS!W83,0) -> 0.25 | H83: =CONCATENATE(CALCULATIONS!T83,CALCULATIONS!X83) -> SQ.M.per hour | I83: =CALCULATIONS!U83*$I$2 -> 586.80556 | J83: =CONCATENATE(CALCULATIONS!Y83,CALCULATIONS!T83) -> per SQ.M. | K83: =CALCULATIONS!V83*$I$2 -> 293.40278 | L83: =CONCATENATE(CALCULATIONS!Y83,CALCULATIONS!T83) -> per SQ.M. | M83: =CALCULATIONS!W83*$I$2 -> 234.72222 | N83: =CONCATENATE(CALCULATIONS!Y83,CALCULATIONS!T83) -> per SQ.M.
B84: GLAZED TILES | C84: =IFERROR(1/CALCULATIONS!U84,0) -> 0.047483381 | D84: =CONCATENATE(CALCULATIONS!T84,CALCULATIONS!X84) -> SQ.M.per hour | E84: =IFERROR(1/CALCULATIONS!V84,0) -> 0.094966762 | F84: =CONCATENATE(CALCULATIONS!T84,CALCULATIONS!X84) -> SQ.M.per hour | G84: =IFERROR(1/CALCULATIONS!W84,0) -> 0.11876485 | H84: =CONCATENATE(CALCULATIONS!T84,CALCULATIONS!X84) -> SQ.M.per hour | I84: =CALCULATIONS!U84*$I$2 -> 1235.8125 | J84: =CONCATENATE(CALCULATIONS!Y84,CALCULATIONS!T84) -> per SQ.M. | K84: =CALCULATIONS!V84*$I$2 -> 617.90625 | L84: =CONCATENATE(CALCULATIONS!Y84,CALCULATIONS!T84) -> per SQ.M. | M84: =CALCULATIONS!W84*$I$2 -> 494.09028 | N84: =CONCATENATE(CALCULATIONS!Y84,CALCULATIONS!T84) -> per SQ.M.
B85: UNGLAZED TILES | C85: =IFERROR(1/CALCULATIONS!U85,0) -> 0.11494253 | D85: =CONCATENATE(CALCULATIONS!T85,CALCULATIONS!X85) -> SQ.M.per hour | E85: =IFERROR(1/CALCULATIONS!V85,0) -> 0.22988506 | F85: =CONCATENATE(CALCULATIONS!T85,CALCULATIONS!X85) -> SQ.M.per hour | G85: =IFERROR(1/CALCULATIONS!W85,0) -> 0.28735632 | H85: =CONCATENATE(CALCULATIONS!T85,CALCULATIONS!X85) -> SQ.M.per hour | I85: =CALCULATIONS!U85*$I$2 -> 510.52083 | J85: =CONCATENATE(CALCULATIONS!Y85,CALCULATIONS!T85) -> per SQ.M. | K85: =CALCULATIONS!V85*$I$2 -> 255.26042 | L85: =CONCATENATE(CALCULATIONS!Y85,CALCULATIONS!T85) -> per SQ.M. | M85: =CALCULATIONS!W85*$I$2 -> 204.20833 | N85: =CONCATENATE(CALCULATIONS!Y85,CALCULATIONS!T85) -> per SQ.M.
B86: GLAZED TILE WALL | C86: =IFERROR(1/CALCULATIONS!U86,0) -> 0.16666667 | D86: =CONCATENATE(CALCULATIONS!T86,CALCULATIONS!X86) -> SQ.M.per hour | E86: =IFERROR(1/CALCULATIONS!V86,0) -> 0.33333333 | F86: =CONCATENATE(CALCULATIONS!T86,CALCULATIONS!X86) -> SQ.M.per hour | G86: =IFERROR(1/CALCULATIONS!W86,0) -> 0.41666667 | H86: =CONCATENATE(CALCULATIONS!T86,CALCULATIONS!X86) -> SQ.M.per hour | I86: =CALCULATIONS!U86*$I$2 -> 352.08333 | J86: =CONCATENATE(CALCULATIONS!Y86,CALCULATIONS!T86) -> per SQ.M. | K86: =CALCULATIONS!V86*$I$2 -> 176.04167 | L86: =CONCATENATE(CALCULATIONS!Y86,CALCULATIONS!T86) -> per SQ.M. | M86: =CALCULATIONS!W86*$I$2 -> 140.83333 | N86: =CONCATENATE(CALCULATIONS!Y86,CALCULATIONS!T86) -> per SQ.M.
B87: CONC. BLOCK INT. WALL | C87: =IFERROR(1/CALCULATIONS!U87,0) -> 0.11111111 | D87: =CONCATENATE(CALCULATIONS!T87,CALCULATIONS!X87) -> SQ.M.per hour | E87: =IFERROR(1/CALCULATIONS!V87,0) -> 0.22222222 | F87: =CONCATENATE(CALCULATIONS!T87,CALCULATIONS!X87) -> SQ.M.per hour | G87: =IFERROR(1/CALCULATIONS!W87,0) -> 0.27777778 | H87: =CONCATENATE(CALCULATIONS!T87,CALCULATIONS!X87) -> SQ.M.per hour | I87: =CALCULATIONS!U87*$I$2 -> 528.125 | J87: =CONCATENATE(CALCULATIONS!Y87,CALCULATIONS!T87) -> per SQ.M. | K87: =CALCULATIONS!V87*$I$2 -> 264.0625 | L87: =CONCATENATE(CALCULATIONS!Y87,CALCULATIONS!T87) -> per SQ.M. | M87: =CALCULATIONS!W87*$I$2 -> 211.25 | N87: =CONCATENATE(CALCULATIONS!Y87,CALCULATIONS!T87) -> per SQ.M.
B88: CONC. BLOCK EXT. WALL | C88: =IFERROR(1/CALCULATIONS!U88,0) -> 0.125 | D88: =CONCATENATE(CALCULATIONS!T88,CALCULATIONS!X88) -> SQ.M.per hour | E88: =IFERROR(1/CALCULATIONS!V88,0) -> 0.25 | F88: =CONCATENATE(CALCULATIONS!T88,CALCULATIONS!X88) -> SQ.M.per hour | G88: =IFERROR(1/CALCULATIONS!W88,0) -> 0.3125 | H88: =CONCATENATE(CALCULATIONS!T88,CALCULATIONS!X88) -> SQ.M.per hour | I88: =CALCULATIONS!U88*$I$2 -> 469.44444 | J88: =CONCATENATE(CALCULATIONS!Y88,CALCULATIONS!T88) -> per SQ.M. | K88: =CALCULATIONS!V88*$I$2 -> 234.72222 | L88: =CONCATENATE(CALCULATIONS!Y88,CALCULATIONS!T88) -> per SQ.M. | M88: =CALCULATIONS!W88*$I$2 -> 187.77778 | N88: =CONCATENATE(CALCULATIONS!Y88,CALCULATIONS!T88) -> per SQ.M.
B89: BRICKWORK | C89: =IFERROR(1/CALCULATIONS!U89,0) -> 1 | D89: =CONCATENATE(CALCULATIONS!T89,CALCULATIONS!X89) -> SQ.M.per hour | E89: =IFERROR(1/CALCULATIONS!V89,0) -> 2 | F89: =CONCATENATE(CALCULATIONS!T89,CALCULATIONS!X89) -> SQ.M.per hour | G89: =IFERROR(1/CALCULATIONS!W89,0) -> 2.5 | H89: =CONCATENATE(CALCULATIONS!T89,CALCULATIONS!X89) -> SQ.M.per hour | I89: =CALCULATIONS!U89*$I$2 -> 58.680556 | J89: =CONCATENATE(CALCULATIONS!Y89,CALCULATIONS!T89) -> per SQ.M. | K89: =CALCULATIONS!V89*$I$2 -> 29.340278 | L89: =CONCATENATE(CALCULATIONS!Y89,CALCULATIONS!T89) -> per SQ.M. | M89: =CALCULATIONS!W89*$I$2 -> 23.472222 | N89: =CONCATENATE(CALCULATIONS!Y89,CALCULATIONS!T89) -> per SQ.M.
B90: PLASTER WALL AND CEILING | C90: =IFERROR(1/CALCULATIONS!U90,0) -> 0.16666667 | D90: =CONCATENATE(CALCULATIONS!T90,CALCULATIONS!X90) -> SQ.M.per hour | E90: =IFERROR(1/CALCULATIONS!V90,0) -> 0.33333333 | F90: =CONCATENATE(CALCULATIONS!T90,CALCULATIONS!X90) -> SQ.M.per hour | G90: =IFERROR(1/CALCULATIONS!W90,0) -> 0.29411765 | H90: =CONCATENATE(CALCULATIONS!T90,CALCULATIONS!X90) -> SQ.M.per hour | I90: =CALCULATIONS!U90*$I$2 -> 352.08333 | J90: =CONCATENATE(CALCULATIONS!Y90,CALCULATIONS!T90) -> per SQ.M. | K90: =CALCULATIONS!V90*$I$2 -> 176.04167 | L90: =CONCATENATE(CALCULATIONS!Y90,CALCULATIONS!T90) -> per SQ.M. | M90: =CALCULATIONS!W90*$I$2 -> 199.51389 | N90: =CONCATENATE(CALCULATIONS!Y90,CALCULATIONS!T90) -> per SQ.M.
B91: HOLLOW TILE WALL | C91: =IFERROR(1/CALCULATIONS!U91,0) -> 0.25 | D91: =CONCATENATE(CALCULATIONS!T91,CALCULATIONS!X91) -> SQ.M.per hour | E91: =IFERROR(1/CALCULATIONS!V91,0) -> 0.5 | F91: =CONCATENATE(CALCULATIONS!T91,CALCULATIONS!X91) -> SQ.M.per hour | G91: =IFERROR(1/CALCULATIONS!W91,0) -> 0.625 | H91: =CONCATENATE(CALCULATIONS!T91,CALCULATIONS!X91) -> SQ.M.per hour | I91: =CALCULATIONS!U91*$I$2 -> 234.72222 | J91: =CONCATENATE(CALCULATIONS!Y91,CALCULATIONS!T91) -> per SQ.M. | K91: =CALCULATIONS!V91*$I$2 -> 117.36111 | L91: =CONCATENATE(CALCULATIONS!Y91,CALCULATIONS!T91) -> per SQ.M. | M91: =CALCULATIONS!W91*$I$2 -> 93.888889 | N91: =CONCATENATE(CALCULATIONS!Y91,CALCULATIONS!T91) -> per SQ.M.
... B102: VIT. TILES WALL | C102: =IFERROR(1/CALCULATIONS!U102,0) -> 0.083752094 | D102: =CONCATENATE(CALCULATIONS!T102,CALCULATIONS!X102) -> SQ.M.per hour | E102: =IFERROR(1/CALCULATIONS!V102,0) -> 0.16750419 | F102: =CONCATENATE(CALCULATIONS!T102,CALCULATIONS!X102) -> SQ.M.per hour | G102: =IFERROR(1/CALCULATIONS!W102,0) -> 0.20920502 | H102: =CONCATENATE(CALCULATIONS!T102,CALCULATIONS!X102) -> SQ.M.per hour | I102: =CALCULATIONS!U102*$I$2 -> 700.64583 | J102: =CONCATENATE(CALCULATIONS!Y102,CALCULATIONS!T102) -> per SQ.M. | K102: =CALCULATIONS!V102*$I$2 -> 350.32292 | L102: =CONCATENATE(CALCULATIONS!Y102,CALCULATIONS!T102) -> per SQ.M. | M102: =CALCULATIONS!W102*$I$2 -> 280.49306 | N102: =CONCATENATE(CALCULATIONS!Y102,CALCULATIONS!T102) -> per SQ.M.
C103: =IFERROR(1/CALCULATIONS!U103,0) -> 0 | D103: =CONCATENATE(CALCULATIONS!T103,CALCULATIONS!X103) | E103: =IFERROR(1/CALCULATIONS!V103,0) -> 0 | F103: =CONCATENATE(CALCULATIONS!T103,CALCULATIONS!X103) | G103: =IFERROR(1/CALCULATIONS!W103,0) -> 0 | H103: =CONCATENATE(CALCULATIONS!T103,CALCULATIONS!X103) | I103: =CALCULATIONS!U103*$I$2 -> 0 | J103: =CONCATENATE(CALCULATIONS!Y103,CALCULATIONS!T103) | K103: =CALCULATIONS!V103*$I$2 -> 0 | L103: =CONCATENATE(CALCULATIONS!Y103,CALCULATIONS!T103) | M103: =CALCULATIONS!W103*$I$2 -> 0 | N103: =CONCATENATE(CALCULATIONS!Y103,CALCULATIONS!T103)
A104: G. | B104: TINSMITHING WORK | C104: =IFERROR(1/CALCULATIONS!U104,0) -> 0 | D104: =CONCATENATE(CALCULATIONS!T104,CALCULATIONS!X104) | E104: =IFERROR(1/CALCULATIONS!V104,0) -> 0 | F104: =CONCATENATE(CALCULATIONS!T104,CALCULATIONS!X104) | G104: =IFERROR(1/CALCULATIONS!W104,0) -> 0 | H104: =CONCATENATE(CALCULATIONS!T104,CALCULATIONS!X104) | I104: =CALCULATIONS!U104*$I$2 -> 0 | J104: =CONCATENATE(CALCULATIONS!Y104,CALCULATIONS!T104) | K104: =CALCULATIONS!V104*$I$2 -> 0 | L104: =CONCATENATE(CALCULATIONS!Y104,CALCULATIONS!T104) | M104: =CALCULATIONS!W104*$I$2 -> 0 | N104: =CONCATENATE(CALCULATIONS!Y104,CALCULATIONS!T104)
B105: CORR GI SHEETS: | C105: =IFERROR(1/CALCULATIONS!U105,0) -> 0 | D105: =CONCATENATE(CALCULATIONS!T105,CALCULATIONS!X105) | E105: =IFERROR(1/CALCULATIONS!V105,0) -> 0 | F105: =CONCATENATE(CALCULATIONS!T105,CALCULATIONS!X105) | G105: =IFERROR(1/CALCULATIONS!W105,0) -> 0 | H105: =CONCATENATE(CALCULATIONS!T105,CALCULATIONS!X105) | I105: =CALCULATIONS!U105*$I$2 -> 0 | J105: =CONCATENATE(CALCULATIONS!Y105,CALCULATIONS!T105) | K105: =CALCULATIONS!V105*$I$2 -> 0 | L105: =CONCATENATE(CALCULATIONS!Y105,CALCULATIONS!T105) | M105: =CALCULATIONS!W105*$I$2 -> 0 | N105: =CONCATENATE(CALCULATIONS!Y105,CALCULATIONS!T105)
B106: LIFTING | C106: =IFERROR(1/CALCULATIONS!U106,0) -> 0.46296296 | D106: =CONCATENATE(CALCULATIONS!T106,CALCULATIONS!X106) -> SQ.M.per hour | E106: =IFERROR(1/CALCULATIONS!V106,0) -> 0.92592593 | F106: =CONCATENATE(CALCULATIONS!T106,CALCULATIONS!X106) -> SQ.M.per hour | G106: =IFERROR(1/CALCULATIONS!W106,0) -> 1.1627907 | H106: =CONCATENATE(CALCULATIONS!T106,CALCULATIONS!X106) -> SQ.M.per hour | I106: =CALCULATIONS!U106*$I$2 -> 126.75 | J106: =CONCATENATE(CALCULATIONS!Y106,CALCULATIONS!T106) -> per SQ.M. | K106: =CALCULATIONS!V106*$I$2 -> 63.375 | L106: =CONCATENATE(CALCULATIONS!Y106,CALCULATIONS!T106) -> per SQ.M. | M106: =CALCULATIONS!W106*$I$2 -> 50.465278 | N106: =CONCATENATE(CALCULATIONS!Y106,CALCULATIONS!T106) -> per SQ.M.
B107: INSTALLATION | C107: =IFERROR(1/CALCULATIONS!U107,0) -> 0.16339869 | D107: =CONCATENATE(CALCULATIONS!T107,CALCULATIONS!X107) -> SQ.M.per hour | E107: =IFERROR(1/CALCULATIONS!V107,0) -> 0.32679739 | F107: =CONCATENATE(CALCULATIONS!T107,CALCULATIONS!X107) -> SQ.M.per hour | G107: =IFERROR(1/CALCULATIONS!W107,0) -> 0.40816327 | H107: =CONCATENATE(CALCULATIONS!T107,CALCULATIONS!X107) -> SQ.M.per hour | I107: =CALCULATIONS!U107*$I$2 -> 359.125 | J107: =CONCATENATE(CALCULATIONS!Y107,CALCULATIONS!T107) -> per SQ.M. | K107: =CALCULATIONS!V107*$I$2 -> 179.5625 | L107: =CONCATENATE(CALCULATIONS!Y107,CALCULATIONS!T107) -> per SQ.M. | M107: =CALCULATIONS!W107*$I$2 -> 143.76736 | N107: =CONCATENATE(CALCULATIONS!Y107,CALCULATIONS!T107) -> per SQ.M.
B108: INSTALLATION OF ASBESTOS ROOFING | C108: =IFERROR(1/CALCULATIONS!U108,0) -> 0.5 | D108: =CONCATENATE(CALCULATIONS!T108,CALCULATIONS!X108) -> SHT.per hour | E108: =IFERROR(1/CALCULATIONS!V108,0) -> 1 | F108: =CONCATENATE(CALCULATIONS!T108,CALCULATIONS!X108) -> SHT.per hour | G108: =IFERROR(1/CALCULATIONS!W108,0) -> 1.25 | H108: =CONCATENATE(CALCULATIONS!T108,CALCULATIONS!X108) -> SHT.per hour | I108: =CALCULATIONS!U108*$I$2 -> 117.36111 | J108: =CONCATENATE(CALCULATIONS!Y108,CALCULATIONS!T108) -> per SHT. | K108: =CALCULATIONS!V108*$I$2 -> 58.680556 | L108: =CONCATENATE(CALCULATIONS!Y108,CALCULATIONS!T108) -> per SHT. | M108: =CALCULATIONS!W108*$I$2 -> 46.944444 | N108: =CONCATENATE(CALCULATIONS!Y108,CALCULATIONS!T108) -> per SHT.
B109: INSTALLATION OF ALUMINUM GI SHEET | C109: =IFERROR(1/CALCULATIONS!U109,0) -> 0.625 | D109: =CONCATENATE(CALCULATIONS!T109,CALCULATIONS!X109) -> SHT.per hour | E109: =IFERROR(1/CALCULATIONS!V109,0) -> 0.10204082 | F109: =CONCATENATE(CALCULATIONS!T109,CALCULATIONS!X109) -> SHT.per hour | G109: =IFERROR(1/CALCULATIONS!W109,0) -> 1.5625 | H109: =CONCATENATE(CALCULATIONS!T109,CALCULATIONS!X109) -> SHT.per hour | I109: =CALCULATIONS!U109*$I$2 -> 93.888889 | J109: =CONCATENATE(CALCULATIONS!Y109,CALCULATIONS!T109) -> per SHT. | K109: =CALCULATIONS!V109*$I$2 -> 575.06944 | L109: =CONCATENATE(CALCULATIONS!Y109,CALCULATIONS!T109) -> per SHT. | M109: =CALCULATIONS!W109*$I$2 -> 37.555556 | N109: =CONCATENATE(CALCULATIONS!Y109,CALCULATIONS!T109) -> per SHT.
B110: COPPER CLADDING ROOF DECK | C110: =IFERROR(1/CALCULATIONS!U110,0) -> 0.99009901 | D110: =CONCATENATE(CALCULATIONS!T110,CALCULATIONS!X110) -> L.M.per hour | E110: =IFERROR(1/CALCULATIONS!V110,0) -> 1.9607843 | F110: =CONCATENATE(CALCULATIONS!T110,CALCULATIONS!X110) -> L.M.per hour | G110: =IFERROR(1/CALCULATIONS!W110,0) -> 2.5 | H110: =CONCATENATE(CALCULATIONS!T110,CALCULATIONS!X110) -> L.M.per hour | I110: =CALCULATIONS!U110*$I$2 -> 59.267361 | J110: =CONCATENATE(CALCULATIONS!Y110,CALCULATIONS!T110) -> per L.M. | K110: =CALCULATIONS!V110*$I$2 -> 29.927083 | L110: =CONCATENATE(CALCULATIONS!Y110,CALCULATIONS!T110) -> per L.M. | M110: =CALCULATIONS!W110*$I$2 -> 23.472222 | N110: =CONCATENATE(CALCULATIONS!Y110,CALCULATIONS!T110) -> per L.M.
B111: FAB, GI GUTTER | C111: =IFERROR(1/CALCULATIONS!U111,0) -> 0.14409222 | D111: =CONCATENATE(CALCULATIONS!T111,CALCULATIONS!X111) -> SHT.per hour | E111: =IFERROR(1/CALCULATIONS!V111,0) -> 0.28818444 | F111: =CONCATENATE(CALCULATIONS!T111,CALCULATIONS!X111) -> SHT.per hour | G111: =IFERROR(1/CALCULATIONS!W111,0) -> 0.35971223 | H111: =CONCATENATE(CALCULATIONS!T111,CALCULATIONS!X111) -> SHT.per hour | I111: =CALCULATIONS!U111*$I$2 -> 407.24306 | J111: =CONCATENATE(CALCULATIONS!Y111,CALCULATIONS!T111) -> per SHT. | K111: =CALCULATIONS!V111*$I$2 -> 203.62153 | L111: =CONCATENATE(CALCULATIONS!Y111,CALCULATIONS!T111) -> per SHT. | M111: =CALCULATIONS!W111*$I$2 -> 163.13194 | N111: =CONCATENATE(CALCULATIONS!Y111,CALCULATIONS!T111) -> per SHT.
B112: GI SHEET ROOFING | C112: =IFERROR(1/CALCULATIONS!U112,0) -> 0.6097561 | D112: =CONCATENATE(CALCULATIONS!T112,CALCULATIONS!X112) -> SHT.per hour | E112: =IFERROR(1/CALCULATIONS!V112,0) -> 1.2195122 | F112: =CONCATENATE(CALCULATIONS!T112,CALCULATIONS!X112) -> SHT.per hour | G112: =IFERROR(1/CALCULATIONS!W112,0) -> 1.5151515 | H112: =CONCATENATE(CALCULATIONS!T112,CALCULATIONS!X112) -> SHT.per hour | I112: =CALCULATIONS!U112*$I$2 -> 96.236111 | J112: =CONCATENATE(CALCULATIONS!Y112,CALCULATIONS!T112) -> per SHT. | K112: =CALCULATIONS!V112*$I$2 -> 48.118056 | L112: =CONCATENATE(CALCULATIONS!Y112,CALCULATIONS!T112) -> per SHT. | M112: =CALCULATIONS!W112*$I$2 -> 38.729167 | N112: =CONCATENATE(CALCULATIONS!Y112,CALCULATIONS!T112) -> per SHT.
B113: FAB OF GI GUTTER | C113: =IFERROR(1/CALCULATIONS!U113,0) -> 0.95238095 | D113: =CONCATENATE(CALCULATIONS!T113,CALCULATIONS!X113) -> L.M.per hour | E113: =IFERROR(1/CALCULATIONS!V113,0) -> 1.8867925 | F113: =CONCATENATE(CALCULATIONS!T113,CALCULATIONS!X113) -> L.M.per hour | G113: =IFERROR(1/CALCULATIONS!W113,0) -> 2.3809524 | H113: =CONCATENATE(CALCULATIONS!T113,CALCULATIONS!X113) -> L.M.per hour | I113: =CALCULATIONS!U113*$I$2 -> 61.614583 | J113: =CONCATENATE(CALCULATIONS!Y113,CALCULATIONS!T113) -> per L.M. | K113: =CALCULATIONS!V113*$I$2 -> 31.100694 | L113: =CONCATENATE(CALCULATIONS!Y113,CALCULATIONS!T113) -> per L.M. | M113: =CALCULATIONS!W113*$I$2 -> 24.645833 | N113: =CONCATENATE(CALCULATIONS!Y113,CALCULATIONS!T113) -> per L.M.
B114: FAB. GI DOWNSPOUT | C114: =IFERROR(1/CALCULATIONS!U114,0) -> 0.51546392 | D114: =CONCATENATE(CALCULATIONS!T114,CALCULATIONS!X114) -> L.M.per hour | E114: =IFERROR(1/CALCULATIONS!V114,0) -> 1.0309278 | F114: =CONCATENATE(CALCULATIONS!T114,CALCULATIONS!X114) -> L.M.per hour | G114: =IFERROR(1/CALCULATIONS!W114,0) -> 0.56179775 | H114: =CONCATENATE(CALCULATIONS!T114,CALCULATIONS!X114) -> L.M.per hour | I114: =CALCULATIONS!U114*$I$2 -> 113.84028 | J114: =CONCATENATE(CALCULATIONS!Y114,CALCULATIONS!T114) -> per L.M. | K114: =CALCULATIONS!V114*$I$2 -> 56.920139 | L114: =CONCATENATE(CALCULATIONS!Y114,CALCULATIONS!T114) -> per L.M. | M114: =CALCULATIONS!W114*$I$2 -> 104.45139 | N114: =CONCATENATE(CALCULATIONS!Y114,CALCULATIONS!T114) -> per L.M.
B115: GUTTER CUT & SHAPE | C115: =IFERROR(1/CALCULATIONS!U115,0) -> 3.125 | D115: =CONCATENATE(CALCULATIONS!T115,CALCULATIONS!X115) -> L.M.per hour | E115: =IFERROR(1/CALCULATIONS!V115,0) -> 6.25 | F115: =CONCATENATE(CALCULATIONS!T115,CALCULATIONS!X115) -> L.M.per hour | G115: =IFERROR(1/CALCULATIONS!W115,0) -> 7.6923077 | H115: =CONCATENATE(CALCULATIONS!T115,CALCULATIONS!X115) -> L.M.per hour | I115: =CALCULATIONS!U115*$I$2 -> 18.777778 | J115: =CONCATENATE(CALCULATIONS!Y115,CALCULATIONS!T115) -> per L.M. | K115: =CALCULATIONS!V115*$I$2 -> 9.3888889 | L115: =CONCATENATE(CALCULATIONS!Y115,CALCULATIONS!T115) -> per L.M. | M115: =CALCULATIONS!W115*$I$2 -> 7.6284722 | N115: =CONCATENATE(CALCULATIONS!Y115,CALCULATIONS!T115) -> per L.M.
B116: INST. OF GUTTER | C116: =IFERROR(1/CALCULATIONS!U116,0) -> 0.56179775 | D116: =CONCATENATE(CALCULATIONS!T116,CALCULATIONS!X116) -> L.M.per hour | E116: =IFERROR(1/CALCULATIONS!V116,0) -> 0.11111111 | F116: =CONCATENATE(CALCULATIONS!T116,CALCULATIONS!X116) -> L.M.per hour | G116: =IFERROR(1/CALCULATIONS!W116,0) -> 1.4084507 | H116: =CONCATENATE(CALCULATIONS!T116,CALCULATIONS!X116) -> L.M.per hour | I116: =CALCULATIONS!U116*$I$2 -> 104.45139 | J116: =CONCATENATE(CALCULATIONS!Y116,CALCULATIONS!T116) -> per L.M. | K116: =CALCULATIONS!V116*$I$2 -> 528.125 | L116: =CONCATENATE(CALCULATIONS!Y116,CALCULATIONS!T116) -> per L.M. | M116: =CALCULATIONS!W116*$I$2 -> 41.663194 | N116: =CONCATENATE(CALCULATIONS!Y116,CALCULATIONS!T116) -> per L.M.
... B124: LEADERS & GUTTERS | C124: =IFERROR(1/CALCULATIONS!U124,0) -> 0.83333333 | D124: =CONCATENATE(CALCULATIONS!T124,CALCULATIONS!X124) -> SQ.M.per hour | E124: =IFERROR(1/CALCULATIONS!V124,0) -> 1.6666667 | F124: =CONCATENATE(CALCULATIONS!T124,CALCULATIONS!X124) -> SQ.M.per hour | G124: =IFERROR(1/CALCULATIONS!W124,0) -> 2.0833333 | H124: =CONCATENATE(CALCULATIONS!T124,CALCULATIONS!X124) -> SQ.M.per hour | I124: =CALCULATIONS!U124*$I$2 -> 70.416667 | J124: =CONCATENATE(CALCULATIONS!Y124,CALCULATIONS!T124) -> per SQ.M. | K124: =CALCULATIONS!V124*$I$2 -> 35.208333 | L124: =CONCATENATE(CALCULATIONS!Y124,CALCULATIONS!T124) -> per SQ.M. | M124: =CALCULATIONS!W124*$I$2 -> 28.166667 | N124: =CONCATENATE(CALCULATIONS!Y124,CALCULATIONS!T124) -> per SQ.M.
C125: =IFERROR(1/CALCULATIONS!U125,0) -> 0 | D125: =CONCATENATE(CALCULATIONS!T125,CALCULATIONS!X125) | E125: =IFERROR(1/CALCULATIONS!V125,0) -> 0 | F125: =CONCATENATE(CALCULATIONS!T125,CALCULATIONS!X125) | G125: =IFERROR(1/CALCULATIONS!W125,0) -> 0 | H125: =CONCATENATE(CALCULATIONS!T125,CALCULATIONS!X125) | I125: =CALCULATIONS!U125*$I$2 -> 0 | J125: =CONCATENATE(CALCULATIONS!Y125,CALCULATIONS!T125) | K125: =CALCULATIONS!V125*$I$2 -> 0 | L125: =CONCATENATE(CALCULATIONS!Y125,CALCULATIONS!T125) | M125: =CALCULATIONS!W125*$I$2 -> 0 | N125: =CONCATENATE(CALCULATIONS!Y125,CALCULATIONS!T125)
A126: H | B126: CONCRETE AND REBAR WORKS | C126: =IFERROR(1/CALCULATIONS!U126,0) -> 0 | D126: =CONCATENATE(CALCULATIONS!T126,CALCULATIONS!X126) | E126: =IFERROR(1/CALCULATIONS!V126,0) -> 0 | F126: =CONCATENATE(CALCULATIONS!T126,CALCULATIONS!X126) | G126: =IFERROR(1/CALCULATIONS!W126,0) -> 0 | H126: =CONCATENATE(CALCULATIONS!T126,CALCULATIONS!X126) | I126: =CALCULATIONS!U126*$I$2 -> 0 | J126: =CONCATENATE(CALCULATIONS!Y126,CALCULATIONS!T126) | K126: =CALCULATIONS!V126*$I$2 -> 0 | L126: =CONCATENATE(CALCULATIONS!Y126,CALCULATIONS!T126) | M126: =CALCULATIONS!W126*$I$2 -> 0 | N126: =CONCATENATE(CALCULATIONS!Y126,CALCULATIONS!T126)
B127: PLACING CONCRETE: | C127: =IFERROR(1/CALCULATIONS!U127,0) -> 0 | D127: =CONCATENATE(CALCULATIONS!T127,CALCULATIONS!X127) | E127: =IFERROR(1/CALCULATIONS!V127,0) -> 0 | F127: =CONCATENATE(CALCULATIONS!T127,CALCULATIONS!X127) | G127: =IFERROR(1/CALCULATIONS!W127,0) -> 0 | H127: =CONCATENATE(CALCULATIONS!T127,CALCULATIONS!X127) | I127: =CALCULATIONS!U127*$I$2 -> 0 | J127: =CONCATENATE(CALCULATIONS!Y127,CALCULATIONS!T127) | K127: =CALCULATIONS!V127*$I$2 -> 0 | L127: =CONCATENATE(CALCULATIONS!Y127,CALCULATIONS!T127) | M127: =CALCULATIONS!W127*$I$2 -> 0 | N127: =CONCATENATE(CALCULATIONS!Y127,CALCULATIONS!T127)
B128: SLAB ON FILL | C128: =IFERROR(1/CALCULATIONS!U128,0) -> 0.1 | D128: =CONCATENATE(CALCULATIONS!T128,CALCULATIONS!X128) -> CU.M.per hour | E128: =IFERROR(1/CALCULATIONS!V128,0) -> 0.2 | F128: =CONCATENATE(CALCULATIONS!T128,CALCULATIONS!X128) -> CU.M.per hour | G128: =IFERROR(1/CALCULATIONS!W128,0) -> 0.25 | H128: =CONCATENATE(CALCULATIONS!T128,CALCULATIONS!X128) -> CU.M.per hour | I128: =CALCULATIONS!U128*$I$2 -> 586.80556 | J128: =CONCATENATE(CALCULATIONS!Y128,CALCULATIONS!T128) -> per CU.M. | K128: =CALCULATIONS!V128*$I$2 -> 293.40278 | L128: =CONCATENATE(CALCULATIONS!Y128,CALCULATIONS!T128) -> per CU.M. | M128: =CALCULATIONS!W128*$I$2 -> 234.72222 | N128: =CONCATENATE(CALCULATIONS!Y128,CALCULATIONS!T128) -> per CU.M.
B129: SLIP FORM | C129: =IFERROR(1/CALCULATIONS!U129,0) -> 0.02 | D129: =CONCATENATE(CALCULATIONS!T129,CALCULATIONS!X129) -> CU.M.per hour | E129: =IFERROR(1/CALCULATIONS!V129,0) -> 0.04 | F129: =CONCATENATE(CALCULATIONS!T129,CALCULATIONS!X129) -> CU.M.per hour | G129: =IFERROR(1/CALCULATIONS!W129,0) -> 0.05 | H129: =CONCATENATE(CALCULATIONS!T129,CALCULATIONS!X129) -> CU.M.per hour | I129: =CALCULATIONS!U129*$I$2 -> 2934.0278 | J129: =CONCATENATE(CALCULATIONS!Y129,CALCULATIONS!T129) -> per CU.M. | K129: =CALCULATIONS!V129*$I$2 -> 1467.0139 | L129: =CONCATENATE(CALCULATIONS!Y129,CALCULATIONS!T129) -> per CU.M. | M129: =CALCULATIONS!W129*$I$2 -> 1173.6111 | N129: =CONCATENATE(CALCULATIONS!Y129,CALCULATIONS!T129) -> per CU.M.
B130: FLR FINISH UNHARDENED | C130: =IFERROR(1/CALCULATIONS!U130,0) -> 0.5 | D130: =CONCATENATE(CALCULATIONS!T130,CALCULATIONS!X130) -> SQ.M.per hour | E130: =IFERROR(1/CALCULATIONS!V130,0) -> 1 | F130: =CONCATENATE(CALCULATIONS!T130,CALCULATIONS!X130) -> SQ.M.per hour | G130: =IFERROR(1/CALCULATIONS!W130,0) -> 1.25 | H130: =CONCATENATE(CALCULATIONS!T130,CALCULATIONS!X130) -> SQ.M.per hour | I130: =CALCULATIONS!U130*$I$2 -> 117.36111 | J130: =CONCATENATE(CALCULATIONS!Y130,CALCULATIONS!T130) -> per SQ.M. | K130: =CALCULATIONS!V130*$I$2 -> 58.680556 | L130: =CONCATENATE(CALCULATIONS!Y130,CALCULATIONS!T130) -> per SQ.M. | M130: =CALCULATIONS!W130*$I$2 -> 46.944444 | N130: =CONCATENATE(CALCULATIONS!Y130,CALCULATIONS!T130) -> per SQ.M.
B131: CONC. FINISH HARDENED | C131: =IFERROR(1/CALCULATIONS!U131,0) -> 0.34965035 | D131: =CONCATENATE(CALCULATIONS!T131,CALCULATIONS!X131) -> SQ.M.per hour | E131: =IFERROR(1/CALCULATIONS!V131,0) -> 0.6993007 | F131: =CONCATENATE(CALCULATIONS!T131,CALCULATIONS!X131) -> SQ.M.per hour | G131: =IFERROR(1/CALCULATIONS!W131,0) -> 0.87719298 | H131: =CONCATENATE(CALCULATIONS!T131,CALCULATIONS!X131) -> SQ.M.per hour | I131: =CALCULATIONS!U131*$I$2 -> 167.82639 | J131: =CONCATENATE(CALCULATIONS!Y131,CALCULATIONS!T131) -> per SQ.M. | K131: =CALCULATIONS!V131*$I$2 -> 83.913194 | L131: =CONCATENATE(CALCULATIONS!Y131,CALCULATIONS!T131) -> per SQ.M. | M131: =CALCULATIONS!W131*$I$2 -> 66.895833 | N131: =CONCATENATE(CALCULATIONS!Y131,CALCULATIONS!T131) -> per SQ.M.
B132: REBAR WORKS: | C132: =IFERROR(1/CALCULATIONS!U132,0) -> 0 | D132: =CONCATENATE(CALCULATIONS!T132,CALCULATIONS!X132) | E132: =IFERROR(1/CALCULATIONS!V132,0) -> 0 | F132: =CONCATENATE(CALCULATIONS!T132,CALCULATIONS!X132) | G132: =IFERROR(1/CALCULATIONS!W132,0) -> 0 | H132: =CONCATENATE(CALCULATIONS!T132,CALCULATIONS!X132) | I132: =CALCULATIONS!U132*$I$2 -> 0 | J132: =CONCATENATE(CALCULATIONS!Y132,CALCULATIONS!T132) | K132: =CALCULATIONS!V132*$I$2 -> 0 | L132: =CONCATENATE(CALCULATIONS!Y132,CALCULATIONS!T132) | M132: =CALCULATIONS!W132*$I$2 -> 0 | N132: =CONCATENATE(CALCULATIONS!Y132,CALCULATIONS!T132)
B133: GROUND FLR. INSTALLATION | C133: =IFERROR(1/CALCULATIONS!U133,0) -> 7.1428571 | D133: =CONCATENATE(CALCULATIONS!T133,CALCULATIONS!X133) -> KGSper hour | E133: =IFERROR(1/CALCULATIONS!V133,0) -> 14.285714 | F133: =CONCATENATE(CALCULATIONS!T133,CALCULATIONS!X133) -> KGSper hour | G133: =IFERROR(1/CALCULATIONS!W133,0) -> 16.666667 | H133: =CONCATENATE(CALCULATIONS!T133,CALCULATIONS!X133) -> KGSper hour | I133: =CALCULATIONS!U133*$I$2 -> 8.2152778 | J133: =CONCATENATE(CALCULATIONS!Y133,CALCULATIONS!T133) -> per KGS | K133: =CALCULATIONS!V133*$I$2 -> 4.1076389 | L133: =CONCATENATE(CALCULATIONS!Y133,CALCULATIONS!T133) -> per KGS | M133: =CALCULATIONS!W133*$I$2 -> 3.5208333 | N133: =CONCATENATE(CALCULATIONS!Y133,CALCULATIONS!T133) -> per KGS
...

Sheet MANHOUR EQUIVALENT
B1: MANHOUR EQUIVALENT RATE | H1: Table of Rates
H2: Area | I2: Position
I3: Foreman | J3: Skilled | K3: Labor
H4: NCR | I4: =K4*$L$6 -> 926.25 | J4: =K4*$L$5 -> 748.125 | K4: 570
H5: CAR | I5: =K5*$L$6 -> 650 | J5: =K5*$L$5 -> 525 | K5: 400 | L5: =525/K5 -> 1.3125
H6: Region 1 | I6: =K6*$L$6 -> 650 | J6: =K6*$L$5 -> 525 | K6: 400 | L6: =650/K7 -> 1.625
H7: Region 2 | I7: =K7*$L$6 -> 650 | J7: =K7*$L$5 -> 525 | K7: 400
H8: Region 3 | I8: =K8*$L$6 -> 747.5 | J8: =K8*$L$5 -> 603.75 | K8: 460
D9: (Drop-Down List) | H9: Region 4A | I9: =K9*$L$6 -> 763.75 | J9: =K9*$L$5 -> 616.875 | K9: 470
B10: CHOOSE RATE : | D10: CAR | E10: Total Daily Rate | F10: Hourly Pay | H10: Region 4B | I10: =K10*$L$6 -> 576.875 | J10: =K10*$L$5 -> 465.9375 | K10: 355
B11: Position | C11: Quantity | D11: Rate | H11: Region 5 | I11: =K11*$L$6 -> 593.125 | J11: =K11*$L$5 -> 479.0625 | K11: 365
B12: Foreman | C12: 1 | D12: =VLOOKUP($D$10,$H$1:$K$20,2,FALSE) -> 650 | E12: =C12*D12 -> 650 | F12: =E12/8 -> 81.25 | H12: Region 6 | I12: =K12*$L$6 -> 731.25 | J12: =K12*$L$5 -> 590.625 | K12: 450
B13: Skilled | C13: 3 | D13: =VLOOKUP($D$10,$H$1:$K$20,3,FALSE) -> 525 | E13: =C13*D13 -> 1575 | F13: =E13/8 -> 196.875 | H13: Region 7 | I13: =K13*$L$6 -> 706.875 | J13: =K13*$L$5 -> 570.9375 | K13: 435
B14: Labor | C14: 5 | D14: =VLOOKUP($D$10,$H$1:$K$20,4,FALSE) -> 400 | E14: =C14*D14 -> 2000 | F14: =E14/8 -> 250 | H14: Region 8 | I14: =K14*$L$6 -> 609.375 | J14: =K14*$L$5 -> 492.1875 | K14: 375
E15: Total Rate per Manhour = | F15: =SUM(F12:F14)/SUM(C12:C14) -> 58.680556 | H15: Region 9 | I15: =K15*$L$6 -> 570.375 | J15: =K15*$L$5 -> 460.6875 | K15: 351
H16: Region 10 | I16: =K16*$L$6 -> 658.125 | J16: =K16*$L$5 -> 531.5625 | K16: 405
B17: NOTE : You can change the quantities of the manpower per position and their respective rates in the Table. | H17: Region 11 | I17: =K17*$L$6 -> 719.875 | J17: =K17*$L$5 -> 581.4375 | K17: 443
H18: Region 12 | I18: =K18*$L$6 -> 598 | J18: =K18*$L$5 -> 483 | K18: 368
H19: Region 13 | I19: =K19*$L$6 -> 568.75 | J19: =K19*$L$5 -> 459.375 | K19: 350
H20: BARMM | I20: =K20*$L$6 -> 554.125 | J20: =K20*$L$5 -> 447.5625 | K20: 341

Sheet LABOR CALCULATOR
A1: ACTIVITIES | C1: INPUT HERE | E1: choose labor productivity rate BELOW | F1: TOTAL COST
E3: LABOR PRODUCTIVITY
A4: ITEM NO. | B4: WORK DESCRIPTION | C4: QUANTITY | D4: UNIT | E4: FAST
E5: RATE PER UNIT
C6: SLOW | D6: AVERAGE | E6: FAST
A7: A. | B7: FORM WORKS INSTALLATION
B8: WALL ON THE GROUND | C8: 20 | D8: =CALCULATIONS!T8 -> SQ.M. | E8: =IF($E$4="LOW",'LABOR PRODUCTIVITY'!I8,IF($E$4="AVERAGE",'LABOR PRODUCTIVITY'!K8,'LABOR PRODUCTIVITY'!M8)) -> 93.888889 | F8: =C8*E8 -> 1877.7778
B9: WALL ABOVER GROUND | C9: 20 | D9: =CALCULATIONS!T9 -> SQ.M. | E9: =IF($E$4="LOW",'LABOR PRODUCTIVITY'!I9,IF($E$4="AVERAGE",'LABOR PRODUCTIVITY'!K9,'LABOR PRODUCTIVITY'!M9)) -> 110.31944 | F9: =C9*E9 -> 2206.3889
B10: BEAMS | D10: =CALCULATIONS!T10 -> SQ.M. | E10: =IF($E$4="LOW",'LABOR PRODUCTIVITY'!I10,IF($E$4="AVERAGE",'LABOR PRODUCTIVITY'!K10,'LABOR PRODUCTIVITY'!M10)) -> 144.35417 | F10: =C10*E10 -> 0
B11: COLUMN | D11: =CALCULATIONS!T11 -> SQ.M. | E11: =IF($E$4="LOW",'LABOR PRODUCTIVITY'!I11,IF($E$4="AVERAGE",'LABOR PRODUCTIVITY'!K11,'LABOR PRODUCTIVITY'!M11)) -> 110.31944 | F11: =C11*E11 -> 0
B12: SUSPENDED SLAB | D12: =CALCULATIONS!T12 | E12: =IF($E$4="LOW",'LABOR PRODUCTIVITY'!I12,IF($E$4="AVERAGE",'LABOR PRODUCTIVITY'!K12,'LABOR PRODUCTIVITY'!M12)) -> 0 | F12: =C12*E12 -> 0
B13: 0 TO 18' | D13: =CALCULATIONS!T13 -> SQ.M. | E13: =IF($E$4="LOW",'LABOR PRODUCTIVITY'!I13,IF($E$4="AVERAGE",'LABOR PRODUCTIVITY'!K13,'LABOR PRODUCTIVITY'!M13)) -> 78.631944 | F13: =C13*E13 -> 0
B14: 18' TO 36' UP | D14: =CALCULATIONS!T14 -> SQ.M. | E14: =IF($E$4="LOW",'LABOR PRODUCTIVITY'!I14,IF($E$4="AVERAGE",'LABOR PRODUCTIVITY'!K14,'LABOR PRODUCTIVITY'!M14)) -> 156.09028 | F14: =C14*E14 -> 0
B15: ELEVATED AND SHORED SLAB FORMING | D15: =CALCULATIONS!T15 | E15: =IF($E$4="LOW",'LABOR PRODUCTIVITY'!I15,IF($E$4="AVERAGE",'LABOR PRODUCTIVITY'!K15,'LABOR PRODUCTIVITY'!M15)) -> 0 | F15: =C15*E15 -> 0
B16: FORMING ONLY | D16: =CALCULATIONS!T16 -> SQ.M. | E16: =IF($E$4="LOW",'LABOR PRODUCTIVITY'!I16,IF($E$4="AVERAGE",'LABOR PRODUCTIVITY'!K16,'LABOR PRODUCTIVITY'!M16)) -> 403.72222 | F16: =C16*E16 -> 0
B17: FORMING AND SHORING | D17: =CALCULATIONS!T17 -> SQ.M. | E17: =IF($E$4="LOW",'LABOR PRODUCTIVITY'!I17,IF($E$4="AVERAGE",'LABOR PRODUCTIVITY'!K17,'LABOR PRODUCTIVITY'!M17)) -> 516.38889 | F17: =C17*E17 -> 0
B18: WOOD WALL AND PARTITION | D18: =CALCULATIONS!T18 -> SQ.M. | E18: =IF($E$4="LOW",'LABOR PRODUCTIVITY'!I18,IF($E$4="AVERAGE",'LABOR PRODUCTIVITY'!K18,'LABOR PRODUCTIVITY'!M18)) -> 23.472222 | F18: =C18*E18 -> 0
D19: =CALCULATIONS!T19 | E19: =IF($E$4="LOW",'LABOR PRODUCTIVITY'!I19,IF($E$4="AVERAGE",'LABOR PRODUCTIVITY'!K19,'LABOR PRODUCTIVITY'!M19)) -> 0 | F19: =C19*E19 -> 0
A20: B. | B20: FORMWORKS FABRICATION | D20: =CALCULATIONS!T20 -> SQ.M. | E20: =IF($E$4="LOW",'LABOR PRODUCTIVITY'!I20,IF($E$4="AVERAGE",'LABOR PRODUCTIVITY'!K20,'LABOR PRODUCTIVITY'!M20)) -> 50.465278 | F20: =C20*E20 -> 0
D21: =CALCULATIONS!T21 | E21: =IF($E$4="LOW",'LABOR PRODUCTIVITY'!I21,IF($E$4="AVERAGE",'LABOR PRODUCTIVITY'!K21,'LABOR PRODUCTIVITY'!M21)) -> 0 | F21: =C21*E21 -> 0
A22: C. | B22: STRIPPING OF FORMS | D22: =CALCULATIONS!T22 | E22: =IF($E$4="LOW",'LABOR PRODUCTIVITY'!I22,IF($E$4="AVERAGE",'LABOR PRODUCTIVITY'!K22,'LABOR PRODUCTIVITY'!M22)) -> 0 | F22: =C22*E22 -> 0
B23: WALL ON GROUND | D23: =CALCULATIONS!T23 -> SQ.M. | E23: =IF($E$4="LOW",'LABOR PRODUCTIVITY'!I23,IF($E$4="AVERAGE",'LABOR PRODUCTIVITY'!K23,'LABOR PRODUCTIVITY'!M23)) -> 11.736111 | F23: =C23*E23 -> 0
B24: WALL ABOVE 10' | D24: =CALCULATIONS!T24 -> SQ.M. | E24: =IF($E$4="LOW",'LABOR PRODUCTIVITY'!I24,IF($E$4="AVERAGE",'LABOR PRODUCTIVITY'!K24,'LABOR PRODUCTIVITY'!M24)) -> 60.440972 | F24: =C24*E24 -> 0
B25: BEAMS | D25: =CALCULATIONS!T25 -> SQ.M. | E25: =IF($E$4="LOW",'LABOR PRODUCTIVITY'!I25,IF($E$4="AVERAGE",'LABOR PRODUCTIVITY'!K25,'LABOR PRODUCTIVITY'!M25)) -> 48.118056 | F25: =C25*E25 -> 0
B26: COLUMNS | D26: =CALCULATIONS!T26 -> SQ.M. | E26: =IF($E$4="LOW",'LABOR PRODUCTIVITY'!I26,IF($E$4="AVERAGE",'LABOR PRODUCTIVITY'!K26,'LABOR PRODUCTIVITY'!M26)) -> 39.902778 | F26: =C26*E26 -> 0
B27: SUSPENDED SLAB | D27: =CALCULATIONS!T27 -> SQ.M. | E27: =IF($E$4="LOW",'LABOR PRODUCTIVITY'!I27,IF($E$4="AVERAGE",'LABOR PRODUCTIVITY'!K27,'LABOR PRODUCTIVITY'!M27)) -> 0 | F27: =C27*E27 -> 0
B28: 0 TO 18' | D28: =CALCULATIONS!T28 -> SQ.M. | E28: =IF($E$4="LOW",'LABOR PRODUCTIVITY'!I28,IF($E$4="AVERAGE",'LABOR PRODUCTIVITY'!K28,'LABOR PRODUCTIVITY'!M28)) -> 39.315972 | F28: =C28*E28 -> 0
B29: 18' TO 36' UP | D29: =CALCULATIONS!T29 -> SQ.M. | E29: =IF($E$4="LOW",'LABOR PRODUCTIVITY'!I29,IF($E$4="AVERAGE",'LABOR PRODUCTIVITY'!K29,'LABOR PRODUCTIVITY'!M29)) -> 50.465278 | F29: =C29*E29 -> 0
B30: ELEVATED AND SHORED SLAB FORMING | D30: =CALCULATIONS!T30 -> SQ.M. | E30: =IF($E$4="LOW",'LABOR PRODUCTIVITY'!I30,IF($E$4="AVERAGE",'LABOR PRODUCTIVITY'!K30,'LABOR PRODUCTIVITY'!M30)) -> 0 | F30: =C30*E30 -> 0
B31: STRIP OF FORMS | D31: =CALCULATIONS!T31 -> SQ.M. | E31: =IF($E$4="LOW",'LABOR PRODUCTIVITY'!I31,IF($E$4="AVERAGE",'LABOR PRODUCTIVITY'!K31,'LABOR PRODUCTIVITY'!M31)) -> 164.30556 | F31: =C31*E31 -> 0
B32: FLOOR SLAB AT GRADE STRIP OF FORMS | D32: =CALCULATIONS!T32 -> SQ.M. | E32: =IF($E$4="LOW",'LABOR PRODUCTIVITY'!I32,IF($E$4="AVERAGE",'LABOR PRODUCTIVITY'!K32,'LABOR PRODUCTIVITY'!M32)) | F32: =C32*E32 -> #VALUE!
D33: =CALCULATIONS!T33 | E33: =IF($E$4="LOW",'LABOR PRODUCTIVITY'!I33,IF($E$4="AVERAGE",'LABOR PRODUCTIVITY'!K33,'LABOR PRODUCTIVITY'!M33)) -> 0 | F33: =C33*E33 -> 0
A34: D | B34: INSTALLION OF CARPENTRY WORKS | D34: =CALCULATIONS!T34 | E34: =IF($E$4="LOW",'LABOR PRODUCTIVITY'!I34,IF($E$4="AVERAGE",'LABOR PRODUCTIVITY'!K34,'LABOR PRODUCTIVITY'!M34)) -> 0 | F34: =C34*E34 -> 0
B35: PLYWOOD PARTITION | D35: =CALCULATIONS!T35 -> PC | E35: =IF($E$4="LOW",'LABOR PRODUCTIVITY'!I35,IF($E$4="AVERAGE",'LABOR PRODUCTIVITY'!K35,'LABOR PRODUCTIVITY'!M35)) -> 46.944444 | F35: =C35*E35 -> 0
B36: T & G FLOORING AND SHORING | D36: =CALCULATIONS!T36 -> B.F. | E36: =IF($E$4="LOW",'LABOR PRODUCTIVITY'!I36,IF($E$4="AVERAGE",'LABOR PRODUCTIVITY'!K36,'LABOR PRODUCTIVITY'!M36)) -> 6.4548611 | F36: =C36*E36 -> 0
B37: CEILING FRAME | D37: =CALCULATIONS!T37 -> B.F. | E37: =IF($E$4="LOW",'LABOR PRODUCTIVITY'!I37,IF($E$4="AVERAGE",'LABOR PRODUCTIVITY'!K37,'LABOR PRODUCTIVITY'!M37)) -> 17.017361 | F37: =C37*E37 -> 0
B38: SIDING FRAME | D38: =CALCULATIONS!T38 -> B.F. | E38: =IF($E$4="LOW",'LABOR PRODUCTIVITY'!I38,IF($E$4="AVERAGE",'LABOR PRODUCTIVITY'!K38,'LABOR PRODUCTIVITY'!M38)) -> 12.322917 | F38: =C38*E38 -> 0
B39: FLOORING FRAME | D39: =CALCULATIONS!T39 -> B.F. | E39: =IF($E$4="LOW",'LABOR PRODUCTIVITY'!I39,IF($E$4="AVERAGE",'LABOR PRODUCTIVITY'!K39,'LABOR PRODUCTIVITY'!M39)) -> 45.184028 | F39: =C39*E39 -> 0
B40: WOODEN POSS ERECTION | D40: =CALCULATIONS!T40 -> B.F. | E40: =IF($E$4="LOW",'LABOR PRODUCTIVITY'!I40,IF($E$4="AVERAGE",'LABOR PRODUCTIVITY'!K40,'LABOR PRODUCTIVITY'!M40)) -> 19.951389 | F40: =C40*E40 -> 0
B41: TRUSS FABRICATION | D41: =CALCULATIONS!T41 -> B.F. | E41: =IF($E$4="LOW",'LABOR PRODUCTIVITY'!I41,IF($E$4="AVERAGE",'LABOR PRODUCTIVITY'!K41,'LABOR PRODUCTIVITY'!M41)) -> 16.430556 | F41: =C41*E41 -> 0
B42: TRUSS INSTALLATION | D42: =CALCULATIONS!T42 -> B.F. | E42: =IF($E$4="LOW",'LABOR PRODUCTIVITY'!I42,IF($E$4="AVERAGE",'LABOR PRODUCTIVITY'!K42,'LABOR PRODUCTIVITY'!M42)) -> 37.555556 | F42: =C42*E42 -> 0
B43: GIRTS INSTALLTION | D43: =CALCULATIONS!T43 -> B.F. | E43: =IF($E$4="LOW",'LABOR PRODUCTIVITY'!I43,IF($E$4="AVERAGE",'LABOR PRODUCTIVITY'!K43,'LABOR PRODUCTIVITY'!M43)) -> 9.9756944 | F43: =C43*E43 -> 0
B44: PLATES INSTALLATION | D44: =CALCULATIONS!T44 -> B.F. | E44: =IF($E$4="LOW",'LABOR PRODUCTIVITY'!I44,IF($E$4="AVERAGE",'LABOR PRODUCTIVITY'!K44,'LABOR PRODUCTIVITY'!M44)) -> 6.4548611 | F44: =C44*E44 -> 0
B45: PURLINS INSTALLATION | D45: =CALCULATIONS!T45 -> B.F. | E45: =IF($E$4="LOW",'LABOR PRODUCTIVITY'!I45,IF($E$4="AVERAGE",'LABOR PRODUCTIVITY'!K45,'LABOR PRODUCTIVITY'!M45)) -> 5.8680556 | F45: =C45*E45 -> 0
B46: FASCIA BOARD INSTALLATION | D46: =CALCULATIONS!T46 -> B.F. | E46: =IF($E$4="LOW",'LABOR PRODUCTIVITY'!I46,IF($E$4="AVERAGE",'LABOR PRODUCTIVITY'!K46,'LABOR PRODUCTIVITY'!M46)) -> 21.125 | F46: =C46*E46 -> 0
... B58: WET FORMING | D58: =CALCULATIONS!T58 -> SQ.M. | E58: =IF($E$4="LOW",'LABOR PRODUCTIVITY'!I58,IF($E$4="AVERAGE",'LABOR PRODUCTIVITY'!K58,'LABOR PRODUCTIVITY'!M58)) -> 164.30556 | F58: =C58*E58 -> 0
D59: =CALCULATIONS!T59 | E59: =IF($E$4="LOW",'LABOR PRODUCTIVITY'!I59,IF($E$4="AVERAGE",'LABOR PRODUCTIVITY'!K59,'LABOR PRODUCTIVITY'!M59)) -> 0 | F59: =C59*E59 -> 0
A60: E. | B60: DOORS AND WINDOWS | D60: =CALCULATIONS!T60 | E60: =IF($E$4="LOW",'LABOR PRODUCTIVITY'!I60,IF($E$4="AVERAGE",'LABOR PRODUCTIVITY'!K60,'LABOR PRODUCTIVITY'!M60)) -> 0 | F60: =C60*E60 -> 0
B61: W-PANEL INSTALLATION | D61: =CALCULATIONS!T61 -> PC. | E61: =IF($E$4="LOW",'LABOR PRODUCTIVITY'!I61,IF($E$4="AVERAGE",'LABOR PRODUCTIVITY'!K61,'LABOR PRODUCTIVITY'!M61)) -> 18.777778 | F61: =C61*E61 -> 0
B62: STEEL WINDOWS INSTALLATION | D62: =CALCULATIONS!T62 -> PC. | E62: =IF($E$4="LOW",'LABOR PRODUCTIVITY'!I62,IF($E$4="AVERAGE",'LABOR PRODUCTIVITY'!K62,'LABOR PRODUCTIVITY'!M62)) -> 93.888889 | F62: =C62*E62 -> 0
B63: LOUVER WINDOWS INSTALLATION: | D63: =CALCULATIONS!T63 | E63: =IF($E$4="LOW",'LABOR PRODUCTIVITY'!I63,IF($E$4="AVERAGE",'LABOR PRODUCTIVITY'!K63,'LABOR PRODUCTIVITY'!M63)) -> 0 | F63: =C63*E63 -> 0
B64: FIXED ASBESTOS | D64: =CALCULATIONS!T64 -> SQ.M. | E64: =IF($E$4="LOW",'LABOR PRODUCTIVITY'!I64,IF($E$4="AVERAGE",'LABOR PRODUCTIVITY'!K64,'LABOR PRODUCTIVITY'!M64)) -> 217.11806 | F64: =C64*E64 -> 0
B65: FIXED METAL LOUVERS | D65: =CALCULATIONS!T65 -> SQ.M. | E65: =IF($E$4="LOW",'LABOR PRODUCTIVITY'!I65,IF($E$4="AVERAGE",'LABOR PRODUCTIVITY'!K65,'LABOR PRODUCTIVITY'!M65)) -> 146.70139 | F65: =C65*E65 -> 0
B66: FIXED GI SHEETS | D66: =CALCULATIONS!T66 -> SQ.M. | E66: =IF($E$4="LOW",'LABOR PRODUCTIVITY'!I66,IF($E$4="AVERAGE",'LABOR PRODUCTIVITY'!K66,'LABOR PRODUCTIVITY'!M66)) -> 217.11806 | F66: =C66*E66 -> 0
B67: FIXED GLASS | D67: =CALCULATIONS!T67 -> SQ.M. | E67: =IF($E$4="LOW",'LABOR PRODUCTIVITY'!I67,IF($E$4="AVERAGE",'LABOR PRODUCTIVITY'!K67,'LABOR PRODUCTIVITY'!M67)) -> 146.70139 | F67: =C67*E67 -> 0
B68: FIXED WOODEN | D68: =CALCULATIONS!T68 -> SQ.M. | E68: =IF($E$4="LOW",'LABOR PRODUCTIVITY'!I68,IF($E$4="AVERAGE",'LABOR PRODUCTIVITY'!K68,'LABOR PRODUCTIVITY'!M68)) -> 158.4375 | F68: =C68*E68 -> 0
B69: ALUMINUM FRAME WINDOWS | D69: =CALCULATIONS!T69 -> EACH | E69: =IF($E$4="LOW",'LABOR PRODUCTIVITY'!I69,IF($E$4="AVERAGE",'LABOR PRODUCTIVITY'!K69,'LABOR PRODUCTIVITY'!M69)) -> 469.44444 | F69: =C69*E69 -> 0
B70: SLIDING GLASS DOOR | D70: =CALCULATIONS!T70 -> EACH | E70: =IF($E$4="LOW",'LABOR PRODUCTIVITY'!I70,IF($E$4="AVERAGE",'LABOR PRODUCTIVITY'!K70,'LABOR PRODUCTIVITY'!M70)) -> 563.33333 | F70: =C70*E70 -> 0
B71: HOLLOW METAL DOOR | D71: =CALCULATIONS!T71 -> EACH | E71: =IF($E$4="LOW",'LABOR PRODUCTIVITY'!I71,IF($E$4="AVERAGE",'LABOR PRODUCTIVITY'!K71,'LABOR PRODUCTIVITY'!M71)) -> 469.44444 | F71: =C71*E71 -> 0
B72: ROLLING DOORS | D72: =CALCULATIONS!T72 -> EACH | E72: =IF($E$4="LOW",'LABOR PRODUCTIVITY'!I72,IF($E$4="AVERAGE",'LABOR PRODUCTIVITY'!K72,'LABOR PRODUCTIVITY'!M72)) -> 1173.6111 | F72: =C72*E72 -> 0
... B77: CYCLONE WIRE INSTALLATION | D77: =CALCULATIONS!T77 -> SQ.M. | E77: =IF($E$4="LOW",'LABOR PRODUCTIVITY'!I77,IF($E$4="AVERAGE",'LABOR PRODUCTIVITY'!K77,'LABOR PRODUCTIVITY'!M77)) -> 146.70139 | F77: =C77*E77 -> 0
D78: =CALCULATIONS!T78 | E78: =IF($E$4="LOW",'LABOR PRODUCTIVITY'!I78,IF($E$4="AVERAGE",'LABOR PRODUCTIVITY'!K78,'LABOR PRODUCTIVITY'!M78)) -> 0 | F78: =C78*E78 -> 0
A79: F. | B79: TRADE MASONRY WORKS | D79: =CALCULATIONS!T79 | E79: =IF($E$4="LOW",'LABOR PRODUCTIVITY'!I79,IF($E$4="AVERAGE",'LABOR PRODUCTIVITY'!K79,'LABOR PRODUCTIVITY'!M79)) -> 0 | F79: =C79*E79 -> 0
B80: GROUTING and TOL PLASTERING | D80: =CALCULATIONS!T80 -> SQ.M. | E80: =IF($E$4="LOW",'LABOR PRODUCTIVITY'!I80,IF($E$4="AVERAGE",'LABOR PRODUCTIVITY'!K80,'LABOR PRODUCTIVITY'!M80)) -> 78.631944 | F80: =C80*E80 -> 0
B81: PEBBLE FINISHED | D81: =CALCULATIONS!T81 -> SQ.M. | E81: =IF($E$4="LOW",'LABOR PRODUCTIVITY'!I81,IF($E$4="AVERAGE",'LABOR PRODUCTIVITY'!K81,'LABOR PRODUCTIVITY'!M81)) -> 78.631944 | F81: =C81*E81 -> 0
B82: MABLE INSTALLATION | D82: =CALCULATIONS!T82 -> SQ.M. | E82: =IF($E$4="LOW",'LABOR PRODUCTIVITY'!I82,IF($E$4="AVERAGE",'LABOR PRODUCTIVITY'!K82,'LABOR PRODUCTIVITY'!M82)) -> 93.888889 | F82: =C82*E82 -> 0
B83: 1/4" x 2' x 8" RED BRICKS | D83: =CALCULATIONS!T83 -> SQ.M. | E83: =IF($E$4="LOW",'LABOR PRODUCTIVITY'!I83,IF($E$4="AVERAGE",'LABOR PRODUCTIVITY'!K83,'LABOR PRODUCTIVITY'!M83)) -> 234.72222 | F83: =C83*E83 -> 0
B84: GLAZED TILES | D84: =CALCULATIONS!T84 -> SQ.M. | E84: =IF($E$4="LOW",'LABOR PRODUCTIVITY'!I84,IF($E$4="AVERAGE",'LABOR PRODUCTIVITY'!K84,'LABOR PRODUCTIVITY'!M84)) -> 494.09028 | F84: =C84*E84 -> 0
B85: UNGLAZED TILES | D85: =CALCULATIONS!T85 -> SQ.M. | E85: =IF($E$4="LOW",'LABOR PRODUCTIVITY'!I85,IF($E$4="AVERAGE",'LABOR PRODUCTIVITY'!K85,'LABOR PRODUCTIVITY'!M85)) -> 204.20833 | F85: =C85*E85 -> 0
B86: GLAZED TILE WALL | D86: =CALCULATIONS!T86 -> SQ.M. | E86: =IF($E$4="LOW",'LABOR PRODUCTIVITY'!I86,IF($E$4="AVERAGE",'LABOR PRODUCTIVITY'!K86,'LABOR PRODUCTIVITY'!M86)) -> 140.83333 | F86: =C86*E86 -> 0
B87: CONC. BLOCK INT. WALL | D87: =CALCULATIONS!T87 -> SQ.M. | E87: =IF($E$4="LOW",'LABOR PRODUCTIVITY'!I87,IF($E$4="AVERAGE",'LABOR PRODUCTIVITY'!K87,'LABOR PRODUCTIVITY'!M87)) -> 211.25 | F87: =C87*E87 -> 0
B88: CONC. BLOCK EXT. WALL | D88: =CALCULATIONS!T88 -> SQ.M. | E88: =IF($E$4="LOW",'LABOR PRODUCTIVITY'!I88,IF($E$4="AVERAGE",'LABOR PRODUCTIVITY'!K88,'LABOR PRODUCTIVITY'!M88)) -> 187.77778 | F88: =C88*E88 -> 0
B89: BRICKWORK | D89: =CALCULATIONS!T89 -> SQ.M. | E89: =IF($E$4="LOW",'LABOR PRODUCTIVITY'!I89,IF($E$4="AVERAGE",'LABOR PRODUCTIVITY'!K89,'LABOR PRODUCTIVITY'!M89)) -> 23.472222 | F89: =C89*E89 -> 0
B90: PLASTER WALL AND CEILING | D90: =CALCULATIONS!T90 -> SQ.M. | E90: =IF($E$4="LOW",'LABOR PRODUCTIVITY'!I90,IF($E$4="AVERAGE",'LABOR PRODUCTIVITY'!K90,'LABOR PRODUCTIVITY'!M90)) -> 199.51389 | F90: =C90*E90 -> 0
B91: HOLLOW TILE WALL | D91: =CALCULATIONS!T91 -> SQ.M. | E91: =IF($E$4="LOW",'LABOR PRODUCTIVITY'!I91,IF($E$4="AVERAGE",'LABOR PRODUCTIVITY'!K91,'LABOR PRODUCTIVITY'!M91)) -> 93.888889 | F91: =C91*E91 -> 0
... B98: 6" CHB | D98: =CALCULATIONS!T98 -> SQ.M. | E98: =IF($E$4="LOW",'LABOR PRODUCTIVITY'!I98,IF($E$4="AVERAGE",'LABOR PRODUCTIVITY'!K98,'LABOR PRODUCTIVITY'!M98)) -> 75.111111 | F98: =C98*E98 -> 0
B99: 4" CHB | C99: 161.7 | D99: =CALCULATIONS!T99 -> SQ.M. | E99: =IF($E$4="LOW",'LABOR PRODUCTIVITY'!I99,IF($E$4="AVERAGE",'LABOR PRODUCTIVITY'!K99,'LABOR PRODUCTIVITY'!M99)) -> 62.201389 | F99: =C99*E99 -> 10057.965
B100: 8" CHB | D100: =CALCULATIONS!T100 -> SQ.M. | E100: =IF($E$4="LOW",'LABOR PRODUCTIVITY'!I100,IF($E$4="AVERAGE",'LABOR PRODUCTIVITY'!K100,'LABOR PRODUCTIVITY'!M100)) -> 93.888889 | F100: =C100*E100 -> 0
B101: VIT. TILES FLOOR | D101: =CALCULATIONS!T101 -> SQ.M. | E101: =IF($E$4="LOW",'LABOR PRODUCTIVITY'!I101,IF($E$4="AVERAGE",'LABOR PRODUCTIVITY'!K101,'LABOR PRODUCTIVITY'!M101)) -> 249.97917 | F101: =C101*E101 -> 0
B102: VIT. TILES WALL | D102: =CALCULATIONS!T102 -> SQ.M. | E102: =IF($E$4="LOW",'LABOR PRODUCTIVITY'!I102,IF($E$4="AVERAGE",'LABOR PRODUCTIVITY'!K102,'LABOR PRODUCTIVITY'!M102)) -> 280.49306 | F102: =C102*E102 -> 0
D103: =CALCULATIONS!T103 | E103: =IF($E$4="LOW",'LABOR PRODUCTIVITY'!I103,IF($E$4="AVERAGE",'LABOR PRODUCTIVITY'!K103,'LABOR PRODUCTIVITY'!M103)) -> 0 | F103: =C103*E103 -> 0
A104: G. | B104: TINSMITHING WORK | D104: =CALCULATIONS!T104 | E104: =IF($E$4="LOW",'LABOR PRODUCTIVITY'!I104,IF($E$4="AVERAGE",'LABOR PRODUCTIVITY'!K104,'LABOR PRODUCTIVITY'!M104)) -> 0 | F104: =C104*E104 -> 0
B105: CORR GI SHEETS: | D105: =CALCULATIONS!T105 | E105: =IF($E$4="LOW",'LABOR PRODUCTIVITY'!I105,IF($E$4="AVERAGE",'LABOR PRODUCTIVITY'!K105,'LABOR PRODUCTIVITY'!M105)) -> 0 | F105: =C105*E105 -> 0
B106: LIFTING | D106: =CALCULATIONS!T106 -> SQ.M. | E106: =IF($E$4="LOW",'LABOR PRODUCTIVITY'!I106,IF($E$4="AVERAGE",'LABOR PRODUCTIVITY'!K106,'LABOR PRODUCTIVITY'!M106)) -> 50.465278 | F106: =C106*E106 -> 0
B107: INSTALLATION | D107: =CALCULATIONS!T107 -> SQ.M. | E107: =IF($E$4="LOW",'LABOR PRODUCTIVITY'!I107,IF($E$4="AVERAGE",'LABOR PRODUCTIVITY'!K107,'LABOR PRODUCTIVITY'!M107)) -> 143.76736 | F107: =C107*E107 -> 0
B108: INSTALLATION OF ASBESTOS ROOFING | D108: =CALCULATIONS!T108 -> SHT. | E108: =IF($E$4="LOW",'LABOR PRODUCTIVITY'!I108,IF($E$4="AVERAGE",'LABOR PRODUCTIVITY'!K108,'LABOR PRODUCTIVITY'!M108)) -> 46.944444 | F108: =C108*E108 -> 0
B109: INSTALLATION OF ALUMINUM GI SHEET | D109: =CALCULATIONS!T109 -> SHT. | E109: =IF($E$4="LOW",'LABOR PRODUCTIVITY'!I109,IF($E$4="AVERAGE",'LABOR PRODUCTIVITY'!K109,'LABOR PRODUCTIVITY'!M109)) -> 37.555556 | F109: =C109*E109 -> 0
B110: COPPER CLADDING ROOF DECK | D110: =CALCULATIONS!T110 -> L.M. | E110: =IF($E$4="LOW",'LABOR PRODUCTIVITY'!I110,IF($E$4="AVERAGE",'LABOR PRODUCTIVITY'!K110,'LABOR PRODUCTIVITY'!M110)) -> 23.472222 | F110: =C110*E110 -> 0
B111: FAB, GI GUTTER | D111: =CALCULATIONS!T111 -> SHT. | E111: =IF($E$4="LOW",'LABOR PRODUCTIVITY'!I111,IF($E$4="AVERAGE",'LABOR PRODUCTIVITY'!K111,'LABOR PRODUCTIVITY'!M111)) -> 163.13194 | F111: =C111*E111 -> 0
B112: GI SHEET ROOFING | D112: =CALCULATIONS!T112 -> SHT. | E112: =IF($E$4="LOW",'LABOR PRODUCTIVITY'!I112,IF($E$4="AVERAGE",'LABOR PRODUCTIVITY'!K112,'LABOR PRODUCTIVITY'!M112)) -> 38.729167 | F112: =C112*E112 -> 0
B113: FAB OF GI GUTTER | D113: =CALCULATIONS!T113 -> L.M. | E113: =IF($E$4="LOW",'LABOR PRODUCTIVITY'!I113,IF($E$4="AVERAGE",'LABOR PRODUCTIVITY'!K113,'LABOR PRODUCTIVITY'!M113)) -> 24.645833 | F113: =C113*E113 -> 0
B114: FAB. GI DOWNSPOUT | D114: =CALCULATIONS!T114 -> L.M. | E114: =IF($E$4="LOW",'LABOR PRODUCTIVITY'!I114,IF($E$4="AVERAGE",'LABOR PRODUCTIVITY'!K114,'LABOR PRODUCTIVITY'!M114)) -> 104.45139 | F114: =C114*E114 -> 0
B115: GUTTER CUT & SHAPE | D115: =CALCULATIONS!T115 -> L.M. | E115: =IF($E$4="LOW",'LABOR PRODUCTIVITY'!I115,IF($E$4="AVERAGE",'LABOR PRODUCTIVITY'!K115,'LABOR PRODUCTIVITY'!M115)) -> 7.6284722 | F115: =C115*E115 -> 0
B116: INST. OF GUTTER | D116: =CALCULATIONS!T116 -> L.M. | E116: =IF($E$4="LOW",'LABOR PRODUCTIVITY'!I116,IF($E$4="AVERAGE",'LABOR PRODUCTIVITY'!K116,'LABOR PRODUCTIVITY'!M116)) -> 41.663194 | F116: =C116*E116 -> 0
... B124: LEADERS & GUTTERS | D124: =CALCULATIONS!T124 -> SQ.M. | E124: =IF($E$4="LOW",'LABOR PRODUCTIVITY'!I124,IF($E$4="AVERAGE",'LABOR PRODUCTIVITY'!K124,'LABOR PRODUCTIVITY'!M124)) -> 28.166667 | F124: =C124*E124 -> 0
D125: =CALCULATIONS!T125 | E125: =IF($E$4="LOW",'LABOR PRODUCTIVITY'!I125,IF($E$4="AVERAGE",'LABOR PRODUCTIVITY'!K125,'LABOR PRODUCTIVITY'!M125)) -> 0 | F125: =C125*E125 -> 0
A126: H | B126: CONCRETE AND REBAR WORKS | D126: =CALCULATIONS!T126 | E126: =IF($E$4="LOW",'LABOR PRODUCTIVITY'!I126,IF($E$4="AVERAGE",'LABOR PRODUCTIVITY'!K126,'LABOR PRODUCTIVITY'!M126)) -> 0 | F126: =C126*E126 -> 0
B127: PLACING CONCRETE: | D127: =CALCULATIONS!T127 | E127: =IF($E$4="LOW",'LABOR PRODUCTIVITY'!I127,IF($E$4="AVERAGE",'LABOR PRODUCTIVITY'!K127,'LABOR PRODUCTIVITY'!M127)) -> 0 | F127: =C127*E127 -> 0
B128: SLAB ON FILL | D128: =CALCULATIONS!T128 -> CU.M. | E128: =IF($E$4="LOW",'LABOR PRODUCTIVITY'!I128,IF($E$4="AVERAGE",'LABOR PRODUCTIVITY'!K128,'LABOR PRODUCTIVITY'!M128)) -> 234.72222 | F128: =C128*E128 -> 0
B129: SLIP FORM | D129: =CALCULATIONS!T129 -> CU.M. | E129: =IF($E$4="LOW",'LABOR PRODUCTIVITY'!I129,IF($E$4="AVERAGE",'LABOR PRODUCTIVITY'!K129,'LABOR PRODUCTIVITY'!M129)) -> 1173.6111 | F129: =C129*E129 -> 0
...

Sheet CALCULATIONS
C1: MANHOUR EQUIVALENT | M1: OUTPUT PER HOUR
C2: ='MANHOUR EQUIVALENT'!F15 -> 58.680556 | D2: =CONCATENATE("per hour in area of ",'MANHOUR EQUIVALENT'!D10) -> per hour in area of CAR
C3: EQUIVALENT LABOR COST
B4: LOW | J4: MANHOURS PER QUANTITY (M.H./UNIT) | M4: 3 WORKER PRODUCTIVITY RATE | U4: MANHOURS PER QUANTITY (M.H./UNIT)
B5: AVERAGE | C5: LOW | D5: PESOS PER | E5: AVERAGE | F5: PESOS PER | G5: HIGH | H5: PESOS PER | I5: UNIT | J5: LOW | K5: AVERAGE | L5: HIGH | M5: LOW | N5: UNIT | O5: AVERAGE | P5: UNIT | Q5: HIGH | R5: UNIT | T5: UNIT | U5: LOW | V5: AVERAGE | W5: HIGH
B6: HIGH
C8: =J8*$C$2 -> 234.72222 | D8: =CONCATENATE(" per ",I8) -> per SQ.M. | E8: =K8*$C$2 -> 117.36111 | F8: =CONCATENATE(" per ",I8) -> per SQ.M. | G8: =L8*$C$2 -> 93.888889 | H8: =CONCATENATE(" per ",I8) -> per SQ.M. | I8: SQ.M. | J8: 4 | K8: 2 | L8: 1.6 | M8: =1/J8 -> 0.25 | N8: =CONCATENATE(I8," per hour") -> SQ.M. per hour | O8: =1/K8 -> 0.5 | P8: =CONCATENATE(I8," per hour") -> SQ.M. per hour | Q8: =1/L8 -> 0.625 | R8: =CONCATENATE(I8," per hour") -> SQ.M. per hour | T8: SQ.M. | U8: 4 | V8: 2 | W8: 1.6 | X8: =IF(T8>0,"per hour","") -> per hour | Y8: =IF(T8>0,"per ","") -> per
C9: =J9*$C$2 -> 275.79861 | E9: =K9*$C$2 -> 137.89931 | G9: =L9*$C$2 -> 110.31944 | I9: SQ.M. | J9: 4.7 | K9: 2.35 | L9: 1.88 | T9: SQ.M. | U9: 4.7 | V9: 2.35 | W9: 1.88 | X9: =IF(T9>0,"per hour","") -> per hour | Y9: =IF(T9>0,"per ","") -> per
C10: =J10*$C$2 -> 361.47222 | E10: =K10*$C$2 -> 180.73611 | G10: =L10*$C$2 -> 144.35417 | I10: SQ.M. | J10: 6.16 | K10: 3.08 | L10: 2.46 | T10: SQ.M. | U10: 6.16 | V10: 3.08 | W10: 2.46 | X10: =IF(T10>0,"per hour","") -> per hour | Y10: =IF(T10>0,"per ","") -> per
C11: =J11*$C$2 -> 275.79861 | E11: =K11*$C$2 -> 137.89931 | G11: =L11*$C$2 -> 110.31944 | I11: SQ.M. | J11: 4.7 | K11: 2.35 | L11: 1.88 | T11: SQ.M. | U11: 4.7 | V11: 2.35 | W11: 1.88 | X11: =IF(T11>0,"per hour","") -> per hour | Y11: =IF(T11>0,"per ","") -> per
C12: =J12*$C$2 -> 0 | E12: =K12*$C$2 -> 0 | G12: =L12*$C$2 -> 0 | X12: =IF(T12>0,"per hour","") | Y12: =IF(T12>0,"per ","")
C13: =J13*$C$2 -> 195.99306 | E13: =K13*$C$2 -> 97.996528 | G13: =L13*$C$2 -> 78.631944 | I13: SQ.M. | J13: 3.34 | K13: 1.67 | L13: 1.34 | T13: SQ.M. | U13: 3.34 | V13: 1.67 | W13: 1.34 | X13: =IF(T13>0,"per hour","") -> per hour | Y13: =IF(T13>0,"per ","") -> per
C14: =J14*$C$2 -> 390.8125 | E14: =K14*$C$2 -> 195.40625 | G14: =L14*$C$2 -> 156.09028 | I14: SQ.M. | J14: 6.66 | K14: 3.33 | L14: 2.66 | T14: SQ.M. | U14: 6.66 | V14: 3.33 | W14: 2.66 | X14: =IF(T14>0,"per hour","") -> per hour | Y14: =IF(T14>0,"per ","") -> per
C15: =J15*$C$2 -> 0 | E15: =K15*$C$2 -> 0 | G15: =L15*$C$2 -> 0 | X15: =IF(T15>0,"per hour","") | Y15: =IF(T15>0,"per ","")
C16: =J16*$C$2 -> 1009.3056 | E16: =K16*$C$2 -> 528.125 | G16: =L16*$C$2 -> 403.72222 | I16: SQ.M. | J16: 17.2 | K16: 9 | L16: 6.88 | T16: SQ.M. | U16: 17.2 | V16: 9 | W16: 6.88 | X16: =IF(T16>0,"per hour","") -> per hour | Y16: =IF(T16>0,"per ","") -> per
C17: =J17*$C$2 -> 1290.9722 | E17: =K17*$C$2 -> 645.48611 | G17: =L17*$C$2 -> 516.38889 | I17: SQ.M. | J17: 22 | K17: 11 | L17: 8.8 | T17: SQ.M. | U17: 22 | V17: 11 | W17: 8.8 | X17: =IF(T17>0,"per hour","") -> per hour | Y17: =IF(T17>0,"per ","") -> per
C18: =J18*$C$2 -> 58.680556 | E18: =K18*$C$2 -> 35.208333 | G18: =L18*$C$2 -> 23.472222 | I18: SQ.M. | J18: 1 | K18: 0.6 | L18: 0.4 | T18: SQ.M. | U18: 1 | V18: 0.6 | W18: 0.4 | X18: =IF(T18>0,"per hour","") -> per hour | Y18: =IF(T18>0,"per ","") -> per
C19: =J19*$C$2 -> 0 | E19: =K19*$C$2 -> 0 | G19: =L19*$C$2 -> 0 | X19: =IF(T19>0,"per hour","") | Y19: =IF(T19>0,"per ","")
C20: =J20*$C$2 -> 126.16319 | E20: =K20*$C$2 -> 63.375 | G20: =L20*$C$2 -> 50.465278 | I20: SQ.M. | J20: 2.15 | K20: 1.08 | L20: 0.86 | T20: SQ.M. | U20: 2.15 | V20: 1.08 | W20: 0.86 | X20: =IF(T20>0,"per hour","") -> per hour | Y20: =IF(T20>0,"per ","") -> per
C21: =J21*$C$2 -> 0 | E21: =K21*$C$2 -> 0 | G21: =L21*$C$2 -> 0 | X21: =IF(T21>0,"per hour","") | Y21: =IF(T21>0,"per ","")
C22: =J22*$C$2 -> 0 | E22: =K22*$C$2 -> 0 | G22: =L22*$C$2 -> 0 | X22: =IF(T22>0,"per hour","") | Y22: =IF(T22>0,"per ","")
C23: =J23*$C$2 -> 29.340278 | E23: =K23*$C$2 -> 14.670139 | G23: =L23*$C$2 -> 11.736111 | I23: SQ.M. | J23: 0.5 | K23: 0.25 | L23: 0.2 | T23: SQ.M. | U23: 0.5 | V23: 0.25 | W23: 0.2 | X23: =IF(T23>0,"per hour","") -> per hour | Y23: =IF(T23>0,"per ","") -> per
C24: =J24*$C$2 -> 151.39583 | E24: =K24*$C$2 -> 75.697917 | G24: =L24*$C$2 -> 60.440972 | I24: SQ.M. | J24: 2.58 | K24: 1.29 | L24: 1.03 | T24: SQ.M. | U24: 2.58 | V24: 1.29 | W24: 1.03 | X24: =IF(T24>0,"per hour","") -> per hour | Y24: =IF(T24>0,"per ","") -> per
C25: =J25*$C$2 -> 120.88194 | E25: =K25*$C$2 -> 60.440972 | G25: =L25*$C$2 -> 48.118056 | I25: SQ.M. | J25: 2.06 | K25: 1.03 | L25: 0.82 | T25: SQ.M. | U25: 2.06 | V25: 1.03 | W25: 0.82 | X25: =IF(T25>0,"per hour","") -> per hour | Y25: =IF(T25>0,"per ","") -> per
C26: =J26*$C$2 -> 99.756944 | E26: =K26*$C$2 -> 49.878472 | G26: =L26*$C$2 -> 39.902778 | I26: SQ.M. | J26: 1.7 | K26: 0.85 | L26: 0.68 | T26: SQ.M. | U26: 1.7 | V26: 0.85 | W26: 0.68 | X26: =IF(T26>0,"per hour","") -> per hour | Y26: =IF(T26>0,"per ","") -> per
C27: =J27*$C$2 -> 0 | E27: =K27*$C$2 -> 0 | G27: =L27*$C$2 -> 0 | I27: SQ.M. | T27: SQ.M. | X27: =IF(T27>0,"per hour","") -> per hour | Y27: =IF(T27>0,"per ","") -> per
C28: =J28*$C$2 -> 97.996528 | E28: =K28*$C$2 -> 48.704861 | G28: =L28*$C$2 -> 39.315972 | I28: SQ.M. | J28: 1.67 | K28: 0.83 | L28: 0.67 | T28: SQ.M. | U28: 1.67 | V28: 0.83 | W28: 0.67 | X28: =IF(T28>0,"per hour","") -> per hour | Y28: =IF(T28>0,"per ","") -> per
C29: =J29*$C$2 -> 126.75 | E29: =K29*$C$2 -> 63.375 | G29: =L29*$C$2 -> 50.465278 | I29: SQ.M. | J29: 2.16 | K29: 1.08 | L29: 0.86 | T29: SQ.M. | U29: 2.16 | V29: 1.08 | W29: 0.86 | X29: =IF(T29>0,"per hour","") -> per hour | Y29: =IF(T29>0,"per ","") -> per
C30: =J30*$C$2 -> 0 | E30: =K30*$C$2 -> 0 | G30: =L30*$C$2 -> 0 | I30: SQ.M. | T30: SQ.M. | X30: =IF(T30>0,"per hour","") -> per hour | Y30: =IF(T30>0,"per ","") -> per
C31: =J31*$C$2 -> 410.76389 | E31: =K31*$C$2 -> 205.38194 | G31: =L31*$C$2 -> 164.30556 | I31: SQ.M. | J31: 7 | K31: 3.5 | L31: 2.8 | T31: SQ.M. | U31: 7 | V31: 3.5 | W31: 2.8 | X31: =IF(T31>0,"per hour","") -> per hour | Y31: =IF(T31>0,"per ","") -> per
C32: =J32*$C$2 -> 328.61111 | E32: =K32*$C$2 -> 164.30556 | G32: =L32*$C$2 -> 131.44444 | I32: SQ.M. | J32: 5.6 | K32: 2.8 | L32: 2.24 | T32: SQ.M. | U32: 5.6 | V32: 2.8 | W32: 2.24 | X32: =IF(T32>0,"per hour","") -> per hour | Y32: =IF(T32>0,"per ","") -> per
C33: =J33*$C$2 -> 0 | E33: =K33*$C$2 -> 0 | G33: =L33*$C$2 -> 0 | X33: =IF(T33>0,"per hour","") | Y33: =IF(T33>0,"per ","")
C34: =J34*$C$2 -> 0 | E34: =K34*$C$2 -> 0 | G34: =L34*$C$2 -> 0 | X34: =IF(T34>0,"per hour","") | Y34: =IF(T34>0,"per ","")
C35: =J35*$C$2 -> 117.36111 | E35: =K35*$C$2 -> 58.680556 | G35: =L35*$C$2 -> 46.944444 | I35: PC | J35: 2 | K35: 1 | L35: 0.8 | T35: PC | U35: 2 | V35: 1 | W35: 0.8 | X35: =IF(T35>0,"per hour","") -> per hour | Y35: =IF(T35>0,"per ","") -> per
C36: =J36*$C$2 -> 17.017361 | E36: =K36*$C$2 -> 8.2152778 | G36: =L36*$C$2 -> 6.4548611 | I36: B.F. | J36: 0.29 | K36: 0.14 | L36: 0.11 | T36: B.F. | U36: 0.29 | V36: 0.14 | W36: 0.11 | X36: =IF(T36>0,"per hour","") -> per hour | Y36: =IF(T36>0,"per ","") -> per
C37: =J37*$C$2 -> 17.604167 | E37: =K37*$C$2 -> 21.125 | G37: =L37*$C$2 -> 17.017361 | I37: B.F. | J37: 0.3 | K37: 0.36 | L37: 0.29 | T37: B.F. | U37: 0.3 | V37: 0.36 | W37: 0.29 | X37: =IF(T37>0,"per hour","") -> per hour | Y37: =IF(T37>0,"per ","") -> per
C38: =J38*$C$2 -> 31.100694 | E38: =K38*$C$2 -> 15.84375 | G38: =L38*$C$2 -> 12.322917 | I38: B.F. | J38: 0.53 | K38: 0.27 | L38: 0.21 | T38: B.F. | U38: 0.53 | V38: 0.27 | W38: 0.21 | X38: =IF(T38>0,"per hour","") -> per hour | Y38: =IF(T38>0,"per ","") -> per
C39: =J39*$C$2 -> 113.84028 | E39: =K39*$C$2 -> 56.920139 | G39: =L39*$C$2 -> 45.184028 | I39: B.F. | J39: 1.94 | K39: 0.97 | L39: 0.77 | T39: B.F. | U39: 1.94 | V39: 0.97 | W39: 0.77 | X39: =IF(T39>0,"per hour","") -> per hour | Y39: =IF(T39>0,"per ","") -> per
C40: =J40*$C$2 -> 49.878472 | E40: =K40*$C$2 -> 25.232639 | G40: =L40*$C$2 -> 19.951389 | I40: B.F. | J40: 0.85 | K40: 0.43 | L40: 0.34 | T40: B.F. | U40: 0.85 | V40: 0.43 | W40: 0.34 | X40: =IF(T40>0,"per hour","") -> per hour | Y40: =IF(T40>0,"per ","") -> per
C41: =J41*$C$2 -> 41.076389 | E41: =K41*$C$2 -> 20.538194 | G41: =L41*$C$2 -> 16.430556 | I41: B.F. | J41: 0.7 | K41: 0.35 | L41: 0.28 | T41: B.F. | U41: 0.7 | V41: 0.35 | W41: 0.28 | X41: =IF(T41>0,"per hour","") -> per hour | Y41: =IF(T41>0,"per ","") -> per
C42: =J42*$C$2 -> 93.888889 | E42: =K42*$C$2 -> 46.944444 | G42: =L42*$C$2 -> 37.555556 | I42: B.F. | J42: 1.6 | K42: 0.8 | L42: 0.64 | T42: B.F. | U42: 1.6 | V42: 0.8 | W42: 0.64 | X42: =IF(T42>0,"per hour","") -> per hour | Y42: =IF(T42>0,"per ","") -> per
C43: =J43*$C$2 -> 25.232639 | E43: =K43*$C$2 -> 12.322917 | G43: =L43*$C$2 -> 9.9756944 | I43: B.F. | J43: 0.43 | K43: 0.21 | L43: 0.17 | T43: B.F. | U43: 0.43 | V43: 0.21 | W43: 0.17 | X43: =IF(T43>0,"per hour","") -> per hour | Y43: =IF(T43>0,"per ","") -> per
C44: =J44*$C$2 -> 15.84375 | E44: =K44*$C$2 -> 7.6284722 | G44: =L44*$C$2 -> 6.4548611 | I44: B.F. | J44: 0.27 | K44: 0.13 | L44: 0.11 | T44: B.F. | U44: 0.27 | V44: 0.13 | W44: 0.11 | X44: =IF(T44>0,"per hour","") -> per hour | Y44: =IF(T44>0,"per ","") -> per
C45: =J45*$C$2 -> 31.100694 | E45: =K45*$C$2 -> 15.84375 | G45: =L45*$C$2 -> 5.8680556 | I45: B.F. | J45: 0.53 | K45: 0.27 | L45: 0.1 | T45: B.F. | U45: 0.53 | V45: 0.27 | W45: 0.1 | X45: =IF(T45>0,"per hour","") -> per hour | Y45: =IF(T45>0,"per ","") -> per
C46: =J46*$C$2 -> 53.399306 | E46: =K46*$C$2 -> 26.993056 | G46: =L46*$C$2 -> 21.125 | I46: B.F. | J46: 0.91 | K46: 0.46 | L46: 0.36 | T46: B.F. | U46: 0.91 | V46: 0.46 | W46: 0.36 | X46: =IF(T46>0,"per hour","") -> per hour | Y46: =IF(T46>0,"per ","") -> per
C47: =J47*$C$2 -> 0 | E47: =K47*$C$2 -> 0 | G47: =L47*$C$2 -> 0 | X47: =IF(T47>0,"per hour","") | Y47: =IF(T47>0,"per ","")
C48: =J48*$C$2 -> 117.36111 | E48: =K48*$C$2 -> 58.680556 | G48: =L48*$C$2 -> 46.944444 | I48: PC | J48: 2 | K48: 1 | L48: 0.8 | T48: PC | U48: 2 | V48: 1 | W48: 0.8 | X48: =IF(T48>0,"per hour","") -> per hour | Y48: =IF(T48>0,"per ","") -> per
C49: =J49*$C$2 -> 48.704861 | E49: =K49*$C$2 -> 24.645833 | G49: =L49*$C$2 -> 19.364583 | I49: S.F. | J49: 0.83 | K49: 0.42 | L49: 0.33 | T49: S.F. | U49: 0.83 | V49: 0.42 | W49: 0.33 | X49: =IF(T49>0,"per hour","") -> per hour | Y49: =IF(T49>0,"per ","") -> per
C50: =J50*$C$2 -> 0 | E50: =K50*$C$2 -> 0 | G50: =L50*$C$2 -> 0 | X50: =IF(T50>0,"per hour","") | Y50: =IF(T50>0,"per ","")
C51: =J51*$C$2 -> 156.09028 | E51: =K51*$C$2 -> 78.045139 | G51: =L51*$C$2 -> 62.201389 | I51: SQ.M. | J51: 2.66 | K51: 1.33 | L51: 1.06 | T51: SQ.M. | U51: 2.66 | V51: 1.33 | W51: 1.06 | X51: =IF(T51>0,"per hour","") -> per hour | Y51: =IF(T51>0,"per ","") -> per
C52: =J52*$C$2 -> 117.36111 | E52: =K52*$C$2 -> 58.680556 | G52: =L52*$C$2 -> 52.8125 | I52: SQ.M. | J52: 2 | K52: 1 | L52: 0.9 | T52: SQ.M. | U52: 2 | V52: 1 | W52: 0.9 | X52: =IF(T52>0,"per hour","") -> per hour | Y52: =IF(T52>0,"per ","") -> per
C53: =J53*$C$2 -> 15.256944 | E53: =K53*$C$2 -> 7.6284722 | G53: =L53*$C$2 -> 5.8680556 | I53: B.F. | J53: 0.26 | K53: 0.13 | L53: 0.1 | T53: B.F. | U53: 0.26 | V53: 0.13 | W53: 0.1 | X53: =IF(T53>0,"per hour","") -> per hour | Y53: =IF(T53>0,"per ","") -> per
C54: =J54*$C$2 -> 21.125 | E54: =K54*$C$2 -> 10.5625 | G54: =L54*$C$2 -> 8.2152778 | I54: B.F. | J54: 0.36 | K54: 0.18 | L54: 0.14 | T54: B.F. | U54: 0.36 | V54: 0.18 | W54: 0.14 | X54: =IF(T54>0,"per hour","") -> per hour | Y54: =IF(T54>0,"per ","") -> per
C55: =J55*$C$2 -> 58.680556 | E55: =K55*$C$2 -> 29.340278 | G55: =L55*$C$2 -> 23.472222 | I55: SQ.M. | J55: 1 | K55: 0.5 | L55: 0.4 | T55: SQ.M. | U55: 1 | V55: 0.5 | W55: 0.4 | X55: =IF(T55>0,"per hour","") -> per hour | Y55: =IF(T55>0,"per ","") -> per
C56: =J56*$C$2 -> 821.52778 | E56: =K56*$C$2 -> 410.76389 | G56: =L56*$C$2 -> 328.61111 | I56: SQ.M. | J56: 14 | K56: 7 | L56: 5.6 | T56: SQ.M. | U56: 14 | V56: 7 | W56: 5.6 | X56: =IF(T56>0,"per hour","") -> per hour | Y56: =IF(T56>0,"per ","") -> per
C57: =J57*$C$2 -> 528.125 | E57: =K57*$C$2 -> 264.0625 | G57: =L57*$C$2 -> 211.25 | I57: SQ.M. | J57: 9 | K57: 4.5 | L57: 3.6 | T57: SQ.M. | U57: 9 | V57: 4.5 | W57: 3.6 | X57: =IF(T57>0,"per hour","") -> per hour | Y57: =IF(T57>0,"per ","") -> per
C58: =J58*$C$2 -> 410.76389 | E58: =K58*$C$2 -> 205.38194 | G58: =L58*$C$2 -> 164.30556 | I58: SQ.M. | J58: 7 | K58: 3.5 | L58: 2.8 | T58: SQ.M. | U58: 7 | V58: 3.5 | W58: 2.8 | X58: =IF(T58>0,"per hour","") -> per hour | Y58: =IF(T58>0,"per ","") -> per
C59: =J59*$C$2 -> 0 | E59: =K59*$C$2 -> 0 | G59: =L59*$C$2 -> 0 | X59: =IF(T59>0,"per hour","") | Y59: =IF(T59>0,"per ","")
C60: =J60*$C$2 -> 0 | E60: =K60*$C$2 -> 0 | G60: =L60*$C$2 -> 0 | X60: =IF(T60>0,"per hour","") | Y60: =IF(T60>0,"per ","")
C61: =J61*$C$2 -> 46.944444 | E61: =K61*$C$2 -> 23.472222 | G61: =L61*$C$2 -> 18.777778 | I61: PC. | J61: 0.8 | K61: 0.4 | L61: 0.32 | T61: PC. | U61: 0.8 | V61: 0.4 | W61: 0.32 | X61: =IF(T61>0,"per hour","") -> per hour | Y61: =IF(T61>0,"per ","") -> per
C62: =J62*$C$2 -> 234.72222 | E62: =K62*$C$2 -> 117.36111 | G62: =L62*$C$2 -> 93.888889 | I62: PC. | J62: 4 | K62: 2 | L62: 1.6 | T62: PC. | U62: 4 | V62: 2 | W62: 1.6 | X62: =IF(T62>0,"per hour","") -> per hour | Y62: =IF(T62>0,"per ","") -> per
C63: =J63*$C$2 -> 0 | E63: =K63*$C$2 -> 0 | G63: =L63*$C$2 -> 0 | X63: =IF(T63>0,"per hour","") | Y63: =IF(T63>0,"per ","")
C64: =J64*$C$2 -> 543.38194 | E64: =K64*$C$2 -> 271.69097 | G64: =L64*$C$2 -> 217.11806 | I64: SQ.M. | J64: 9.26 | K64: 4.63 | L64: 3.7 | T64: SQ.M. | U64: 9.26 | V64: 4.63 | W64: 3.7 | X64: =IF(T64>0,"per hour","") -> per hour | Y64: =IF(T64>0,"per ","") -> per
C65: =J65*$C$2 -> 366.16667 | E65: =K65*$C$2 -> 183.08333 | G65: =L65*$C$2 -> 146.70139 | I65: SQ.M. | J65: 6.24 | K65: 3.12 | L65: 2.5 | T65: SQ.M. | U65: 6.24 | V65: 3.12 | W65: 2.5 | X65: =IF(T65>0,"per hour","") -> per hour | Y65: =IF(T65>0,"per ","") -> per
C66: =J66*$C$2 -> 543.38194 | E66: =K66*$C$2 -> 271.69097 | G66: =L66*$C$2 -> 217.11806 | I66: SQ.M. | J66: 9.26 | K66: 4.63 | L66: 3.7 | T66: SQ.M. | U66: 9.26 | V66: 4.63 | W66: 3.7 | X66: =IF(T66>0,"per hour","") -> per hour | Y66: =IF(T66>0,"per ","") -> per
C67: =J67*$C$2 -> 372.03472 | E67: =K67*$C$2 -> 183.08333 | G67: =L67*$C$2 -> 146.70139 | I67: SQ.M. | J67: 6.34 | K67: 3.12 | L67: 2.5 | T67: SQ.M. | U67: 6.34 | V67: 3.12 | W67: 2.5 | X67: =IF(T67>0,"per hour","") -> per hour | Y67: =IF(T67>0,"per ","") -> per
C68: =J68*$C$2 -> 396.68056 | E68: =K68*$C$2 -> 198.34028 | G68: =L68*$C$2 -> 158.4375 | I68: SQ.M. | J68: 6.76 | K68: 3.38 | L68: 2.7 | T68: SQ.M. | U68: 6.76 | V68: 3.38 | W68: 2.7 | X68: =IF(T68>0,"per hour","") -> per hour | Y68: =IF(T68>0,"per ","") -> per
C69: =J69*$C$2 -> 1173.6111 | E69: =K69*$C$2 -> 586.80556 | G69: =L69*$C$2 -> 469.44444 | I69: EACH | J69: 20 | K69: 10 | L69: 8 | T69: EACH | U69: 20 | V69: 10 | W69: 8 | X69: =IF(T69>0,"per hour","") -> per hour | Y69: =IF(T69>0,"per ","") -> per
C70: =J70*$C$2 -> 1408.3333 | E70: =K70*$C$2 -> 704.16667 | G70: =L70*$C$2 -> 563.33333 | I70: EACH | J70: 24 | K70: 12 | L70: 9.6 | T70: EACH | U70: 24 | V70: 12 | W70: 9.6 | X70: =IF(T70>0,"per hour","") -> per hour | Y70: =IF(T70>0,"per ","") -> per
C71: =J71*$C$2 -> 1173.6111 | E71: =K71*$C$2 -> 586.80556 | G71: =L71*$C$2 -> 469.44444 | I71: EACH | J71: 20 | K71: 10 | L71: 8 | T71: EACH | U71: 20 | V71: 10 | W71: 8 | X71: =IF(T71>0,"per hour","") -> per hour | Y71: =IF(T71>0,"per ","") -> per
C72: =J72*$C$2 -> 2934.0278 | E72: =K72*$C$2 -> 1467.0139 | G72: =L72*$C$2 -> 1173.6111 | I72: EACH | J72: 50 | K72: 25 | L72: 20 | T72: EACH | U72: 50 | V72: 25 | W72: 20 | X72: =IF(T72>0,"per hour","") -> per hour | Y72: =IF(T72>0,"per ","") -> per
C73: =J73*$C$2 -> 36.96875 | E73: =K73*$C$2 -> 18.190972 | G73: =L73*$C$2 -> 14.670139 | I73: S.F. | J73: 0.63 | K73: 0.31 | L73: 0.25 | T73: S.F. | U73: 0.63 | V73: 0.31 | W73: 0.25 | X73: =IF(T73>0,"per hour","") -> per hour | Y73: =IF(T73>0,"per ","") -> per
C74: =J74*$C$2 -> 187.77778 | E74: =K74*$C$2 -> 93.888889 | G74: =L74*$C$2 -> 75.111111 | I74: SET | J74: 3.2 | K74: 1.6 | L74: 1.28 | T74: SET | U74: 3.2 | V74: 1.6 | W74: 1.28 | X74: =IF(T74>0,"per hour","") -> per hour | Y74: =IF(T74>0,"per ","") -> per
C75: =J75*$C$2 -> 25.819444 | E75: =K75*$C$2 -> 12.909722 | G75: =L75*$C$2 -> 10.5625 | I75: B.F. | J75: 0.44 | K75: 0.22 | L75: 0.18 | T75: B.F. | U75: 0.44 | V75: 0.22 | W75: 0.18 | X75: =IF(T75>0,"per hour","") -> per hour | Y75: =IF(T75>0,"per ","") -> per
... C77: =J77*$C$2 -> 366.16667 | E77: =K77*$C$2 -> 183.08333 | G77: =L77*$C$2 -> 146.70139 | I77: SQ.M. | J77: 6.24 | K77: 3.12 | L77: 2.5 | T77: SQ.M. | U77: 6.24 | V77: 3.12 | W77: 2.5 | X77: =IF(T77>0,"per hour","") -> per hour | Y77: =IF(T77>0,"per ","") -> per
C78: =J78*$C$2 -> 0 | E78: =K78*$C$2 -> 0 | G78: =L78*$C$2 -> 0 | X78: =IF(T78>0,"per hour","") | Y78: =IF(T78>0,"per ","")
C79: =J79*$C$2 -> 0 | E79: =K79*$C$2 -> 0 | G79: =L79*$C$2 -> 0 | X79: =IF(T79>0,"per hour","") | Y79: =IF(T79>0,"per ","")
C80: =J80*$C$2 -> 195.99306 | E80: =K80*$C$2 -> 97.996528 | G80: =L80*$C$2 -> 78.631944 | I80: SQ.M. | J80: 3.34 | K80: 1.67 | L80: 1.34 | T80: SQ.M. | U80: 3.34 | V80: 1.67 | W80: 1.34 | X80: =IF(T80>0,"per hour","") -> per hour | Y80: =IF(T80>0,"per ","") -> per
C81: =J81*$C$2 -> 167.82639 | E81: =K81*$C$2 -> 83.913194 | G81: =L81*$C$2 -> 78.631944 | I81: SQ.M. | J81: 2.86 | K81: 1.43 | L81: 1.34 | T81: SQ.M. | U81: 2.86 | V81: 1.43 | W81: 1.34 | X81: =IF(T81>0,"per hour","") -> per hour | Y81: =IF(T81>0,"per ","") -> per
C82: =J82*$C$2 -> 234.72222 | E82: =K82*$C$2 -> 117.36111 | G82: =L82*$C$2 -> 93.888889 | I82: SQ.M. | J82: 4 | K82: 2 | L82: 1.6 | T82: SQ.M. | U82: 4 | V82: 2 | W82: 1.6 | X82: =IF(T82>0,"per hour","") -> per hour | Y82: =IF(T82>0,"per ","") -> per
C83: =J83*$C$2 -> 586.80556 | E83: =K83*$C$2 -> 293.40278 | G83: =L83*$C$2 -> 234.72222 | I83: SQ.M. | J83: 10 | K83: 5 | L83: 4 | T83: SQ.M. | U83: 10 | V83: 5 | W83: 4 | X83: =IF(T83>0,"per hour","") -> per hour | Y83: =IF(T83>0,"per ","") -> per
C84: =J84*$C$2 -> 1235.8125 | E84: =K84*$C$2 -> 617.90625 | G84: =L84*$C$2 -> 494.09028 | I84: SQ.M. | J84: 21.06 | K84: 10.53 | L84: 8.42 | T84: SQ.M. | U84: 21.06 | V84: 10.53 | W84: 8.42 | X84: =IF(T84>0,"per hour","") -> per hour | Y84: =IF(T84>0,"per ","") -> per
C85: =J85*$C$2 -> 510.52083 | E85: =K85*$C$2 -> 255.26042 | G85: =L85*$C$2 -> 204.20833 | I85: SQ.M. | J85: 8.7 | K85: 4.35 | L85: 3.48 | T85: SQ.M. | U85: 8.7 | V85: 4.35 | W85: 3.48 | X85: =IF(T85>0,"per hour","") -> per hour | Y85: =IF(T85>0,"per ","") -> per
C86: =J86*$C$2 -> 352.08333 | E86: =K86*$C$2 -> 176.04167 | G86: =L86*$C$2 -> 140.83333 | I86: SQ.M. | J86: 6 | K86: 3 | L86: 2.4 | T86: SQ.M. | U86: 6 | V86: 3 | W86: 2.4 | X86: =IF(T86>0,"per hour","") -> per hour | Y86: =IF(T86>0,"per ","") -> per
C87: =J87*$C$2 -> 528.125 | E87: =K87*$C$2 -> 264.0625 | G87: =L87*$C$2 -> 211.25 | I87: SQ.M. | J87: 9 | K87: 4.5 | L87: 3.6 | T87: SQ.M. | U87: 9 | V87: 4.5 | W87: 3.6 | X87: =IF(T87>0,"per hour","") -> per hour | Y87: =IF(T87>0,"per ","") -> per
C88: =J88*$C$2 -> 469.44444 | E88: =K88*$C$2 -> 234.72222 | G88: =L88*$C$2 -> 187.77778 | I88: SQ.M. | J88: 8 | K88: 4 | L88: 3.2 | T88: SQ.M. | U88: 8 | V88: 4 | W88: 3.2 | X88: =IF(T88>0,"per hour","") -> per hour | Y88: =IF(T88>0,"per ","") -> per
C89: =J89*$C$2 -> 58.680556 | E89: =K89*$C$2 -> 29.340278 | G89: =L89*$C$2 -> 23.472222 | I89: SQ.M. | J89: 1 | K89: 0.5 | L89: 0.4 | T89: SQ.M. | U89: 1 | V89: 0.5 | W89: 0.4 | X89: =IF(T89>0,"per hour","") -> per hour | Y89: =IF(T89>0,"per ","") -> per
C90: =J90*$C$2 -> 352.08333 | E90: =K90*$C$2 -> 176.04167 | G90: =L90*$C$2 -> 199.51389 | I90: SQ.M. | J90: 6 | K90: 3 | L90: 3.4 | T90: SQ.M. | U90: 6 | V90: 3 | W90: 3.4 | X90: =IF(T90>0,"per hour","") -> per hour | Y90: =IF(T90>0,"per ","") -> per
C91: =J91*$C$2 -> 234.72222 | E91: =K91*$C$2 -> 117.36111 | G91: =L91*$C$2 -> 93.888889 | I91: SQ.M. | J91: 4 | K91: 2 | L91: 1.6 | T91: SQ.M. | U91: 4 | V91: 2 | W91: 1.6 | X91: =IF(T91>0,"per hour","") -> per hour | Y91: =IF(T91>0,"per ","") -> per
... C96: =J96*$C$2 -> 83.913194 | E96: =K96*$C$2 -> 42.25 | G96: =L96*$C$2 -> 33.447917 | I96: SQ.M. | J96: 1.43 | K96: 0.72 | L96: 0.57 | T96: SQ.M. | U96: 1.43 | V96: 0.72 | W96: 0.57 | X96: =IF(T96>0,"per hour","") -> per hour | Y96: =IF(T96>0,"per ","") -> per
C97: =J97*$C$2 -> 0 | E97: =K97*$C$2 -> 0 | G97: =L97*$C$2 -> 0 | X97: =IF(T97>0,"per hour","") | Y97: =IF(T97>0,"per ","")
C98: =J98*$C$2 -> 187.77778 | E98: =K98*$C$2 -> 93.888889 | G98: =L98*$C$2 -> 75.111111 | I98: SQ.M. | J98: 3.2 | K98: 1.6 | L98: 1.28 | T98: SQ.M. | U98: 3.2 | V98: 1.6 | W98: 1.28 | X98: =IF(T98>0,"per hour","") -> per hour | Y98: =IF(T98>0,"per ","") -> per
C99: =J99*$C$2 -> 156.09028 | E99: =K99*$C$2 -> 78.045139 | G99: =L99*$C$2 -> 62.201389 | I99: SQ.M. | J99: 2.66 | K99: 1.33 | L99: 1.06 | T99: SQ.M. | U99: 2.66 | V99: 1.33 | W99: 1.06 | X99: =IF(T99>0,"per hour","") -> per hour | Y99: =IF(T99>0,"per ","") -> per
C100: =J100*$C$2 -> 234.72222 | E100: =K100*$C$2 -> 117.36111 | G100: =L100*$C$2 -> 93.888889 | I100: SQ.M. | J100: 4 | K100: 2 | L100: 1.6 | T100: SQ.M. | U100: 4 | V100: 2 | W100: 1.6 | X100: =IF(T100>0,"per hour","") -> per hour | Y100: =IF(T100>0,"per ","") -> per
C101: =J101*$C$2 -> 625.53472 | E101: =K101*$C$2 -> 312.76736 | G101: =L101*$C$2 -> 249.97917 | I101: SQ.M. | J101: 10.66 | K101: 5.33 | L101: 4.26 | T101: SQ.M. | U101: 10.66 | V101: 5.33 | W101: 4.26 | X101: =IF(T101>0,"per hour","") -> per hour | Y101: =IF(T101>0,"per ","") -> per
C102: =J102*$C$2 -> 700.64583 | E102: =K102*$C$2 -> 350.32292 | G102: =L102*$C$2 -> 280.49306 | I102: SQ.M. | J102: 11.94 | K102: 5.97 | L102: 4.78 | T102: SQ.M. | U102: 11.94 | V102: 5.97 | W102: 4.78 | X102: =IF(T102>0,"per hour","") -> per hour | Y102: =IF(T102>0,"per ","") -> per
C103: =J103*$C$2 -> 0 | E103: =K103*$C$2 -> 0 | G103: =L103*$C$2 -> 0 | X103: =IF(T103>0,"per hour","") | Y103: =IF(T103>0,"per ","")
C104: =J104*$C$2 -> 0 | E104: =K104*$C$2 -> 0 | G104: =L104*$C$2 -> 0 | X104: =IF(T104>0,"per hour","") | Y104: =IF(T104>0,"per ","")
C105: =J105*$C$2 -> 0 | E105: =K105*$C$2 -> 0 | G105: =L105*$C$2 -> 0 | X105: =IF(T105>0,"per hour","") | Y105: =IF(T105>0,"per ","")
C106: =J106*$C$2 -> 126.75 | E106: =K106*$C$2 -> 63.375 | G106: =L106*$C$2 -> 50.465278 | I106: SQ.M. | J106: 2.16 | K106: 1.08 | L106: 0.86 | T106: SQ.M. | U106: 2.16 | V106: 1.08 | W106: 0.86 | X106: =IF(T106>0,"per hour","") -> per hour | Y106: =IF(T106>0,"per ","") -> per
...

Sheet EST. SHEET
A1: UNIT COST DERIVATION FORM
A3: PROJECT TITLE:
A4: LOCATION:
A5: ITEM NO. | C5: ITEM OF WORK:
A6: ESTIMATED QUANTITIES: | C6: UNIT:
A7: A. | B7: MATERIALS:
B8: DESCRIPTION | C8: QTY. | D8: UNIT | E8: UNIT COST | F8: AMOUNT
A24: B. | B24: LABOR/MANPOWER:
A25: NO. | B25: DESCRIPTION | C25: NO. | D25: NO.-DAYS | E25: DAILY RATE | F25: AMOUNT
A38: C. | B38: EQUIPMENT/TOOLS:
A39: NO. | B39: DESCRIPTION | C39: NO. | D39: NO.-DAYS | E39: HOURLY RATE | F39: AMOUNT
A56: D | B56: TOTAL DIRECT COST (A+B+C)
A57: E | B57: O.C.M. (% of D)
A58: F | B58: CONTRACTIRS PROFIT (% OF D)
A59: G | B59: VAT (10% Oof B+C)
A60: H | B60: TOTAL COST (D+E+F+G)
A61: I | B61: UNIT COST ( DIRECT)

Sheet EQUIPMENT
A1: PROBABLE OUTPUT OF HEAVY EQUIPMENT
B3: EQUIPMENT | C3: PROBABLE OUTPUT
G5: Clearing & Grubbing | H5: Lot Grading (Cut & Fill) m3 | J5: Trench Excavation | L5: Disposal of Unsuitable Materials m3-km | N5: Road way Excavation (m3) | P5: Embankment/Imported Backfill (m3) | R5: Subgrade Preparation (m2) | T5: Aggregate Sub-base Course (m3) | V5: Aggregate Base Course (m3) | X5: Bituminous Asphalt Pavement (MT) | Z5: Concrete Pavement (m3)
A6: A.1 | B6: EXCAVATOR 200
B7: Excavation | C7: 45 | D7: cu.m./hr. | E7: =1/C7 -> 0.022222222 | F7: hr/m³
B8: Clearing & Grubbing | C8: 150 | D8: sq.m./hr | E8: =1/C8 -> 0.0066666667 | F8: hr/m²
A9: A.1 | B9: DOZER 165 HP
B10: Cutting & Stockpiling | C10: 30 | D10: cu.m./hr. | E10: =1/C10 -> 0.033333333 | F10: hr/m³
B11: Clearing & Grubbing | C11: 300 | D11: sq.m./hr | E11: =1/C11 -> 0.0033333333 | F11: hr/m²
A12: A.2 | B12: DOZER D65P-7 | G12: 300 | H12: 30 | I12: m3/hr | N12: 29.41 | O12: m3/hr
B13: Stripping | C13: 200 | D13: sq.m./hr | E13: =1/C13 -> 0.005 | F13: hr/m²
B14: Excavation | C14: 25 | D14: cu.m./hr. | E14: =1/C14 -> 0.04 | F14: hr/m³
B15: Quarrying | C15: 50 | D15: cu.m./hr. | E15: =1/C15 -> 0.02 | F15: hr/m³
B16: Pushing | C16: 3 | D16: sq.m./hr | E16: =1/C16 -> 0.33333333 | F16: hr/m²
A18: B.1 | B18: LOADER -1.91 CU.M.
B19: Loading | C19: 70 | D19: cu.m./hr. | E19: =1/C19 -> 0.014285714 | F19: hr/m³ | L19: 125 | M19: m3/hr
A20: B.2 | B20: LOADER 950 | H20: 232.55 | I20: m3/hr
A22: C. | B22: DUMP TRUCK - 10 CU.M. | H22: 232.55 | I22: m3/hr | L22: 125 | M22: m3/hr
B23: Hauling (dist. = 600M) | C23: 90 | D23: cu.m./hr. | E23: =1/C23 -> 0.011111111 | F23: hr/m³
A25: D. | B25: GRADER- 130G | H25: 384.62 | I25: m3/hr | P25: 142.86 | Q25: m3/hr | R25: 769.23 | S25: sq.m./hr | T25: 76.92 | U25: m3/hr | V25: 115.38 | W25: m3/hr
B26: 10 Passes | C26: 700 | D26: sq.m./hr | E26: =1/C26 -> 0.0014285714 | F26: hr/m²
B27: Subgrading | C27: 300 | D27: sq.m./hr | E27: =1/C27 -> 0.0033333333 | F27: hr/m²
B28: Spreading | C28: 40 | D28: cu.m./hr. | E28: =1/C28 -> 0.025 | F28: hr/m³
A30: E.1 | B30: ROLLER VIBRATORY | T30: 58.82 | U30: m3/hr | V30: 88.23 | W30: m3/hr | X30: 65 | Y30: MT/hr
B31: 10 Passes | C31: 600 | D31: sq.m./hr | E31: =1/C31 -> 0.0016666667 | F31: hr/m²
B32: SHEETS FOOT ROLLER
B33: Static Rolling 12 passes-15m3 lift
B34: Vibratory Rolling-4 pases-15m3 lift | C34: 135 | D34: cu.m./hr. | E34: =1/C34 -> 0.0074074074 | F34: hr/m³
B35: No.3W Road Roller-static rolling
B36: 4 passes-15 m3 lift | C36: 24 | D36: cu.m./hr. | E36: =1/C36 -> 0.041666667 | F36: hr/m³
B37: Tractor Drawn Roller (1-d)
B38: Static Rolling 6 passes-20m3 lift | C38: 240 | D38: cu.m./hr. | E38: =1/C38 -> 0.0041666667 | F38: hr/m³
B39: Tandem Roller-static rolling
B40: 6 passes-20 m3 lift | C40: 24 | D40: cu.m./hr. | E40: =1/C40 -> 0.041666667 | F40: hr/m³
A42: E.2 | B42: VIBRATORY COMPACTOR CA25D | H42: 303.03 | I42: m3/hr | P42: 125 | Q42: m3/hr | R42: 588.23 | S42: sq.m./hr
A44: G. | B44: WATER TRUCK - 10 CU.M. | H44: 769.23 | I44: m3/hr | P44: 333.33 | Q44: m3/hr | R44: 1666.67 | S44: sq.m./hr | T44: 166.67 | U44: m3/hr | V44: 250 | W44: m3/hr
B45: Watering | C45: 1600 | D45: sq.m./hr | E45: =1/C45 -> 0.000625 | F45: hr/m²
B47: ASPHALT PAVER | X47: 32.5 | Y47: MT/hr
B48: ASPHALT DISTRIBUTOR | C48: SPRAYING PHALT | X48: 300 | Y48: SQ.M.
B49: PLATE COMPACTOR
B50: Grave Bedding | C50: 8 | D50: cu.m./hr. | E50: =1/C50 -> 0.125 | F50: hr/m³
B51: Concrete Vibrator:
B52: Vibrating Concrete | C52: 40 | D52: cu.m./hr. | E52: =1/C52 -> 0.025 | F52: hr/m³
X63: Asphalt prime coat, SS-1 (.042 drum/mt) | Y63: drums
X65: Note:1MT of asphalt conc. Covers 8 m2
X66: of pavement 2" thick or 0.43 m3 of asphalt
X67: concrete
X68: Coverage = 2.33 MT/CM
X69: Bitumil = 0.70 ltr/sq, 200 ltr/drum

Sheet BONUS DATA - STEEL ERECTION
A1: A. | B1: STRIPPING OF METAL FORMS
B3: MANHOURS PER SQ. METER OF CONTACT AREA
C4: WOOD SHORES 215 TO 316 FLOORS
C5: FORM HEIGHT | E5: LOW | F5: AVERAGE | G5: HIGH
C6: (METER)
C7: 3 TO 4 | E7: 0.58 | F7: 0.22 | G7: 0.16
C8: 4 TO 5 | E8: 0.59 | F8: 0.23 | G8: 0.16
C9: 5 TO 6 | E9: 0.6 | F9: 0.23 | G9: 0.17
C10: 6 TO 7 | E10: 0.61 | F10: 0.24 | G10: 0.17
C11: 7 TO 8 | E11: 0.64 | F11: 0.25 | G11: 0.18
C13: WOOD SHORES 368 TO 419 FLOORS
C14: 3 TO 4 | E14: 0.6 | F14: 0.23 | G14: 0.17
C15: 4 TO 5 | E15: 0.61 | F15: 0.24 | G15: 0.17
C16: 5 TO 6 | E16: 0.64 | F16: 0.25 | G16: 0.18
C17: 6 TO 7 | E17: 0.66 | F17: 0.25 | G17: 0.18
C18: 7 TO 8 | E18: 0.68 | F18: 0.26 | G18: 0.19
B20: CREW: | H20: TOOLS:
B21: 1 | C21: CARPENTER LEAD MAN | E21: 8 | H21: ONE LOT CARPENTRY TOOLS
B22: 3 | C22: CARPENTERS | E22: 24 | H22: 8 | I22: TOOLS HOUR
B23: 6 | C23: HELPERS | E23: 48
B24: =SUM(B21:B23) -> 10 | C24: MANDAYS | E24: =SUM(E21:E23) -> 80 | F24: MANHOURS
A27: B. | B27: STEEL ERECTION FOR MULTI STOREY BUILDING FRAME
B28: PREFAB SECTIONS, HIGHLY MECHANIZED OPERATION
C30: MANHOURS & EQUIPMENTHOUR PER TON ERECTED:
E32: MAN-HOURS | I32: EQUIPMENT-HOURS
E33: LOW | F33: AVERAGE | G33: HIGH | I33: LOW | J33: AVERAGE | K33: HIGH
B34: MEDIUM FRAME | E34: 36 | F34: 13.85 | G34: 10 | I34: 7 | J34: 2.69 | K34: 1.94
B35: HEAVY FRAME | E35: 32.73 | F35: 12.63 | G35: 9.11 | I35: 6.36 | J35: 2.46 | K35: 1.77
B36: STEEL JOIST | E36: 40 | F36: 15.37 | G36: 11.08 | I36: 7.78 | J36: 2.98 | K36: 2.15
B38: CREW: | H38: TOOLS:
B39: 1 | C39: LEAD MAN | E39: 8 | H39: 0.5 | I39: TOWER CRANE | L39: =H39*8 -> 4
B40: 4 | C40: RIGGERS | E40: =B40*8 -> 32 | H40: 2 | I40: WELDING TRANSFORMER | L40: =H40*8 -> 16
B41: 4 | C41: FITTERS | E41: =B41*8 -> 32 | H41: 1 | I41: LOT TOOLS | L41: =H41*8 -> 8
B42: 2 | C42: WELDERS | E42: =B42*8 -> 16 | H42: =SUM(H39:H41) -> 3.5 | L42: =SUM(L39:L41) -> 28 | M42: TOOL HOURS
B43: 1 | C43: CRANE OPERATOR | E43: =B43*8 -> 8
B44: 6 | C44: HELPERS | E44: =B44*8 -> 48
B45: =SUM(B39:B44) -> 18 | C45: MANDAYS | E45: =SUM(E39:E44) -> 144 | F45: MANHOURS
B47: MATERIALS : A36 WELDED CONNECTION
A51: C. | B51: STEEL ERECTION FOR COMMERCIAL AND MILL BUILDING FRAME
B52: PREFAB SECTIONS, HIGHLY MECHANIZED OPERATION
C54: MANHOURS & EQUIPMENTHOUR PER TON ERECTED:
E56: MAN-HOURS | I56: EQUIPMENT-HOURS
E57: LOW | F57: AVERAGE | G57: HIGH | I57: LOW | J57: AVERAGE | K57: HIGH
B59: COMMERCIAL TYPE BUILDING:
B60: LIGHT FRAME | E60: 46.67 | F60: 18.06 | G60: 13.02 | I60: 18.33 | J60: 7.1 | K60: 5.12
B61: MEDIUM FRAME | E61: 40 | F61: 15.56 | G61: 11.2 | I61: 15.71 | J61: 6.11 | K61: 4.4
B62: HEAVY FRAME | E62: 35 | F62: 13.33 | G62: 9.66 | I62: 13.75 | J62: 5.24 | K62: 3.79
B63: STEEL JOIST | E63: 43.08 | F63: 16.47 | G63: 11.91 | I63: 16.92 | J63: 6.47 | K63: 4.68
B66: MILL TYPE BUILDING:
B67: LIGHT FRAME | E67: 35 | F67: 13.33 | G67: 9.66 | I67: 13.75 | J67: 5.24 | K67: 3.79
B68: MEDIUM FRAME | E68: 31.11 | F68: 11.91 | G68: 8.62 | I68: 12.22 | J68: 4.68 | K68: 3.38
B69: HEAVY FRAME | E69: 35 | F69: 10.77 | G69: 7.78 | I69: 13.75 | J69: 4.23 | K69: 3.06
B70: STEEL JOIST | E70: 32.94 | F70: 12.27 | G70: 9.18 | I70: 12.94 | J70: 5 | K70: 3.61
B72: CREW: | H72: TOOLS:
B73: 1 | C73: LEAD MAN | E73: 8 | H73: 0.5 | I73: 20 TON TOWER CRANE | L73: =H73*8 -> 4
B74: 2 | C74: RIGGERS | E74: =B74*8 -> 16 | H74: 2 | I74: WELDING TRANSFORMER | L74: =H74*8 -> 16
B75: 4 | C75: FITTERS | E75: =B75*8 -> 32 | H75: 2 | I75: CUTTING OUTFIT | L75: =H75*8 -> 16
B76: 2 | C76: WELDERS | E76: =B76*8 -> 16 | H76: 1 | I76: LOT TOOLS | L76: =H76*8 -> 8
B77: 1 | C77: CRANE OPERATOR | E77: =B77*8 -> 8 | H77: =SUM(H73:H76) -> 5.5 | I77: EQPT. DAYS | L77: =SUM(L73:L76) -> 44 | M77: EQPT. HOURS
B78: 4 | C78: HELPERS | E78: =B78*8 -> 32
B79: =SUM(B73:B78) -> 14 | C79: MANDAYS | E79: =SUM(E73:E78) -> 112 | F79: MANHOURS
B81: MATERIALS : A36 WELDED CONNECTION
