Workbook

Sheet Estimate
A1: Project Title: | C1: PROPOSED CONSTRUCTION OF TWO STOREY RESIDENTIAL/APARTMENT BUILDING.
A2: Location: | C2: Maganay, Buug, Zamboanga Sibugay | K2: Budget | L2: 1200000 | O2: No window grilles
A3: Date: | K3: Matls Markup | L3: 0 | M3: =E430 -> 857193.83 | O3: No boulders
A4: DETAILED ESTIMATE | K4: Hauling Rate | L4: 0.01 | M4: =H430 -> 7840.205 | O4: Septic Tank at 1.50m x 3.00m
A5: ITEM NO. | B5: ITEM DESCRIPTION | F5: QTY | G5: UNIT | H5: UNIT PRICE | I5: AMOUNT | K5: Labor Rate | L5: 0.3 | M5: =F430 -> 246942.15
K6: EDC | L6: =ABC!G33 -> 1220214.3
A7: I. | B7: LAYOUT AND EXCAVATION | F7: =F10+F11+F12 -> 58.68 | G7: cu.m of excavation | K7: OCM | L7: =5%+0.5%+0.5% -> 0.06
B8: Scope of Work: | K8: Contr Profit | L8: 0.1
C9: 1. Includes clearing, layout, and excavation works for: | K9: Indirect Cost | L9: =ABC!N33 -> 266006.71
C10: a. Wall and Zoccalo Footings | F10: 10.68 | K10: TOTAL | L10: =ABC!O33 -> 1486221
C11: b. Column Footings | F11: 21
C12: c. Septic Tank | F12: 27
B13: Labor:
C14: Excavation works | F14: =F7 -> 58.68 | G14: cu.m | H14: 200 | I14: =H14*F14 -> 11736
B15: Materials:
C16: Assorted Form Lumber | F16: =2*2*10/12*50 -> 166.66667 | G16: bd.ft | H16: 23 | I16: =H16*F16 -> 3833.3333
C17: Assorted CW Nails | F17: 3 | G17: kgs | H17: 80 | I17: =H17*F17 -> 240
C18: Nylon Chord | F18: 3 | G18: rolls | H18: 50 | I18: =H18*F18 -> 150
H20: Material Cost | I20: =SUM(I16:I18) -> 4223.3333
H21: Labor Cost | I21: =I14 -> 11736
H22: Total Cost | I22: =I20+I21 -> 15959.333
A23: II. | B23: EMBANKMENT WORKS | F23: 14 | G23: cu.m
B24: Scope of Work:
C25: 1. Embankment for buildable areas
C26: 2. Backfilling Works
B28: Materials:
C29: Filling Materials - to elevate the buildable area by 0.20m | F29: =F23 -> 14 | G29: cu.m | H29: 250 | I29: =H29*F29 -> 3500
H31: Material Cost | I31: =SUM(I29:I30) -> 3500
H32: ="Hauling/Handling Cost "&TEXT(L$4,"#%")&" of MC" -> Hauling/Handling Cost 1% of MC | I32: =L$4*I31 -> 35
H33: ="Labor Cost "&TEXT(L$5,"#%")&" of MC" -> Labor Cost 30% of MC | I33: =L$5*I31 -> 1050
H34: Total Cost | I34: =I31+I32+I33 -> 4585
A35: III. | B35: REINFORCED CONCRETE WORKS | G35: cu.m concrete
B36: Scope of Work:
B37: 1. Construction of reinforced concrete works system with deformed bars layout arranged according to structural plans
B38: and specification, includes the following:
B39: a. | C39: Column Footings
B40: b. | C40: Columns
B41: c. | C41: Floor Slabs on Grade - all areas includ. Porch, Back Exit Landing, Ramp
C42: Slab thickness shall be 0.10m with temperature bars spaced 0.60m bothways on top of gravel bed throughout.
B43: NOTE: | C43: Finishing of Ramp with horizontal grooves every 10 cm along entire length
B44: d. | C44: Roof Beams
B45: e. | C45: Lavatory Counters
B46: f. | C46: Lintel Beam
B47: NOTE: | C47: Use Grade 40 Reinforcing Steel and 28 days curing period for concrete.
C48: All column footings shall be laid with boulders underneath, tampered thoroughly to compact soil.
C49: This item includes cement-plastering of all exposed surfaces of columns, beams,and stiffeners.
B50: Materials:
C51: Portland Cement | F51: 103 | G51: bags | H51: =L61 -> 265 | I51: =H51*F51 -> 27295
C52: Sand | F52: 5.75 | G52: cu.m | H52: 950 | I52: =H52*F52 -> 5462.5
C53: Gravel | F53: 11.5 | G53: cu.m | H53: 950 | I53: =H53*F53 -> 10925
C54: GI Tie Wire #16 | F54: 22 | G54: kgs | H54: =CEILING(L64,0.5) -> 67 | I54: =H54*F54 -> 1474 | K54: =6.8+8+6.8+8+6.8 -> 36.4
C55: Deformed Bar 10mmØ x 6m | F55: 273 | G55: lgths | H55: =CEILING(L65,0.5) -> 154.5 | I55: =H55*F55 -> 42178.5
C56: Deformed Bar 12mmØ x 6m | F56: 36 | G56: lgths | H56: =CEILING(L66,0.5) -> 223.5 | I56: =H56*F56 -> 8046
C57: Deformed Bar 16mmØ x 6m (for columns and footings only) | F57: 45 | G57: lgths | H57: =CEILING(L67,0.5) -> 396 | I57: =H57*F57 -> 17820
C58: Hacksaw Blade | F58: 3 | G58: pcs | H58: =CEILING(L68,0.5) -> 55 | I58: =H58*F58 -> 165
H60: Material Cost | I60: =SUM(I51:I59) -> 113366
H61: ="Hauling/Handling Cost "&TEXT(L$4,"#%")&" of MC" -> Hauling/Handling Cost 1% of MC | I61: =L$4*I60 -> 1133.66 | K61: 255 | L61: =K61*(1+L$3)+10 -> 265 | N61: Portland Cement | O61: 128
H62: ="Labor Cost "&TEXT(L$5,"#%")&" of MC" -> Labor Cost 30% of MC | I62: =L$5*I60 -> 34009.8 | K62: 900 | L62: =K62*(1+L$3) -> 900 | N62: Sand | O62: 8.5
H63: Total Cost | I63: =I60+I61+I62 -> 148509.46 | K63: 900 | L63: =K63*(1+L$3) -> 900 | N63: Gravel | O63: 12
A64: IV. | B64: MASONRY WORKS | G64: sq.m (net) | K64: 58 | L64: =K64*(1+L$3)+8.7 -> 66.7 | N64: GI Tie Wire #16 | O64: 16
B65: Scope of Work: | K65: 134 | L65: =K65*(1+L$3)+20.1 -> 154.1 | N65: Deformed Bar 10mmø x 6m | O65: 113
B66: 1. Construction of wall/zocallo footing with deformed bars arranged according to structural plans and specification: | K66: 194 | L66: =K66*(1+L$3)+29.1 -> 223.1 | N66: Deformed Bar 12mmø x 6m | O66: 23
B67: a. | C67: Wall Footing - 0.30m x 0.15m x 40 lin.m | F67: =(0.3*0.15)*40 -> 1.8 | G67: cu.m | K67: 344 | L67: =K67*(1+L$3)+51.6 -> 395.6 | N67: Deformed Bar 16mmø x 6m | O67: 52
B68: b. | C68: Zocallo Footing - 0.30m x 0.10m x 14.10 lin.m | F68: =(0.3*0.1)*14.1 -> 0.423 | G68: cu.m | K68: 55 | L68: =K68*(1+L$3) -> 55 | N68: Hacksaw Blade | O68: 3
B69: 2. Erecting of CHB walls/zocallo - 135.51 sq.m net area | L69: s
B70: 3. Cement-plastering smooth-finish of all exposed concrete walls and window jambs - 210.98 sq.m net area
B71: NOTE: | C71: Plastering and finishing of concrete surfaces includes fashioning of exterior window mouldings and window sill rabbets.
B73: Materials:
C74: Portland Cement | F74: 204 | G74: bags | H74: =L84 -> 265 | I74: =H74*F74 -> 54060
C75: Sand | F75: 8 | G75: cu.m | H75: =CEILING(L85,0.5) -> 900 | I75: =H75*F75 -> 7200
C76: Gravel | F76: 2.25 | G76: cu.m | H76: =CEILING(L86,0.5) -> 900 | I76: =H76*F76 -> 2025
C77: Fine Sand | F77: 3.5 | G77: cu.m | H77: 1200 | I77: =H77*F77 -> 4200 | K77: =6.8*2+8*2+3.7+2.9+2.6+1.65+1.9+3.7+3.2 -> 49.25 | L77: =6.8*2+8*2+2.45+2.9+1.65 -> 36.6 | N77: All concrete hollow blocks shall be laid plumb and true to line.
C78: GI Tie Wire #16 | F78: =4.5+2 -> 6.5 | G78: kgs | H78: =CEILING(L88,0.5) -> 67 | I78: =H78*F78 -> 435.5 | K78: =(2.2+2)+(1.6+4)+(1.1+1.8) -> 12.7 | N78: Joint fillers and mortar for block laying shall be concrete of the class “B”, with ratio 1:3.
C79: Deformed Bar 10mmØ x 6m | F79: 16 | G79: lgths | H79: =CEILING(L89,0.5) -> 154.5 | I79: =H79*F79 -> 2472 | N79: All walls shall be provided with vertical and horizontal bars tied and securely anchored at the foundation.
C80: Deformed Bar 12mmØ x 6m | F80: 116 | G80: lgths | H80: =CEILING(L90,0.5) -> 223.5 | I80: =H80*F80 -> 25926
C81: Hacksaw Blade | F81: 1 | G81: pcs | H81: =CEILING(L91,0.5) -> 55 | I81: =H81*F81 -> 55
C82: Concrete Hollow Block 4" x 8" x 16" | F82: 1494 | G82: pcs | H82: =CEILING(L92,0.5) -> 14 | I82: =H82*F82 -> 20916
C83: Concrete Hollow Block 6" x 8" x 16" | F83: 284 | G83: pcs | H83: 18 | I83: =H83*F83 -> 5112 | O83: 49.25 lin.m
K84: 255 | L84: =K84*(1+L$3)+10 -> 265 | N84: Portland Cement | O84: 244
H85: Material Cost | I85: =SUM(I74:I84) -> 122401.5 | K85: 900 | L85: =K85*(1+L$3) -> 900 | N85: Sand | O85: 18
H86: ="Hauling/Handling Cost "&TEXT(L$4,"#%")&" of MC" -> Hauling/Handling Cost 1% of MC | I86: =L$4*I85 -> 1224.015 | K86: 900 | L86: =K86*(1+L$3) -> 900 | N86: Gravel | O86: 3
H87: ="Labor Cost "&TEXT(L$5,"#%")&" of MC" -> Labor Cost 30% of MC | I87: =L$5*I85 -> 36720.45
H88: Total Cost | I88: =I85+I86+I87 -> 160345.96 | K88: 58 | L88: =K88*(1+L$3)+8.7 -> 66.7 | N88: GI Tie Wire #16 | O88: 6.5
A89: V. | B89: CARPENTRY WORKS | G89: sq.m ceiling area | K89: 134 | L89: =K89*(1+L$3)+20.1 -> 154.1 | N89: Deformed Bar 10mmø x 6m | O89: 125
B90: Scope of Work: | K90: 194 | L90: =K90*(1+L$3)+29.1 -> 223.1 | N90: Deformed Bar 12mmø x 6m | O90: 17
C91: 1. Installation of Interior and Exterior Ceilings | K91: 55 | L91: =K91*(1+L$3) -> 55 | N91: Hacksaw Blade | O91: 1
C92: 2. Installation of Ceiling Air Ventilation | K92: 14 | L92: =K92*(1+L$3) -> 14 | N92: Concrete Hollow Block 4" x 8" x 12" | O92: 1832
C93: 3. Formworks and Scaffoldings
B95: Materials:
B96: CEILING BOARDS AND JOISTS FOR INTERIOR AND EXTERIOR CEILING - 96.80 sq.m
C97: HardiLite Fiber-Cement Board 3.5mm x 4' x 8' | F97: 47 | G97: shts | H97: =CEILING(L108,0.5) -> 368 | I97: =H97*F97 -> 17296 | R97: 6
C98: Metal Furring Double 0.400mm x 3/4" x 2" x 5m | F98: 43 | G98: lgths | H98: =CEILING(L109,0.5) -> 135 | I98: =H98*F98 -> 5805 | R98: 6
C99: Carrying Channel 0.400mm x 3/4" x 2" x 5m | F99: 37 | G99: lgths | H99: =CEILING(L110,0.5) -> 155 | I99: =H99*F99 -> 5735
C100: Metal Wall Angle 0.400mm x 1" x 1" x 8' | F100: 53 | G100: lgths | H100: =CEILING(L111,0.5) -> 65 | I100: =H100*F100 -> 3445
C101: W-Clip | F101: 250 | G101: pcs | H101: =CEILING(L112,0.5) -> 5 | I101: =H101*F101 -> 1250
C102: Scoring Knife | F102: 1 | G102: pcs | H102: =CEILING(L113,0.5) -> 139 | I102: =H102*F102 -> 139
C103: Hacksaw Blade | F103: 3 | G103: pcs | H103: =CEILING(L114,0.5) -> 55 | I103: =H103*F103 -> 165
C104: Alum. Blind Rivets 1/8" x 3/8" | F104: 1200 | G104: pcs | H104: =CEILING(L115,0.5) -> 1 | I104: =H104*F104 -> 1200
C105: Ficem Screw 1" | F105: 585 | G105: pcs | H105: =CEILING(L116,0.5) -> 1.5 | I105: =H105*F105 -> 877.5
C106: Concrete Nail 1" | F106: 2 | G106: kgs | H106: =CEILING(L117,0.5) -> 60 | I106: =H106*F106 -> 120
...

Sheet Sheet2

Sheet ABC
A1: Republic of the Philippines
A2: DEPARTMENT OF HEALTH | R2: 2 copies Detailed Estimate (File, COA)
A3: REGIONAL OFFICE IX | R3: 1 copy BOQ
A4: Upper Calarian, Zamboanga City 7000 | R4: 3 copies ABC (File, BAC, COA)
A5: Phone : (062) 983-0314, (062) 983-0416, Fax : (062) 991-3380 | R5: 3 copies PERT-CPM (File, BAC, COA)
A6: Email : dohchdzp@yahoo.com, Web : www.doh.gov.ph | R6: 3 copies Scope of Work (File, BAC, COA)
A8: APPROVED BUDGET FOR THE CONTRACT
A10: =Estimate!C1 -> PROPOSED CONSTRUCTION OF TWO STOREY RESIDENTIAL/APARTMENT BUILDING.
A11: =Estimate!C2 -> Maganay, Buug, Zamboanga Sibugay
A12: Type of Facility : Barangay Health Station (BHS)
A13: Floor Area : 54.40 sq.m | O13: Contract Duration: | P13: 150 C.D.
A14: ITEM NO. | B14: DESCRIPTION | E14: QUANTITY | F14: UNIT | G14: ESTIMATED DIRECT COST | H14: MARKUPS IN PERCENT | J14: TOTAL MARKUP | L14: VAT | N14: TOTAL INDIRECT COST | O14: TOTAL COST | P14: UNIT COST
H15: OCM | I15: PROFIT | J15: % | K15: VALUE
A16: (1) | B16: (2) | E16: (3) | F16: (4) | G16: (5) | H16: (6) | I16: (7) | J16: (8) | K16: (9) | L16: (10) | N16: (11) | O16: (12) | P16: (13)
H17: =Estimate!L7 -> 0.06 | I17: =Estimate!L8 -> 0.1 | J17: (6) + (7) | K17: (5) x (8) | L17: 0.05 | M17: [(5)+(9)] | N17: (9) + (10) | O17: (5) + (11) | P17: (12) / (3)
A18: I | B18: LAYOUT AND EXCAVATION | E18: =20.002+10.53 -> 30.532 | F18: cu.m | G18: =Estimate!I22 -> 15959.333 | H18: =H$17 -> 0.06 | I18: =I$17 -> 0.1 | J18: =SUM(H18:I18) -> 0.16 | K18: =G18*J18 -> 2553.4933 | L18: =(G18+K18)*0.05 -> 925.64133 | N18: =SUM(K18+L18) -> 3479.1347 | O18: =G18+N18 -> 19438.468 | P18: =O18/E18 -> 636.65885
A19: II | B19: EMBANKMENT WORKS | E19: =ROUNDUP(8*6.8*(0.4),0) -> 22 | F19: cu.m | G19: =Estimate!I34 -> 4585 | H19: =H$17 -> 0.06 | I19: =I$17 -> 0.1 | J19: =SUM(H19:I19) -> 0.16 | K19: =G19*J19 -> 733.6 | L19: =(G19+K19)*0.05 -> 265.93 | N19: =SUM(K19+L19) -> 999.53 | O19: =G19+N19 -> 5584.53 | P19: =O19/E19 -> 253.84227
A20: III | B20: REINFORCED CONCRETE WORKS | E20: 11.43 | F20: cu.m | G20: =Estimate!I63 -> 148509.46 | H20: =H$17 -> 0.06 | I20: =I$17 -> 0.1 | J20: =SUM(H20:I20) -> 0.16 | K20: =G20*J20 -> 23761.514 | L20: =(G20+K20)*0.05 -> 8613.5487 | N20: =SUM(K20+L20) -> 32375.062 | O20: =G20+N20 -> 180884.52 | P20: =O20/E20 -> 15825.418
A21: IV | B21: MASONRY WORKS | E21: 135.54 | F21: sq.m | G21: =Estimate!I88 -> 160345.96 | H21: =H$17 -> 0.06 | I21: =I$17 -> 0.1 | J21: =SUM(H21:I21) -> 0.16 | K21: =G21*J21 -> 25655.354 | L21: =(G21+K21)*0.05 -> 9300.066 | N21: =SUM(K21+L21) -> 34955.42 | O21: =G21+N21 -> 195301.39 | P21: =O21/E21 -> 1440.9133
A22: V | B22: CARPENTRY WORKS | E22: 96.8 | F22: sq.m | G22: =Estimate!I123 -> 82234.595 | H22: =H$17 -> 0.06 | I22: =I$17 -> 0.1 | J22: =SUM(H22:I22) -> 0.16 | K22: =G22*J22 -> 13157.535 | L22: =(G22+K22)*0.05 -> 4769.6065 | N22: =SUM(K22+L22) -> 17927.142 | O22: =G22+N22 -> 100161.74 | P22: =O22/E22 -> 1034.7287
A23: VI | B23: DOORS AND WINDOWS | E23: 14 | F23: job orders | G23: =Estimate!I144 -> 68950 | H23: =H$17 -> 0.06 | I23: =I$17 -> 0.1 | J23: =SUM(H23:I23) -> 0.16 | K23: =G23*J23 -> 11032 | L23: =(G23+K23)*0.05 -> 3999.1 | N23: =SUM(K23+L23) -> 15031.1 | O23: =G23+N23 -> 83981.1 | P23: =O23/E23 -> 5998.65
A24: VII | B24: STEEL WORKS AND SIGNAGE | E24: 1 | F24: lot | G24: =Estimate!I178 -> 83208.58 | H24: =H$17 -> 0.06 | I24: =I$17 -> 0.1 | J24: =SUM(H24:I24) -> 0.16 | K24: =G24*J24 -> 13313.373 | L24: =(G24+K24)*0.05 -> 4826.0976 | N24: =SUM(K24+L24) -> 18139.47 | O24: =G24+N24 -> 101348.05 | P24: =O24/E24 -> 101348.05
A25: VIII | B25: ROOFING WORKS | E25: 98.56 | F25: lin.m | G25: =Estimate!I197 -> 102247.46 | H25: =H$17 -> 0.06 | I25: =I$17 -> 0.1 | J25: =SUM(H25:I25) -> 0.16 | K25: =G25*J25 -> 16359.594 | L25: =(G25+K25)*0.05 -> 5930.353 | N25: =SUM(K25+L25) -> 22289.947 | O25: =G25+N25 -> 124537.41 | P25: =O25/E25 -> 1263.5695
A26: IX | B26: TILE WORKS | E26: 77.34 | F26: sq.m | G26: =Estimate!I226 -> 242972.25 | H26: =H$17 -> 0.06 | I26: =I$17 -> 0.1 | J26: =SUM(H26:I26) -> 0.16 | K26: =G26*J26 -> 38875.56 | L26: =(G26+K26)*0.05 -> 14092.391 | N26: =SUM(K26+L26) -> 52967.95 | O26: =G26+N26 -> 295940.2 | P26: =O26/E26 -> 3826.4831
A27: X | B27: SEPTIC TANK | E27: =1.5*3*1.8+1.2*1.2*1.5 -> 10.26 | F27: cu.m | G27: =Estimate!I251 -> 30023.89 | H27: =H$17 -> 0.06 | I27: =I$17 -> 0.1 | J27: =SUM(H27:I27) -> 0.16 | K27: =G27*J27 -> 4803.8224 | L27: =(G27+K27)*0.05 -> 1741.3856 | N27: =SUM(K27+L27) -> 6545.208 | O27: =G27+N27 -> 36569.098 | P27: =O27/E27 -> 3564.2396
A28: XI | B28: ELECTRICAL WORKS | E28: 3 | F28: circuits | G28: =Estimate!I301 -> 96068.85 | H28: =H$17 -> 0.06 | I28: =I$17 -> 0.1 | J28: =SUM(H28:I28) -> 0.16 | K28: =G28*J28 -> 15371.016 | L28: =(G28+K28)*0.05 -> 5571.9933 | N28: =SUM(K28+L28) -> 20943.009 | O28: =G28+N28 -> 117011.86 | P28: =O28/E28 -> 39003.953
A29: XII | B29: PLUMBING WORKS | E29: 1 | F29: unit | G29: =Estimate!I347 -> 35592.7 | H29: =H$17 -> 0.06 | I29: =I$17 -> 0.1 | J29: =SUM(H29:I29) -> 0.16 | K29: =G29*J29 -> 5694.832 | L29: =(G29+K29)*0.05 -> 2064.3766 | N29: =SUM(K29+L29) -> 7759.2086 | O29: =G29+N29 -> 43351.909 | P29: =O29/E29 -> 43351.909
A30: XIII | B30: PAINTING WORKS | E30: =354.12 -> 354.12 | F30: sq.m | G30: =Estimate!I377 -> 41278.1 | H30: =H$17 -> 0.06 | I30: =I$17 -> 0.1 | J30: =SUM(H30:I30) -> 0.16 | K30: =G30*J30 -> 6604.496 | L30: =(G30+K30)*0.05 -> 2394.1298 | N30: =SUM(K30+L30) -> 8998.6258 | O30: =G30+N30 -> 50276.726 | P30: =O30/E30 -> 141.97652
A31: =Estimate!A378 -> XIV. | B31: =Estimate!B378 -> WATER TOWER | E31: =Estimate!F378 -> 1 | F31: =Estimate!G378 -> unit | G31: =Estimate!I411 -> 108238.1 | H31: =H$17 -> 0.06 | I31: =I$17 -> 0.1 | J31: =SUM(H31:I31) -> 0.16 | K31: =G31*J31 -> 17318.095 | L31: =(G31+K31)*0.05 -> 6277.8095 | N31: =SUM(K31+L31) -> 23595.905 | O31: =G31+N31 -> 131834 | P31: =O31/E31 -> 131834
A33: TOTAL | G33: =SUM(G18:G32) -> 1220214.3 | K33: =SUM(K18:K32) -> 195234.29 | L33: =SUM(L18:L32) -> 70772.428 | N33: =SUM(N18:N32) -> 266006.71 | O33: =SUM(O18:O32) -> 1486221
A36: Prepared by: | D36: Verified and Certified by: | H36: Recommending Approval by: | N36: Approved by:
A37: CAMILO Y. NEE, CE | D37: BARJUNAID T. AMILASAN, CE | H37: only as to documents presented
H38: ATTY. TIMOTHY E. GALVEZ, RN, MPA | N38: JOSHUA G. BRILLANTES, MD, MPH
A41: HFEP Engineer II | D41: Engineer III / HFEP Infra In-Charge | H41: R.L.E.D. Chief / HFEP Coordinator | N41: BAC Chairman

Sheet BOQ
A1: Standard Form Number: SF-INFR-55
A2: Revised on: August 11, 2004
A3: BILL OF QUANTITIES
A5: Project Title: | C5: =Estimate!C1 -> PROPOSED CONSTRUCTION OF TWO STOREY RESIDENTIAL/APARTMENT BUILDING.
A6: Location: | C6: =Estimate!C2 -> Maganay, Buug, Zamboanga Sibugay
A8: ITEM# | B8: ITEM DESCRIPTION | F8: QTY | G8: UNIT | H8: UNIT PRICE | I8: AMOUNT
A10: I. | B10: LAYOUT AND EXCAVATION | F10: =Estimate!F7 -> 58.68 | G10: cu.m of excavation
B11: Scope of Work:
C12: 1. Includes clearing, layout, and excavation works for:
C13: a. Wall and Zoccalo Footings
C14: b. Column Footings
C15: c. Septic Tank
B16: Labor:
C17: Excavation works | G17: cu.m
B18: Materials:
C19: Assorted Form Lumber | G19: bd.ft
C20: Assorted CW Nails | G20: kgs
C21: Nylon Chord | G21: rolls
B24: (Pesos) _________________________ Amount in Words ____________________________________________________________________
C25: _____________________________________________________________________________________________________________
A27: II. | B27: EMBANKMENT WORKS | F27: =ROUNDUP(8*6.8*(0.4),0) -> 22 | G27: cu.m
B28: Scope of Work:
C29: 1. Embankment for buildable areas
C30: 2. Backfilling Works
B31: NOTE: | C31: If actual terrain and level of surface ground of the project site is hilly or too low such that rainwater may certainly flow into the building,
C32: proposal shall be made as extra work to raise the building further by such level higher than the road that is safe from flooding.
C33: Initial provision shall be included in this scope of work for the buildable area.
B35: Materials:
C36: Filling Materials - to elevate the buildable area by 0.40m | G36: cu.m
B39: (Pesos) _________________________ Amount in Words ____________________________________________________________________
C40: _____________________________________________________________________________________________________________
A42: III. | B42: REINFORCED CONCRETE WORKS | F42: =Estimate!F35 -> 0 | G42: cu.m concrete
B43: Scope of Work:
B44: 1. Construction of reinforced concrete works system with deformed bars layout arranged according to structural plans
B45: and specification, includes the following:
B46: a. | C46: Column Footings
B47: b. | C47: Columns
B48: c. | C48: Floor Slabs on Grade - all areas includ. Porch, Back Exit Landing, Ramp
C49: Slab thickness shall be 0.10m with temperature bars spaced 0.60m bothways on top of gravel bed throughout.
B50: NOTE: | C50: Finishing of Ramp with horizontal grooves every 10 cm along entire length
B51: d. | C51: Roof Beams
B52: e. | C52: Lavatory Counters
B53: f. | C53: Lintel Beam
B54: NOTE: | C54: Use Grade 40 Reinforcing Steel and 28 days curing period for concrete.
C55: All column footings shall be laid with boulders underneath, tampered thoroughly to compact soil.
C56: This item includes cement-plastering of all exposed surfaces of columns, beams,and stiffeners.
B57: Materials:
C58: Portland Cement | G58: bags
C59: Sand | G59: cu.m
C60: Gravel | G60: cu.m
C61: GI Tie Wire #16 | G61: kgs
C62: Deformed Bar 10mmØ x 6m | G62: lgths
C63: Deformed Bar 12mmØ x 6m | G63: lgths
C64: Deformed Bar 16mmØ x 6m (for columns and footings only) | G64: lgths
C65: Hacksaw Blade | G65: pcs
B68: (Pesos) _________________________ Amount in Words ____________________________________________________________________
C69: _____________________________________________________________________________________________________________
A71: IV. | B71: MASONRY WORKS | F71: =Estimate!F64 -> 0 | G71: sq.m (net)
B72: Scope of Work:
B73: 1. Construction of wall/zocallo footing with deformed bars arranged according to structural plans and specification:
B74: a. | C74: Wall Footing - 0.30m x 0.15m x 40 lin.m | F74: =(0.3*0.15)*40 -> 1.8 | G74: cu.m
B75: b. | C75: Zocallo Footing - 0.30m x 0.10m x 14.10 lin.m | F75: =(0.3*0.1)*14.1 -> 0.423 | G75: cu.m
B76: 2. Erecting of CHB walls/zocallo - 135.51 sq.m net area
B77: 3. Cement-plastering smooth-finish of all exposed concrete walls and window jambs - 210.98 sq.m net area
B78: NOTE: | C78: Plastering and finishing of concrete surfaces includes fashioning of exterior window mouldings and window sill rabbets.
B80: Materials:
C81: Portland Cement | G81: bags
C82: Sand | G82: cu.m
C83: Gravel | G83: cu.m
C84: Fine Sand | G84: cu.m
C85: GI Tie Wire #16 | G85: kgs
C86: Deformed Bar 10mmØ x 6m | G86: lgths
C87: Deformed Bar 12mmØ x 6m | G87: lgths
C88: Hacksaw Blade | G88: pcs
C89: Concrete Hollow Block 4" x 8" x 16" | G89: pcs
C90: Concrete Hollow Block 6" x 8" x 16" | G90: pcs
B93: (Pesos) _________________________ Amount in Words ____________________________________________________________________
C94: _____________________________________________________________________________________________________________
A96: V. | B96: CARPENTRY WORKS | F96: =Estimate!F89 -> 0 | G96: sq.m ceiling area
B97: Scope of Work:
C98: 1. Installation of Interior and Exterior Ceilings
C99: 2. Installation of Ceiling Air Ventilation - 4 units
C100: 3. Fabrication and Installation of Door Jambs - 4 units
C101: 4. Formworks and Scaffoldings
B103: Materials:
B104: CEILING BOARDS AND JOISTS FOR INTERIOR AND EXTERIOR CEILING - 96.80 sq.m
C105: HardiLite Fiber-Cement Board 3.5mm x 4' x 8' | G105: shts
C106: Metal Furring Double 0.400mm x 3/4" x 2" x 5m | G106: lgths
C107: Carrying Channel 0.400mm x 3/4" x 2" x 5m | G107: lgths
C108: Metal Wall Angle 0.400mm x 1" x 1" x 8' | G108: lgths
C109: W-Clip | G109: pcs
C110: Scoring Knife | G110: pcs
C111: Hacksaw Blade | G111: pcs
C112: Alum. Blind Rivets 1/8" x 3/8" | G112: pcs
C113: Ficem Screw 1" | G113: pcs
C114: Concrete Nail 1" | G114: kgs
C115: Masonry Drill Bit 1/8" | G115: pcs
C116: Metal Screw 1" and PVC Tox | G116: pcs
B117: CEILING AIR VENTILATION - 4 units
C118: Pre-Fabricated Wooden Ceiling Airvent | G118: pcs
...

Sheet BOQ w quantity
A1: Standard Form Number: SF-INFR-55
A2: Revised on: August 11, 2004
A3: BILL OF QUANTITIES
A5: Project Title: | C5: =Estimate!C1 -> PROPOSED CONSTRUCTION OF TWO STOREY RESIDENTIAL/APARTMENT BUILDING.
A6: Location: | C6: =Estimate!C2 -> Maganay, Buug, Zamboanga Sibugay
A8: ITEM# | B8: ITEM DESCRIPTION | F8: QTY | G8: UNIT | H8: UNIT PRICE | I8: AMOUNT
A10: I. | B10: LAYOUT AND EXCAVATION | F10: 25.191 | G10: cu.m of excavation
B11: Scope of Work:
C12: 1. Includes clearing, layout, and excavation works for:
C13: a. Wall and Zoccalo Footings
C14: b. Column Footings
C15: c. Septic Tank and Placenta Pit
B16: Labor: | F16: 1 | G16: lumpsum | I16: =H16*F16 -> 0
B17: Materials:
C18: Assorted Form Lumber | F18: 166.66667 | G18: bd.ft | I18: =H18*F18 -> 0
C19: Assorted CW Nails | F19: 3 | G19: kgs | I19: =H19*F19 -> 0
C20: Nylon Chord | F20: 3 | G20: rolls | I20: =H20*F20 -> 0
B22: (Pesos) _________________________ Amount in Words ____________________________________________________________________
C23: _____________________________________________________________________________________________________________
A25: II. | B25: EMBANKMENT WORKS | F25: 22 | G25: cu.m
B26: Scope of Work:
C27: 1. Embankment for buildable areas
C28: 2. Backfilling Works
B29: NOTE: | C29: If actual terrain and level of surface ground of the project site is hilly or too low such that rainwater may certainly flow into the building,
C30: proposal shall be made as extra work to raise the building further by such level higher than the road that is safe from flooding.
C31: Initial provision shall be included in this scope of work for the buildable area.
B33: Materials:
C34: Filling Materials - to elevate the buildable area by 0.40m | F34: 22 | G34: cu.m | I34: =H34*F34 -> 0
B37: (Pesos) _________________________ Amount in Words ____________________________________________________________________
C38: _____________________________________________________________________________________________________________
A40: III. | B40: REINFORCED CONCRETE WORKS | F40: 10.852 | G40: cu.m concrete
B41: Scope of Work:
B42: 1. Construction of reinforced concrete works system with deformed bars layout arranged according to structural plans
B43: and specification, includes the following:
B44: a. | C44: Column Footings - 3 of 1.0m x 1.0m x 0.20m + 6 of 0.80m x 0.80m x 0.20m | F44: 1.368 | G44: cu.m
B45: b. | C45: Columns - 9 of 0.20m x 0.20m x 4.10m | F45: 1.476 | G45: cu.m
B46: c. | C46: Floor Slabs on Grade - all areas includ. Porch, Back Exit Landing, Ramp - 67.2 sq.m | F46: 6.718 | G46: cu.m
C47: Slab thickness shall be 0.10m with temperature bars spaced 0.60m bothways on top of gravel bed throughout.
B48: NOTE: | C48: Finishing of Ramp with horizontal grooves every 10 cm along entire length
B49: d. | C49: Roof Beams - 0.15m x 0.20m x 36.40 lin.m | F49: 1.092 | G49: cu.m
B50: e. | C50: Lavatory Counters | F50: 0.198 | G50: cu.m
C51: Labor Room Lavatory Counter - 0.60m x 1.50m (with s/s sink)
C52: Sterilization (with s/s sink) & Scrub-up (tiled) Lavatory Counters - 0.60m x (1.30m + 0.60m)
C53: New-Born Counter - 0.60m x 1.50m
B54: NOTE: | C54: Use Grade 40 Reinforcing Steel and 28 days curing period for concrete.
C55: All column footings shall be laid with boulders underneath, tampered thoroughly to compact soil.
C56: This item includes cement-plastering of all exposed surfaces of columns, beams,and stiffeners.
B57: Materials:
C58: Portland Cement | F58: 126 | G58: bags | I58: =H58*F58 -> 0
C59: Sand | F59: 8.5 | G59: cu.m | I59: =H59*F59 -> 0
C60: Gravel | F60: 12 | G60: cu.m | I60: =H60*F60 -> 0
C61: GI Tie Wire #16 | F61: 16 | G61: kgs | I61: =H61*F61 -> 0
C62: Deformed Bar 10mmØ x 6m | F62: 112 | G62: lgths | I62: =H62*F62 -> 0
C63: Deformed Bar 12mmØ x 6m | F63: 23 | G63: lgths | I63: =H63*F63 -> 0
C64: Deformed Bar 16mmØ x 6m (for columns and footings only) | F64: 52 | G64: lgths | I64: =H64*F64 -> 0
C65: Hacksaw Blade | F65: 3 | G65: pcs | I65: =H65*F65 -> 0
B68: (Pesos) _________________________ Amount in Words ____________________________________________________________________
C69: _____________________________________________________________________________________________________________
A71: IV. | B71: MASONRY WORKS | F71: 156.6 | G71: sq.m (net)
B72: Scope of Work:
B73: 1. Construction of wall/zocallo footing with deformed bars arranged according to structural plans and specification:
B74: a. | C74: Wall Footing - 0.30m x 0.15m x 49.25 lin.m | F74: 2.21625 | G74: cu.m
B75: b. | C75: Zocallo Footing - 0.30m x 0.10m x 12.70 lin.m | F75: 0.381 | G75: cu.m
B76: 2. Erecting of CHB walls/zocallo - 156.6 sq.m net area
B77: NOTE: | C77: Provide stiffener with a minimum depth of 0.15m throughout perimeter along headers of doors and windows (w/ bars and C-ties).
B78: 3. Cement-plastering smooth-finish of all exposed concrete walls and window jambs - 231.9 sq.m net area
B79: NOTE: | C79: Plastering and finishing of concrete surfaces includes fashioning of exterior window mouldings and window sill rabbets.
B81: Materials:
C82: Portland Cement | F82: 242 | G82: bags | I82: =H82*F82 -> 0
C83: Sand | F83: 17.5 | G83: cu.m | I83: =H83*F83 -> 0
C84: Gravel | F84: 3 | G84: cu.m | I84: =H84*F84 -> 0
C85: GI Tie Wire #16 | F85: 6 | G85: kgs | I85: =H85*F85 -> 0
C86: Deformed Bar 10mmØ x 6m | F86: 124 | G86: lgths | I86: =H86*F86 -> 0
C87: Deformed Bar 12mmØ x 6m | F87: 17 | G87: lgths | I87: =H87*F87 -> 0
C88: Hacksaw Blade | F88: 1 | G88: pcs | I88: =H88*F88 -> 0
C89: Concrete Hollow Block 4" x 8" x 16" | F89: 1821 | G89: pcs | I89: =H89*F89 -> 0
B92: (Pesos) _________________________ Amount in Words ____________________________________________________________________
C93: _____________________________________________________________________________________________________________
A95: V. | B95: CARPENTRY WORKS | F95: 100.1 | G95: sq.m ceiling area
B96: Scope of Work:
C97: 1. Installation of Interior and Exterior Ceilings
C98: 2. Installation of Ceiling Air Ventilation - 4 units
C99: 3. Fabrication and Installation of Door Jambs - 4 units
C100: 4. Formworks and Scaffoldings
B102: Materials:
B103: CEILING BOARDS AND JOISTS FOR INTERIOR AND EXTERIOR CEILING - 100.10 sq.m
C104: HardiLite Fiber-Cement Board 3.5mm x 4' x 8' | F104: 37 | G104: shts | I104: =H104*F104 -> 0
C105: Metal Furring Double 0.400mm x 3/4" x 2" x 5m | F105: 72 | G105: lgths | I105: =H105*F105 -> 0
C106: Carrying Channel 0.400mm x 3/4" x 2" x 5m | F106: 37 | G106: lgths | I106: =H106*F106 -> 0
C107: Metal Wall Angle 0.400mm x 1" x 1" x 8' | F107: 34 | G107: lgths | I107: =H107*F107 -> 0
C108: W-Clip | F108: 111 | G108: pcs | I108: =H108*F108 -> 0
C109: Scoring Knife | F109: 1 | G109: pcs | I109: =H109*F109 -> 0
C110: Hacksaw Blade | F110: 3 | G110: pcs | I110: =H110*F110 -> 0
C111: Alum. Blind Rivets 1/8" x 3/8" | F111: 1202 | G111: pcs | I111: =H111*F111 -> 0
C112: Ficem Screw 1" | F112: 585 | G112: pcs | I112: =H112*F112 -> 0
C113: Concrete Nail 1" | F113: 2 | G113: kgs | I113: =H113*F113 -> 0
C114: Masonry Drill Bit 1/8" | F114: 2 | G114: pcs | I114: =H114*F114 -> 0
C115: Metal Screw 1" and PVC Tox | F115: 51 | G115: pcs | I115: =H115*F115 -> 0
B116: CEILING AIR VENTILATION - 4 units
C117: Pre-Fabricated Wooden Ceiling Airvent 12" x 48" | F117: 4 | G117: pcs | I117: =H117*F117 -> 0
...

Sheet Sheet1
A1: CIRCUIT No. | B1: LOAD DESCRIPTION | C1: LIGHT | E1: SWITCH | H1: POWER OUTLET | I1: VOLT-AMPERE | J1: VOLTAGE | K1: AMPERE | L1: WIRE SIZE | M1: CONDUIT | N1: CIRCUIT BREAKER
C2: FL (20w) | D2: PL 18w | E2: S1 | F2: S2 | G2: S3
A3: 1 | B3: Lighting Load | C3: 5 | D3: 6 | E3: 4 | G3: 2 | I3: =5*20+6*18 -> 208 | J3: 220 | K3: =IF(ISBLANK(J3),"",I3/J3) -> 0.94545455 | L3: 2 - 3.5mm2 TW (#12) | M3: uPVC Pipe 1/2”Ø | N3: 15 amp. 2P | P3: TW Cu. Wire 2.0 mm2 (#14) [150 mtrs/box] (for lights)
A4: 2 | B4: Lighting Load | D4: 7 | G4: 1 | I4: =7*18 -> 126 | J4: 220 | K4: =IF(ISBLANK(J4),"",I4/J4) -> 0.57272727 | L4: 2 - 3.5mm2 TW (#12) | M4: uPVC Pipe 1/2”Ø | N4: 15 amp. 2P | P4: TW Cu. Wire 3.5 mm2 (#12) [150 mtrs/box] (for lights & outlets)
A5: 3 | B5: Power Outlets (Left Side) | H5: 6 | I5: =H5*360 -> 2160 | J5: 220 | K5: =IF(ISBLANK(J5),"",I5/J5) -> 9.8181818 | L5: 2 - 3.5mm2 TW (#12) | M5: uPVC Pipe 1/2”Ø | N5: 15 amp. 2P | P5: TW Cu. Wire Stranded 5.5 mm2 (#10) (for aircon provision)
A6: 4 | B6: Power Outlets (Right Side) | H6: 7 | I6: =H6*360 -> 2520 | J6: 220 | K6: =IF(ISBLANK(J6),"",I6/J6) -> 11.454545 | L6: 2 - 3.5mm2 TW (#12) | M6: uPVC Pipe 1/2”Ø | N6: 15 amp. 2P | P6: TW Cu. Wire Stranded 8 mm2 (#8) (for aircon provision)
A7: 5 | B7: Power Outlets | H7: 4 | I7: =H7*360 -> 1440 | J7: 220 | K7: =IF(ISBLANK(J7),"",I7/J7) -> 6.5454545 | L7: 2 - 3.5mm2 TW (#12) | M7: uPVC Pipe 1/2”Ø | N7: 15 amp. 2P | P7: TW Cu. Wire Stranded 14 mm2 (#6) (for aircon provision)
A8: 6 | B8: Spare | K8: =IF(ISBLANK(J8),"",I8/J8) | N8: 15 amp. 2P | P8: TW Cu. Wire Stranded 22 mm2 (#4) (for main entrance)
A9: TOTAL | C9: =SUM(C3:C8) -> 5 | D9: =SUM(D3:D8) -> 13 | E9: =SUM(E3:E8) -> 4 | F9: =SUM(F3:F8) -> 0 | G9: =SUM(G3:G8) -> 3 | H9: =SUM(H3:H8) -> 17 | I9: =SUM(I3:I8) -> 6454 | J9: =SUM(J3:J8) -> 1100 | K9: =SUM(K3:K8) -> 29.336364
B11: DIRECT COST
B12: A.1 Cost of Materials to be used in doing the work item called for, which shall include, the following:
B13: A.1.1 Cost at source, including processing, crushing, stockpiling, loading, royalties, local taxes, construction and/or maintenance of haul roads, etc.
B14: A.1.2 Expenses for Hauling to project site
B15: A.1.3 Handling expenses
B16: A.1.4 Storage expenses
B17: A.1.5 Allowance for waste and/or losses, not to exceed 5% of materials requirement
B18: A.2 Cost of Labor
B19: A.2.1 Salaries and wages, as authorized by the Department of Labor and Employment
B20: A.2.2 Fringe benefits, such as vacation and sick leaves, benefits under the Workmen's Compensation Act, GSIS and/or SSS contributions, allowances, 13th month pay, bonuses, etc
B21: A.3 Equipment Expenses
B22: A.3.1 Rental of equipment which shall be based on the prevailing "Associated Construction Equipment Lessors, Inc" (ACEL) rental rates approved for use by the DPWH (Presently it is the 2009 ACEL Rates). Rental rates of equipment not indicated in the ACEL booklet shall be taken from the rental rates prepared by the Bureau of Equipment. For simplicity in computation, the operated rental rates are preferred over the bare rental rates as the former includes operator's wages, fringe benefits, fuel, oil, lubricants and equipment maintenance. The make, model and capacity of the equipment should be indicated in the detailed unit cost analysis.
... B38: B.5 VAT Component – shall be 12% of the sum of the EDC, OCM and Profit

Sheet ARDYL
A1: Project Title: | C1: PROPOSED CONSTRUCTION OF TWO STOREY RESIDENTIAL/APARTMENT BUILDING.
A2: Location: | K2: Budget | L2: 1200000 | O2: No window grilles
A3: Date: | K3: Matls Markup | L3: 0 | M3: =E357 -> 1276735 | O3: No boulders
A4: DETAILED ESTIMATE | K4: Hauling Rate | L4: 0.01 | M4: =H357 -> 0 | O4: Septic Tank at 1.50m x 3.00m
A5: ITEM NO. | B5: ITEM DESCRIPTION | F5: QTY | G5: UNIT | H5: UNIT PRICE | I5: AMOUNT | K5: Labor Rate | L5: 0.3 | M5: =F357 -> 0
K6: EDC | L6: =ABC!G33 -> 1220214.3
A7: I. | B7: LAYOUT AND EXCAVATION | F7: =F10+F11+F12 -> 58.68 | G7: cu.m of excavation | K7: OCM | L7: =5%+0.5%+0.5% -> 0.06
B8: Scope of Work: | K8: Contr Profit | L8: 0.1
C9: 1. Includes clearing, layout, and excavation works for: | K9: Indirect Cost | L9: =ABC!N33 -> 266006.71
C10: a. Wall and Zoccalo Footings | F10: 10.68 | K10: TOTAL | L10: =ABC!O33 -> 1486221
C11: b. Column Footings | F11: 21
C12: c. Septic Tank | F12: 27
B13: Labor:
C14: Excavation works | F14: =F7 -> 58.68 | G14: cu.m | H14: 200 | I14: =H14*F14 -> 11736
B15: Materials:
C16: Assorted Form Lumber | F16: =2*2*10/12*50 -> 166.66667 | G16: bd.ft | H16: 21 | I16: =H16*F16 -> 3500
C17: Assorted CW Nails | F17: 3 | G17: kgs | H17: 80 | I17: =H17*F17 -> 240
C18: Nylon Chord | F18: 3 | G18: rolls | H18: 50 | I18: =H18*F18 -> 150
H20: Material Cost | I20: =SUM(I16:I18) -> 3890
H21: Labor Cost | I21: =I14 -> 11736
H22: Total Cost | I22: =I20+I21 -> 15626
A23: II. | B23: EMBANKMENT WORKS | F23: 14 | G23: cu.m
B24: Scope of Work:
C25: 1. Embankment for buildable areas
C26: 2. Backfilling Works
B28: Materials:
C29: Filling Materials - to elevate the buildable area by 0.20m | F29: =F23 -> 14 | G29: cu.m | H29: 250 | I29: =H29*F29 -> 3500
H31: Material Cost | I31: =SUM(I29:I30) -> 3500
H32: ="Labor Cost "&TEXT(L$5,"#%")&" of MC" -> Labor Cost 30% of MC | I32: =L$5*I31 -> 1050
H33: Total Cost | I33: =I31+I32 -> 4550
A34: III. | B34: REINFORCED CONCRETE WORKS | F34: 64.93 | G34: cu.m concrete
B35: Scope of Work:
B36: 1. Construction of reinforced concrete works system with deformed bars layout arranged according to structural plans
B37: and specification, includes the following:
B38: a. | C38: Column Footings
B39: b. | C39: Columns
B40: c. | C40: Floor Slabs on Grade - all areas includ. Porch,
C41: Slab thickness shall be 0.10m with temperature bars spaced 0.60m bothways on top of gravel bed throughout.
B42: d. | C42: Roof Beams
B43: e. | C43: Lavatory Counters
B44: f. | C44: Lintel Beam
B45: NOTE: | C45: Use Grade 40 Reinforcing Steel and 28 days curing period for concrete.
C46: All column footings shall be laid with boulders underneath, tampered thoroughly to compact soil.
C47: This item includes cement-plastering of all exposed surfaces of columns, beams,and stiffeners.
B48: Materials:
C49: Portland Cement | F49: =ROUNDUP(F34*9,0) -> 585 | G49: bags | H49: 250 | I49: =H49*F49 -> 146250
C50: Sand | F50: =ROUNDUP(F34*0.5,0) -> 33 | G50: cu.m | H50: 950 | I50: =H50*F50 -> 31350
C51: Gravel | F51: =ROUNDDOWN(F34*1,0) -> 64 | G51: cu.m | H51: 950 | I51: =H51*F51 -> 60800
C52: GI Tie Wire #16 | F52: 15 | G52: kgs | H52: =CEILING(L64,0.5) -> 67 | I52: =H52*F52 -> 1005
C53: Deformed Bar 8mmØ x 6m | F53: 148 | G53: lgths | H53: 95 | I53: =H53*F53 -> 14060
C54: Deformed Bar 10mmØ x 6m | F54: 194 | G54: lgths | H54: =CEILING(L65,0.5) -> 154.5 | I54: =H54*F54 -> 29973 | K54: =6.8+8+6.8+8+6.8 -> 36.4
C55: Deformed Bar 12mmØ x 6m | F55: 164 | G55: lgths | H55: =CEILING(L66,0.5) -> 223.5 | I55: =H55*F55 -> 36654
C56: Hacksaw Blade | F56: 18 | G56: pcs | H56: =CEILING(L68,0.5) -> 55 | I56: =H56*F56 -> 990
H58: Material Cost | I58: =I49+I50+I51+I52+I53+I54+I55+I56 -> 321082
H59: ="Labor Cost "&TEXT(L$5,"#%")&" of MC" -> Labor Cost 30% of MC | I59: =L$5*I58 -> 96324.6
H60: Total Cost | I60: =I58+I59 -> 417406.6
A61: IV. | B61: MASONRY WORKS | F61: 539.91 | G61: sq.m | K61: 255 | L61: =K61*(1+L$3)+10 -> 265 | N61: Portland Cement | O61: 128
B62: Scope of Work: | K62: 900 | L62: =K62*(1+L$3) -> 900 | N62: Sand | O62: 8.5
B63: 1. Construction of wall/zocallo footing with deformed bars arranged according to structural plans and specification: | K63: 900 | L63: =K63*(1+L$3) -> 900 | N63: Gravel | O63: 12
B64: a. | C64: Wall Footing - 0.30m x 0.15m x 40 lin.m | K64: 58 | L64: =K64*(1+L$3)+8.7 -> 66.7 | N64: GI Tie Wire #16 | O64: 16
B65: b. | C65: Zocallo Footing - 0.30m x 0.10m x 14.10 lin.m | K65: 134 | L65: =K65*(1+L$3)+20.1 -> 154.1 | N65: Deformed Bar 10mmø x 6m | O65: 113
B66: 2. Erecting of CHB walls/zocallo | K66: 194 | L66: =K66*(1+L$3)+29.1 -> 223.1 | N66: Deformed Bar 12mmø x 6m | O66: 23
B67: 3. Cement-plastering smooth-finish of all exposed concrete walls and window jambs | K67: 344 | L67: =K67*(1+L$3)+51.6 -> 395.6 | N67: Deformed Bar 16mmø x 6m | O67: 52
B68: NOTE: | C68: Plastering and finishing of concrete surfaces includes fashioning of exterior window mouldings and window sill rabbets. | K68: 55 | L68: =K68*(1+L$3) -> 55 | N68: Hacksaw Blade | O68: 3
L69: s
B70: Materials:
C71: Portland Cement | F71: ='Masonry Works.'!F33 -> 386 | G71: bags | H71: 250 | I71: =H71*F71 -> 96500
C72: Mix Sand (Mortar) | F72: 24 | G72: cu.m | H72: =CEILING(L85,0.5) -> 900 | I72: =H72*F72 -> 21600
C73: Fine Sand (Paste) | F73: 8 | G73: cu.m | H73: 1100 | I73: =H73*F73 -> 8800
C74: GI Tie Wire #16 | F74: 15 | G74: kgs | H74: =CEILING(L88,0.5) -> 67 | I74: =H74*F74 -> 1005
C75: Deformed Bar 10mmØ x 6m | F75: ='Masonry Works.'!F37 -> 338 | G75: lgths | H75: =CEILING(L89,0.5) -> 154.5 | I75: =H75*F75 -> 52221
C76: Hacksaw Blade | F76: 10 | G76: pcs | H76: =CEILING(L91,0.5) -> 55 | I76: =H76*F76 -> 550
C77: Concrete Hollow Block 4" x 8" x 16" | F77: =ROUNDUP('Masonry Works.'!E42,0) -> 6749 | G77: pcs | H77: 10 | I77: =H77*F77 -> 67490 | K77: =6.8*2+8*2+3.7+2.9+2.6+1.65+1.9+3.7+3.2 -> 49.25 | L77: =6.8*2+8*2+2.45+2.9+1.65 -> 36.6 | N77: All concrete hollow blocks shall be laid plumb and true to line.
C78: Concrete Hollow Block 6" x 8" x 16" | F78: 334 | G78: pcs | H78: 18 | I78: =H78*F78 -> 6012 | K78: =(2.2+2)+(1.6+4)+(1.1+1.8) -> 12.7 | N78: Joint fillers and mortar for block laying shall be concrete of the class “B”, with ratio 1:3.
N79: All walls shall be provided with vertical and horizontal bars tied and securely anchored at the foundation.
H80: Material Cost | I80: =SUM(I71:I79) -> 254178
H81: ="Labor Cost "&TEXT(L$5,"#%")&" of MC" -> Labor Cost 30% of MC | I81: =L$5*I80 -> 76253.4
H82: Total Cost | I82: =I80+I81 -> 330431.4
A83: V. | B83: CARPENTRY WORKS | F83: 137.31 | G83: sq.m ceiling area | O83: 49.25 lin.m
B84: Scope of Work: | K84: 255 | L84: =K84*(1+L$3)+10 -> 265 | N84: Portland Cement | O84: 244
C85: 1. Installation of Interior Ceilings | K85: 900 | L85: =K85*(1+L$3) -> 900 | N85: Sand | O85: 18
C86: 2. Installation o Roofing Air Ventilation | K86: 900 | L86: =K86*(1+L$3) -> 900 | N86: Gravel | O86: 3
C87: 3. Formworks and Scaffoldings
K88: 58 | L88: =K88*(1+L$3)+8.7 -> 66.7 | N88: GI Tie Wire #16 | O88: 6.5
B89: Materials: | K89: 134 | L89: =K89*(1+L$3)+20.1 -> 154.1 | N89: Deformed Bar 10mmø x 6m | O89: 125
B90: CEILING BOARDS AND JOISTS FOR INTERIOR AND EXTERIOR CEILING - 96.80 sq.m | K90: 194 | L90: =K90*(1+L$3)+29.1 -> 223.1 | N90: Deformed Bar 12mmø x 6m | O90: 17
C91: Marine Plywood 3.5mm x 4' x 8' | F91: 48 | G91: shts | H91: 360 | I91: =H91*F91 -> 17280 | K91: 55 | L91: =K91*(1+L$3) -> 55 | N91: Hacksaw Blade | O91: 1
C92: Metal Furring Double 0.400mm x 3/4" x 2" x 5m | F92: =ROUNDUP((F91*12)/5,0) -> 116 | G92: lgths | H92: 125 | I92: =H92*F92 -> 14500 | K92: 14 | L92: =K92*(1+L$3) -> 14 | N92: Concrete Hollow Block 4" x 8" x 12" | O92: 1832
C93: Carrying Channel 0.400mm x 3/4" x 2" x 5m | F93: 48 | G93: lgths | H93: 135 | I93: =H93*F93 -> 6480
C94: Metal Wall Angle 0.400mm x 1" x 1" x 8' | F94: 35 | G94: lgths | H94: =CEILING(L111,0.5) -> 65 | I94: =H94*F94 -> 2275
C95: W-Clip | F95: 432 | G95: pcs | H95: =CEILING(L112,0.5) -> 5 | I95: =H95*F95 -> 2160
C96: Scoring Knife | F96: 2 | G96: pcs | H96: =CEILING(L113,0.5) -> 139 | I96: =H96*F96 -> 278
C97: Hacksaw Blade | F97: 3 | G97: pcs | H97: =CEILING(L114,0.5) -> 55 | I97: =H97*F97 -> 165 | R97: 6
C98: Alum. Blind Rivets 1/8" x 3/8" | F98: 5 | G98: box | H98: 240 | I98: =H98*F98 -> 1200 | R98: 6
C99: Concrete Nail 1" | F99: 2 | G99: kgs | H99: =CEILING(L117,0.5) -> 60 | I99: =H99*F99 -> 120
C100: Masonry Drill Bit 1/8" | F100: 2 | G100: pcs | H100: =CEILING(L118,0.5) -> 95 | I100: =H100*F100 -> 190
C101: Metal Screw 1" and PVC Tox | F101: 500 | G101: pcs | H101: =CEILING(L119,0.5) -> 2 | I101: =H101*F101 -> 1000
B102: CEILING AIR VENTILATION
C103: Mesh Wire 1/8" x 36" | F103: 5 | G103: mtrs | H103: =CEILING(L122,0.5) -> 75 | I103: =H103*F103 -> 375
B104: FORMWORKS AND FALSEWORKS (for Columns, Beams and Cover Slabs)
...

Sheet Masonry Works.
A1: TOTAL AREA = | C1: 539.91 | D1: sq.m
A3: Front
A4: total Area | C4: sq.m
A6: Rare
A7: total Area | C7: sq.m
A9: Right Side's
A10: Total area | C10: sq.m
A12: Left Side's
A13: Total area | C13: sq.m
A15: Interior wall
A16: area | C16: sq.m
A19: Deductive
A20: Door's
A21: width | B21: 1
A22: height | B22: 2.1
A23: area | B23: =B22*B21 -> 2.1 | C23: sq.m
A26: Window's
A27: width | B27: 1.9 | K27: 28 | L27: 3 | M27: =K27*L27 -> 84
A28: height | B28: 1.2
A29: area | B29: =B28*B27 -> 2.28 | C29: sq.m
A31: 100m thinck CHB = | D31: =C1*12.5 -> 6748.875 | E31: pcs | J31: =D31*0.128 -> 863.856 | K31: =J31/6 -> 143.976 | L31: =K31+K32 -> 337.44375
D32: Mortar | E32: Plaster | F32: Total | J32: =D31*0.172 -> 1160.8065 | K32: =J32/6 -> 193.46775
A33: Portland Cement (40kg/bag) = | D33: =(D31/100)*4.176 -> 281.83302 | E33: =C1*0.192 -> 103.66272 | F33: =ROUNDUP(D33+E33,0) -> 386 | G33: bags
A34: Washed Sand = | D34: =(D31/100)*0.348 -> 23.486085 | E34: =C1*0.016 -> 8.63856 | F34: =ROUNDUP(D34+E34,0) -> 33 | G34: cu.m
D36: Horizontal | E36: Vertical
A37: 10mmØ x 6.0m Def. Bar = | D37: =ROUNDUP(((D31*0.128)/6),0) -> 144 | E37: =ROUNDUP(((D31*0.172)/6),0) -> 194 | F37: =D37+E37 -> 338 | G37: pcs
A41: Summary
A42: 1 | B42: CHB= | E42: =D31 -> 6748.875 | F42: Pcs
A43: 2 | B43: Cement= | E43: =F33 -> 386 | F43: Bags
A44: 3 | B44: Fine Aggregates= | E44: =F34 -> 33 | F44: Cu.m
A45: 4 | B45: 10mm Def. Bars= | E45: =F37 -> 338 | F45: Pcs
