Workbook
Name A: #REF!
Name A: #REF!
Name A: #REF!
Name A: #REF!
Name A: #REF!
Name A: #REF!
Name A: #REF!
Name A: #REF!
Name A: #REF!
Name A: #REF!
Name A: #REF!
Name A: #REF!
Name A: #REF!
Name A: #REF!
Name A: #REF!
Name A: #REF!
Name A: #REF!
Name A: #REF!
Name A: #REF!
Name A: #REF!
Name A: #REF!
Name A: #REF!
Name A: #REF!
Name A: #REF!
Name A: #REF!
Name A: #REF!
Name A: #REF!
Name A: #REF!
Name A: #REF!
Name A: #REF!
Name A: #REF!
Name A: #REF!
Name A: #REF!
Name A: #REF!
Name A: #REF!
Name A: #REF!
Name A: #REF!
Name A: #REF!
Name A: #REF!
Name A: #REF!
Name A: #REF!
Name A: #REF!
Name A: #REF!
Name A: #REF!
Name A: #REF!
Name A: #REF!
Name A: #REF!
Name A: #REF!
Name A: #REF!
Name add: #REF!
Name add: #REF!
Name add: #REF!
Name add: #REF!
Name add: #REF!
Name add: #REF!
Name add: #REF!
Name add: #REF!
Name add: #REF!
Name add: #REF!
Name add: #REF!

Sheet INPUT DATA
A2: INPUT ONLY ON GRAY CELLS
B4: PROJECT TITLE: | C4: PROPOSED ONE STOREY TWO BED ROOM RESIDENTIAL BUILDING
B5: PROJECT LOCATION: | C5: ANGELES, PAMPANGA
A7: Item Number | B7: Item of Works | C7: Qty | D7: Units | E7: Remarks | F7: DIRECT COST | I7: INDIRECT COST
F8: Manpower /Labor | G8: Equipment/ Tools | H8: Materials | I8: OCM | J8: Profit | K8: VAT | L8: Total Cost | M8: Unit Cost
A9: ARCHITECTURAL / CIVIL WORKS
A10: ='800(1) Clearing & Grab'!E5 -> 800(1) | B10: ='800(1) Clearing & Grab'!G5 -> CLEARING AND GRUBBING | C10: 200 | D10: ='800(1) Clearing & Grab'!G8 -> SQ.M. | E10: Area of the project for clearing | F10: ='800(1) Clearing & Grab'!T20 -> 600 | G10: ='800(1) Clearing & Grab'!T29 -> 21555.2 | H10: ='800(1) Clearing & Grab'!T46 -> 0 | I10: ='800(1) Clearing & Grab'!T48 -> 1107.76 | J10: ='800(1) Clearing & Grab'!T49 -> 2215.52 | K10: ='800(1) Clearing & Grab'!T50 -> 0 | L10: =SUM(F10:K10) -> 25478.48 | M10: =L10/C10 -> 127.3924
A11: ='800(3)a Ind Remov of Trees'!E5 -> 800(3)a | B11: ='800(3)a Ind Remov of Trees'!G5 -> INDIVIDUAL REMOVAL OF TREES (UPTO 300MM DIAMETER) | C11: 2 | D11: ='800(3)a Ind Remov of Trees'!E6 -> EACH | E11: Number of trees to be removed from project site | F11: ='800(3)a Ind Remov of Trees'!T20 -> 550 | G11: ='800(3)a Ind Remov of Trees'!T30 -> 3908.94 | H11: ='800(3)a Ind Remov of Trees'!T47 -> 0 | I11: ='800(3)a Ind Remov of Trees'!T49 -> 222.947 | J11: ='800(3)a Ind Remov of Trees'!T50 -> 445.894 | K11: ='800(3)a Ind Remov of Trees'!T51 -> 0 | L11: =SUM(F11:K11) -> 5127.781 | M11: =L11/C11 -> 2563.8905
A12: ='803(1)a-Struc Exca Common Soil'!E5 -> 803(1)a | B12: ='803(1)a-Struc Exca Common Soil'!G5 -> STRUCTURE EXCAVATION (COMMON SOIL) | C12: 23 | D12: ='803(1)a-Struc Exca Common Soil'!G8 -> CU.M. | E12: Volume to be excavated by Backhoe | F12: ='803(1)a-Struc Exca Common Soil'!T19 -> 287.5 | G12: ='803(1)a-Struc Exca Common Soil'!T29 -> 4905.9 | H12: ='803(1)a-Struc Exca Common Soil'!T42 -> 0 | I12: ='803(1)a-Struc Exca Common Soil'!T44 -> 259.67 | J12: ='803(1)a-Struc Exca Common Soil'!T45 -> 519.34 | K12: ='803(1)a-Struc Exca Common Soil'!T46 -> 0 | L12: =SUM(F12:K12) -> 5972.41 | M12: =L12/C12 -> 259.67
A13: ='803(1)a-Struc Exca Soft Rock'!E5 -> 803(1)a | B13: ='803(1)a-Struc Exca Soft Rock'!G5 -> STRUCTURE EXCAVATION (SOFT ROCK) | C13: 0 | D13: ='803(1)a-Struc Exca Soft Rock'!E6 -> CU.M. | E13: Volume to be excavated by Backhoe | F13: ='803(1)a-Struc Exca Soft Rock'!T19 -> 0 | G13: ='803(1)a-Struc Exca Soft Rock'!T30 -> 0 | H13: ='803(1)a-Struc Exca Soft Rock'!T43 -> 0 | I13: ='803(1)a-Struc Exca Soft Rock'!T45 -> 0 | J13: ='803(1)a-Struc Exca Soft Rock'!T46 -> 0 | K13: ='803(1)a-Struc Exca Soft Rock'!T47 -> 0 | L13: =SUM(F13:K13) -> 0 | M13: =L13/C13 -> #DIV/0!
A14: ='804(4) Gravel Bedding'!E5 -> 804(4) | B14: ='804(4) Gravel Bedding'!G5 -> GRAVEL BEDDING | C14: 3 | D14: ='804(4) Gravel Bedding'!G8 -> CU.M. | E14: Putting gravel as bedding in foundation | F14: ='804(4) Gravel Bedding'!T19 -> 625 | G14: ='804(4) Gravel Bedding'!T28 -> 677.5 | H14: ='804(4) Gravel Bedding'!T41 -> 4200 | I14: ='804(4) Gravel Bedding'!T43 -> 275.125 | J14: ='804(4) Gravel Bedding'!T44 -> 550.25 | K14: ='804(4) Gravel Bedding'!T45 -> 0 | L14: =SUM(F14:K14) -> 6327.875 | M14: =L14/C14 -> 2109.2917
A15: ='902(1)-Reinforced S for 1Storey'!E5 -> 902(1) | B15: ='902(1)-Reinforced S for 1Storey'!G5 -> REINFORCING STEEL OF REINFORCED CONCRETE STRUCTURES FOR ONE-STOREY, GRADE 40/60 | C15: 1200 | D15: ='902(1)-Reinforced S for 1Storey'!E6 -> KGS. | E15: After estimating the number of steel bars by direct counting on plan, get its total weight in kgs. | F15: ='902(1)-Reinforced S for 1Storey'!T17 -> 7738.54 | G15: ='902(1)-Reinforced S for 1Storey'!T26 -> 3772.43 | H15: ='902(1)-Reinforced S for 1Storey'!T38 -> 96201 | I15: ='902(1)-Reinforced S for 1Storey'!T40 -> 5385.5985 | J15: ='902(1)-Reinforced S for 1Storey'!T41 -> 10771.197 | K15: ='902(1)-Reinforced S for 1Storey'!T42 -> 0 | L15: =SUM(F15:K15) -> 123868.77 | M15: =L15/C15 -> 103.22397
A16: ='902(1)-Rein St for 2-5storey'!E5 -> 902(1) | B16: ='902(1)-Rein St for 2-5storey'!G5 -> REINFORCING STEEL OF REINFORCED CONCRETE STRUCTURES FOR TWO UPTO FIVE STOREY | C16: 50 | D16: ='902(1)-Rein St for 2-5storey'!E6 -> KGS. | E16: This is for two to 5 storey only. After estimating the number of steel bars by direct counting on plan, get its total weight in kgs. | F16: ='902(1)-Rein St for 2-5storey'!T17 -> 358.27 | G16: ='902(1)-Rein St for 2-5storey'!T26 -> 146.45 | H16: ='902(1)-Rein St for 2-5storey'!T38 -> 4008.38 | I16: ='902(1)-Rein St for 2-5storey'!T40 -> 225.655 | J16: ='902(1)-Rein St for 2-5storey'!T41 -> 451.31 | K16: ='902(1)-Rein St for 2-5storey'!T42 -> 0 | L16: =SUM(F16:K16) -> 5190.065 | M16: =L16/C16 -> 103.8013
A17: ='900(1)c2 Struc Con for footing'!E5 -> 900(1)c2 | B17: ='900(1)c2 Struc Con for footing'!G5 -> STRUCTURAL CONCRETE FOR FOOTING AND SLAB ON FILL (CLASS A, 28 DAYS) | C17: 12.4 | D17: ='900(1)c2 Struc Con for footing'!G8 -> CU.M. | E17: Total concrete volume of Footing & Slab on grade | F17: ='900(1)c2 Struc Con for footing'!T21 -> 13025.21 | G17: ='900(1)c2 Struc Con for footing'!T30 -> 7276.75 | H17: ='900(1)c2 Struc Con for footing'!T46 -> 55942.6 | I17: ='900(1)c2 Struc Con for footing'!T48 -> 3812.228 | J17: ='900(1)c2 Struc Con for footing'!T49 -> 7624.456 | K17: ='900(1)c2 Struc Con for footing'!T50 -> 0 | L17: =SUM(F17:K17) -> 87681.244 | M17: =L17/C17 -> 7071.0681
A18: ='900(1)Struc Con for beam col su'!E5 -> 900(1) | B18: ='900(1)Struc Con for beam col su'!G5 -> STRUCTURAL CONCRETE FOR FOOTING TIE BEAM, COLUMN, SUSPENDED SLAB, GIRDER/BEAM (CLASS A, 28 DAYS) | C18: 23.6 | D18: ='900(1)Struc Con for beam col su'!G8 -> CU.M. | E18: Total volume of concrete for beam, column tie beam, suspended slab & girder | F18: ='900(1)Struc Con for beam col su'!T21 -> 32777.78 | G18: ='900(1)Struc Con for beam col su'!T30 -> 18311.85 | H18: ='900(1)Struc Con for beam col su'!T46 -> 99391.4 | I18: ='900(1)Struc Con for beam col su'!T48 -> 7524.0515 | J18: ='900(1)Struc Con for beam col su'!T49 -> 15048.103 | K18: ='900(1)Struc Con for beam col su'!T50 -> 0 | L18: =SUM(F18:K18) -> 173053.18 | M18: =L18/C18 -> 7332.7621
A19: ='903(2) Formworks for 1-storey'!E5 -> 903(2) | B19: ='903(2) Formworks for 1-storey'!G5 -> FORMWORKS AND FALSEWORKS (FOR ONE-STOREY BUILDING) | C19: 49 | D19: ='903(2) Formworks for 1-storey'!G8 -> SQ.M. | E19: Area of the surface to be covered. E.i. compute the areas of columns, beams and other structural members that need form for concreting | F19: ='903(2) Formworks for 1-storey'!T22 -> 9285.8 | G19: ='903(2) Formworks for 1-storey'!T31 -> 928.58 | H19: ='903(2) Formworks for 1-storey'!T47 -> 29647.03 | I19: ='903(2) Formworks for 1-storey'!T49 -> 1993.0705 | J19: ='903(2) Formworks for 1-storey'!T50 -> 3986.141 | K19: ='903(2) Formworks for 1-storey'!T51 -> 0 | L19: =SUM(F19:K19) -> 45840.621 | M19: =L19/C19 -> 935.52289
A20: ='1046 4"CHB'!E5 -> 1046 | B20: ='1046 4"CHB'!G5 -> 100MM CHB NON LOAD BEARING/LOAD BEARING (INCLUDING REINFORCING STEEL) | C20: 189 | D20: ='1046 4"CHB'!E6 -> SQ.M. | E20: Total area of wall using 4" CHB | F20: ='1046 4"CHB'!T21 -> 19764.71 | G20: ='1046 4"CHB'!T30 -> 10475.29 | H20: ='1046 4"CHB'!T46 -> 120511.13 | I20: ='1046 4"CHB'!T48 -> 7537.5565 | J20: ='1046 4"CHB'!T49 -> 15075.113 | K20: ='1046 4"CHB'!T50 -> 0 | L20: =SUM(F20:K20) -> 173363.8 | M20: =L20/C20 -> 917.26878
A21: ='1046 6" CHB'!E5 -> 1046 | B21: ='1046 6" CHB'!G5 -> 150mm. CHB NON LOAD BEARING (including Reinforcing Steel) | C21: 36 | D21: ='1046 6" CHB'!E6 -> SQ.M. | E21: Total area of wall using 6" CHB | F21: ='1046 6" CHB'!T21 -> 4528.3 | G21: ='1046 6" CHB'!T30 -> 2400 | H21: ='1046 6" CHB'!T46 -> 33660 | I21: ='1046 6" CHB'!T48 -> 2029.415 | J21: ='1046 6" CHB'!T49 -> 4058.83 | K21: ='1046 6" CHB'!T50 -> 0 | L21: =SUM(F21:K21) -> 46676.545 | M21: =L21/C21 -> 1296.5707
A22: ='1027-Plaster'!E5 -> 1027(1) | B22: ='1027-Plaster'!G5 -> CEMENT PLASTER FINISH WITH 19MM THICK & 1:3 MORTAR MIXTURE | C22: 420 | D22: ='1027-Plaster'!G8 -> SQ.M. | E22: Total area of concrete surface to be plastered | F22: ='1027-Plaster'!T20 -> 26526.32 | G22: ='1027-Plaster'!T29 -> 2652.63 | H22: ='1027-Plaster'!T45 -> 57141 | I22: ='1027-Plaster'!T47 -> 4315.9975 | J22: ='1027-Plaster'!T48 -> 8631.995 | K22: ='1027-Plaster'!T49 -> 0 | L22: =SUM(F22:K22) -> 99267.942 | M22: =L22/C22 -> 236.35224
A23: ='1047(2)b Struc Steel Truss'!E5 -> 1047(2)b | B23: ='1047(2)b Struc Steel Truss'!G5 -> STRUCTURAL STEEL ROOF TRUSS | C23: 0 | D23: ='1047(2)b Struc Steel Truss'!G8 -> KGS. | E23: Determine the steel materials by direct counting on plan, then convert it to weight in kilograms | F23: ='1047(2)b Struc Steel Truss'!T27 -> 0 | G23: ='1047(2)b Struc Steel Truss'!T36 -> 0 | H23: ='1047(2)b Struc Steel Truss'!T52 -> 0 | I23: ='1047(2)b Struc Steel Truss'!T54 -> 0 | J23: ='1047(2)b Struc Steel Truss'!T55 -> 0 | K23: ='1047(2)b Struc Steel Truss'!T56 -> 0 | L23: =SUM(F23:K23) -> 0 | M23: =L23/C23 -> #DIV/0!
A24: ='1047(2)C Struc Steel Purlins'!E5 -> 1047(2)c | B24: ='1047(2)C Struc Steel Purlins'!G5 -> STRUCTURAL STEEL PURLINS | C24: 200 | D24: ='1047(2)C Struc Steel Purlins'!G8 -> KGS. | E24: Determine the number of C-Purlins by direct counting on plan, then convert it to weight in kilograms | F24: ='1047(2)C Struc Steel Purlins'!T21 -> 995.02 | G24: ='1047(2)C Struc Steel Purlins'!T30 -> 895.52 | H24: ='1047(2)C Struc Steel Purlins'!T44 -> 16107 | I24: ='1047(2)C Struc Steel Purlins'!T46 -> 899.877 | J24: ='1047(2)C Struc Steel Purlins'!T47 -> 1799.754 | K24: ='1047(2)C Struc Steel Purlins'!T48 -> 0 | L24: =SUM(F24:K24) -> 20697.171 | M24: =L24/C24 -> 103.48586
A25: ='1013(1) Corr Metal Roofing'!E5 -> 1013(1) | B25: ='1013(1) Corr Metal Roofing'!G5 -> CORRUGATED METAL ROOFING | C25: 0 | D25: ='1013(1) Corr Metal Roofing'!E6 -> SQ.M. | E25: Determine the roof area to be covered by corrugated roof sheet | F25: ='1013(1) Corr Metal Roofing'!T22 -> 0 | G25: ='1013(1) Corr Metal Roofing'!T31 -> 0 | H25: ='1013(1) Corr Metal Roofing'!T47 -> 0 | I25: ='1013(1) Corr Metal Roofing'!T47 -> 0 | J25: ='1013(1) Corr Metal Roofing'!T50 -> 0 | K25: ='1013(1) Corr Metal Roofing'!T51 -> 0 | L25: =SUM(F25:K25) -> 0 | M25: =L25/C25 -> #DIV/0!
A26: ='1013(2) Roof ridge flash valley'!E5 -> 1013(2) | B26: ='1013(2) Roof ridge flash valley'!G5 -> FABRICATED METAL ROOFING ACCESSORY (RIDGE/HIP ROLLS/FLASHING/COUNTER FLASHING/ VALLEY ROLL) | C26: 38 | D26: ='1013(2) Roof ridge flash valley'!E6 -> M. | E26: Determine the total length of Flashing, Ridge Roll and Valley Roll | F26: ='1013(2) Roof ridge flash valley'!T22 -> 855 | G26: ='1013(2) Roof ridge flash valley'!T31 -> 85.5 | H26: ='1013(2) Roof ridge flash valley'!T47 -> 8167.21 | I26: ='1013(2) Roof ridge flash valley'!T49 -> 455.3855 | J26: ='1013(2) Roof ridge flash valley'!T50 -> 910.771 | K26: ='1013(2) Roof ridge flash valley'!T51 -> 0 | L26: =SUM(F26:K26) -> 10473.867 | M26: =L26/C26 -> 275.62807
A27: ='1013(2) Metal Roof Acc (Gutter'!E5 -> 1013(2) | B27: ='1013(2) Metal Roof Acc (Gutter'!G5 -> FABRICATED METAL ROOFING ACCESSORY (GUTTER) | C27: 13 | D27: ='1013(2) Metal Roof Acc (Gutter'!G8 -> M. | E27: Determine the total length of Gutter | F27: ='1013(2) Metal Roof Acc (Gutter'!T22 -> 247.88 | G27: ='1013(2) Metal Roof Acc (Gutter'!T31 -> 24.79 | H27: ='1013(2) Metal Roof Acc (Gutter'!T48 -> 2941.34 | I27: ='1013(2) Metal Roof Acc (Gutter'!T50 -> 160.7005 | J27: ='1013(2) Metal Roof Acc (Gutter'!T51 -> 321.401 | K27: ='1013(2) Metal Roof Acc (Gutter'!T52 -> 0 | L27: =SUM(F27:K27) -> 3696.1115 | M27: =L27/C27 -> 284.31627
A28: ='1014 Prepainted Met Sheets-Roof'!E5 -> 1014 | B28: ='1014 Prepainted Met Sheets-Roof'!G5 -> PREPAINTED METAL SHEETS (CORRUGATE, SHORT SPAN/LONG SPAN) | C28: 0 | D28: ='1014 Prepainted Met Sheets-Roof'!E6 -> SQ.M. | E28: Determine the roof area to be covered by prepainted corrugated roof sheet | F28: ='1014 Prepainted Met Sheets-Roof'!T22 -> 0 | G28: ='1014 Prepainted Met Sheets-Roof'!T31 -> 0 | H28: ='1014 Prepainted Met Sheets-Roof'!T47 -> 0 | I28: ='1014 Prepainted Met Sheets-Roof'!T49 -> 0 | J28: ='1014 Prepainted Met Sheets-Roof'!T50 -> 0 | K28: ='1014 Prepainted Met Sheets-Roof'!T51 -> 0 | L28: =SUM(F28:K28) -> 0 | M28: =L28/C28 -> #DIV/0!
A29: ='1014 Prepainted Met Sheets RIB'!E5 -> 1014 | B29: ='1014 Prepainted Met Sheets RIB'!G5 -> PREPAINTED METAL SHEETS (RIB TYPE 0.4-0.5MM THICK) | C29: 140 | D29: ='1014 Prepainted Met Sheets RIB'!E6 -> SQ.M. | E29: Determine the roof area to be covered by prepainted rib-type roof sheet | F29: ='1014 Prepainted Met Sheets RIB'!T22 -> 13903.94 | G29: ='1014 Prepainted Met Sheets RIB'!T31 -> 1390.39 | H29: ='1014 Prepainted Met Sheets RIB'!T47 -> 53354 | I29: ='1014 Prepainted Met Sheets RIB'!T49 -> 3432.4165 | J29: ='1014 Prepainted Met Sheets RIB'!T50 -> 6864.833 | K29: ='1014 Prepainted Met Sheets RIB'!T51 -> 0 | L29: =SUM(F29:K29) -> 78945.58 | M29: =L29/C29 -> 563.897
A30: ='1016-Waterproof Cement'!E5 -> 1016(1)a | B30: ='1016-Waterproof Cement'!G5 -> WATERPROOFING CEMENT BASE | C30: 66 | D30: ='1016-Waterproof Cement'!E6 -> SQ.M. | E30: Determine the area for waterproofing | F30: ='1016-Waterproof Cement'!T20 -> 7920 | G30: ='1016-Waterproof Cement'!T29 -> 792 | H30: ='1016-Waterproof Cement'!T46 -> 3499.47 | I30: ='1016-Waterproof Cement'!T48 -> 610.5735 | J30: ='1016-Waterproof Cement'!T49 -> 1221.147 | K30: ='1016-Waterproof Cement'!T50 -> 0 | L30: =SUM(F30:K30) -> 14043.191 | M30: =L30/C30 -> 212.77561
A31: ='1018- Tiles'!E5 -> 1018 | B31: ='1018- Tiles'!G5 -> UNGLAZED TILES/ GRANITE TILES/ SYNTHETIC GRANITE TILES | C31: 80 | D31: ='1018- Tiles'!G8 -> SQ.M. | E31: Determine the area for tiles | F31: ='1018- Tiles'!T20 -> 29743.59 | G31: ='1018- Tiles'!T29 -> 2974.359 | H31: ='1018- Tiles'!T46 -> 70502 | I31: ='1018- Tiles'!T48 -> 5160.9974 | J31: ='1018- Tiles'!T49 -> 10321.995 | K31: ='1018- Tiles'!T50 -> 0 | L31: =SUM(F31:K31) -> 118702.94 | M31: =L31/C31 -> 1483.7868
A32: ='1003(1) Ceiling'!E5 -> 1003(1) | B32: ='1003(1) Ceiling'!G5 -> FIBER CEMENT BOARD/MARINE PLYWOOD/ORDINARY PLYWOOD ON METAL FRAME CEILING | C32: 130 | D32: ='1003(1) Ceiling'!G8 -> SQ.M. | E32: Determine the area for Ceiling | F32: ='1003(1) Ceiling'!T20 -> 28761.06 | G32: ='1003(1) Ceiling'!T29 -> 2876.106 | H32: ='1003(1) Ceiling'!T46 -> 125787.57 | I32: ='1003(1) Ceiling'!T48 -> 7871.2368 | J32: ='1003(1) Ceiling'!T49 -> 15742.474 | K32: ='1003(1) Ceiling'!T50 -> 0 | L32: =SUM(F32:K32) -> 181038.45 | M32: =L32/C32 -> 1392.6034
A33: ='1010(2) Hollow Flush Door'!E5 -> 1010(2)a | B33: ='1010(2) Hollow Flush Door'!G5 -> HOLLOW CORE FLUSH DOOR | C33: 5.04 | D33: ='1010(2) Hollow Flush Door'!G8 -> SQ.M. | E33: Determine and input the total area of flush type door | F33: ='1010(2) Hollow Flush Door'!T20 -> 3543.75 | G33: ='1010(2) Hollow Flush Door'!T29 -> 354.38 | H33: ='1010(2) Hollow Flush Door'!T46 -> 11550 | I33: ='1010(2) Hollow Flush Door'!T48 -> 772.4065 | J33: ='1010(2) Hollow Flush Door'!T49 -> 1544.813 | K33: ='1010(2) Hollow Flush Door'!T50 -> 0 | L33: =SUM(F33:K33) -> 17765.35 | M33: =L33/C33 -> 3524.8709
A34: ='1010(2) Panel Door'!E5 -> 1010(2) | B34: ='1010(2) Panel Door'!G5 -> WOODEN PANEL DOOR WITH HEAVY DUTY DOOR KNOB | C34: 2.1 | D34: ='1010(2) Panel Door'!G8 -> SQ.M. | E34: Determine the total area of Wooden Panel Door | F34: ='1010(2) Panel Door'!T20 -> 1604.17 | G34: ='1010(2) Panel Door'!T29 -> 160.42 | H34: ='1010(2) Panel Door'!T46 -> 6600 | I34: ='1010(2) Panel Door'!T48 -> 418.2295 | J34: ='1010(2) Panel Door'!T49 -> 836.459 | K34: ='1010(2) Panel Door'!T50 -> 0 | L34: =SUM(F34:K34) -> 9619.2785 | M34: =L34/C34 -> 4580.6088
A35: ='1043(1) PVC Door'!E5 -> 1043(1) | B35: ='1043(1) PVC Door'!G5 -> PVC DOORS AND FRAMES W/ HEAVY DUTY DOOR KNOB | C35: 1.26 | D35: ='1043(1) PVC Door'!G8 -> SQ.M. | E35: Determine the total area of PVC Door | F35: ='1043(1) PVC Door'!T20 -> 900 | G35: ='1043(1) PVC Door'!T29 -> 90 | H35: ='1043(1) PVC Door'!T45 -> 2625 | I35: ='1043(1) PVC Door'!T47 -> 180.75 | J35: ='1043(1) PVC Door'!T48 -> 361.5 | K35: ='1043(1) PVC Door'!T49 -> 0 | L35: =SUM(F35:K35) -> 4157.25 | M35: =L35/C35 -> 3299.4048
A36: ='1032-Paint Concrete'!E5 -> 1032(1)a | B36: ='1032-Paint Concrete'!G5 -> PAINTING WORKS (MASONRY PAINTING) | C36: 540 | D36: ='1032-Paint Concrete'!G8 -> SQ.M. | E36: Determine the area of concrete surface for painting | F36: ='1032-Paint Concrete'!T20 -> 77142.86 | G36: ='1032-Paint Concrete'!T29 -> 0 | H36: ='1032-Paint Concrete'!T46 -> 78160.1 | I36: ='1032-Paint Concrete'!T48 -> 7765.148 | J36: ='1032-Paint Concrete'!T49 -> 15530.296 | K36: ='1032-Paint Concrete'!T50 -> 0 | L36: =SUM(F36:K36) -> 178598.4 | M36: =L36/C36 -> 330.73779
A37: ='1032-Paint Metal'!E5 -> 1032(1)c | B37: ='1032-Paint Metal'!G5 -> PAINTING WORKS (METAL PAINTING) | C37: 45 | D37: ='1032-Paint Metal'!G8 -> SQ.M. | E37: Determine the area of metal surface for painting | F37: ='1032-Paint Metal'!T20 -> 6750 | G37: ='1032-Paint Metal'!T29 -> 0 | H37: ='1032-Paint Metal'!T46 -> 22411.13 | I37: ='1032-Paint Metal'!T48 -> 1458.0565 | J37: ='1032-Paint Metal'!T49 -> 2916.113 | K37: ='1032-Paint Metal'!T50 -> 0 | L37: =SUM(F37:K37) -> 33535.3 | M37: =L37/C37 -> 745.22888
A38: ='Sliding Glass'!E5 -> SPL - ? | B38: ='Sliding Glass'!G5 -> SUPPLY AND INSTALLATION OF ANALOK TYPE SLIDING WINDOW | C38: 11.34 | D38: ='Sliding Glass'!G8 -> SQ.M. | E38: Determine the total area of sliding window | F38: ='Sliding Glass'!T20 -> 0 | G38: ='Sliding Glass'!T29 -> 0 | H38: ='Sliding Glass'!T45 -> 45360 | I38: ='Sliding Glass'!T47 -> 2268 | J38: ='Sliding Glass'!T48 -> 4536 | K38: ='Sliding Glass'!T49 -> 0 | L38: =SUM(F38:K38) -> 52164 | M38: =L38/C38 -> 4600
A39: ='Other item-Civil Works'!E5 -> SPL - ? | B39: ='Other item-Civil Works'!G5 -> (INPUT ITEM DESCRIPTION) | C39: 1 | D39: ='Other item-Civil Works'!E6 -> L.S. | E39: If you need additional item that is not found in this spreadsheet, you may use this and go to "Other Item" Tab to create item of work | F39: ='Other item-Civil Works'!T20 -> 0 | G39: ='Other item-Civil Works'!T29 -> 0 | H39: ='Other item-Civil Works'!T45 -> 0 | I39: ='Other item-Civil Works'!T47 -> 0 | J39: ='Other item-Civil Works'!T48 -> 0 | K39: ='Other item-Civil Works'!T49 -> 0 | L39: =SUM(F39:K39) -> 0 | M39: =L39/C39 -> 0
A40: PLUMBING WORKS
A41: ='1001(1)a 2" -4" San PVC Pipe'!E5 -> 1001(1)a | B41: ='1001(1)a 2" -4" San PVC Pipe'!G5 -> 50MM DIA - 100MM DIA SANITARY PVC PIPE, SERIES 600/1000 | C41: 12 | D41: ='1001(1)a 2" -4" San PVC Pipe'!E6 -> M. | E41: Determine the number and length of Sanitary Pipes by Sizes and indicate in in the estimate DUPA tab | F41: ='1001(1)a 2" -4" San PVC Pipe'!T20 -> 1100 | G41: ='1001(1)a 2" -4" San PVC Pipe'!T29 -> 110 | H41: ='1001(1)a 2" -4" San PVC Pipe'!T45 -> 1980 | I41: ='1001(1)a 2" -4" San PVC Pipe'!T47 -> 159.5 | J41: ='1001(1)a 2" -4" San PVC Pipe'!T48 -> 319 | K41: ='1001(1)a 2" -4" San PVC Pipe'!T49 -> 0 | L41: =SUM(F41:K41) -> 3668.5 | M41: =L41/C41 -> 305.70833
A42: ='1002(6) Waterline Pipes fitting'!E5 -> 1002(6) | B42: ='1002(6) Waterline Pipes fitting'!G5 -> WATERLINE PIPES & FITTINGS | C42: 1 | D42: ='1002(6) Waterline Pipes fitting'!G8 -> L.S. | E42: It is suggested that the unit for this item is always 1.00 Lump Sum. The estimator shall go to its DUPA tab and indicate the necessary materials, tools and manpower | F42: ='1002(6) Waterline Pipes fitting'!T20 -> 2200 | G42: ='1002(6) Waterline Pipes fitting'!T29 -> 220 | H42: ='1002(6) Waterline Pipes fitting'!T45 -> 2780 | I42: ='1002(6) Waterline Pipes fitting'!T47 -> 260 | J42: ='1002(6) Waterline Pipes fitting'!T48 -> 520 | K42: ='1002(6) Waterline Pipes fitting'!T49 -> 0 | L42: =SUM(F42:K42) -> 5980 | M42: =L42/C42 -> 5980
A43: ='1002(5) W Closet w acc'!E5 -> 1002(5) | B43: ='1002(5) W Closet w acc'!G5 -> WATER CLOSET/ URINAL W/ COMPLETE ACCESSORIES | C43: 1 | D43: ='1002(5) W Closet w acc'!G8 -> SET | E43: Input the total quantity of the water closet plus urinal. Also, go to the DUPA and input in the necessary materials. | F43: ='1002(5) W Closet w acc'!T20 -> 450 | G43: ='1002(5) W Closet w acc'!T29 -> 45 | H43: ='1002(5) W Closet w acc'!T45 -> 6600 | I43: ='1002(5) W Closet w acc'!T47 -> 354.75 | J43: ='1002(5) W Closet w acc'!T48 -> 709.5 | K43: ='1002(5) W Closet w acc'!T49 -> 0 | L43: =SUM(F43:K43) -> 8159.25 | M43: =L43/C43 -> 8159.25
A44: ='1002(5) Kitch SInk'!E5 -> 1002(5) | B44: ='1002(5) Kitch SInk'!G5 -> KITCHEN SINK/ SCRUB/ SLOP SINK W/ COMPLETE ACCESSORIES | C44: 1 | D44: ='1002(5) Kitch SInk'!G8 -> SET | E44: Input the total quantity of the Sinks. Also, go to the DUPA and input in the necessary materials. | F44: ='1002(5) Kitch SInk'!T20 -> 450 | G44: ='1002(5) Kitch SInk'!T29 -> 45 | H44: ='1002(5) Kitch SInk'!T45 -> 4950 | I44: ='1002(5) Kitch SInk'!T47 -> 272.25 | J44: ='1002(5) Kitch SInk'!T48 -> 544.5 | K44: ='1002(5) Kitch SInk'!T49 -> 0 | L44: =SUM(F44:K44) -> 6261.75 | M44: =L44/C44 -> 6261.75
A45: ='1002(5) Counter Lavatory'!E5 -> 1002(5) | B45: ='1002(5) Counter Lavatory'!G5 -> WALL HANG/COUNTERTOP/ UNDER COUNTER LAVATORY W/ COMPLETE ACCESSORIES | C45: 1 | D45: ='1002(5) Counter Lavatory'!G8 -> SET | E45: Input the total quantity of the Countertops/Lavatory. Also, go to the DUPA and input in the necessary materials. | F45: ='1002(5) Counter Lavatory'!T20 -> 450 | G45: ='1002(5) Counter Lavatory'!T29 -> 45 | H45: ='1002(5) Counter Lavatory'!T45 -> 3850 | I45: ='1002(5) Counter Lavatory'!T47 -> 217.25 | J45: ='1002(5) Counter Lavatory'!T48 -> 434.5 | K45: ='1002(5) Counter Lavatory'!T49 -> 0 | L45: =SUM(F45:K45) -> 4996.75 | M45: =L45/C45 -> 4996.75
A46: ='1002(5) h Floor Drain'!E5 -> 1002(5) | B46: ='1002(5) h Floor Drain'!G5 -> FLOOR DRAIN PLATES (ANY SIZE) | C46: 2 | D46: ='1002(5) h Floor Drain'!G8 -> SET | E46: Input the total number of floor drain. Go to DUPA and update or input the necessary materials | F46: ='1002(5) h Floor Drain'!T20 -> 180 | G46: ='1002(5) h Floor Drain'!T29 -> 18 | H46: ='1002(5) h Floor Drain'!T45 -> 770 | I46: ='1002(5) h Floor Drain'!T47 -> 48.4 | J46: ='1002(5) h Floor Drain'!T48 -> 96.8 | K46: ='1002(5) h Floor Drain'!T49 -> 0 | L46: =SUM(F46:K46) -> 1113.2 | M46: =L46/C46 -> 556.6
A47: ='1002(5) Soap Holder'!E5 -> 1002(5) | B47: ='1002(5) Soap Holder'!G5 -> SOAP HOLDER /TOILET SOAP/LIQUID SOAP/TISSUE HOLDER | C47: 1 | D47: ='1002(5) Soap Holder'!G8 -> SET | E47: Input the total number of Toilet & Soap Holder. Go to DUPA and update or input the necessary materials | F47: ='1002(5) Soap Holder'!T20 -> 168.75 | G47: ='1002(5) Soap Holder'!T29 -> 16.875 | H47: ='1002(5) Soap Holder'!T45 -> 385 | I47: ='1002(5) Soap Holder'!T47 -> 28.53125 | J47: ='1002(5) Soap Holder'!T48 -> 57.0625 | K47: ='1002(5) Soap Holder'!T49 -> 0 | L47: =SUM(F47:K47) -> 656.21875 | M47: =L47/C47 -> 656.21875
A48: ='1002(5)p Facial Mirror'!E5 -> 1002(5)p | B48: ='1002(5)p Facial Mirror'!G5 -> FACIAL MIRROR | C48: 0.5 | D48: ='1002(5)p Facial Mirror'!G8 -> SQ.M. | E48: Input the area of the mirrior. Update the DUPA by inputting the necessary materials | F48: ='1002(5)p Facial Mirror'!T20 -> 281.25 | G48: ='1002(5)p Facial Mirror'!T29 -> 28.125 | H48: ='1002(5)p Facial Mirror'!T45 -> 495 | I48: ='1002(5)p Facial Mirror'!T47 -> 40.21875 | J48: ='1002(5)p Facial Mirror'!T48 -> 80.4375 | K48: ='1002(5)p Facial Mirror'!T49 -> 0 | L48: =SUM(F48:K48) -> 925.03125 | M48: =L48/C48 -> 1850.0625
A49: ='Other item-Plumbing'!E5 -> SPL- ? | B49: ='Other item-Plumbing'!G5 -> (INPUT OTHER PLUMBING WORK ITEM THAT IS NOT FOUND IN THIS SPREADSHEET) | C49: 1 | D49: ='Other item-Plumbing'!G8 -> L.S. | E49: Go to DUPA Tab and input the necessary materials, manpower and equipment requirements. | F49: ='Other item-Plumbing'!T20 -> 0 | G49: ='Other item-Plumbing'!T29 -> 0 | H49: ='Other item-Plumbing'!T45 -> 0 | I49: ='Other item-Plumbing'!T47 -> 0 | J49: ='Other item-Plumbing'!T48 -> 0 | K49: ='Other item-Plumbing'!T49 -> 0 | L49: =SUM(F49:K49) -> 0 | M49: =L49/C49 -> 0
A50: ELECTRICAL WORKS
A51: ='1100(1) Conduit'!E5 -> 1002(5) | B51: ='1100(1) Conduit'!G5 -> 15MM-25MM DIA. FLEXIBLE CONDUIT | C51: 200 | D51: ='1100(1) Conduit'!G8 -> M. | E51: Input the total length of the conduit and update the materials requirement in the DUPA Tab | F51: ='1100(1) Conduit'!T20 -> 12733.45 | G51: ='1100(1) Conduit'!T29 -> 1273.345 | H51: ='1100(1) Conduit'!T45 -> 3300 | I51: ='1100(1) Conduit'!T47 -> 865.33975 | J51: ='1100(1) Conduit'!T48 -> 1730.6795 | K51: ='1100(1) Conduit'!T49 -> 0 | L51: =SUM(F51:K51) -> 19902.814 | M51: =L51/C51 -> 99.514071
A52: ='1100 Junc Utility Box'!E5 -> 1100 | B52: ='1100 Junc Utility Box'!G5 -> JUNCTION UTILITY/PULL / SQUARE BOX | C52: 33 | D52: ='1100 Junc Utility Box'!G8 -> PC. | E52: Inpu the total number of utility box, junction box. Go to DUPA Tab and update the necessary materials | F52: ='1100 Junc Utility Box'!T20 -> 2970 | G52: ='1100 Junc Utility Box'!T29 -> 297 | H52: ='1100 Junc Utility Box'!T45 -> 1633.5 | I52: ='1100 Junc Utility Box'!T47 -> 245.025 | J52: ='1100 Junc Utility Box'!T48 -> 490.05 | K52: ='1100 Junc Utility Box'!T49 -> 0 | L52: =SUM(F52:K52) -> 5635.575 | M52: =L52/C52 -> 170.775
A53: ='1101(2) 1.6-5.5 mm2 Elec Wire'!E5 -> 1101(2) | B53: ='1101(2) 1.6-5.5 mm2 Elec Wire'!G5 -> 1.6MM2 - 5.5MM2 ELECTRIC WIRE (TW/THHN/TWHN2) | C53: 600 | D53: ='1101(2) 1.6-5.5 mm2 Elec Wire'!E6 -> M. | E53: Input the total length of Electrical Wire. Go to DUPA Tab and breakdown the materials accroding to wire size | F53: ='1101(2) 1.6-5.5 mm2 Elec Wire'!T20 -> 5400 | G53: ='1101(2) 1.6-5.5 mm2 Elec Wire'!T29 -> 540 | H53: ='1101(2) 1.6-5.5 mm2 Elec Wire'!T45 -> 19140 | I53: ='1101(2) 1.6-5.5 mm2 Elec Wire'!T47 -> 1254 | J53: ='1101(2) 1.6-5.5 mm2 Elec Wire'!T48 -> 2508 | K53: ='1101(2) 1.6-5.5 mm2 Elec Wire'!T49 -> 0 | L53: =SUM(F53:K53) -> 28842 | M53: =L53/C53 -> 48.07
A54: ='1101 Single C Outlet'!E5 -> 1101 | B54: ='1101 Single C Outlet'!G5 -> SINGLE CONVINENCE OUTLET/ RECEPTACLE, GROUNDING TYPE/HEAVY DUTY CONVENIENCE OUTLET | C54: 13 | D54: ='1101 Single C Outlet'!E6 -> SET | E54: Input the total number of Single Convenience Outlet | F54: ='1101 Single C Outlet'!T20 -> 731.25 | G54: ='1101 Single C Outlet'!T29 -> 0 | H54: ='1101 Single C Outlet'!T45 -> 2574 | I54: ='1101 Single C Outlet'!T47 -> 165.2625 | J54: ='1101 Single C Outlet'!T48 -> 330.525 | K54: ='1101 Single C Outlet'!T49 -> 0 | L54: =SUM(F54:K54) -> 3801.0375 | M54: =L54/C54 -> 292.3875
A55: ='1101 Duplex C Outlet'!E5 -> 1101 | B55: ='1101 Duplex C Outlet'!G5 -> DUPLEX CONVINENCE OUTLET/ RECEPTACLE, GROUNDING TYPE/HEAVY DUTY CONVENIENCE OUTLET | C55: 10 | D55: ='1101 Duplex C Outlet'!E6 -> SET | E55: Input the total number of Double Convenience Outlet | F55: ='1101 Duplex C Outlet'!T20 -> 675 | G55: ='1101 Duplex C Outlet'!T29 -> 0 | H55: ='1101 Duplex C Outlet'!T45 -> 2530 | I55: ='1101 Duplex C Outlet'!T47 -> 160.25 | J55: ='1101 Duplex C Outlet'!T48 -> 320.5 | K55: ='1101 Duplex C Outlet'!T49 -> 0 | L55: =SUM(F55:K55) -> 3685.75 | M55: =L55/C55 -> 368.575
A56: ='1102 Panel Board'!E5 -> 1102 | B56: ='1102 Panel Board'!G5 -> PANEL BOARD WITH MAIN BREAKER/BRANCHES, 3 WIRES, 1 NEUTRAL, 50AMP-200AMP | C56: 1 | D56: ='1102 Panel Board'!G8 -> SET | E56: Input the number of set. Go to DUPA tab and update the materials component and indicate the needed Circuit Breakers. | F56: ='1102 Panel Board'!T20 -> 1512.5 | G56: ='1102 Panel Board'!T29 -> 0 | H56: ='1102 Panel Board'!T45 -> 6656 | I56: ='1102 Panel Board'!T47 -> 408.425 | J56: ='1102 Panel Board'!T48 -> 816.85 | K56: ='1102 Panel Board'!T49 -> 0 | L56: =SUM(F56:K56) -> 9393.775 | M56: =L56/C56 -> 9393.775
A57: ='1103(2) Lighting Fixtures'!E5 -> 1103(2) | B57: ='1103(2) Lighting Fixtures'!G5 -> FLOURESCENT LIGHTING FIXTURE WITH BALLAST/ LIGHT EMITTING DIODE (LED) BULB, 1 BULB | C57: 40 | D57: ='1103(2) Lighting Fixtures'!G8 -> SET | E57: Count and input the number of Bulbs. Go to DUPA tab to update the materials requirements | F57: ='1103(2) Lighting Fixtures'!T20 -> 9000 | G57: ='1103(2) Lighting Fixtures'!T29 -> 900 | H57: ='1103(2) Lighting Fixtures'!T45 -> 7920 | I57: ='1103(2) Lighting Fixtures'!T47 -> 891 | J57: ='1103(2) Lighting Fixtures'!T48 -> 1782 | K57: ='1103(2) Lighting Fixtures'!T49 -> 0 | L57: =SUM(F57:K57) -> 20493 | M57: =L57/C57 -> 512.325
A58: ='Other item-Electrical'!E5 -> SPL- ? | B58: ='Other item-Electrical'!G5 -> (INPUT OTHER ELECTRICAL WORK ITEM THAT IS NOT FOUND IN THIS SPREADSHEET) | C58: 1 | D58: ='Other item-Electrical'!G8 -> L.S. | E58: Go to DUPA Tab and input the necessary materials, manpower and equipment requirements. | F58: ='Other item-Electrical'!T20 -> 0 | G58: ='Other item-Electrical'!T29 -> 0 | H58: ='Other item-Electrical'!T45 -> 0 | I58: ='Other item-Electrical'!T47 -> 0 | J58: ='Other item-Electrical'!T48 -> 0 | K58: ='Other item-Electrical'!T49 -> 0 | L58: =SUM(F58:K58) -> 0
F59: =SUM(F10:F58) -> 326736.9 | G59: =SUM(G10:G58) -> 90193.33 | H59: =SUM(H10:H58) -> 1013330.9 | I59: =SUM(I10:I58) -> 71513.054 | J59: =SUM(J10:J58) -> 143026.11 | K59: =SUM(K10:K58) -> 0 | L59: =SUM(L10:L58) -> 1644800.3
B61: MARK-UPS | F61: Manpower /Labor | G61: Equipment/ Tools | H61: Materials | I61: OCM | J61: Profit | K61: VAT | L61: Total Cost
B62: OCM | C62: 0.05
B63: PROFIT | C63: 0.1
B64: VALUE ADDED TAX (VAT) | C64: 0

Sheet BOE
B6: PROJECT TITLE: | F6: ='INPUT DATA'!C4 -> PROPOSED ONE STOREY TWO BED ROOM RESIDENTIAL BUILDING
B7: Project Location: | F7: ='INPUT DATA'!C5 -> ANGELES, PAMPANGA
B9: BREAKDOWN OF EXPENDITURES | N9: % OF TOTAL | Q9: AMOUNT | U9: PERCENTAGE
C10: DIRECT COST:
D11: Materials | N11: =Q11/$Q$20 -> 0.61608141 | Q11: ='INPUT DATA'!H59 -> 1013330.9 | U11: =Q11/$Q$14 -> 0.70849362 | V11: MATERIALS
D12: Labor/Manpower | N12: =Q12/$Q$20 -> 0.19864838 | Q12: ='INPUT DATA'!F59 -> 326736.9 | U12: =Q12/$Q$14 -> 0.22844563 | V12: LABOR
D13: Equipment/Tools Expenses | N13: =Q13/$Q$20 -> 0.054835431 | Q13: ='INPUT DATA'!G59 -> 90193.33 | U13: =Q13/$Q$14 -> 0.063060745 | V13: EQUIPMENT
B14: S U B - T O T A L (DIRECT COST) | N14: =SUM(N11:P13) -> 0.86956522 | Q14: =SUM(Q11:S13) -> 1430261.1 | AG14: =AI14 -> 34376992 | AH14: xxx p-1 | AI14: 34376992
C15: INDIRECT COST:
D16: Overhead, Contingency & Misc. | N16: =Q16/$Q$20 -> 0.043478261 | Q16: ='INPUT DATA'!I59 -> 71513.054
D17: Contractor's Profit | N17: =Q17/$Q$20 -> 0.086956522 | Q17: ='INPUT DATA'!J59 -> 143026.11
D18: Value Added Tax | N18: =Q18/$Q$20 -> 0 | Q18: ='INPUT DATA'!K59 -> 0
B19: S U B - T O T A L (INDIRECT COST)
B20: TOTAL PROJECT COST | N20: =SUM(N16:P18)+N14 -> 1 | Q20: =SUM(Q16:S18)+Q14 -> 1644800.3 | AG20: 27089626
C23: Prepared by:
E26: Licensed Engineer/Registered Master Plumber/Master Electrician
C38: NOTE:
C40: 1. FOR QUERIES REGARDING THIS, YOU MAY COMMUNICATE WITH THE AUTHOR AT em.bautistajr@yahoo.com OR ON HIS YOUTUBE CHANNEL
C41: 2. THIS ESTIMATE FORMAT IN DETAILED UNIT PRICE ANALYSIS IS A PERSONAL PROPERTY OF ENGR. EDITO M. BAUTISTA, JR. CE, EnP, RMP, RME
C42: 3. IF YOU USE THIS IN A STUDY OR RESEARCH, PLEASE ACKNOWLEDGE THE AUTHOR.
C43: 4. DISCLAIMER: THE AUTHOR OF THIS SPREADSHEET IS DENYING ANY AND ALL LIABILITY FOR ANY DAMAGES ARISING OUT FROM USING THIS SPREADSHEET.
C44: 5. THE BASIS FOR THE DERIVATION OF THIS SPREADSHEET IS THE DPWH DEPARTMENT ORDER NO. 137 SERIES OF 2017, COST ESTIMATION MANUAL FOR LOW RISE BUILDING (UPTO 5 STOREY BUILDING)
C45: 6. THE USER MAY CHANGE THE MANPOWER RATES, EQUIPMENT RATES, MATERIALS PRICES AND THE MARK-UPS (OCM, PROFIT & TAX)

Sheet ABC
A2: =BOE!B2 -> 0
B6: =BOE!B6 -> PROJECT TITLE: | D6: ='INPUT DATA'!C4 -> PROPOSED ONE STOREY TWO BED ROOM RESIDENTIAL BUILDING
B7: =BOE!B7 -> Project Location: | D7: ='INPUT DATA'!C5 -> ANGELES, PAMPANGA
B10: DESCRIPTION | D10: QUANTITY | E10: UNIT | G10: MARK-UPS | I10: TOTAL MARK-UP | K10: VAT | M10: TOTAL COST
A11: ITEM | F11: ESTIMATED | G11: IN PERCENT | L11: TOTAL | O11: UNIT
A12: NO. | F12: DIRECT COST | G12: OCM | H12: PROFIT | I12: % | J12: VALUE | L12: INDIRECT COST | O12: COST
A14: -1 | B14: -2 | D14: -3 | E14: -4 | F14: -5 | G14: -6 | H14: -7 | I14: -8 | J14: -9 | K14: -10 | L14: -11 | M14: -12 | O14: -13
J15: (5)X(8) | K15: (5)+(9)) | L15: (9)+(10) | M15: (5)+(11) | O15: (12)/(3)
A16: ='INPUT DATA'!A9 -> ARCHITECTURAL / CIVIL WORKS
A17: ='INPUT DATA'!A10 -> 800(1) | B17: ='INPUT DATA'!B10 -> CLEARING AND GRUBBING | D17: ='INPUT DATA'!C10 -> 200 | E17: ='INPUT DATA'!D10 -> SQ.M. | F17: ='INPUT DATA'!F10+'INPUT DATA'!G10+'INPUT DATA'!H10 -> 22155.2 | G17: ='INPUT DATA'!$C$62 -> 0.05 | H17: ='INPUT DATA'!$C$63 -> 0.1 | I17: =H17+G17 -> 0.15 | J17: =I17*F17 -> 3323.28 | K17: ='INPUT DATA'!$C$64*(ABC!J17+ABC!F17) -> 0 | L17: =J17+K17 -> 3323.28 | M17: =L17+F17 -> 25478.48 | O17: =M17/D17 -> 127.3924 | P17: =M17-'INPUT DATA'!L10 -> 0
A18: ='INPUT DATA'!A11 -> 800(3)a | B18: ='INPUT DATA'!B11 -> INDIVIDUAL REMOVAL OF TREES (UPTO 300MM DIAMETER) | D18: ='INPUT DATA'!C11 -> 2 | E18: ='INPUT DATA'!D11 -> EACH | F18: ='INPUT DATA'!F11+'INPUT DATA'!G11+'INPUT DATA'!H11 -> 4458.94 | G18: ='INPUT DATA'!$C$62 -> 0.05 | H18: ='INPUT DATA'!$C$63 -> 0.1 | I18: =H18+G18 -> 0.15 | J18: =I18*F18 -> 668.841 | K18: ='INPUT DATA'!$C$64*(ABC!J18+ABC!F18) -> 0 | L18: =J18+K18 -> 668.841 | M18: =L18+F18 -> 5127.781 | O18: =M18/D18 -> 2563.8905 | P18: =M18-'INPUT DATA'!L11 -> 0
A19: ='INPUT DATA'!A12 -> 803(1)a | B19: ='INPUT DATA'!B12 -> STRUCTURE EXCAVATION (COMMON SOIL) | D19: ='INPUT DATA'!C12 -> 23 | E19: ='INPUT DATA'!D12 -> CU.M. | F19: ='INPUT DATA'!F12+'INPUT DATA'!G12+'INPUT DATA'!H12 -> 5193.4 | G19: ='INPUT DATA'!$C$62 -> 0.05 | H19: ='INPUT DATA'!$C$63 -> 0.1 | I19: =H19+G19 -> 0.15 | J19: =I19*F19 -> 779.01 | K19: ='INPUT DATA'!$C$64*(ABC!J19+ABC!F19) -> 0 | L19: =J19+K19 -> 779.01 | M19: =L19+F19 -> 5972.41 | O19: =M19/D19 -> 259.67 | P19: =M19-'INPUT DATA'!L12 -> 0
A20: ='INPUT DATA'!A13 -> 803(1)a | B20: ='INPUT DATA'!B13 -> STRUCTURE EXCAVATION (SOFT ROCK) | D20: ='INPUT DATA'!C13 -> 0 | E20: ='INPUT DATA'!D13 -> CU.M. | F20: ='INPUT DATA'!F13+'INPUT DATA'!G13+'INPUT DATA'!H13 -> 0 | G20: ='INPUT DATA'!$C$62 -> 0.05 | H20: ='INPUT DATA'!$C$63 -> 0.1 | I20: =H20+G20 -> 0.15 | J20: =I20*F20 -> 0 | K20: ='INPUT DATA'!$C$64*(ABC!J20+ABC!F20) -> 0 | L20: =J20+K20 -> 0 | M20: =L20+F20 -> 0 | O20: =M20/D20 -> #DIV/0! | P20: =M20-'INPUT DATA'!L13 -> 0
A21: ='INPUT DATA'!A14 -> 804(4) | B21: ='INPUT DATA'!B14 -> GRAVEL BEDDING | D21: ='INPUT DATA'!C14 -> 3 | E21: ='INPUT DATA'!D14 -> CU.M. | F21: ='INPUT DATA'!F14+'INPUT DATA'!G14+'INPUT DATA'!H14 -> 5502.5 | G21: ='INPUT DATA'!$C$62 -> 0.05 | H21: ='INPUT DATA'!$C$63 -> 0.1 | I21: =H21+G21 -> 0.15 | J21: =I21*F21 -> 825.375 | K21: ='INPUT DATA'!$C$64*(ABC!J21+ABC!F21) -> 0 | L21: =J21+K21 -> 825.375 | M21: =L21+F21 -> 6327.875 | O21: =M21/D21 -> 2109.2917 | P21: =M21-'INPUT DATA'!L14 -> 0
A22: ='INPUT DATA'!A15 -> 902(1) | B22: ='INPUT DATA'!B15 -> REINFORCING STEEL OF REINFORCED CONCRETE STRUCTURES FOR ONE-STOREY, GRADE 40/60 | D22: ='INPUT DATA'!C15 -> 1200 | E22: ='INPUT DATA'!D15 -> KGS. | F22: ='INPUT DATA'!F15+'INPUT DATA'!G15+'INPUT DATA'!H15 -> 107711.97 | G22: ='INPUT DATA'!$C$62 -> 0.05 | H22: ='INPUT DATA'!$C$63 -> 0.1 | I22: =H22+G22 -> 0.15 | J22: =I22*F22 -> 16156.796 | K22: ='INPUT DATA'!$C$64*(ABC!J22+ABC!F22) -> 0 | L22: =J22+K22 -> 16156.796 | M22: =L22+F22 -> 123868.77 | O22: =M22/D22 -> 103.22397 | P22: =M22-'INPUT DATA'!L15 -> 0
A23: ='INPUT DATA'!A16 -> 902(1) | B23: ='INPUT DATA'!B16 -> REINFORCING STEEL OF REINFORCED CONCRETE STRUCTURES FOR TWO UPTO FIVE STOREY | D23: ='INPUT DATA'!C16 -> 50 | E23: ='INPUT DATA'!D16 -> KGS. | F23: ='INPUT DATA'!F16+'INPUT DATA'!G16+'INPUT DATA'!H16 -> 4513.1 | G23: ='INPUT DATA'!$C$62 -> 0.05 | H23: ='INPUT DATA'!$C$63 -> 0.1 | I23: =H23+G23 -> 0.15 | J23: =I23*F23 -> 676.965 | K23: ='INPUT DATA'!$C$64*(ABC!J23+ABC!F23) -> 0 | L23: =J23+K23 -> 676.965 | M23: =L23+F23 -> 5190.065 | O23: =M23/D23 -> 103.8013 | P23: =M23-'INPUT DATA'!L16 -> 0
A24: ='INPUT DATA'!A17 -> 900(1)c2 | B24: ='INPUT DATA'!B17 -> STRUCTURAL CONCRETE FOR FOOTING AND SLAB ON FILL (CLASS A, 28 DAYS) | D24: ='INPUT DATA'!C17 -> 12.4 | E24: ='INPUT DATA'!D17 -> CU.M. | F24: ='INPUT DATA'!F17+'INPUT DATA'!G17+'INPUT DATA'!H17 -> 76244.56 | G24: ='INPUT DATA'!$C$62 -> 0.05 | H24: ='INPUT DATA'!$C$63 -> 0.1 | I24: =H24+G24 -> 0.15 | J24: =I24*F24 -> 11436.684 | K24: ='INPUT DATA'!$C$64*(ABC!J24+ABC!F24) -> 0 | L24: =J24+K24 -> 11436.684 | M24: =L24+F24 -> 87681.244 | O24: =M24/D24 -> 7071.0681 | P24: =M24-'INPUT DATA'!L17 -> 0
A25: ='INPUT DATA'!A18 -> 900(1) | B25: ='INPUT DATA'!B18 -> STRUCTURAL CONCRETE FOR FOOTING TIE BEAM, COLUMN, SUSPENDED SLAB, GIRDER/BEAM (CLASS A, 28 DAYS) | D25: ='INPUT DATA'!C18 -> 23.6 | E25: ='INPUT DATA'!D18 -> CU.M. | F25: ='INPUT DATA'!F18+'INPUT DATA'!G18+'INPUT DATA'!H18 -> 150481.03 | G25: ='INPUT DATA'!$C$62 -> 0.05 | H25: ='INPUT DATA'!$C$63 -> 0.1 | I25: =H25+G25 -> 0.15 | J25: =I25*F25 -> 22572.155 | K25: ='INPUT DATA'!$C$64*(ABC!J25+ABC!F25) -> 0 | L25: =J25+K25 -> 22572.155 | M25: =L25+F25 -> 173053.18 | O25: =M25/D25 -> 7332.7621 | P25: =M25-'INPUT DATA'!L18 -> 0
A26: ='INPUT DATA'!A19 -> 903(2) | B26: ='INPUT DATA'!B19 -> FORMWORKS AND FALSEWORKS (FOR ONE-STOREY BUILDING) | D26: ='INPUT DATA'!C19 -> 49 | E26: ='INPUT DATA'!D19 -> SQ.M. | F26: ='INPUT DATA'!F19+'INPUT DATA'!G19+'INPUT DATA'!H19 -> 39861.41 | G26: ='INPUT DATA'!$C$62 -> 0.05 | H26: ='INPUT DATA'!$C$63 -> 0.1 | I26: =H26+G26 -> 0.15 | J26: =I26*F26 -> 5979.2115 | K26: ='INPUT DATA'!$C$64*(ABC!J26+ABC!F26) -> 0 | L26: =J26+K26 -> 5979.2115 | M26: =L26+F26 -> 45840.621 | O26: =M26/D26 -> 935.52289 | P26: =M26-'INPUT DATA'!L19 -> 0
A27: ='INPUT DATA'!A20 -> 1046 | B27: ='INPUT DATA'!B20 -> 100MM CHB NON LOAD BEARING/LOAD BEARING (INCLUDING REINFORCING STEEL) | D27: ='INPUT DATA'!C20 -> 189 | E27: ='INPUT DATA'!D20 -> SQ.M. | F27: ='INPUT DATA'!F20+'INPUT DATA'!G20+'INPUT DATA'!H20 -> 150751.13 | G27: ='INPUT DATA'!$C$62 -> 0.05 | H27: ='INPUT DATA'!$C$63 -> 0.1 | I27: =H27+G27 -> 0.15 | J27: =I27*F27 -> 22612.67 | K27: ='INPUT DATA'!$C$64*(ABC!J27+ABC!F27) -> 0 | L27: =J27+K27 -> 22612.67 | M27: =L27+F27 -> 173363.8 | O27: =M27/D27 -> 917.26878 | P27: =M27-'INPUT DATA'!L20 -> 0
A28: ='INPUT DATA'!A21 -> 1046 | B28: ='INPUT DATA'!B21 -> 150mm. CHB NON LOAD BEARING (including Reinforcing Steel) | D28: ='INPUT DATA'!C21 -> 36 | E28: ='INPUT DATA'!D21 -> SQ.M. | F28: ='INPUT DATA'!F21+'INPUT DATA'!G21+'INPUT DATA'!H21 -> 40588.3 | G28: ='INPUT DATA'!$C$62 -> 0.05 | H28: ='INPUT DATA'!$C$63 -> 0.1 | I28: =H28+G28 -> 0.15 | J28: =I28*F28 -> 6088.245 | K28: ='INPUT DATA'!$C$64*(ABC!J28+ABC!F28) -> 0 | L28: =J28+K28 -> 6088.245 | M28: =L28+F28 -> 46676.545 | O28: =M28/D28 -> 1296.5707 | P28: =M28-'INPUT DATA'!L21 -> 0
... A46: ='INPUT DATA'!A39 -> SPL - ? | B46: ='INPUT DATA'!B39 -> (INPUT ITEM DESCRIPTION) | D46: ='INPUT DATA'!C39 -> 1 | E46: ='INPUT DATA'!D39 -> L.S. | F46: ='INPUT DATA'!F39+'INPUT DATA'!G39+'INPUT DATA'!H39 -> 0 | G46: ='INPUT DATA'!$C$62 -> 0.05 | H46: ='INPUT DATA'!$C$63 -> 0.1 | I46: =H46+G46 -> 0.15 | J46: =I46*F46 -> 0 | K46: ='INPUT DATA'!$C$64*(ABC!J46+ABC!F46) -> 0 | L46: =J46+K46 -> 0 | M46: =L46+F46 -> 0 | O46: =M46/D46 -> 0 | P46: =M46-'INPUT DATA'!L39 -> 0
A47: ='INPUT DATA'!A40 -> PLUMBING WORKS | P47: =M47-'INPUT DATA'!L40 -> 0
A48: ='INPUT DATA'!A41 -> 1001(1)a | B48: ='INPUT DATA'!B41 -> 50MM DIA - 100MM DIA SANITARY PVC PIPE, SERIES 600/1000 | D48: ='INPUT DATA'!C41 -> 12 | E48: ='INPUT DATA'!D41 -> M. | F48: ='INPUT DATA'!F41+'INPUT DATA'!G41+'INPUT DATA'!H41 -> 3190 | G48: ='INPUT DATA'!$C$62 -> 0.05 | H48: ='INPUT DATA'!$C$63 -> 0.1 | I48: =H48+G48 -> 0.15 | J48: =I48*F48 -> 478.5 | K48: ='INPUT DATA'!$C$64*(ABC!J48+ABC!F48) -> 0 | L48: =J48+K48 -> 478.5 | M48: =L48+F48 -> 3668.5 | O48: =M48/D48 -> 305.70833 | P48: =M48-'INPUT DATA'!L41 -> 0
A49: ='INPUT DATA'!A42 -> 1002(6) | B49: ='INPUT DATA'!B42 -> WATERLINE PIPES & FITTINGS | D49: ='INPUT DATA'!C42 -> 1 | E49: ='INPUT DATA'!D42 -> L.S. | F49: ='INPUT DATA'!F42+'INPUT DATA'!G42+'INPUT DATA'!H42 -> 5200 | G49: ='INPUT DATA'!$C$62 -> 0.05 | H49: ='INPUT DATA'!$C$63 -> 0.1 | I49: =H49+G49 -> 0.15 | J49: =I49*F49 -> 780 | K49: ='INPUT DATA'!$C$64*(ABC!J49+ABC!F49) -> 0 | L49: =J49+K49 -> 780 | M49: =L49+F49 -> 5980 | O49: =M49/D49 -> 5980 | P49: =M49-'INPUT DATA'!L42 -> 0
A50: ='INPUT DATA'!A43 -> 1002(5) | B50: ='INPUT DATA'!B43 -> WATER CLOSET/ URINAL W/ COMPLETE ACCESSORIES | D50: ='INPUT DATA'!C43 -> 1 | E50: ='INPUT DATA'!D43 -> SET | F50: ='INPUT DATA'!F43+'INPUT DATA'!G43+'INPUT DATA'!H43 -> 7095 | G50: ='INPUT DATA'!$C$62 -> 0.05 | H50: ='INPUT DATA'!$C$63 -> 0.1 | I50: =H50+G50 -> 0.15 | J50: =I50*F50 -> 1064.25 | K50: ='INPUT DATA'!$C$64*(ABC!J50+ABC!F50) -> 0 | L50: =J50+K50 -> 1064.25 | M50: =L50+F50 -> 8159.25 | O50: =M50/D50 -> 8159.25 | P50: =M50-'INPUT DATA'!L43 -> 0
A51: ='INPUT DATA'!A44 -> 1002(5) | B51: ='INPUT DATA'!B44 -> KITCHEN SINK/ SCRUB/ SLOP SINK W/ COMPLETE ACCESSORIES | D51: ='INPUT DATA'!C44 -> 1 | E51: ='INPUT DATA'!D44 -> SET | F51: ='INPUT DATA'!F44+'INPUT DATA'!G44+'INPUT DATA'!H44 -> 5445 | G51: ='INPUT DATA'!$C$62 -> 0.05 | H51: ='INPUT DATA'!$C$63 -> 0.1 | I51: =H51+G51 -> 0.15 | J51: =I51*F51 -> 816.75 | K51: ='INPUT DATA'!$C$64*(ABC!J51+ABC!F51) -> 0 | L51: =J51+K51 -> 816.75 | M51: =L51+F51 -> 6261.75 | O51: =M51/D51 -> 6261.75 | P51: =M51-'INPUT DATA'!L44 -> 0
A52: ='INPUT DATA'!A45 -> 1002(5) | B52: ='INPUT DATA'!B45 -> WALL HANG/COUNTERTOP/ UNDER COUNTER LAVATORY W/ COMPLETE ACCESSORIES | D52: ='INPUT DATA'!C45 -> 1 | E52: ='INPUT DATA'!D45 -> SET | F52: ='INPUT DATA'!F45+'INPUT DATA'!G45+'INPUT DATA'!H45 -> 4345 | G52: ='INPUT DATA'!$C$62 -> 0.05 | H52: ='INPUT DATA'!$C$63 -> 0.1 | I52: =H52+G52 -> 0.15 | J52: =I52*F52 -> 651.75 | K52: ='INPUT DATA'!$C$64*(ABC!J52+ABC!F52) -> 0 | L52: =J52+K52 -> 651.75 | M52: =L52+F52 -> 4996.75 | O52: =M52/D52 -> 4996.75 | P52: =M52-'INPUT DATA'!L45 -> 0
A53: ='INPUT DATA'!A46 -> 1002(5) | B53: ='INPUT DATA'!B46 -> FLOOR DRAIN PLATES (ANY SIZE) | D53: ='INPUT DATA'!C46 -> 2 | E53: ='INPUT DATA'!D46 -> SET | F53: ='INPUT DATA'!F46+'INPUT DATA'!G46+'INPUT DATA'!H46 -> 968 | G53: ='INPUT DATA'!$C$62 -> 0.05 | H53: ='INPUT DATA'!$C$63 -> 0.1 | I53: =H53+G53 -> 0.15 | J53: =I53*F53 -> 145.2 | K53: ='INPUT DATA'!$C$64*(ABC!J53+ABC!F53) -> 0 | L53: =J53+K53 -> 145.2 | M53: =L53+F53 -> 1113.2 | O53: =M53/D53 -> 556.6 | P53: =M53-'INPUT DATA'!L46 -> 0
A54: ='INPUT DATA'!A47 -> 1002(5) | B54: ='INPUT DATA'!B47 -> SOAP HOLDER /TOILET SOAP/LIQUID SOAP/TISSUE HOLDER | D54: ='INPUT DATA'!C47 -> 1 | E54: ='INPUT DATA'!D47 -> SET | F54: ='INPUT DATA'!F47+'INPUT DATA'!G47+'INPUT DATA'!H47 -> 570.625 | G54: ='INPUT DATA'!$C$62 -> 0.05 | H54: ='INPUT DATA'!$C$63 -> 0.1 | I54: =H54+G54 -> 0.15 | J54: =I54*F54 -> 85.59375 | K54: ='INPUT DATA'!$C$64*(ABC!J54+ABC!F54) -> 0 | L54: =J54+K54 -> 85.59375 | M54: =L54+F54 -> 656.21875 | O54: =M54/D54 -> 656.21875 | P54: =M54-'INPUT DATA'!L47 -> 0
A55: ='INPUT DATA'!A48 -> 1002(5)p | B55: ='INPUT DATA'!B48 -> FACIAL MIRROR | D55: ='INPUT DATA'!C48 -> 0.5 | E55: ='INPUT DATA'!D48 -> SQ.M. | F55: ='INPUT DATA'!F48+'INPUT DATA'!G48+'INPUT DATA'!H48 -> 804.375 | G55: ='INPUT DATA'!$C$62 -> 0.05 | H55: ='INPUT DATA'!$C$63 -> 0.1 | I55: =H55+G55 -> 0.15 | J55: =I55*F55 -> 120.65625 | K55: ='INPUT DATA'!$C$64*(ABC!J55+ABC!F55) -> 0 | L55: =J55+K55 -> 120.65625 | M55: =L55+F55 -> 925.03125 | O55: =M55/D55 -> 1850.0625 | P55: =M55-'INPUT DATA'!L48 -> 0
A56: ='INPUT DATA'!A49 -> SPL- ? | B56: ='INPUT DATA'!B49 -> (INPUT OTHER PLUMBING WORK ITEM THAT IS NOT FOUND IN THIS SPREADSHEET) | D56: ='INPUT DATA'!C49 -> 1 | E56: ='INPUT DATA'!D49 -> L.S. | F56: ='INPUT DATA'!F49+'INPUT DATA'!G49+'INPUT DATA'!H49 -> 0 | G56: ='INPUT DATA'!$C$62 -> 0.05 | H56: ='INPUT DATA'!$C$63 -> 0.1 | I56: =H56+G56 -> 0.15 | J56: =I56*F56 -> 0 | K56: ='INPUT DATA'!$C$64*(ABC!J56+ABC!F56) -> 0 | L56: =J56+K56 -> 0 | M56: =L56+F56 -> 0 | O56: =M56/D56 -> 0 | P56: =M56-'INPUT DATA'!L49 -> 0
A57: ='INPUT DATA'!A50 -> ELECTRICAL WORKS | P57: =M57-'INPUT DATA'!L50 -> 0
A58: ='INPUT DATA'!A51 -> 1002(5) | B58: ='INPUT DATA'!B51 -> 15MM-25MM DIA. FLEXIBLE CONDUIT | D58: ='INPUT DATA'!C51 -> 200 | E58: ='INPUT DATA'!D51 -> M. | F58: ='INPUT DATA'!F51+'INPUT DATA'!G51+'INPUT DATA'!H51 -> 17306.795 | G58: ='INPUT DATA'!$C$62 -> 0.05 | H58: ='INPUT DATA'!$C$63 -> 0.1 | I58: =H58+G58 -> 0.15 | J58: =I58*F58 -> 2596.0193 | K58: ='INPUT DATA'!$C$64*(ABC!J58+ABC!F58) -> 0 | L58: =J58+K58 -> 2596.0193 | M58: =L58+F58 -> 19902.814 | O58: =M58/D58 -> 99.514071 | P58: =M58-'INPUT DATA'!L51 -> 0
A59: ='INPUT DATA'!A52 -> 1100 | B59: ='INPUT DATA'!B52 -> JUNCTION UTILITY/PULL / SQUARE BOX | D59: ='INPUT DATA'!C52 -> 33 | E59: ='INPUT DATA'!D52 -> PC. | F59: ='INPUT DATA'!F52+'INPUT DATA'!G52+'INPUT DATA'!H52 -> 4900.5 | G59: ='INPUT DATA'!$C$62 -> 0.05 | H59: ='INPUT DATA'!$C$63 -> 0.1 | I59: =H59+G59 -> 0.15 | J59: =I59*F59 -> 735.075 | K59: ='INPUT DATA'!$C$64*(ABC!J59+ABC!F59) -> 0 | L59: =J59+K59 -> 735.075 | M59: =L59+F59 -> 5635.575 | O59: =M59/D59 -> 170.775 | P59: =M59-'INPUT DATA'!L52 -> 0
A60: ='INPUT DATA'!A53 -> 1101(2) | B60: ='INPUT DATA'!B53 -> 1.6MM2 - 5.5MM2 ELECTRIC WIRE (TW/THHN/TWHN2) | D60: ='INPUT DATA'!C53 -> 600 | E60: ='INPUT DATA'!D53 -> M. | F60: ='INPUT DATA'!F53+'INPUT DATA'!G53+'INPUT DATA'!H53 -> 25080 | G60: ='INPUT DATA'!$C$62 -> 0.05 | H60: ='INPUT DATA'!$C$63 -> 0.1 | I60: =H60+G60 -> 0.15 | J60: =I60*F60 -> 3762 | K60: ='INPUT DATA'!$C$64*(ABC!J60+ABC!F60) -> 0 | L60: =J60+K60 -> 3762 | M60: =L60+F60 -> 28842 | O60: =M60/D60 -> 48.07 | P60: =M60-'INPUT DATA'!L53 -> 0
A61: ='INPUT DATA'!A54 -> 1101 | B61: ='INPUT DATA'!B54 -> SINGLE CONVINENCE OUTLET/ RECEPTACLE, GROUNDING TYPE/HEAVY DUTY CONVENIENCE OUTLET | D61: ='INPUT DATA'!C54 -> 13 | E61: ='INPUT DATA'!D54 -> SET | F61: ='INPUT DATA'!F54+'INPUT DATA'!G54+'INPUT DATA'!H54 -> 3305.25 | G61: ='INPUT DATA'!$C$62 -> 0.05 | H61: ='INPUT DATA'!$C$63 -> 0.1 | I61: =H61+G61 -> 0.15 | J61: =I61*F61 -> 495.7875 | K61: ='INPUT DATA'!$C$64*(ABC!J61+ABC!F61) -> 0 | L61: =J61+K61 -> 495.7875 | M61: =L61+F61 -> 3801.0375 | O61: =M61/D61 -> 292.3875 | P61: =M61-'INPUT DATA'!L54 -> 0
A62: ='INPUT DATA'!A55 -> 1101 | B62: ='INPUT DATA'!B55 -> DUPLEX CONVINENCE OUTLET/ RECEPTACLE, GROUNDING TYPE/HEAVY DUTY CONVENIENCE OUTLET | D62: ='INPUT DATA'!C55 -> 10 | E62: ='INPUT DATA'!D55 -> SET | F62: ='INPUT DATA'!F55+'INPUT DATA'!G55+'INPUT DATA'!H55 -> 3205 | G62: ='INPUT DATA'!$C$62 -> 0.05 | H62: ='INPUT DATA'!$C$63 -> 0.1 | I62: =H62+G62 -> 0.15 | J62: =I62*F62 -> 480.75 | K62: ='INPUT DATA'!$C$64*(ABC!J62+ABC!F62) -> 0 | L62: =J62+K62 -> 480.75 | M62: =L62+F62 -> 3685.75 | O62: =M62/D62 -> 368.575 | P62: =M62-'INPUT DATA'!L55 -> 0
A63: ='INPUT DATA'!A56 -> 1102 | B63: ='INPUT DATA'!B56 -> PANEL BOARD WITH MAIN BREAKER/BRANCHES, 3 WIRES, 1 NEUTRAL, 50AMP-200AMP | D63: ='INPUT DATA'!C56 -> 1 | E63: ='INPUT DATA'!D56 -> SET | F63: ='INPUT DATA'!F56+'INPUT DATA'!G56+'INPUT DATA'!H56 -> 8168.5 | G63: ='INPUT DATA'!$C$62 -> 0.05 | H63: ='INPUT DATA'!$C$63 -> 0.1 | I63: =H63+G63 -> 0.15 | J63: =I63*F63 -> 1225.275 | K63: ='INPUT DATA'!$C$64*(ABC!J63+ABC!F63) -> 0 | L63: =J63+K63 -> 1225.275 | M63: =L63+F63 -> 9393.775 | O63: =M63/D63 -> 9393.775 | P63: =M63-'INPUT DATA'!L56 -> 0
A64: ='INPUT DATA'!A57 -> 1103(2) | B64: ='INPUT DATA'!B57 -> FLOURESCENT LIGHTING FIXTURE WITH BALLAST/ LIGHT EMITTING DIODE (LED) BULB, 1 BULB | D64: ='INPUT DATA'!C57 -> 40 | E64: ='INPUT DATA'!D57 -> SET | F64: ='INPUT DATA'!F57+'INPUT DATA'!G57+'INPUT DATA'!H57 -> 17820 | G64: ='INPUT DATA'!$C$62 -> 0.05 | H64: ='INPUT DATA'!$C$63 -> 0.1 | I64: =H64+G64 -> 0.15 | J64: =I64*F64 -> 2673 | K64: ='INPUT DATA'!$C$64*(ABC!J64+ABC!F64) -> 0 | L64: =J64+K64 -> 2673 | M64: =L64+F64 -> 20493 | O64: =M64/D64 -> 512.325 | P64: =M64-'INPUT DATA'!L57 -> 0
A65: ='INPUT DATA'!A58 -> SPL- ? | B65: ='INPUT DATA'!B58 -> (INPUT OTHER ELECTRICAL WORK ITEM THAT IS NOT FOUND IN THIS SPREADSHEET) | D65: ='INPUT DATA'!C58 -> 1 | E65: ='INPUT DATA'!D58 -> L.S. | F65: ='INPUT DATA'!F58+'INPUT DATA'!G58+'INPUT DATA'!H58 -> 0 | G65: ='INPUT DATA'!$C$62 -> 0.05 | H65: ='INPUT DATA'!$C$63 -> 0.1 | I65: =H65+G65 -> 0.15 | J65: =I65*F65 -> 0 | K65: ='INPUT DATA'!$C$64*(ABC!J65+ABC!F65) -> 0 | L65: =J65+K65 -> 0 | M65: =L65+F65 -> 0 | O65: =M65/D65 -> 0 | P65: =M65-'INPUT DATA'!L58 -> 0
L66: =SUM(M58:N65)+SUM(M48:N56)+SUM(M17:N46) -> 1644800.3
B68: Prepared by:
C71: Licensed Engineer/Registered Master Plumber/Master Electrician

Sheet 800(1) Clearing & Grab
B1: DETAILED UNIT PRICE ANALYSIS
B3: PROJECT NAME: | E3: ='INPUT DATA'!C4 -> PROPOSED ONE STOREY TWO BED ROOM RESIDENTIAL BUILDING
A5: ITEM NO. | B5: Item No./Description: | E5: 800(1) | G5: CLEARING AND GRUBBING
A6: UNIT | B6: Unit of Measurement: | E6: SQ.M.
B7: Output per day: | E7: 500 | G7: SQ.M./DAY
A8: QTY | B8: Quantity: | E8: ='INPUT DATA'!C10 -> 200 | G8: =E6 -> SQ.M.
B10: Designation | K10: No. Person | N10: No. of Days | Q10: Daily Rate | T10: Amount
B12: A. | C12: Labor
A13: DURATION | C13: a. | D13: Construction Foreman/Engineering Assistant | K13: 1 | N13: =E8/E7 -> 0.4 | Q13: 700 | T13: =K13*N13*Q13 -> 280
C14: b. | D14: Laborer | K14: 2 | N14: =N13 -> 0.4 | Q14: 400 | T14: =K14*N14*Q14 -> 320
Y19: Number of Teams:
A20: LABOR | C20: Sub-Total for A | S20: P | T20: =ROUND(SUM(T13:V18),2) -> 600 | Y20: 1
B21: Name and Capacity | K21: No. of Units | N21: No. of Days | Q21: Daily Rate | T21: Amount
B23: B. | C23: Equipment
C24: a. | D24: Dump Truck | K24: 2 | N24: =N14 -> 0.4 | Q24: 10816 | T24: =K24*N24*Q24 -> 8652.8
C25: b. | D25: Payloader | K25: 1 | N25: =N24 -> 0.4 | Q25: 13864 | T25: =K25*N25*Q25 -> 5545.6
C26: c. | D26: Bulldozer | K26: 1 | N26: =N25 -> 0.4 | Q26: 18392 | T26: =K26*N26*Q26 -> 7356.8
A29: EQUIPMENT | C29: Sub-Total for B | S29: P | T29: =ROUND(SUM(T24:V28),2) -> 21555.2
B30: C. | C30: Total (A+B) | T30: =T20+T29 -> 22155.2
B31: D. | C31: Output per day | G31: = | H31: =E7 -> 500 | J31: =G7 -> SQ.M./DAY | AK31: 2Ø 45° bend | AL31: 2Øx2Ø tee | AM31: 4Øx4Ø coupling
B32: Name and Specifications | K32: Quantity | N32: Unit | Q32: Unit Cost | T32: Amount
B34: E. | C34: Materials | AL34: 2
C35: N/A | AM35: 4
AK37: =SUM(AK32:AK35) -> 0 | AL37: =SUM(AL32:AL35) -> 2 | AM37: =SUM(AM32:AM35) -> 4
A46: MATERIAL | C46: Sub-Total for E | S46: P
B47: F. | C47: Direct Cost (C+E) | T47: =T30+T46 -> 22155.2
B48: G. | C48: Overhead, Contingencies & Miscellaneous | N48: ='INPUT DATA'!C62 -> 0.05 | T48: =T47*N48 -> 1107.76
B49: H. | C49: Contractor's Profit (CP) | N49: ='INPUT DATA'!C63 -> 0.1 | T49: =T47*N49 -> 2215.52
B50: I. | C50: Value Added Tax (VAT) | N50: ='INPUT DATA'!C64 -> 0 | T50: =(T47+T48+T49)*N50 -> 0
A51: CHECKING | B51: J. | C51: Total Cost | T51: =SUM(T47:V50) -> 25478.48
A52: ADJUSTED CHECKING | B52: k. | C52: Total Unit Cost | T52: =T51/E8 -> 127.3924

Sheet 800(3)a Ind Remov of Trees
B1: DETAILED UNIT PRICE ANALYSIS
B3: PROJECT NAME: | E3: ='INPUT DATA'!C4 -> PROPOSED ONE STOREY TWO BED ROOM RESIDENTIAL BUILDING
A5: ITEM NO. | B5: Item No./Description: | E5: 800(3)a | G5: INDIVIDUAL REMOVAL OF TREES (UPTO 300MM DIAMETER)
A6: UNIT | B6: Unit of Measurement: | E6: EACH
B7: Output per day: | E7: 8 | G7: EACH/DAY
A8: QTY | B8: Quantity: | E8: ='INPUT DATA'!C11 -> 2 | G8: =E6 -> EACH
B10: Designation | K10: No. Person | N10: No. of Days | Q10: Daily Rate | T10: Amount
B12: A. | C12: Labor
A13: DURATION | C13: a. | D13: Construction Foreman/Engineering Assistant | K13: 1 | N13: =E8/E7 -> 0.25 | Q13: 800 | T13: =K13*N13*Q13 -> 200
C14: b. | D14: Skilled Laborer | K14: 1 | N14: =N13 -> 0.25 | Q14: 600 | T14: =K14*N14*Q14 -> 150
C15: c. | D15: Laborer | K15: 2 | N15: =N14 -> 0.25 | Q15: 400 | T15: =K15*N15*Q15 -> 200
Y19: Number of Teams:
A20: LABOR | C20: Sub-Total for A | S20: P | T20: =ROUND(SUM(T13:V18),2) -> 550 | Y20: 1
B21: Name and Capacity | K21: No. of Units | N21: No. of Days | Q21: Daily Rate | T21: Amount
B23: B. | C23: Equipment
C24: a. | D24: Backhoe | K24: 1 | N24: =0.25*E8 -> 0.5 | Q24: 16599 | T24: =K24*N24*Q24 -> 8299.5
C25: b. | D25: Dump Truck | K25: 1 | N25: =0.17*E8 -> 0.34 | Q25: 10816 | T25: =K25*N25*Q25 -> 3677.44
C26: c. | D26: Chainsaw | K26: 1 | N26: =N25 -> 0.34 | Q26: 600 | T26: =K26*N26*Q26 -> 204
C27: Minor Tools (5% of Labor Cost) | K27: 1 | T27: =0.05*T20 -> 27.5
A30: EQUIPMENT | C30: Sub-Total for B | S30: P | T30: =ROUND(SUM(T25:V29),2) -> 3908.94
B31: C. | C31: Total (A+B) | T31: =T20+T30 -> 4458.94
B32: D. | C32: Output per day | G32: = | H32: =E7 -> 8 | J32: =G7 -> EACH/DAY | AK32: 2Ø 45° bend | AL32: 2Øx2Ø tee | AM32: 4Øx4Ø coupling
B33: Name and Specifications | K33: Quantity | N33: Unit | Q33: Unit Cost | T33: Amount
B35: E. | C35: Materials | AL35: 2
C36: N/A | AM36: 4
AK38: =SUM(AK33:AK36) -> 0 | AL38: =SUM(AL33:AL36) -> 2 | AM38: =SUM(AM33:AM36) -> 4
A47: MATERIAL | C47: Sub-Total for E | S47: P
B48: F. | C48: Direct Cost (C+E) | T48: =T31+T47 -> 4458.94
B49: G. | C49: Overhead, Contingencies & Miscellaneous | N49: ='INPUT DATA'!C62 -> 0.05 | T49: =T48*N49 -> 222.947
B50: H. | C50: Contractor's Profit (CP) | N50: ='INPUT DATA'!C63 -> 0.1 | T50: =T48*N50 -> 445.894
B51: I. | C51: Value Added Tax (VAT) | N51: ='INPUT DATA'!C64 -> 0 | T51: =(T48+T49+T50)*N51 -> 0
A52: CHECKING | B52: J. | C52: Total Cost | T52: =SUM(T48:V51) -> 5127.781
A53: ADJUSTED CHECKING | B53: k. | C53: Total Unit Cost | T53: =T52/E8 -> 2563.8905

Sheet 803(1)a-Struc Exca Common Soil
B1: DETAILED UNIT PRICE ANALYSIS
B3: PROJECT NAME: | E3: ='INPUT DATA'!C4 -> PROPOSED ONE STOREY TWO BED ROOM RESIDENTIAL BUILDING
A5: ITEM NO. | B5: Item No./Description: | E5: 803(1)a | G5: STRUCTURE EXCAVATION (COMMON SOIL) | X5: NO. OF TEAM: | Y5: 1
A6: UNIT | B6: Unit of Measurement: | E6: CU.M.
B7: Output per day: | E7: =20*8*Y5 -> 160 | G7: CU.M./DAY
A8: QTY | B8: Quantity: | E8: ='INPUT DATA'!C12 -> 23 | G8: =E6 -> CU.M.
B10: Designation | K10: No. Person | N10: No. of Days | Q10: Daily Rate | T10: Amount
B12: A. | C12: Labor
A13: DURATION | C13: a. | D13: Construction Foreman/Engineering Assistant | K13: 1 | N13: =E8/E7 -> 0.14375 | Q13: 800 | T13: =K13*N13*Q13 -> 115
C14: b. | D14: Laborer | K14: =3*Y5 -> 3 | N14: =E8/E7 -> 0.14375 | Q14: 400 | T14: =K14*N14*Q14 -> 172.5
A19: LABOR | C19: Sub-Total for A | S19: P | T19: =ROUND(SUM(T13:V14),2) -> 287.5
B20: Name and Capacity | K20: No. of Units | N20: No. of Days | Q20: Daily Rate | T20: Amount
B22: B. | C22: Equipment
C23: a. | D23: Dump Truck | K23: =2*Y5 -> 2 | N23: =N14 -> 0.14375 | Q23: 10816 | T23: =K23*N23*Q23 -> 3109.6
C24: b. | D24: Backhoe | K24: =1*Y5 -> 1 | N24: =N23 -> 0.14375 | Q24: 12296 | T24: =K24*N24*Q24 -> 1767.55
D25: Minor Tools (10%) | T25: =T19*0.1 -> 28.75
A29: EQUIPMENT | C29: Sub-Total for B | S29: P | T29: =ROUND(SUM(T23:V25),2) -> 4905.9
B30: C. | C30: Total (A+B) | T30: =T19+T29 -> 5193.4
B31: D. | C31: Output per day | G31: = | H31: =E7 -> 160 | J31: =G7 -> CU.M./DAY
B32: Name and Specifications | K32: Quantity | N32: Unit | Q32: Unit Cost | T32: Amount
B34: E. | C34: Materials
C35: N.A.
A42: MATERIAL | C42: Sub-Total for E | S42: P
B43: F. | C43: Direct Cost (C+E) | T43: =T30+T42 -> 5193.4
B44: G. | C44: Overhead, Contingencies & Miscellaneous | N44: ='INPUT DATA'!C62 -> 0.05 | T44: =T43*N44 -> 259.67
B45: H. | C45: Contractor's Profit (CP) | N45: ='INPUT DATA'!C63 -> 0.1 | T45: =T43*N45 -> 519.34
B46: I. | C46: Value Added Tax (VAT) | N46: ='INPUT DATA'!C64 -> 0 | T46: =(T43+T44+T45)*N46 -> 0
A47: CHECKING | B47: J. | C47: Total Cost | T47: =SUM(T43:V46) -> 5972.41
A48: ADJUSTED CHECKING | B48: k. | C48: Total Unit Cost | T48: =T47/E8 -> 259.67

Sheet 803(1)a-Struc Exca Soft Rock
B1: DETAILED UNIT PRICE ANALYSIS
B3: PROJECT NAME: | E3: ='INPUT DATA'!C4 -> PROPOSED ONE STOREY TWO BED ROOM RESIDENTIAL BUILDING
A5: ITEM NO. | B5: Item No./Description: | E5: 803(1)a | G5: STRUCTURE EXCAVATION (SOFT ROCK) | X5: NO. OF TEAM: | Y5: 1
A6: UNIT | B6: Unit of Measurement: | E6: CU.M.
B7: Output per day: | E7: =14*8*Y5 -> 112 | G7: CU.M./DAY
A8: QTY | B8: Quantity: | E8: ='INPUT DATA'!C13 -> 0 | G8: =E6 -> CU.M.
B10: Designation | K10: No. Person | N10: No. of Days | Q10: Daily Rate | T10: Amount
B12: A. | C12: Labor
A13: DURATION | C13: a. | D13: Construction Foreman/Engineering Assistant | K13: 1 | N13: =E8/E7 -> 0 | Q13: 800 | T13: =K13*N13*Q13 -> 0
C14: b. | D14: Laborer | K14: =3*Y5 -> 3 | N14: =E8/E7 -> 0 | Q14: 400 | T14: =K14*N14*Q14 -> 0
A19: LABOR | C19: Sub-Total for A | S19: P | T19: =ROUND(SUM(T13:V14),2) -> 0
B20: Name and Capacity | K20: No. of Units | N20: No. of Days | Q20: Daily Rate | T20: Amount
B22: B. | C22: Equipment
C23: a. | D23: Dump Truck | K23: =2*Y5 -> 2 | N23: =N14 -> 0 | Q23: 10816 | T23: =K23*N23*Q23 -> 0
C24: b. | D24: Backhoe | K24: =1*Y5 -> 1 | N24: =0.5*N23 -> 0 | Q24: 12296 | T24: =K24*N24*Q24 -> 0
C25: c. | D25: Backhoe with Breaker | K25: 1 | N25: =N24 -> 0 | Q25: 16599.6 | T25: =K25*N25*Q25 -> 0
D26: Minor Tools (10%) | T26: =T19*0.1 -> 0
A30: EQUIPMENT | C30: Sub-Total for B | S30: P | T30: =ROUND(SUM(T23:V26),2) -> 0
B31: C. | C31: Total (A+B) | T31: =T19+T30 -> 0
B32: D. | C32: Output per day | G32: = | H32: =E7 -> 112 | J32: =G7 -> CU.M./DAY
B33: Name and Specifications | K33: Quantity | N33: Unit | Q33: Unit Cost | T33: Amount
B35: E. | C35: Materials
C36: N.A.
A43: MATERIAL | C43: Sub-Total for E | S43: P
B44: F. | C44: Direct Cost (C+E) | T44: =T31+T43 -> 0
B45: G. | C45: Overhead, Contingencies & Miscellaneous | N45: ='INPUT DATA'!C62 -> 0.05 | T45: =T44*N45 -> 0
B46: H. | C46: Contractor's Profit (CP) | N46: ='INPUT DATA'!C63 -> 0.1 | T46: =T44*N46 -> 0
B47: I. | C47: Value Added Tax (VAT) | N47: ='INPUT DATA'!C64 -> 0 | T47: =(T44+T45+T46)*N47 -> 0
A48: CHECKING | B48: J. | C48: Total Cost | T48: =SUM(T44:V47) -> 0
A49: ADJUSTED CHECKING | B49: k. | C49: Total Unit Cost | T49: =T48/E8 -> #DIV/0!

Sheet 804(4) Gravel Bedding
B1: DETAILED UNIT PRICE ANALYSIS
B3: PROJECT NAME: | E3: ='INPUT DATA'!C4 -> PROPOSED ONE STOREY TWO BED ROOM RESIDENTIAL BUILDING
A5: ITEM NO. | B5: Item No./Description: | E5: 804(4) | G5: GRAVEL BEDDING | X5: NO. OF TEAM: | Y5: 1
A6: UNIT | B6: Unit of Measurement: | E6: CU.M.
B7: Output per day: | E7: =1.2*8*Y5 -> 9.6 | G7: CU.M./DAY
A8: QTY | B8: Quantity: | E8: ='INPUT DATA'!C14 -> 3 | G8: =E6 -> CU.M.
B10: Designation | K10: No. Person | N10: No. of Days | Q10: Daily Rate | T10: Amount
B12: A. | C12: Labor
A13: DURATION | C13: a. | D13: Construction Foreman/Engineering Assistant | K13: 1 | N13: =E8/E7 -> 0.3125 | Q13: 800 | T13: =K13*N13*Q13 -> 250
C14: b. | D14: Laborer | K14: =3*Y5 -> 3 | N14: =E8/E7 -> 0.3125 | Q14: 400 | T14: =K14*N14*Q14 -> 375
A19: LABOR | C19: Sub-Total for A | S19: P | T19: =ROUND(SUM(T13:V14),2) -> 625
B20: Name and Capacity | K20: No. of Units | N20: No. of Days | Q20: Daily Rate | T20: Amount
B22: B. | C22: Equipment
C23: a. | D23: Plate Compactor | K23: =2*Y5 -> 2 | N23: =N14 -> 0.3125 | Q23: 984 | T23: =K23*N23*Q23 -> 615
D24: Minor Tools (10%) | T24: =T19*0.1 -> 62.5
A28: EQUIPMENT | C28: Sub-Total for B | S28: P | T28: =ROUND(SUM(T23:V24),2) -> 677.5
B29: C. | C29: Total (A+B) | T29: =T19+T28 -> 1302.5
B30: D. | C30: Output per day | G30: = | H30: =E7 -> 9.6 | J30: =G7 -> CU.M./DAY
B31: Name and Specifications | K31: Quantity | N31: Unit | Q31: Unit Cost | T31: Amount
B33: E. | C33: Materials
C34: a. | D34: Gravel Bedding | K34: =E8 -> 3 | N34: cu.m. | Q34: 1400 | T34: =Q34*K34 -> 4200
A41: MATERIAL | C41: Sub-Total for E | S41: P | T41: =SUM(T34:V40) -> 4200
B42: F. | C42: Direct Cost (C+E) | T42: =T29+T41 -> 5502.5
B43: G. | C43: Overhead, Contingencies & Miscellaneous | N43: ='INPUT DATA'!C62 -> 0.05 | T43: =T42*N43 -> 275.125
B44: H. | C44: Contractor's Profit (CP) | N44: ='INPUT DATA'!C63 -> 0.1 | T44: =T42*N44 -> 550.25
B45: I. | C45: Value Added Tax (VAT) | N45: ='INPUT DATA'!C64 -> 0 | T45: =(T42+T43+T44)*N45 -> 0
A46: CHECKING | B46: J. | C46: Total Cost | T46: =SUM(T42:V45) -> 6327.875
A47: ADJUSTED CHECKING | B47: k. | C47: Total Unit Cost | T47: =T46/E8 -> 2109.2917

Sheet 902(1)-Reinforced S for 1Storey
B1: DETAILED UNIT PRICE ANALYSIS
B3: PROJECT NAME: | E3: ='INPUT DATA'!C4 -> PROPOSED ONE STOREY TWO BED ROOM RESIDENTIAL BUILDING
A5: ITEM NO. | B5: Item No./Description: | E5: 902(1) | G5: REINFORCING STEEL OF REINFORCED CONCRETE STRUCTURES FOR ONE-STOREY, GRADE 40/60
A6: UNIT | B6: Unit of Measurement: | E6: KGS.
B7: Output per day: | E7: =143.438*8*Y11 -> 1147.504 | G7: KGS./DAY
A8: QTY | B8: Quantity: | E8: ='INPUT DATA'!C15 -> 1200 | G8: =E6 -> KGS.
B10: Designation | K10: No. Person | N10: No. of Days | Q10: Daily Rate | T10: Amount | Y10: NO. OF TEAM
Y11: 1
B12: A. | C12: Labor
A13: DURATION | C13: a. | D13: Construction Foreman/Engineering Assistant | K13: 1 | N13: =E8/E7 -> 1.045748 | Q13: 800 | T13: =K13*N13*Q13 -> 836.59839
C14: b. | D14: Skilled Laborer | K14: 3 | N14: =N13 -> 1.045748 | Q14: 600 | T14: =K14*N14*Q14 -> 1882.3464
C15: b. | D15: Laborer | K15: 12 | N15: =N14 -> 1.045748 | Q15: 400 | T15: =K15*N15*Q15 -> 5019.5903
A17: LABOR | C17: Sub-Total for A | S17: P | T17: =ROUND(SUM(T13:V15),2) -> 7738.54
B18: Name and Capacity | K18: No. of Units | N18: No. of Days | Q18: Daily Rate | T18: Amount
B20: B. | C20: Equipment
C21: a. | D21: Bar Cutter | K21: =Y11 -> 1 | N21: =N13/2 -> 0.52287399 | Q21: 1758 | T21: =K21*N21*Q21 -> 919.21248
C22: b. | D22: Bar Bender | K22: =K21 -> 1 | N22: =N21 -> 0.52287399 | Q22: 2812 | T22: =K22*N22*Q22 -> 1470.3217
C23: c. | D23: Cargo Truck/Hauling Truck | K23: =K22 -> 1 | N23: =N15*0.15 -> 0.1568622 | Q23: 8816 | T23: =K23*N23*Q23 -> 1382.8971
A26: EQUIPMENT | C26: Sub-Total for B | S26: P | T26: =ROUND(SUM(T21:V25),2) -> 3772.43
B27: C. | C27: Total (A+B) | T27: =T17+T26 -> 11510.97
B28: D. | C28: Output per day | G28: = | H28: =E7 -> 1147.504 | J28: =G7 -> KGS./DAY
B29: Name and Specifications | K29: Quantity | N29: Unit | Q29: Unit Cost | T29: Amount
B31: E. | C31: Materials
C32: a. | D32: Deformed Reinforcing Steel Bar (Grade 40) | K32: =E8 -> 1200 | N32: =IF(K32>1,"kgs.","kg.") -> kgs. | Q32: 75 | T32: =K32*Q32 -> 90000
C33: b. | D33: #16 G.I. Tie-wire | K33: =E8*0.015 -> 18 | N33: =IF(K33>1,"kgs.","kg.") -> kgs. | Q33: 90 | T33: =K33*Q33 -> 1620
D34: Consumables (5% of Materials Cost) | T34: =0.05*SUM(T32:V33) -> 4581
A38: MATERIAL | C38: Sub-Total for E | S38: P | T38: =ROUND(SUM(T32:V37),2) -> 96201
B39: F. | C39: Direct Cost (C+E) | T39: =T27+T38 -> 107711.97
B40: G. | C40: Overhead, Contingencies & Miscellaneous | N40: ='INPUT DATA'!C62 -> 0.05 | T40: =T39*N40 -> 5385.5985
B41: H. | C41: Contractor's Profit (CP) | N41: ='INPUT DATA'!C63 -> 0.1 | T41: =T39*N41 -> 10771.197
B42: I. | C42: Value Added Tax (VAT) | N42: ='INPUT DATA'!C64 -> 0 | T42: =(T39+T40+T41)*N42 -> 0
A43: CHECKING | B43: J. | C43: Total Cost | T43: =SUM(T39:V42) -> 123868.77
A44: ADJUSTED CHECKING | B44: k. | C44: Total Unit Cost | T44: =T43/E8 -> 103.22397
F49: Input here the quantity of Steel Bars:
K50: Unit Wt. | M50: Total kgs
C51: *25mmØ x 6.00m Deformed Reinforcing Steel Bar | J51: 1 | K51: 3.855 | M51: =J51*K51*6 -> 23.13
C52: *20mmØ x 6.00m Deformed Reinforcing Steel Bar | J52: 1 | K52: 2.467 | M52: =J52*K52*6 -> 14.802
C53: *16mmØ x 6.00m Deformed Reinforcing Steel Bar | J53: 1 | K53: 1.579 | M53: =J53*K53*6 -> 9.474
C54: *12mmØ x 6.00m Deformed Reinforcing Steel Bar | J54: 1 | K54: 0.888 | M54: =J54*K54*6 -> 5.328
C55: *10mmØ x 6.00m Deformed Reinforcing Steel Bar | J55: 1 | K55: 0.616 | M55: =J55*K55*6 -> 3.696
M57: =SUM(M51:N55) -> 56.43

Sheet 902(1)-Rein St for 2-5storey
B1: DETAILED UNIT PRICE ANALYSIS
B3: PROJECT NAME: | E3: ='INPUT DATA'!C4 -> PROPOSED ONE STOREY TWO BED ROOM RESIDENTIAL BUILDING
A5: ITEM NO. | B5: Item No./Description: | E5: 902(1) | G5: REINFORCING STEEL OF REINFORCED CONCRETE STRUCTURES FOR TWO UPTO FIVE STOREY
A6: UNIT | B6: Unit of Measurement: | E6: KGS.
B7: Output per day: | E7: =129.094*8*Y11 -> 1032.752 | G7: KGS./DAY
A8: QTY | B8: Quantity: | E8: ='INPUT DATA'!C16 -> 50 | G8: =E6 -> KGS.
B10: Designation | K10: No. Person | N10: No. of Days | Q10: Daily Rate | T10: Amount | Y10: NO. OF TEAM
Y11: 1
B12: A. | C12: Labor
A13: DURATION | C13: a. | D13: Construction Foreman/Engineering Assistant | K13: 1 | N13: =E8/E7 -> 0.048414334 | Q13: 800 | T13: =K13*N13*Q13 -> 38.731467
C14: b. | D14: Skilled Laborer | K14: 3 | N14: =N13 -> 0.048414334 | Q14: 600 | T14: =K14*N14*Q14 -> 87.145801
C15: b. | D15: Laborer | K15: 12 | N15: =N14 -> 0.048414334 | Q15: 400 | T15: =K15*N15*Q15 -> 232.3888
A17: LABOR | C17: Sub-Total for A | S17: P | T17: =ROUND(SUM(T13:V15),2) -> 358.27
B18: Name and Capacity | K18: No. of Units | N18: No. of Days | Q18: Daily Rate | T18: Amount
B20: B. | C20: Equipment
C21: a. | D21: Bar Cutter | K21: =Y11 -> 1 | N21: =N13/2 -> 0.024207167 | Q21: 1758 | T21: =K21*N21*Q21 -> 42.556199
C22: b. | D22: Bar Bender | K22: =K21 -> 1 | N22: =N21 -> 0.024207167 | Q22: 2812 | T22: =K22*N22*Q22 -> 68.070553
C23: Minor Tools (10% of Labor Cost) | T23: =0.1*T17 -> 35.827
A26: EQUIPMENT | C26: Sub-Total for B | S26: P | T26: =ROUND(SUM(T21:V25),2) -> 146.45
B27: C. | C27: Total (A+B) | T27: =T17+T26 -> 504.72
B28: D. | C28: Output per day | G28: = | H28: =E7 -> 1032.752 | J28: =G7 -> KGS./DAY
B29: Name and Specifications | K29: Quantity | N29: Unit | Q29: Unit Cost | T29: Amount
B31: E. | C31: Materials
C32: a. | D32: Deformed Reinforcing Steel Bar (Grade 40) | K32: =E8 -> 50 | N32: =IF(K32>1,"kgs.","kg.") -> kgs. | Q32: 75 | T32: =K32*Q32 -> 3750
C33: b. | D33: #16 G.I. Tie-wire | K33: =E8*0.015 -> 0.75 | N33: =IF(K33>1,"kgs.","kg.") -> kg. | Q33: 90 | T33: =K33*Q33 -> 67.5
D34: Consumables (5% of Materials Cost) | T34: =0.05*SUM(T32:V33) -> 190.875
A38: MATERIAL | C38: Sub-Total for E | S38: P | T38: =ROUND(SUM(T32:V37),2) -> 4008.38
B39: F. | C39: Direct Cost (C+E) | T39: =T27+T38 -> 4513.1
B40: G. | C40: Overhead, Contingencies & Miscellaneous | N40: ='INPUT DATA'!C62 -> 0.05 | T40: =T39*N40 -> 225.655
B41: H. | C41: Contractor's Profit (CP) | N41: ='INPUT DATA'!C63 -> 0.1 | T41: =T39*N41 -> 451.31
B42: I. | C42: Value Added Tax (VAT) | N42: ='INPUT DATA'!C64 -> 0 | T42: =(T39+T40+T41)*N42 -> 0
A43: CHECKING | B43: J. | C43: Total Cost | T43: =SUM(T39:V42) -> 5190.065
A44: ADJUSTED CHECKING | B44: k. | C44: Total Unit Cost | T44: =T43/E8 -> 103.8013
F49: Input here the quantity of Steel Bars:
K50: Unit Wt. | M50: Total kgs
C51: *25mmØ x 6.00m Deformed Reinforcing Steel Bar | J51: 1 | K51: 3.855 | M51: =J51*K51*6 -> 23.13
C52: *20mmØ x 6.00m Deformed Reinforcing Steel Bar | J52: 1 | K52: 2.467 | M52: =J52*K52*6 -> 14.802
C53: *16mmØ x 6.00m Deformed Reinforcing Steel Bar | J53: 1 | K53: 1.579 | M53: =J53*K53*6 -> 9.474
C54: *12mmØ x 6.00m Deformed Reinforcing Steel Bar | J54: 1 | K54: 0.888 | M54: =J54*K54*6 -> 5.328
C55: *10mmØ x 6.00m Deformed Reinforcing Steel Bar | J55: 1 | K55: 0.616 | M55: =J55*K55*6 -> 3.696
M57: =SUM(M51:N55) -> 56.43

Sheet 900(1)c2 Struc Con for footing
B1: DETAILED UNIT PRICE ANALYSIS
B3: PROJECT NAME: | E3: ='INPUT DATA'!C4 -> PROPOSED ONE STOREY TWO BED ROOM RESIDENTIAL BUILDING
A5: ITEM NO. | B5: Item No./Description: | E5: 900(1)c2 | G5: STRUCTURAL CONCRETE FOR FOOTING AND SLAB ON FILL (CLASS A, 28 DAYS)
A6: UNIT | B6: Unit of Measurement: | E6: CU.M.
B7: Output per day: | E7: =0.357*8*Y11 -> 2.856 | G7: CU.M./DAY
A8: QTY | B8: Quantity: | E8: ='INPUT DATA'!C17 -> 12.4 | G8: =E6 -> CU.M.
B10: Designation | K10: No. Person | N10: No. of Days | Q10: Daily Rate | T10: Amount | Y10: NO. OF TEAM
Y11: 1
B12: A. | C12: Labor
C13: Concrete Pouring Works
A14: DURATION | C14: a. | D14: Construction Foreman/Engineering Assistant | K14: 1 | N14: =E8/E7 -> 4.3417367 | Q14: 800 | T14: =K14*N14*Q14 -> 3473.3894
C15: b. | D15: Skilled Laborer | K15: 1 | N15: =N14 -> 4.3417367 | Q15: 600 | T15: =K15*N15*Q15 -> 2605.042
C16: c. | D16: Laborer | K16: 4 | N16: =N15 -> 4.3417367 | Q16: 400 | T16: =K16*N16*Q16 -> 6946.7787
A21: LABOR | C21: Sub-Total for A | S21: P | T21: =ROUND(SUM(T13:V19),2) -> 13025.21
B22: Name and Capacity | K22: No. of Units | N22: No. of Days | Q22: Daily Rate | T22: Amount
B24: B. | C24: Equipment
C25: a. | D25: One Bagger Mixer | K25: =Y11 -> 1 | N25: =N14 -> 4.3417367 | Q25: 1376 | T25: =K25*N25*Q25 -> 5974.2297
C26: Minor Tools (10% of Labor Cost) | T26: =0.1*T21 -> 1302.521
A30: EQUIPMENT | C30: Sub-Total for B | S30: P | T30: =ROUND(SUM(T25:V29),2) -> 7276.75
B31: C. | C31: Total (A+B) | T31: =T21+T30 -> 20301.96
B32: D. | C32: Output per day | G32: = | H32: =E7 -> 2.856 | J32: =G7 -> CU.M./DAY
B33: Name and Specifications | K33: Quantity | N33: Unit | Q33: Unit Cost | T33: Amount
B35: E. | C35: Materials
C36: a. | D36: Portland Cement | K36: =9.1*E8 -> 112.84 | N36: =IF(K36>1,"bags","bag") -> bags | O36: =IF(L36>1,"bags","bag") -> bag | P36: =IF(M36>1,"bags","bag") -> bag | Q36: 265 | T36: =K36*Q36 -> 29902.6
C37: b. | D37: Sand | K37: =0.5*E8 -> 6.2 | N37: =IF(K37>1,"cu.m.","cu.m.") -> cu.m. | O37: =IF(L37>1,"cu.m.","cu.m.") -> cu.m. | P37: =IF(M37>1,"cu.m.","cu.m.") -> cu.m. | Q37: 1400 | T37: =K37*Q37 -> 8680
C38: c. | D38: Gravel | K38: =1*E8 -> 12.4 | N38: =IF(K38>1,"cu.m.","cu.m.") -> cu.m. | O38: =IF(L38>1,"cu.m.","cu.m.") -> cu.m. | P38: =IF(M38>1,"cu.m.","cu.m.") -> cu.m. | Q38: 1400 | T38: =K38*Q38 -> 17360
A46: MATERIAL | C46: Sub-Total for E | S46: P | T46: =ROUND(SUM(T36:V45),2) -> 55942.6
B47: F. | C47: Direct Cost (C+E) | T47: =T31+T46 -> 76244.56
B48: G. | C48: Overhead, Contingencies & Miscellaneous | N48: ='INPUT DATA'!C62 -> 0.05 | T48: =T47*N48 -> 3812.228
B49: H. | C49: Contractor's Profit (CP) | N49: ='INPUT DATA'!C63 -> 0.1 | T49: =T47*N49 -> 7624.456
B50: I. | C50: Value Added Tax (VAT) | N50: ='INPUT DATA'!C64 -> 0 | T50: =(T47+T48+T49)*N50 -> 0
A51: CHECKING | B51: J. | C51: Total Cost | T51: =SUM(T47:V50) -> 87681.244
A52: ADJUSTED CHECKING | B52: k. | C52: Total Unit Cost | T52: =T51/E8 -> 7071.0681
AF110: =250*14 -> 3500
AF111: =250-80 -> 170
AF112: =2500/170 -> 14.705882

Sheet 900(1)Struc Con for beam col su
B1: DETAILED UNIT PRICE ANALYSIS
B3: PROJECT NAME: | E3: ='INPUT DATA'!C4 -> PROPOSED ONE STOREY TWO BED ROOM RESIDENTIAL BUILDING
A5: ITEM NO. | B5: Item No./Description: | E5: 900(1) | G5: STRUCTURAL CONCRETE FOR FOOTING TIE BEAM, COLUMN, SUSPENDED SLAB, GIRDER/BEAM (CLASS A, 28 DAYS)
A6: UNIT | B6: Unit of Measurement: | E6: CU.M.
B7: Output per day: | E7: =0.27*8*Y11 -> 2.16 | G7: CU.M./DAY
A8: QTY | B8: Quantity: | E8: ='INPUT DATA'!C18 -> 23.6 | G8: =E6 -> CU.M.
B10: Designation | K10: No. Person | N10: No. of Days | Q10: Daily Rate | T10: Amount | Y10: NO. OF TEAM
Y11: 1
B12: A. | C12: Labor
C13: Concrete Pouring Works
A14: DURATION | C14: a. | D14: Construction Foreman/Engineering Assistant | K14: 1 | N14: =E8/E7 -> 10.925926 | Q14: 800 | T14: =K14*N14*Q14 -> 8740.7407
C15: b. | D15: Skilled Laborer | K15: 1 | N15: =N14 -> 10.925926 | Q15: 600 | T15: =K15*N15*Q15 -> 6555.5556
C16: c. | D16: Laborer | K16: 4 | N16: =N15 -> 10.925926 | Q16: 400 | T16: =K16*N16*Q16 -> 17481.481
A21: LABOR | C21: Sub-Total for A | S21: P | T21: =ROUND(SUM(T13:V19),2) -> 32777.78
B22: Name and Capacity | K22: No. of Units | N22: No. of Days | Q22: Daily Rate | T22: Amount
B24: B. | C24: Equipment
C25: a. | D25: One Bagger Mixer | K25: =Y11 -> 1 | N25: =N14 -> 10.925926 | Q25: 1376 | T25: =K25*N25*Q25 -> 15034.074
C26: Minor Tools (10% of Labor Cost) | T26: =0.1*T21 -> 3277.778
A30: EQUIPMENT | C30: Sub-Total for B | S30: P | T30: =ROUND(SUM(T25:V29),2) -> 18311.85
B31: C. | C31: Total (A+B) | T31: =T21+T30 -> 51089.63
B32: D. | C32: Output per day | G32: = | H32: =E7 -> 2.16 | J32: =G7 -> CU.M./DAY
B33: Name and Specifications | K33: Quantity | N33: Unit | Q33: Unit Cost | T33: Amount
B35: E. | C35: Materials
C36: a. | D36: Portland Cement | K36: =9.1*E8 -> 214.76 | N36: =IF(K36>1,"bags","bag") -> bags | O36: =IF(L36>1,"bags","bag") -> bag | P36: =IF(M36>1,"bags","bag") -> bag | Q36: 265 | T36: =K36*Q36 -> 56911.4
C37: b. | D37: Sand | K37: =0.5*E8 -> 11.8 | N37: =IF(K37>1,"cu.m.","cu.m.") -> cu.m. | O37: =IF(L37>1,"cu.m.","cu.m.") -> cu.m. | P37: =IF(M37>1,"cu.m.","cu.m.") -> cu.m. | Q37: 1200 | T37: =K37*Q37 -> 14160
C38: c. | D38: Gravel | K38: =1*E8 -> 23.6 | N38: =IF(K38>1,"cu.m.","cu.m.") -> cu.m. | O38: =IF(L38>1,"cu.m.","cu.m.") -> cu.m. | P38: =IF(M38>1,"cu.m.","cu.m.") -> cu.m. | Q38: 1200 | T38: =K38*Q38 -> 28320
A46: MATERIAL | C46: Sub-Total for E | S46: P | T46: =ROUND(SUM(T36:V45),2) -> 99391.4
B47: F. | C47: Direct Cost (C+E) | T47: =T31+T46 -> 150481.03
B48: G. | C48: Overhead, Contingencies & Miscellaneous | N48: ='INPUT DATA'!C62 -> 0.05 | T48: =T47*N48 -> 7524.0515
B49: H. | C49: Contractor's Profit (CP) | N49: ='INPUT DATA'!C63 -> 0.1 | T49: =T47*N49 -> 15048.103
B50: I. | C50: Value Added Tax (VAT) | N50: ='INPUT DATA'!C64 -> 0 | T50: =(T47+T48+T49)*N50 -> 0
A51: CHECKING | B51: J. | C51: Total Cost | T51: =SUM(T47:V50) -> 173053.18
A52: ADJUSTED CHECKING | B52: k. | C52: Total Unit Cost | T52: =T51/E8 -> 7332.7621
AF110: =250*14 -> 3500
AF111: =250-80 -> 170
AF112: =2500/170 -> 14.705882

Sheet 903(2) Formworks for 1-storey
B1: DETAILED UNIT PRICE ANALYSIS
B3: PROJECT NAME: | E3: ='INPUT DATA'!C4 -> PROPOSED ONE STOREY TWO BED ROOM RESIDENTIAL BUILDING
A5: ITEM NO. | B5: Item No./Description: | E5: 903(2) | G5: FORMWORKS AND FALSEWORKS (FOR ONE-STOREY BUILDING)
A6: UNIT | B6: Unit of Measurement: | E6: SQ.M.
B7: Output per day: | E7: =3.24*8*Y11 -> 25.92 | G7: SQ.M.DAY
A8: QTY | B8: Quantity: | E8: ='INPUT DATA'!C19 -> 49 | G8: =E6 -> SQ.M.
B10: Designation | K10: No. Person | N10: No. of Days | Q10: Daily Rate | T10: Amount | Y10: NO. OF TEAM
Y11: 1
B12: A. | C12: Labor
C13: Installation:
A14: DURATION | C14: a. | D14: Construction Foreman/Engineering Assistant | K14: 1 | N14: =E8/E7 -> 1.8904321 | Q14: 800 | T14: =K14*N14*Q14 -> 1512.3457
C15: b. | D15: Skilled Laborer | K15: 2 | N15: =N14 -> 1.8904321 | Q15: 600 | T15: =K15*N15*Q15 -> 2268.5185
C16: c. | D16: Laborer | K16: 4 | N16: =N15 -> 1.8904321 | Q16: 400 | T16: =K16*N16*Q16 -> 3024.6914
C18: Stripping:
C19: a. | D19: Construction Foreman/Engineering Assistant | K19: 1 | N19: =0.41*N16 -> 0.77507716 | Q19: 800 | T19: =K19*N19*Q19 -> 620.06173
C20: b. | D20: Laborer | K20: 6 | N20: =N19 -> 0.77507716 | Q20: 400 | T20: =K20*N20*Q20 -> 1860.1852
A22: LABOR | C22: Sub-Total for A | S22: P | T22: =ROUND(SUM(T13:V20),2) -> 9285.8
B23: Name and Capacity | K23: No. of Units | N23: No. of Days | Q23: Daily Rate | T23: Amount
B25: B. | C25: Equipment
C27: Minor Tools (10% of Labor Cost) | T27: =0.1*T22 -> 928.58
A31: EQUIPMENT | C31: Sub-Total for B | S31: P | T31: =ROUND(SUM(T26:V30),2) -> 928.58
B32: C. | C32: Total (A+B) | T32: =T22+T31 -> 10214.38
B33: D. | C33: Output per day | G33: = | H33: =E7 -> 25.92 | J33: =G7 -> SQ.M.DAY
B34: Name and Specifications | K34: Quantity | N34: Unit | Q34: Unit Cost | T34: Amount
B36: E. | C36: Materials
C37: a. | D37: Ordinary Plywood - 3 uses | K37: =0.347*E8 -> 17.003 | N37: pcs. | O37: =IF(L37>1,"bags","bag") -> bag | P37: =IF(M37>1,"bags","bag") -> bag | Q37: 890 | T37: =K37*Q37 -> 15132.67
C38: b. | D38: Good Lumber - 3 uses | K38: =7.19*E8 -> 352.31 | N38: bd. Ft. | O38: =IF(L38>1,"cu.m.","cu.m.") -> cu.m. | P38: =IF(M38>1,"cu.m.","cu.m.") -> cu.m. | Q38: 35 | T38: =K38*Q38 -> 12330.85
C39: c. | D39: Assorted Common Wire Nails | K39: =0.21*E8 -> 10.29 | N39: kgs. | O39: =IF(L39>1,"cu.m.","cu.m.") -> cu.m. | P39: =IF(M39>1,"cu.m.","cu.m.") -> cu.m. | Q39: 75 | T39: =K39*Q39 -> 771.75
C40: d. | D40: Consumables (5% of Materials Cost) | T40: =0.05*SUM(T37:V39) -> 1411.7635
A47: MATERIAL | C47: Sub-Total for E | S47: P | T47: =ROUND(SUM(T37:V46),2) -> 29647.03
B48: F. | C48: Direct Cost (C+E) | T48: =T32+T47 -> 39861.41
B49: G. | C49: Overhead, Contingencies & Miscellaneous | N49: ='INPUT DATA'!C62 -> 0.05 | T49: =T48*N49 -> 1993.0705
B50: H. | C50: Contractor's Profit (CP) | N50: ='INPUT DATA'!C63 -> 0.1 | T50: =T48*N50 -> 3986.141
B51: I. | C51: Value Added Tax (VAT) | N51: ='INPUT DATA'!C64 -> 0 | T51: =(T48+T49+T50)*N51 -> 0
A52: CHECKING | B52: J. | C52: Total Cost | T52: =SUM(T48:V51) -> 45840.621
A53: ADJUSTED CHECKING | B53: k. | C53: Total Unit Cost | T53: =T52/E8 -> 935.52289
AF111: =250*14 -> 3500
AF112: =250-80 -> 170
AF113: =2500/170 -> 14.705882

Sheet 1046 4"CHB
B1: DETAILED UNIT PRICE ANALYSIS
Y2: NO. OF TEAMS | Z2: 1
B3: PROJECT NAME: | E3: ='INPUT DATA'!C4 -> PROPOSED ONE STOREY TWO BED ROOM RESIDENTIAL BUILDING
AL4: =SUM(AJ4:AJ5) -> 0
A5: ITEM NO. | B5: Item No./Description: | E5: 1046 | G5: 100MM CHB NON LOAD BEARING/LOAD BEARING (INCLUDING REINFORCING STEEL)
A6: UNIT | B6: Unit of Measurement: | E6: SQ.M.
B7: Output per day: | E7: =3.825*8*Z2 -> 30.6 | G7: =CONCATENATE(G8,"/DAY") -> SQ.M./DAY
A8: QTY | B8: Quantity: | E8: ='INPUT DATA'!C20 -> 189 | G8: =E6 -> SQ.M.
B10: Designation | K10: No. Person | N10: No. of Days | Q10: Daily Rate | T10: Amount
B12: A. | C12: Labor
C13: Concrete Pouring Works
A14: DURATION | C14: a. | D14: Construction Foreman/Engineering Assistant | K14: 1 | N14: =E8/E7 -> 6.1764706 | Q14: 800 | T14: =K14*N14*Q14 -> 4941.1765
C15: b. | D15: Mason | K15: =2*Z2 -> 2 | N15: =N14 -> 6.1764706 | Q15: 600 | T15: =K15*N15*Q15 -> 7411.7647
C16: c. | D16: Laborer | K16: =3*Z2 -> 3 | N16: =N15 -> 6.1764706 | Q16: 400 | T16: =K16*N16*Q16 -> 7411.7647
A21: LABOR | C21: Sub-Total for A | S21: P | T21: =ROUND(SUM(T13:V19),2) -> 19764.71
B22: Name and Capacity | K22: No. of Units | N22: No. of Days | Q22: Daily Rate | T22: Amount
B24: B. | C24: Equipment
C25: a. | D25: One Bagger Mixer | K25: 1 | N25: =N14 -> 6.1764706 | Q25: 1376 | T25: =K25*N25*Q25 -> 8498.8235
D26: Minor Tools (10% of Labor Cost) | T26: =T21*10% -> 1976.471
A30: EQUIPMENT | C30: Sub-Total for B | S30: P | T30: =ROUND(SUM(T24:V29),2) -> 10475.29
B31: C. | C31: Total (A+B) | T31: =T21+T30 -> 30240
B32: D. | C32: Output per day | G32: = | H32: =E7 -> 30.6 | J32: =G7 -> SQ.M./DAY
B33: Name and Specifications | K33: Quantity | N33: Unit | Q33: Unit Cost | T33: Amount
B35: E. | C35: Materials
C36: a. | D36: 100mm x 200mm x 400mm Concrete Hollow Blocks | K36: =13*E8 -> 2457 | N36: =IF(K36>1,"pcs.","pc.") -> pcs. | O36: =IF(L36>1,"pcs.","pc.") -> pc. | P36: =IF(M36>1,"pcs.","pc.") -> pc. | Q36: 15 | T36: =K36*Q36 -> 36855
C37: b. | D37: Portland Cement | K37: =0.525*E8 -> 99.225 | N37: =IF(K37>1,"bags","bag") -> bags | O37: =IF(L37>1,"bags","bag") -> bag | P37: =IF(M37>1,"bags","bag") -> bag | Q37: 265 | T37: =K37*Q37 -> 26294.625
C38: c. | D38: Washed Sand | K38: =0.04*E8 -> 7.56 | N38: =IF(K38>1,"cu.m.","cu.m.") -> cu.m. | O38: =IF(L38>1,"cu.m.","cu.m.") -> cu.m. | P38: =IF(M38>1,"cu.m.","cu.m.") -> cu.m. | Q38: 1400 | T38: =K38*Q38 -> 10584
C39: d. | D39: Deformed Reinforcing Steel Bar (Sizes to be determined by Estimator) | K39: =3.24*E8 -> 612.36 | N39: =IF(K39>1,"kgs.","kg.") -> kgs. | O39: =IF(L39>1,"kgs.","kg.") -> kg. | P39: =IF(M39>1,"kgs.","kg.") -> kg. | Q39: 75 | T39: =K39*Q39 -> 45927
C40: e. | D40: #16 G.I. Tie-wire | K40: =0.05*E8 -> 9.45 | N40: =IF(K40>1,"kgs.","kg.") -> kgs. | O40: =IF(L40>1,"kgs.","kg.") -> kg. | P40: =IF(M40>1,"kgs.","kg.") -> kg. | Q40: 90 | T40: =K40*Q40 -> 850.5
A46: MATERIAL | C46: Sub-Total for E | S46: P | T46: =ROUND(SUM(T36:V45),2) -> 120511.13
B47: F. | C47: Direct Cost (C+E) | T47: =T31+T46 -> 150751.13
B48: G. | C48: Overhead, Contingencies & Miscellaneous | N48: ='INPUT DATA'!C62 -> 0.05 | T48: =T47*N48 -> 7537.5565
B49: H. | C49: Contractor's Profit (CP) | N49: ='INPUT DATA'!C63 -> 0.1 | T49: =T47*N49 -> 15075.113
B50: I. | C50: Value Added Tax (VAT) | N50: ='INPUT DATA'!C64 -> 0 | T50: =(T47+T48+T49)*N50 -> 0
A51: CHECKING | B51: J. | C51: Total Cost | T51: =SUM(T47:V50) -> 173363.8
A52: ADJUSTED CHECKING | B52: k. | C52: Total Unit Cost | T52: =T51/E8 -> 917.26878

Sheet 1046 6" CHB
B1: DETAILED UNIT PRICE ANALYSIS
Y2: NO. OF TEAMS | Z2: 1
B3: PROJECT NAME: | E3: ='INPUT DATA'!C4 -> PROPOSED ONE STOREY TWO BED ROOM RESIDENTIAL BUILDING
A5: ITEM NO. | B5: Item No./Description: | E5: 1046 | G5: 150mm. CHB NON LOAD BEARING (including Reinforcing Steel)
A6: UNIT | B6: Unit of Measurement: | E6: SQ.M.
B7: Output per day: | E7: =3.18*8*Z2 -> 25.44 | G7: =CONCATENATE(G8,"/DAY") -> SQ.M./DAY
A8: QTY | B8: Quantity: | E8: ='INPUT DATA'!C21 -> 36 | G8: =E6 -> SQ.M.
B10: Designation | K10: No. Person | N10: No. of Days | Q10: Daily Rate | T10: Amount
B12: A. | C12: Labor
C13: Concrete Pouring Works
A14: DURATION | C14: a. | D14: Construction Foreman/Engineering Assistant | K14: 1 | N14: =E8/E7 -> 1.4150943 | Q14: 800 | T14: =K14*N14*Q14 -> 1132.0755
C15: b. | D15: Mason | K15: =2*Z2 -> 2 | N15: =N14 -> 1.4150943 | Q15: 600 | T15: =K15*N15*Q15 -> 1698.1132
C16: c. | D16: Laborer | K16: =3*Z2 -> 3 | N16: =N15 -> 1.4150943 | Q16: 400 | T16: =K16*N16*Q16 -> 1698.1132
A21: LABOR | C21: Sub-Total for A | S21: P | T21: =ROUND(SUM(T13:V19),2) -> 4528.3
B22: Name and Capacity | K22: No. of Units | N22: No. of Days | Q22: Daily Rate | T22: Amount
B24: B. | C24: Equipment
C25: a. | D25: One Bagger Mixer | K25: 1 | N25: =N14 -> 1.4150943 | Q25: 1376 | T25: =K25*N25*Q25 -> 1947.1698
D26: Minor Tools (10% of Labor Cost) | T26: =T21*10% -> 452.83
A30: EQUIPMENT | C30: Sub-Total for B | S30: P | T30: =ROUND(SUM(T24:V29),2) -> 2400
B31: C. | C31: Total (A+B) | T31: =T21+T30 -> 6928.3
B32: D. | C32: Output per day | G32: = | H32: =E7 -> 25.44 | J32: =G7 -> SQ.M./DAY
B33: Name and Specifications | K33: Quantity | N33: Unit | Q33: Unit Cost | T33: Amount
B35: E. | C35: Materials
C36: a. | D36: 150mm x 200mm x 400mm Concrete Hollow Blocks | K36: =13*E8 -> 468 | N36: =IF(K36>1,"pcs.","pc.") -> pcs. | O36: =IF(L36>1,"pcs.","pc.") -> pc. | P36: =IF(M36>1,"pcs.","pc.") -> pc. | Q36: 18 | T36: =K36*Q36 -> 8424
C37: b. | D37: Portland Cement | K37: =1.5*E8 -> 54 | N37: =IF(K37>1,"bags","bag") -> bags | O37: =IF(L37>1,"bags","bag") -> bag | P37: =IF(M37>1,"bags","bag") -> bag | Q37: 265 | T37: =K37*Q37 -> 14310
C38: c. | D38: Washed Sand | K38: =0.04*E8 -> 1.44 | N38: =IF(K38>1,"cu.m.","cu.m.") -> cu.m. | O38: =IF(L38>1,"cu.m.","cu.m.") -> cu.m. | P38: =IF(M38>1,"cu.m.","cu.m.") -> cu.m. | Q38: 1400 | T38: =K38*Q38 -> 2016
C39: d. | D39: Deformed Reinforcing Steel Bar (Sizes to be determined by Estimator) | K39: =3.24*E8 -> 116.64 | N39: =IF(K39>1,"kgs.","kg.") -> kgs. | O39: =IF(L39>1,"kgs.","kg.") -> kg. | P39: =IF(M39>1,"kgs.","kg.") -> kg. | Q39: 75 | T39: =K39*Q39 -> 8748
C40: e. | D40: #16 G.I. Tie-wire | K40: =0.05*E8 -> 1.8 | N40: =IF(K40>1,"kgs.","kg.") -> kgs. | O40: =IF(L40>1,"kgs.","kg.") -> kg. | P40: =IF(M40>1,"kgs.","kg.") -> kg. | Q40: 90 | T40: =K40*Q40 -> 162
A46: MATERIAL | C46: Sub-Total for E | S46: P | T46: =ROUND(SUM(T36:V45),2) -> 33660
B47: F. | C47: Direct Cost (C+E) | T47: =T31+T46 -> 40588.3
B48: G. | C48: Overhead, Contingencies & Miscellaneous | N48: ='INPUT DATA'!C62 -> 0.05 | T48: =T47*N48 -> 2029.415
B49: H. | C49: Contractor's Profit (CP) | N49: ='INPUT DATA'!C63 -> 0.1 | T49: =T47*N49 -> 4058.83
B50: I. | C50: Value Added Tax (VAT) | N50: ='INPUT DATA'!C64 -> 0 | T50: =(T47+T48+T49)*N50 -> 0
A51: CHECKING | B51: J. | C51: Total Cost | T51: =SUM(T47:V50) -> 46676.545
A52: ADJUSTED CHECKING | B52: k. | C52: Total Unit Cost | T52: =T51/E8 -> 1296.5707

Sheet 1027-Plaster
B1: DETAILED UNIT PRICE ANALYSIS
B3: PROJECT NAME: | E3: ='INPUT DATA'!C4 -> PROPOSED ONE STOREY TWO BED ROOM RESIDENTIAL BUILDING
A5: ITEM NO. | B5: Item No./Description: | E5: 1027(1) | G5: CEMENT PLASTER FINISH WITH 19MM THICK & 1:3 MORTAR MIXTURE
A6: UNIT | B6: Unit of Measurement: | E6: SQ.M.
B7: Output per day: | E7: =7.125*8*Y11 -> 57 | G7: SQ.M./DAY
A8: QTY | B8: Quantity: | E8: ='INPUT DATA'!C22 -> 420 | G8: =E6 -> SQ.M.
B10: Designation | K10: No. Person | N10: No. of Days | Q10: Daily Rate | T10: Amount
X11: NO .OF TEAM | Y11: 1
B12: A. | C12: Labor
A13: DURATION | C13: a. | D13: Construction Foreman/Engineering Assistant | K13: 1 | N13: =E8/E7 -> 7.3684211 | Q13: 800 | T13: =K13*N13*Q13 -> 5894.7368
C14: b. | D14: Mason | K14: =2*Y11 -> 2 | N14: =N13 -> 7.3684211 | Q14: 600 | T14: =K14*N14*Q14 -> 8842.1053
C15: c. | D15: Laborer | K15: =4*Y11 -> 4 | N15: =N14 -> 7.3684211 | Q15: 400 | T15: =K15*N15*Q15 -> 11789.474
A20: LABOR | C20: Sub-Total for A | S20: P | T20: =ROUND(SUM(T13:V18),2) -> 26526.32
B21: Name and Capacity | K21: No. of Units | N21: No. of Days | Q21: Daily Rate | T21: Amount
B23: B. | C23: Equipment
C24: a. | D24: Minor Tools (10% of labor Cost) | T24: =10%*T20 -> 2652.632
A29: EQUIPMENT | C29: Sub-Total for B | S29: P | T29: =ROUND(SUM(T24:V28),2) -> 2652.63
B30: C. | C30: Total (A+B) | T30: =T20+T29 -> 29178.95
B31: D. | C31: Output per day | G31: = | H31: =E7 -> 57 | J31: =G7 -> SQ.M./DAY
B32: Name and Specifications | K32: Quantity | N32: Unit | Q32: Unit Cost | T32: Amount
B34: E. | C34: Materials
C35: a. | D35: Portland Cement | K35: =0.33*E8 -> 138.6 | N35: =IF(K35>1,"bags","bag") -> bags | O35: =IF(L35>1,"bags","bag") -> bag | P35: =IF(M35>1,"bags","bag") -> bag | Q35: 265 | T35: =K35*Q35 -> 36729
C36: b. | D36: Fine Sand | K36: =0.027*E8 -> 11.34 | N36: =IF(K36>1,"cu.m.","cu.m.") -> cu.m. | O36: =IF(L36>1,"cu.m.","cu.m.") -> cu.m. | P36: =IF(M36>1,"cu.m.","cu.m.") -> cu.m. | Q36: 1800 | T36: =K36*Q36 -> 20412
A45: MATERIAL | C45: Sub-Total for E | S45: P | T45: =ROUND(SUM(T35:V44),2) -> 57141
B46: F. | C46: Direct Cost (C+E) | T46: =T30+T45 -> 86319.95
B47: G. | C47: Overhead, Contingencies & Miscellaneous | N47: ='INPUT DATA'!C62 -> 0.05 | T47: =T46*N47 -> 4315.9975
B48: H. | C48: Contractor's Profit (CP) | N48: ='INPUT DATA'!C63 -> 0.1 | T48: =T46*N48 -> 8631.995
B49: I. | C49: Value Added Tax (VAT) | N49: ='INPUT DATA'!C64 -> 0 | T49: =(T46+T47+T48)*N49 -> 0
A50: CHECKING | B50: J. | C50: Total Cost | T50: =SUM(T46:V49) -> 99267.942
A51: ADJUSTED CHECKING | B51: k. | C51: Total Unit Cost | T51: =T50/E8 -> 236.35224

Sheet 1047(2)b Struc Steel Truss
B1: DETAILED UNIT PRICE ANALYSIS
B3: PROJECT NAME: | E3: ='INPUT DATA'!C4 -> PROPOSED ONE STOREY TWO BED ROOM RESIDENTIAL BUILDING
A5: ITEM NO. | B5: Item No./Description: | E5: 1047(2)b | G5: STRUCTURAL STEEL ROOF TRUSS
A6: UNIT | B6: Unit of Measurement: | E6: KGS.
B7: Output per day: | E7: =85*8 -> 680 | G7: KGS./DAY
A8: QTY | B8: Quantity: | E8: ='INPUT DATA'!C23 -> 0 | G8: =E6 -> KGS.
B10: Designation | K10: No. Person | N10: No. of Days | Q10: Daily Rate | T10: Amount
X11: NO .OF TEAM | Y11: 1
B12: A. | C12: Labor
C13: Fabrication:
A14: DURATION | C14: a. | D14: Construction Foreman/Engineering Assistant | K14: 1 | N14: =E8/E7 -> 0 | Q14: 800 | T14: =K14*N14*Q14 -> 0
C15: b. | D15: Skilled Laborer | K15: =2*Y11 -> 2 | N15: =N14 -> 0 | Q15: 600 | T15: =K15*N15*Q15 -> 0
C16: c. | D16: Laborer | K16: 2 | N16: =N15 -> 0 | Q16: 400 | T16: =K16*N16*Q16 -> 0
C19: Erection:
C20: a. | D20: Skilled Laborer | K20: 3 | N20: =0.49*N16 -> 0 | Q20: 600 | T20: =K20*N20*Q20 -> 0
C21: b. | D21: Laborer | K21: 3 | N21: =0.49*N16 -> 0 | Q21: 400 | T21: =K21*N21*Q21 -> 0
A27: LABOR | C27: Sub-Total for A | S27: P | T27: =ROUND(SUM(T14:V25),2) -> 0
B28: Name and Capacity | K28: No. of Units | N28: No. of Days | Q28: Daily Rate | T28: Amount
B30: B. | C30: Equipment
C31: a. | D31: Welding Machine | K31: 1 | N31: =0.75*N16 -> 0 | Q31: 2160 | T31: =Q31*N31*K31 -> 0
C32: b. | D32: Cutting Outfit | K32: 1 | N32: =0.25*N16 -> 0 | Q32: 364 | T32: =Q32*N32*K32 -> 0
C33: c. | D33: Truck Mounted Crane (20-25 mt) | K33: 1 | N33: =0.49*N16 -> 0 | Q33: 14176 | T33: =Q33*N33*K33 -> 0
D34: Minor Tools (10% of Labor Cost) | T34: =0.1*SUM(T31:V33) -> 0
A36: EQUIPMENT | C36: Sub-Total for B | S36: P | T36: =ROUND(SUM(T31:V35),2) -> 0
B37: C. | C37: Total (A+B) | T37: =T27+T36 -> 0
B38: D. | C38: Output per day | G38: = | H38: =E7 -> 680 | J38: =G7 -> KGS./DAY
B39: Name and Specifications | K39: Quantity | N39: Unit | Q39: Unit Cost | T39: Amount
B41: E. | C41: Materials
C42: a. | D42: Structural Steel | K42: =E8 -> 0 | N42: kgs. | O42: =IF(L42>1,"bags","bag") -> bag | P42: =IF(M42>1,"bags","bag") -> bag | Q42: 70 | T42: =K42*Q42 -> 0
C43: b. | D43: Acetylene | K43: =0.011*E8 -> 0 | N43: cyl | O43: =IF(L43>1,"bags","bag") -> bag | P43: =IF(M43>1,"bags","bag") -> bag | Q43: 3500 | T43: =K43*Q43 -> 0
C44: c. | D44: Oxygene | K44: =0.022*E8 -> 0 | N44: cyl | O44: =IF(L44>1,"bags","bag") -> bag | P44: =IF(M44>1,"bags","bag") -> bag | Q44: 1800 | T44: =K44*Q44 -> 0
C45: d. | D45: Welding Rod | K45: =0.02*E8 -> 0 | N45: kgs. | O45: =IF(L45>1,"bags","bag") -> bag | P45: =IF(M45>1,"bags","bag") -> bag | Q45: 160 | T45: =K45*Q45 -> 0
D46: Consumable (5% of Materials Cost) | T46: =0.05*SUM(T42:V45) -> 0
D48: The estimate need to count and specify the stee materials and compute for its weight in kilograms
A52: MATERIAL | C52: Sub-Total for E | S52: P | T52: =ROUND(SUM(T42:V51),2) -> 0
B53: F. | C53: Direct Cost (C+E) | T53: =T37+T52 -> 0
B54: G. | C54: Overhead, Contingencies & Miscellaneous | N54: ='INPUT DATA'!C62 -> 0.05 | T54: =T53*N54 -> 0
B55: H. | C55: Contractor's Profit (CP) | N55: ='INPUT DATA'!C63 -> 0.1 | T55: =T53*N55 -> 0
B56: I. | C56: Value Added Tax (VAT) | N56: ='INPUT DATA'!C64 -> 0 | T56: =(T53+T54+T55)*N56 -> 0
A57: CHECKING | B57: J. | C57: Total Cost | T57: =SUM(T53:V56) -> 0
A58: ADJUSTED CHECKING | B58: k. | C58: Total Unit Cost | T58: =T57/E8 -> #DIV/0!

Sheet 1047(2)C Struc Steel Purlins
B1: DETAILED UNIT PRICE ANALYSIS
B3: PROJECT NAME: | E3: ='INPUT DATA'!C4 -> PROPOSED ONE STOREY TWO BED ROOM RESIDENTIAL BUILDING
A5: ITEM NO. | B5: Item No./Description: | E5: 1047(2)c | G5: STRUCTURAL STEEL PURLINS
A6: UNIT | B6: Unit of Measurement: | E6: KGS.
B7: Output per day: | E7: =90.45*8 -> 723.6 | G7: KGS./DAY
A8: QTY | B8: Quantity: | E8: ='INPUT DATA'!C24 -> 200 | G8: =E6 -> KGS.
B10: Designation | K10: No. Person | N10: No. of Days | Q10: Daily Rate | T10: Amount
X11: NO .OF TEAM | Y11: 1
B12: A. | C12: Labor
C13: Fabrication:
A14: DURATION | C14: a. | D14: Construction Foreman/Engineering Assistant | K14: 1 | N14: =E8/E7 -> 0.2763958 | Q14: 800 | T14: =K14*N14*Q14 -> 221.11664
C15: b. | D15: Skilled Laborer | K15: =2*Y11 -> 2 | N15: =N14 -> 0.2763958 | Q15: 600 | T15: =K15*N15*Q15 -> 331.67496
C16: c. | D16: Laborer | K16: 4 | N16: =N15 -> 0.2763958 | Q16: 400 | T16: =K16*N16*Q16 -> 442.23328
A21: LABOR | C21: Sub-Total for A | S21: P | T21: =ROUND(SUM(T14:V19),2) -> 995.02
B22: Name and Capacity | K22: No. of Units | N22: No. of Days | Q22: Daily Rate | T22: Amount
B24: B. | C24: Equipment
C25: a. | D25: Welding Machine | K25: 2 | N25: =0.75*N16 -> 0.20729685 | Q25: 2160 | T25: =Q25*N25*K25 -> 895.52239
A30: EQUIPMENT | C30: Sub-Total for B | S30: P | T30: =ROUND(SUM(T25:V29),2) -> 895.52
B31: C. | C31: Total (A+B) | T31: =T21+T30 -> 1890.54
B32: D. | C32: Output per day | G32: = | H32: =E7 -> 723.6 | J32: =G7 -> KGS./DAY
B33: Name and Specifications | K33: Quantity | N33: Unit | Q33: Unit Cost | T33: Amount
B35: E. | C35: Materials
C36: a. | D36: Structural Steel Purlins | K36: =E8*1.05 -> 210 | N36: kgs. | O36: =IF(L36>1,"bags","bag") -> bag | P36: =IF(M36>1,"bags","bag") -> bag | Q36: 70 | T36: =K36*Q36 -> 14700
C37: b. | D37: Welding Rod | K37: =0.02*E8 -> 4 | N37: kgs. | O37: =IF(L37>1,"bags","bag") -> bag | P37: =IF(M37>1,"bags","bag") -> bag | Q37: 160 | T37: =K37*Q37 -> 640
C38: c. | D38: Consumable (5% of Materials Cost) | T38: =0.05*SUM(T36:V37) -> 767
D40: The estimate need to count and specify the stee materials and compute for its weight in kilograms
A44: MATERIAL | C44: Sub-Total for E | S44: P | T44: =ROUND(SUM(T36:V43),2) -> 16107
B45: F. | C45: Direct Cost (C+E) | T45: =T31+T44 -> 17997.54
B46: G. | C46: Overhead, Contingencies & Miscellaneous | N46: ='INPUT DATA'!C62 -> 0.05 | T46: =T45*N46 -> 899.877
B47: H. | C47: Contractor's Profit (CP) | N47: ='INPUT DATA'!C63 -> 0.1 | T47: =T45*N47 -> 1799.754
B48: I. | C48: Value Added Tax (VAT) | N48: ='INPUT DATA'!C64 -> 0 | T48: =(T45+T46+T47)*N48 -> 0
A49: CHECKING | B49: J. | C49: Total Cost | T49: =SUM(T45:V48) -> 20697.171
A50: ADJUSTED CHECKING | B50: k. | C50: Total Unit Cost | T50: =T49/E8 -> 103.48586

Sheet 1013(1) Corr Metal Roofing
B1: DETAILED UNIT PRICE ANALYSIS
B3: PROJECT NAME: | E3: ='INPUT DATA'!C4 -> PROPOSED ONE STOREY TWO BED ROOM RESIDENTIAL BUILDING
A5: ITEM NO. | B5: Item No./Description: | E5: 1013(1) | G5: CORRUGATED METAL ROOFING
A6: UNIT | B6: Unit of Measurement: | E6: SQ.M.
B7: Output per day: | E7: =2.076*8 -> 16.608 | G7: SQ.M./DAY
A8: QTY | B8: Quantity: | E8: ='INPUT DATA'!C25 -> 0 | G8: =E6 -> SQ.M.
B10: Designation | K10: No. Person | N10: No. of Days | Q10: Daily Rate | T10: Amount
X11: NO .OF TEAM | Y11: 1
B12: A. | C12: Labor
C13: Fabrication:
A14: DURATION | C14: a. | D14: Construction Foreman/Engineering Assistant | K14: 1 | N14: =E8/E7 -> 0 | Q14: 800 | T14: =K14*N14*Q14 -> 0
C15: b. | D15: Skilled Laborer | K15: 1 | N15: =N14 -> 0 | Q15: 600 | T15: =K15*N15*Q15 -> 0
C16: c. | D16: Laborer | K16: 2 | N16: =N15 -> 0 | Q16: 400 | T16: =K16*N16*Q16 -> 0
A22: LABOR | C22: Sub-Total for A | S22: P | T22: =ROUND(SUM(T14:V20),2) -> 0
B23: Name and Capacity | K23: No. of Units | N23: No. of Days | Q23: Daily Rate | T23: Amount
B25: B. | C25: Equipment
D26: Minor Tools (10% of Labor Cost) | T26: =0.1*T22 -> 0
A31: EQUIPMENT | C31: Sub-Total for B | S31: P | T31: =ROUND(SUM(T26:V30),2) -> 0
B32: C. | C32: Total (A+B) | T32: =T22+T31 -> 0
B33: D. | C33: Output per day | G33: = | H33: =E7 -> 16.608 | J33: =G7 -> SQ.M./DAY
B34: Name and Specifications | K34: Quantity | N34: Unit | Q34: Unit Cost | T34: Amount
B36: E. | C36: Materials
C37: a. | D37: Corrugated Roofing Sheet | K37: =E8 -> 0 | N37: sq.m. | O37: =IF(L37>1,"bags","bag") -> bag | P37: =IF(M37>1,"bags","bag") -> bag | Q37: 400 | T37: =K37*Q37 -> 0
C38: b. | D38: Tekscrew/ J-bolt with Washers | K38: =0.011*E8 -> 0 | N38: pc. | O38: =IF(L38>1,"bags","bag") -> bag | P38: =IF(M38>1,"bags","bag") -> bag | Q38: 1.5 | T38: =K38*Q38 -> 0
C39: c. | D39: Consumables (3% of Materials Costs) | T39: =0.03*SUM(T37:V38) -> 0
D43: The estimator may include additional materials such as insualtor foam to meet the detailed engineering plan.
A47: MATERIAL | C47: Sub-Total for E | S47: P | T47: =ROUND(SUM(T37:V46),2) -> 0
B48: F. | C48: Direct Cost (C+E) | T48: =T32+T47 -> 0
B49: G. | C49: Overhead, Contingencies & Miscellaneous | N49: ='INPUT DATA'!C62 -> 0.05 | T49: =T48*N49 -> 0
B50: H. | C50: Contractor's Profit (CP) | N50: ='INPUT DATA'!C63 -> 0.1 | T50: =T48*N50 -> 0
B51: I. | C51: Value Added Tax (VAT) | N51: ='INPUT DATA'!C64 -> 0 | T51: =(T48+T49+T50)*N51 -> 0
A52: CHECKING | B52: J. | C52: Total Cost | T52: =SUM(T48:V51) -> 0
A53: ADJUSTED CHECKING | B53: k. | C53: Total Unit Cost | T53: =T52/E8 -> #DIV/0!

Sheet 1013(2) Roof ridge flash valley
B1: DETAILED UNIT PRICE ANALYSIS
B3: PROJECT NAME: | E3: ='INPUT DATA'!C4 -> PROPOSED ONE STOREY TWO BED ROOM RESIDENTIAL BUILDING
A5: ITEM NO. | B5: Item No./Description: | E5: 1013(2) | G5: FABRICATED METAL ROOFING ACCESSORY (RIDGE/HIP ROLLS/FLASHING/COUNTER FLASHING/ VALLEY ROLL)
A6: UNIT | B6: Unit of Measurement: | E6: M.
B7: Output per day: | E7: =10*8 -> 80 | G7: M./DAY
A8: QTY | B8: Quantity: | E8: ='INPUT DATA'!C26 -> 38 | G8: =E6 -> M.
B10: Designation | K10: No. Person | N10: No. of Days | Q10: Daily Rate | T10: Amount
X11: NO .OF TEAM | Y11: 1
B12: A. | C12: Labor
C13: Fabrication:
A14: DURATION | C14: a. | D14: Construction Foreman/Engineering Assistant | K14: 1 | N14: =E8/E7 -> 0.475 | Q14: 800 | T14: =K14*N14*Q14 -> 380
C15: b. | D15: Skilled Laborer | K15: 1 | N15: =N14 -> 0.475 | Q15: 600 | T15: =K15*N15*Q15 -> 285
C16: c. | D16: Laborer | K16: 1 | N16: =N15 -> 0.475 | Q16: 400 | T16: =K16*N16*Q16 -> 190
A22: LABOR | C22: Sub-Total for A | S22: P | T22: =ROUND(SUM(T14:V20),2) -> 855
B23: Name and Capacity | K23: No. of Units | N23: No. of Days | Q23: Daily Rate | T23: Amount
B25: B. | C25: Equipment
D26: Minor Tools (10% of Labor Cost) | T26: =0.1*T22 -> 85.5
A31: EQUIPMENT | C31: Sub-Total for B | S31: P | T31: =ROUND(SUM(T26:V30),2) -> 85.5
B32: C. | C32: Total (A+B) | T32: =T22+T31 -> 940.5
B33: D. | C33: Output per day | G33: = | H33: =E7 -> 80 | J33: =G7 -> M./DAY
B34: Name and Specifications | K34: Quantity | N34: Unit | Q34: Unit Cost | T34: Amount
B36: E. | C36: Materials
C37: a. | D37: Ridge/Hip Rolls/Flashing/Valley Roll/ Counter Flashing (0.4-0.6mm Thk | K37: =E8 -> 38 | N37: m | O37: =IF(L37>1,"bags","bag") -> bag | P37: =IF(M37>1,"bags","bag") -> bag | Q37: =440/2.4 -> 183.33333 | T37: =K37*Q37 -> 6966.6667
C38: b. | D38: Blind Rivets | K38: =19*E8 -> 722 | N38: pc. | O38: =IF(L38>1,"bags","bag") -> bag | P38: =IF(M38>1,"bags","bag") -> bag | Q38: =400/300 -> 1.3333333 | T38: =K38*Q38 -> 962.66667
C39: c. | D39: Consumables (3% of Materials Costs) | T39: =0.03*SUM(T37:V38) -> 237.88
A47: MATERIAL | C47: Sub-Total for E | S47: P | T47: =ROUND(SUM(T37:V46),2) -> 8167.21
B48: F. | C48: Direct Cost (C+E) | T48: =T32+T47 -> 9107.71
B49: G. | C49: Overhead, Contingencies & Miscellaneous | N49: ='INPUT DATA'!C62 -> 0.05 | T49: =T48*N49 -> 455.3855
B50: H. | C50: Contractor's Profit (CP) | N50: ='INPUT DATA'!C63 -> 0.1 | T50: =T48*N50 -> 910.771
B51: I. | C51: Value Added Tax (VAT) | N51: ='INPUT DATA'!C64 -> 0 | T51: =(T48+T49+T50)*N51 -> 0
A52: CHECKING | B52: J. | C52: Total Cost | T52: =SUM(T48:V51) -> 10473.867
A53: ADJUSTED CHECKING | B53: k. | C53: Total Unit Cost | T53: =T52/E8 -> 275.62807

Sheet 1013(2) Metal Roof Acc (Gutter
B1: DETAILED UNIT PRICE ANALYSIS
B3: PROJECT NAME: | E3: ='INPUT DATA'!C4 -> PROPOSED ONE STOREY TWO BED ROOM RESIDENTIAL BUILDING
A5: ITEM NO. | B5: Item No./Description: | E5: 1013(2) | G5: FABRICATED METAL ROOFING ACCESSORY (GUTTER)
A6: UNIT | B6: Unit of Measurement: | E6: M.
B7: Output per day: | E7: =11.8*8 -> 94.4 | G7: M./DAY
A8: QTY | B8: Quantity: | E8: ='INPUT DATA'!C27 -> 13 | G8: =E6 -> M.
B10: Designation | K10: No. Person | N10: No. of Days | Q10: Daily Rate | T10: Amount
X11: NO .OF TEAM | Y11: 1
B12: A. | C12: Labor
C13: Fabrication:
A14: DURATION | C14: a. | D14: Construction Foreman/Engineering Assistant | K14: 1 | N14: =E8/E7 -> 0.13771186 | Q14: 800 | T14: =K14*N14*Q14 -> 110.16949
C15: b. | D15: Skilled Laborer | K15: 1 | N15: =N14 -> 0.13771186 | Q15: 600 | T15: =K15*N15*Q15 -> 82.627119
C16: c. | D16: Laborer | K16: 1 | N16: =N15 -> 0.13771186 | Q16: 400 | T16: =K16*N16*Q16 -> 55.084746
A22: LABOR | C22: Sub-Total for A | S22: P | T22: =ROUND(SUM(T14:V20),2) -> 247.88
B23: Name and Capacity | K23: No. of Units | N23: No. of Days | Q23: Daily Rate | T23: Amount
B25: B. | C25: Equipment
D26: Minor Tools (10% of Labor Cost) | T26: =0.1*T22 -> 24.788
A31: EQUIPMENT | C31: Sub-Total for B | S31: P | T31: =ROUND(SUM(T26:V30),2) -> 24.79
B32: C. | C32: Total (A+B) | T32: =T22+T31 -> 272.67
B33: D. | C33: Output per day | G33: = | H33: =E7 -> 94.4 | J33: =G7 -> M./DAY
B34: Name and Specifications | K34: Quantity | N34: Unit | Q34: Unit Cost | T34: Amount
B36: E. | C36: Materials
C37: a. | D37: Ridge/Hip Rolls/Flashing/Valley Roll/ Counter Flashing (0.4-0.6mm Thk | K37: =E8 -> 13 | N37: m | O37: =IF(L37>1,"bags","bag") -> bag | P37: =IF(M37>1,"bags","bag") -> bag | Q37: =440/2.4 -> 183.33333 | T37: =K37*Q37 -> 2383.3333
C38: b. | D38: 12" x 1" Plain GI Strap | K38: =3*E8 -> 39 | N38: pc. | O38: =IF(L38>1,"bags","bag") -> bag | P38: =IF(M38>1,"bags","bag") -> bag | Q38: 5 | T38: =K38*Q38 -> 195
C39: c. | D39: Blind Rivets | K39: =16*E8 -> 208 | N39: pc. | O39: =IF(L39>1,"bags","bag") -> bag | P39: =IF(M39>1,"bags","bag") -> bag | Q39: =400/300 -> 1.3333333 | T39: =K39*Q39 -> 277.33333
C40: d. | D40: Consumables (3% of Materials Costs) | T40: =0.03*SUM(T37:V39) -> 85.67
A48: MATERIAL | C48: Sub-Total for E | S48: P | T48: =ROUND(SUM(T37:V47),2) -> 2941.34
B49: F. | C49: Direct Cost (C+E) | T49: =T32+T48 -> 3214.01
B50: G. | C50: Overhead, Contingencies & Miscellaneous | N50: ='INPUT DATA'!C62 -> 0.05 | T50: =T49*N50 -> 160.7005
B51: H. | C51: Contractor's Profit (CP) | N51: ='INPUT DATA'!C63 -> 0.1 | T51: =T49*N51 -> 321.401
B52: I. | C52: Value Added Tax (VAT) | N52: ='INPUT DATA'!C64 -> 0 | T52: =(T49+T50+T51)*N52 -> 0
A53: CHECKING | B53: J. | C53: Total Cost | T53: =SUM(T49:V52) -> 3696.1115
A54: ADJUSTED CHECKING | B54: k. | C54: Total Unit Cost | T54: =T53/E8 -> 284.31627

Sheet 1014 Prepainted Met Sheets-Roof
B1: DETAILED UNIT PRICE ANALYSIS
B3: PROJECT NAME: | E3: ='INPUT DATA'!C4 -> PROPOSED ONE STOREY TWO BED ROOM RESIDENTIAL BUILDING
A5: ITEM NO. | B5: Item No./Description: | E5: 1014 | G5: PREPAINTED METAL SHEETS (CORRUGATE, SHORT SPAN/LONG SPAN)
A6: UNIT | B6: Unit of Measurement: | E6: SQ.M.
B7: Output per day: | E7: =2.076*8 -> 16.608 | G7: SQ.M./DAY
A8: QTY | B8: Quantity: | E8: ='INPUT DATA'!C28 -> 0 | G8: =E6 -> SQ.M.
B10: Designation | K10: No. Person | N10: No. of Days | Q10: Daily Rate | T10: Amount
X11: NO .OF TEAM | Y11: 1
B12: A. | C12: Labor
C13: Fabrication:
A14: DURATION | C14: a. | D14: Construction Foreman/Engineering Assistant | K14: 1 | N14: =E8/E7 -> 0 | Q14: 800 | T14: =K14*N14*Q14 -> 0
C15: b. | D15: Skilled Laborer | K15: 1 | N15: =N14 -> 0 | Q15: 600 | T15: =K15*N15*Q15 -> 0
C16: c. | D16: Laborer | K16: 2 | N16: =N15 -> 0 | Q16: 400 | T16: =K16*N16*Q16 -> 0
A22: LABOR | C22: Sub-Total for A | S22: P | T22: =ROUND(SUM(T14:V20),2) -> 0
B23: Name and Capacity | K23: No. of Units | N23: No. of Days | Q23: Daily Rate | T23: Amount
B25: B. | C25: Equipment
D26: Minor Tools (10% of Labor Cost) | H26: . | T26: =0.1*T22 -> 0
A31: EQUIPMENT | C31: Sub-Total for B | S31: P | T31: =ROUND(SUM(T26:V30),2) -> 0
B32: C. | C32: Total (A+B) | T32: =T22+T31 -> 0
B33: D. | C33: Output per day | G33: = | H33: =E7 -> 16.608 | J33: =G7 -> SQ.M./DAY
B34: Name and Specifications | K34: Quantity | N34: Unit | Q34: Unit Cost | T34: Amount
B36: E. | C36: Materials
C37: a. | D37: Prepainted Metal Roof Sheets (0.4-0.6mm Thick) | K37: =E8*1.05 -> 0 | N37: sq.m. | O37: =IF(L37>1,"bags","bag") -> bag | P37: =IF(M37>1,"bags","bag") -> bag | Q37: =320/1 -> 320 | T37: =K37*Q37 -> 0
C38: b. | D38: Teks Screw/ J-Bolt With Washers | K38: =10*E8 -> 0 | N38: pc. | O38: =IF(L38>1,"bags","bag") -> bag | P38: =IF(M38>1,"bags","bag") -> bag | Q38: 5 | T38: =K38*Q38 -> 0
C39: c. | D39: Consumables (3% of Materials Costs) | T39: =0.03*SUM(T37:V38) -> 0
A47: MATERIAL | C47: Sub-Total for E | S47: P | T47: =ROUND(SUM(T37:V46),2) -> 0
B48: F. | C48: Direct Cost (C+E) | T48: =T32+T47 -> 0
B49: G. | C49: Overhead, Contingencies & Miscellaneous | N49: ='INPUT DATA'!C62 -> 0.05 | T49: =T48*N49 -> 0
B50: H. | C50: Contractor's Profit (CP) | N50: ='INPUT DATA'!C63 -> 0.1 | T50: =T48*N50 -> 0
B51: I. | C51: Value Added Tax (VAT) | N51: ='INPUT DATA'!C64 -> 0 | T51: =(T48+T49+T50)*N51 -> 0
A52: CHECKING | B52: J. | C52: Total Cost | T52: =SUM(T48:V51) -> 0
A53: ADJUSTED CHECKING | B53: k. | C53: Total Unit Cost | T53: =T52/E8 -> #DIV/0!

Sheet 1014 Prepainted Met Sheets RIB
B1: DETAILED UNIT PRICE ANALYSIS
B3: PROJECT NAME: | E3: ='INPUT DATA'!C4 -> PROPOSED ONE STOREY TWO BED ROOM RESIDENTIAL BUILDING
A5: ITEM NO. | B5: Item No./Description: | E5: 1014 | G5: PREPAINTED METAL SHEETS (RIB TYPE 0.4-0.5MM THICK)
A6: UNIT | B6: Unit of Measurement: | E6: SQ.M.
B7: Output per day: | E7: =2.769*8 -> 22.152 | G7: SQ.M./DAY
A8: QTY | B8: Quantity: | E8: ='INPUT DATA'!C29 -> 140 | G8: =E6 -> SQ.M.
B10: Designation | K10: No. Person | N10: No. of Days | Q10: Daily Rate | T10: Amount
X11: NO .OF TEAM | Y11: 1
B12: A. | C12: Labor
C13: Fabrication:
A14: DURATION | C14: a. | D14: Construction Foreman/Engineering Assistant | K14: 1 | N14: =E8/E7 -> 6.3199711 | Q14: 800 | T14: =K14*N14*Q14 -> 5055.9769
C15: b. | D15: Skilled Laborer | K15: 1 | N15: =N14 -> 6.3199711 | Q15: 600 | T15: =K15*N15*Q15 -> 3791.9827
C16: c. | D16: Laborer | K16: 2 | N16: =N15 -> 6.3199711 | Q16: 400 | T16: =K16*N16*Q16 -> 5055.9769
A22: LABOR | C22: Sub-Total for A | S22: P | T22: =ROUND(SUM(T14:V20),2) -> 13903.94
B23: Name and Capacity | K23: No. of Units | N23: No. of Days | Q23: Daily Rate | T23: Amount
B25: B. | C25: Equipment
D26: Minor Tools (10% of Labor Cost) | H26: . | T26: =0.1*T22 -> 1390.394
A31: EQUIPMENT | C31: Sub-Total for B | S31: P | T31: =ROUND(SUM(T26:V30),2) -> 1390.39
B32: C. | C32: Total (A+B) | T32: =T22+T31 -> 15294.33
B33: D. | C33: Output per day | G33: = | H33: =E7 -> 22.152 | J33: =G7 -> SQ.M./DAY
B34: Name and Specifications | K34: Quantity | N34: Unit | Q34: Unit Cost | T34: Amount
B36: E. | C36: Materials
C37: a. | D37: Prepainted Metal Roof Sheets (Rib Type) | K37: =E8*1 -> 140 | N37: m | O37: =IF(L37>1,"bags","bag") -> bag | P37: =IF(M37>1,"bags","bag") -> bag | Q37: 320 | T37: =K37*Q37 -> 44800
C38: b. | D38: Teks Screw/ J-Bolt With Washers | K38: =10*E8 -> 1400 | N38: pc. | O38: =IF(L38>1,"bags","bag") -> bag | P38: =IF(M38>1,"bags","bag") -> bag | Q38: 5 | T38: =K38*Q38 -> 7000
C39: c. | D39: Consumables (3% of Materials Costs) | T39: =0.03*SUM(T37:V38) -> 1554
A47: MATERIAL | C47: Sub-Total for E | S47: P | T47: =ROUND(SUM(T37:V46),2) -> 53354
B48: F. | C48: Direct Cost (C+E) | T48: =T32+T47 -> 68648.33
B49: G. | C49: Overhead, Contingencies & Miscellaneous | N49: ='INPUT DATA'!C62 -> 0.05 | T49: =T48*N49 -> 3432.4165
B50: H. | C50: Contractor's Profit (CP) | N50: ='INPUT DATA'!C63 -> 0.1 | T50: =T48*N50 -> 6864.833
B51: I. | C51: Value Added Tax (VAT) | N51: ='INPUT DATA'!C64 -> 0 | T51: =(T48+T49+T50)*N51 -> 0
A52: CHECKING | B52: J. | C52: Total Cost | T52: =SUM(T48:V51) -> 78945.58
A53: ADJUSTED CHECKING | B53: k. | C53: Total Unit Cost | T53: =T52/E8 -> 563.897

Sheet 1016-Waterproof Cement
B1: DETAILED UNIT PRICE ANALYSIS
B3: PROJECT NAME: | E3: ='INPUT DATA'!C4 -> PROPOSED ONE STOREY TWO BED ROOM RESIDENTIAL BUILDING
A5: ITEM NO. | B5: Item No./Description: | E5: 1016(1)a | G5: WATERPROOFING CEMENT BASE
A6: UNIT | B6: Unit of Measurement: | E6: SQ.M. | AG6: =AE6/2 -> 0
B7: Output per day: | E7: =1.875*8*Y11 -> 15 | G7: SQ.M./DAY | AG7: =AE7/2 -> 0
A8: QTY | B8: Quantity: | E8: ='INPUT DATA'!C30 -> 66 | G8: =E6 -> SQ.M.
B10: Designation | K10: No. Person | N10: No. of Days | Q10: Daily Rate | T10: Amount
X11: NO .OF TEAM | Y11: 1
B12: A. | C12: Labor
A13: DURATION | C13: a. | D13: Construction Foreman/Engineering Assistant | K13: 1 | N13: =E8/E7 -> 4.4 | Q13: 800 | T13: =K13*N13*Q13 -> 3520
C14: b. | D14: Skilled Worker | K14: =1*Y11 -> 1 | N14: =N13 -> 4.4 | Q14: 600 | T14: =K14*N14*Q14 -> 2640
C15: c. | D15: Laborer | K15: =1*Y11 -> 1 | N15: =N14 -> 4.4 | Q15: 400 | T15: =K15*N15*Q15 -> 1760
A20: LABOR | C20: Sub-Total for A | S20: P | T20: =ROUND(SUM(T13:V18),2) -> 7920
B21: Name and Capacity | K21: No. of Units | N21: No. of Days | Q21: Daily Rate | T21: Amount
B23: B. | C23: Equipment
C24: a. | D24: Minor Tools (10% of labor Cost) | T24: =10%*T20 -> 792
A29: EQUIPMENT | C29: Sub-Total for B | S29: P | T29: =SUM(T23:V28) -> 792
B30: C. | C30: Total (A+B) | T30: =T20+T29 -> 8712
B31: D. | C31: Output per day | G31: = | AK31: 2Ø 45° bend | AL31: 2Øx2Ø tee | AM31: 4Øx4Ø coupling
B32: Name and Specifications | K32: Quantity | N32: Unit | Q32: Unit Cost | T32: Amount
B34: E. | C34: Materials | AL34: 2
C35: a. | D35: Cementitious Type Waterproofing Membrane | K35: =(E8*3)/56 -> 3.5357143 | N35: =IF(K35>1,"gals.","gal.") -> gals. | Q35: 950 | T35: =K35*Q35 -> 3358.9286 | AM35: 4
C36: b. | D36: Portland Cement | K36: =K35*7.5/50 -> 0.53035714 | N36: =IF(K36>1,"bags","bag") -> bag | Q36: 265 | T36: =K36*Q36 -> 140.54464
AK37: =SUM(AK32:AK35) -> 0 | AL37: =SUM(AL32:AL35) -> 2 | AM37: =SUM(AM32:AM35) -> 4
A46: MATERIAL | C46: Sub-Total for E | S46: P | T46: =ROUND(SUM(T35:V45),2) -> 3499.47
B47: F. | C47: Direct Cost (C+E) | T47: =T30+T46 -> 12211.47
B48: G. | C48: Overhead, Contingencies & Miscellaneous | N48: ='INPUT DATA'!C62 -> 0.05 | T48: =T47*N48 -> 610.5735
B49: H. | C49: Contractor's Profit (CP) | N49: ='INPUT DATA'!C63 -> 0.1 | T49: =T47*N49 -> 1221.147
B50: I. | C50: Value Added Tax (VAT) | N50: ='INPUT DATA'!C64 -> 0 | T50: =(T47+T48+T49)*N50 -> 0
A51: CHECKING | B51: J. | C51: Total Cost | T51: =SUM(T47:V50) -> 14043.191
A52: ADJUSTED CHECKING | B52: k. | C52: Total Unit Cost | T52: =T51/E8 -> 212.77561

Sheet 1018- Tiles
B1: DETAILED UNIT PRICE ANALYSIS
B3: PROJECT NAME: | E3: ='INPUT DATA'!C4 -> PROPOSED ONE STOREY TWO BED ROOM RESIDENTIAL BUILDING
A5: ITEM NO. | B5: Item No./Description: | E5: 1018 | G5: UNGLAZED TILES/ GRANITE TILES/ SYNTHETIC GRANITE TILES
A6: UNIT | B6: Unit of Measurement: | E6: SQ.M. | AG6: =AE6/2 -> 0
B7: Output per day: | E7: =1.95*8*Y11 -> 15.6 | G7: SQ.M./DAY | AG7: =AE7/2 -> 0
A8: QTY | B8: Quantity: | E8: ='INPUT DATA'!C31 -> 80 | G8: =E6 -> SQ.M.
B10: Designation | K10: No. Person | N10: No. of Days | Q10: Daily Rate | T10: Amount
X11: NO .OF TEAM | Y11: 1
B12: A. | C12: Labor
A13: DURATION | C13: a. | D13: Construction Foreman/Engineering Assistant | K13: 1 | N13: =E8/E7 -> 5.1282051 | Q13: 800 | T13: =K13*N13*Q13 -> 4102.5641
C14: b. | D14: Skilled Worker | K14: 5 | N14: =N13 -> 5.1282051 | Q14: 600 | T14: =K14*N14*Q14 -> 15384.615
C15: c. | D15: Laborer | K15: 5 | N15: =N14 -> 5.1282051 | Q15: 400 | T15: =K15*N15*Q15 -> 10256.41
A20: LABOR | C20: Sub-Total for A | S20: P | T20: =ROUND(SUM(T13:V18),2) -> 29743.59
B21: Name and Capacity | K21: No. of Units | N21: No. of Days | Q21: Daily Rate | T21: Amount
B23: B. | C23: Equipment
C24: a. | D24: Minor Tools (10% of labor Cost) | T24: =10%*T20 -> 2974.359
A29: EQUIPMENT | C29: Sub-Total for B | S29: P | T29: =SUM(T23:V28) -> 2974.359
B30: C. | C30: Total (A+B) | T30: =T20+T29 -> 32717.949
B31: D. | C31: Output per day | G31: = | AK31: 2Ø 45° bend | AL31: 2Øx2Ø tee | AM31: 4Øx4Ø coupling
B32: Name and Specifications | K32: Quantity | N32: Unit | Q32: Unit Cost | T32: Amount
B34: E. | C34: Materials | AL34: 2
C35: a. | D35: Unglazed Tiles/Granite Tiles | K35: =E8 -> 80 | N35: sq.m. | Q35: =270/(0.6*0.6) -> 750 | T35: =K35*Q35 -> 60000 | AM35: 4
C36: b. | D36: Portland Cement | K36: =0.325*E8 -> 26 | N36: =IF(K36>1,"bags","bag") -> bags | Q36: 265 | T36: =K36*Q36 -> 6890
C37: c. | D37: Sand | K37: =0.026*E8 -> 2.08 | N37: cu.m. | Q37: 1400 | T37: =K37*Q37 -> 2912 | AK37: =SUM(AK32:AK35) -> 0 | AL37: =SUM(AL32:AL35) -> 2 | AM37: =SUM(AM32:AM35) -> 4
C38: d. | D38: Tile Grout | K38: =0.125*E8 -> 10 | N38: bag | Q38: 70 | T38: =K38*Q38 -> 700
A46: MATERIAL | C46: Sub-Total for E | S46: P | T46: =ROUND(SUM(T35:V45),2) -> 70502
B47: F. | C47: Direct Cost (C+E) | T47: =T30+T46 -> 103219.95
B48: G. | C48: Overhead, Contingencies & Miscellaneous | N48: ='INPUT DATA'!C62 -> 0.05 | T48: =T47*N48 -> 5160.9974
B49: H. | C49: Contractor's Profit (CP) | N49: ='INPUT DATA'!C63 -> 0.1 | T49: =T47*N49 -> 10321.995
B50: I. | C50: Value Added Tax (VAT) | N50: ='INPUT DATA'!C64 -> 0 | T50: =(T47+T48+T49)*N50 -> 0
A51: CHECKING | B51: J. | C51: Total Cost | T51: =SUM(T47:V50) -> 118702.94
A52: ADJUSTED CHECKING | B52: k. | C52: Total Unit Cost | T52: =T51/E8 -> 1483.7868

Sheet 1003(1) Ceiling
B1: DETAILED UNIT PRICE ANALYSIS
B3: PROJECT NAME: | E3: ='INPUT DATA'!C4 -> PROPOSED ONE STOREY TWO BED ROOM RESIDENTIAL BUILDING
A5: ITEM NO. | B5: Item No./Description: | E5: 1003(1) | G5: FIBER CEMENT BOARD/MARINE PLYWOOD/ORDINARY PLYWOOD ON METAL FRAME CEILING
A6: UNIT | B6: Unit of Measurement: | E6: SQ.M. | AG6: =AE6/2 -> 0
B7: Output per day: | E7: =1.243*8*Y11 -> 9.944 | G7: SQ.M./DAY | AG7: =AE7/2 -> 0
A8: QTY | B8: Quantity: | E8: ='INPUT DATA'!C32 -> 130 | G8: =E6 -> SQ.M.
B10: Designation | K10: No. Person | N10: No. of Days | Q10: Daily Rate | T10: Amount
X11: NO .OF TEAM | Y11: 1
B12: A. | C12: Labor
A13: DURATION | C13: a. | D13: Construction Foreman/Engineering Assistant | K13: 1 | N13: =E8/E7 -> 13.07321 | Q13: 800 | T13: =K13*N13*Q13 -> 10458.568
C14: b. | D14: Skilled Worker | K14: 1 | N14: =N13 -> 13.07321 | Q14: 600 | T14: =K14*N14*Q14 -> 7843.926
C15: c. | D15: Laborer | K15: 2 | N15: =N14 -> 13.07321 | Q15: 400 | T15: =K15*N15*Q15 -> 10458.568
A20: LABOR | C20: Sub-Total for A | S20: P | T20: =ROUND(SUM(T13:V18),2) -> 28761.06
B21: Name and Capacity | K21: No. of Units | N21: No. of Days | Q21: Daily Rate | T21: Amount
B23: B. | C23: Equipment
C24: a. | D24: Minor Tools (10% of labor Cost) | T24: =10%*T20 -> 2876.106
A29: EQUIPMENT | C29: Sub-Total for B | S29: P | T29: =SUM(T23:V28) -> 2876.106
B30: C. | C30: Total (A+B) | T30: =T20+T29 -> 31637.166
B31: D. | C31: Output per day | G31: = | AK31: 2Ø 45° bend | AL31: 2Øx2Ø tee | AM31: 4Øx4Ø coupling
B32: Name and Specifications | K32: Quantity | N32: Unit | Q32: Unit Cost | T32: Amount
B34: E. | C34: Materials | AL34: 2
C35: a. | D35: 4.5mm Fiber Cement Board | K35: =0.365*E8 -> 47.45 | N35: pc. | Q35: 420 | T35: =K35*Q35 -> 19929 | AM35: 4
C36: b. | D36: 2" Metal Furring x 3 meter length | K36: =1.131*E8 -> 147.03 | N36: =IF(K36>1,"bags","bag") -> bags | Q36: 150 | T36: =K36*Q36 -> 22054.5
C37: c. | D37: Carrying Channels 2" | K37: =0.357*E8 -> 46.41 | N37: cu.m. | Q37: 80 | T37: =K37*Q37 -> 3712.8 | AK37: =SUM(AK32:AK35) -> 0 | AL37: =SUM(AL32:AL35) -> 2 | AM37: =SUM(AM32:AM35) -> 4
C38: d. | D38: Hanger Bars/Rod - 12mm | K38: =1*E8 -> 130 | N38: pc. | Q38: =280/6 -> 46.666667 | T38: =K38*Q38 -> 6066.6667
C39: e. | D39: Channel Clip | K39: =6*E8 -> 780 | N39: pc. | Q39: 90 | T39: =K39*Q39 -> 70200
C40: f. | D40: Wall Angle | K40: =0.238*E8 -> 30.94 | N40: pc. | Q40: 90 | T40: =K40*Q40 -> 2784.6
C41: g. | D41: 1/8" Blind Rivet | K41: =E8/60 -> 2.1666667 | N41: boxes | Q41: 480 | T41: =K41*Q41 -> 1040
A46: MATERIAL | C46: Sub-Total for E | S46: P | T46: =ROUND(SUM(T35:V45),2) -> 125787.57
B47: F. | C47: Direct Cost (C+E) | T47: =T30+T46 -> 157424.74
B48: G. | C48: Overhead, Contingencies & Miscellaneous | N48: ='INPUT DATA'!C62 -> 0.05 | T48: =T47*N48 -> 7871.2368
B49: H. | C49: Contractor's Profit (CP) | N49: ='INPUT DATA'!C63 -> 0.1 | T49: =T47*N49 -> 15742.474
B50: I. | C50: Value Added Tax (VAT) | N50: ='INPUT DATA'!C64 -> 0 | T50: =(T47+T48+T49)*N50 -> 0
A51: CHECKING | B51: J. | C51: Total Cost | T51: =SUM(T47:V50) -> 181038.45
A52: ADJUSTED CHECKING | B52: k. | C52: Total Unit Cost | T52: =T51/E8 -> 1392.6034

Sheet 1010(2) Hollow Flush Door
B1: DETAILED UNIT PRICE ANALYSIS
B3: PROJECT NAME: | E3: ='INPUT DATA'!C4 -> PROPOSED ONE STOREY TWO BED ROOM RESIDENTIAL BUILDING
A5: ITEM NO. | B5: Item No./Description: | E5: 1010(2)a | G5: HOLLOW CORE FLUSH DOOR
A6: UNIT | B6: Unit of Measurement: | E6: =G8 -> SQ.M.
B7: Output per day: | E7: =0.32*8 -> 2.56 | G7: SQ.M./DAY
A8: QTY | B8: Quantity: | E8: ='INPUT DATA'!C33 -> 5.04 | G8: SQ.M.
B10: Designation | K10: No. Person | N10: No. of Days | Q10: Daily Rate | T10: Amount
B12: A. | C12: Labor
A13: DURATION | C13: a. | D13: Construction Foreman/Engineering Assistant | K13: 1 | N13: =E8/E7 -> 1.96875 | Q13: 800 | T13: =K13*N13*Q13 -> 1575
C14: b. | D14: Carpenter | K14: 1 | N14: =N13 -> 1.96875 | Q14: 600 | T14: =K14*N14*Q14 -> 1181.25 | AC14: =10/3.281 -> 3.0478513
C15: c. | D15: Laborer | K15: 1 | N15: =N14 -> 1.96875 | Q15: 400 | T15: =K15*N15*Q15 -> 787.5
A20: LABOR | C20: Sub-Total for A | S20: P | T20: =ROUND(SUM(T13:V18),2) -> 3543.75
B21: Name and Capacity | K21: No. of Units | N21: No. of Days | Q21: Daily Rate | T21: Amount
B23: B. | C23: Equipment
C24: a. | D24: Minor Tools (10% of labor Cost) | T24: =10%*T20 -> 354.375
A29: EQUIPMENT | C29: Sub-Total for B | S29: P | T29: =ROUND(SUM(T24:V28),2) -> 354.38
B30: C. | C30: Total (A+B) | T30: =T20+T29 -> 3898.13
B31: D. | C31: Output per day | G31: = | H31: =E7 -> 2.56 | J31: =G7 -> SQ.M./DAY
B32: Name and Specifications | K32: Quantity | N32: Unit | Q32: Unit Cost | T32: Amount
B34: E. | C34: Materials
C35: a. | D35: Hollow Core Flush Door | K35: =E8 -> 5.04 | N35: sq.m. | O35: =IF(L35>1,"bags","bag") -> bag | P35: =IF(M35>1,"bags","bag") -> bag | Q35: =3500/(0.8*2.1) -> 2083.3333 | T35: =K35*Q35 -> 10500
C36: b. | D36: Consumables (5% of Material Cost) | T36: =10%*SUM(T34:V35) -> 1050
A46: MATERIAL | C46: Sub-Total for E | S46: P | T46: =ROUND(SUM(T35:V45),2) -> 11550
B47: F. | C47: Direct Cost (C+E) | T47: =T30+T46 -> 15448.13
B48: G. | C48: Overhead, Contingencies & Miscellaneous | N48: ='INPUT DATA'!C62 -> 0.05 | T48: =T47*N48 -> 772.4065
B49: H. | C49: Contractor's Profit (CP) | N49: ='INPUT DATA'!C63 -> 0.1 | T49: =T47*N49 -> 1544.813
B50: I. | C50: Value Added Tax (VAT) | N50: ='INPUT DATA'!C64 -> 0 | T50: =(T47+T48+T49)*N50 -> 0
A51: CHECKING | B51: J. | C51: Total Cost | T51: =SUM(T47:V50) -> 17765.35
A52: ADJUSTED CHECKING | B52: k. | C52: Total Unit Cost | T52: =T51/E8 -> 3524.8709

Sheet 1010(2) Panel Door
B1: DETAILED UNIT PRICE ANALYSIS
B3: PROJECT NAME: | E3: ='INPUT DATA'!C4 -> PROPOSED ONE STOREY TWO BED ROOM RESIDENTIAL BUILDING
A5: ITEM NO. | B5: Item No./Description: | E5: 1010(2) | G5: WOODEN PANEL DOOR WITH HEAVY DUTY DOOR KNOB
A6: UNIT | B6: Unit of Measurement: | E6: =G8 -> SQ.M.
B7: Output per day: | E7: =0.36*8 -> 2.88 | G7: SQ.M./DAY
A8: QTY | B8: Quantity: | E8: ='INPUT DATA'!C34 -> 2.1 | G8: SQ.M.
B10: Designation | K10: No. Person | N10: No. of Days | Q10: Daily Rate | T10: Amount
B12: A. | C12: Labor
A13: DURATION | C13: a. | D13: Construction Foreman/Engineering Assistant | K13: 1 | N13: =E8/E7 -> 0.72916667 | Q13: 800 | T13: =K13*N13*Q13 -> 583.33333
C14: b. | D14: Skilled Laborer | K14: 1 | N14: =N13 -> 0.72916667 | Q14: 600 | T14: =K14*N14*Q14 -> 437.5 | AC14: =10/3.281 -> 3.0478513
C15: c. | D15: Laborer | K15: 2 | N15: =N14 -> 0.72916667 | Q15: 400 | T15: =K15*N15*Q15 -> 583.33333
A20: LABOR | C20: Sub-Total for A | S20: P | T20: =ROUND(SUM(T13:V18),2) -> 1604.17
B21: Name and Capacity | K21: No. of Units | N21: No. of Days | Q21: Daily Rate | T21: Amount
B23: B. | C23: Equipment
C24: a. | D24: Minor Tools (10% of labor Cost) | T24: =10%*T20 -> 160.417
A29: EQUIPMENT | C29: Sub-Total for B | S29: P | T29: =ROUND(SUM(T24:V28),2) -> 160.42
B30: C. | C30: Total (A+B) | T30: =T20+T29 -> 1764.59
B31: D. | C31: Output per day | G31: = | H31: =E7 -> 2.88 | J31: =G7 -> SQ.M./DAY
B32: Name and Specifications | K32: Quantity | N32: Unit | Q32: Unit Cost | T32: Amount
B34: E. | C34: Materials
C35: a. | D35: Wooden PANEL Type Door with Jambs and Header | K35: =E8 -> 2.1 | N35: SQ.M. | O35: =IF(L35>1,"bags","bag") -> bag | P35: =IF(M35>1,"bags","bag") -> bag | Q35: =6000/(1*2.1) -> 2857.1429 | T35: =K35*Q35 -> 6000
C36: b. | D36: Consumables (5% of Material Cost) | T36: =10%*SUM(T32:V35) -> 600
A46: MATERIAL | C46: Sub-Total for E | S46: P | T46: =ROUND(SUM(T35:V45),2) -> 6600
B47: F. | C47: Direct Cost (C+E) | T47: =T30+T46 -> 8364.59
B48: G. | C48: Overhead, Contingencies & Miscellaneous | N48: ='INPUT DATA'!C62 -> 0.05 | T48: =T47*N48 -> 418.2295
B49: H. | C49: Contractor's Profit (CP) | N49: ='INPUT DATA'!C63 -> 0.1 | T49: =T47*N49 -> 836.459
B50: I. | C50: Value Added Tax (VAT) | N50: ='INPUT DATA'!C64 -> 0 | T50: =(T47+T48+T49)*N50 -> 0
A51: CHECKING | B51: J. | C51: Total Cost | T51: =SUM(T47:V50) -> 9619.2785
A52: ADJUSTED CHECKING | B52: k. | C52: Total Unit Cost | T52: =T51/E8 -> 4580.6088

Sheet 1043(1) PVC Door
B1: DETAILED UNIT PRICE ANALYSIS
B3: PROJECT NAME: | E3: ='INPUT DATA'!C4 -> PROPOSED ONE STOREY TWO BED ROOM RESIDENTIAL BUILDING
A5: ITEM NO. | B5: Item No./Description: | E5: 1043(1) | G5: PVC DOORS AND FRAMES W/ HEAVY DUTY DOOR KNOB
A6: UNIT | B6: Unit of Measurement: | E6: =G8 -> SQ.M.
B7: Output per day: | E7: =0.315*8 -> 2.52 | G7: SQ.M./DAY
A8: QTY | B8: Quantity: | E8: ='INPUT DATA'!C35 -> 1.26 | G8: SQ.M.
B10: Designation | K10: No. Person | N10: No. of Days | Q10: Daily Rate | T10: Amount
B12: A. | C12: Labor
A13: DURATION | C13: a. | D13: Construction Foreman/Engineering Assistant | K13: 1 | N13: =E8/E7 -> 0.5 | Q13: 800 | T13: =K13*N13*Q13 -> 400
C14: b. | D14: Carpenter | K14: 1 | N14: =N13 -> 0.5 | Q14: 600 | T14: =K14*N14*Q14 -> 300 | AC14: =10/3.281 -> 3.0478513
C15: c. | D15: Laborer | K15: 1 | N15: =N14 -> 0.5 | Q15: 400 | T15: =K15*N15*Q15 -> 200
A20: LABOR | C20: Sub-Total for A | S20: P | T20: =ROUND(SUM(T13:V18),2) -> 900
B21: Name and Capacity | K21: No. of Units | N21: No. of Days | Q21: Daily Rate | T21: Amount
B23: B. | C23: Equipment
C24: a. | D24: Minor Tools (10% of labor Cost) | T24: =10%*T20 -> 90
A29: EQUIPMENT | C29: Sub-Total for B | S29: P | T29: =ROUND(SUM(T24:V28),2) -> 90
B30: C. | C30: Total (A+B) | T30: =T20+T29 -> 990
B31: D. | C31: Output per day | G31: = | H31: =E7 -> 2.52 | J31: =G7 -> SQ.M./DAY
B32: Name and Specifications | K32: Quantity | N32: Unit | Q32: Unit Cost | T32: Amount
B34: E. | C34: Materials
C35: a. | D35: Wooden PANEL Type Door with Jambs and Header | K35: =E8 -> 1.26 | N35: SQ.M. | O35: =IF(L35>1,"bags","bag") -> bag | P35: =IF(M35>1,"bags","bag") -> bag | Q35: =2500/(2.1*0.6) -> 1984.127 | T35: =K35*Q35 -> 2500
C36: b. | D36: Consumables (5% of Materials Cost) | T36: =0.05*SUM(T35:V35) -> 125
A45: MATERIAL | C45: Sub-Total for E | S45: P | T45: =ROUND(SUM(T35:V44),2) -> 2625
B46: F. | C46: Direct Cost (C+E) | T46: =T30+T45 -> 3615
B47: G. | C47: Overhead, Contingencies & Miscellaneous | N47: ='INPUT DATA'!C62 -> 0.05 | T47: =T46*N47 -> 180.75
B48: H. | C48: Contractor's Profit (CP) | N48: ='INPUT DATA'!C63 -> 0.1 | T48: =T46*N48 -> 361.5
B49: I. | C49: Value Added Tax (VAT) | N49: ='INPUT DATA'!C64 -> 0 | T49: =(T46+T47+T48)*N49 -> 0
A50: CHECKING | B50: J. | C50: Total Cost | T50: =SUM(T46:V49) -> 4157.25
A51: ADJUSTED CHECKING | B51: k. | C51: Total Unit Cost | T51: =T50/E8 -> 3299.4048

Sheet 1032-Paint Concrete
B1: DETAILED UNIT PRICE ANALYSIS
B3: PROJECT NAME: | E3: ='INPUT DATA'!C4 -> PROPOSED ONE STOREY TWO BED ROOM RESIDENTIAL BUILDING
A5: ITEM NO. | B5: Item No./Description: | E5: 1032(1)a | G5: PAINTING WORKS (MASONRY PAINTING)
A6: UNIT | B6: Unit of Measurement: | E6: SQ.M.
B7: Output per day: | E7: =2.1*8*Y11 -> 16.8 | G7: SQ.M./DAY
A8: QTY | B8: Quantity: | E8: ='INPUT DATA'!C36 -> 540 | G8: =E6 -> SQ.M.
B10: Designation | K10: No. Person | N10: No. of Days | Q10: Daily Rate | T10: Amount
X11: NO .OF TEAM | Y11: 1
B12: A. | C12: Labor
A13: DURATION | C13: a. | D13: Construction Foreman/Engineering Assistant | K13: 1 | N13: =E8/E7 -> 32.142857 | Q13: 800 | T13: =K13*N13*Q13 -> 25714.286
C14: b. | D14: Painter | K14: =2*Y11 -> 2 | N14: =N13 -> 32.142857 | Q14: 600 | T14: =K14*N14*Q14 -> 38571.429
C15: c. | D15: Laborer | K15: =1*Y11 -> 1 | N15: =N14 -> 32.142857 | Q15: 400 | T15: =K15*N15*Q15 -> 12857.143
A20: LABOR | C20: Sub-Total for A | S20: P | T20: =ROUND(SUM(T13:V18),2) -> 77142.86
B21: Name and Capacity | K21: No. of Units | N21: No. of Days | Q21: Daily Rate | T21: Amount
B23: B. | C23: Equipment
C24: N/A
A29: EQUIPMENT | C29: Sub-Total for B | S29: P
B30: C. | C30: Total (A+B) | T30: =T20+T29 -> 77142.86
B31: D. | C31: Output per day | G31: = | AK31: 2Ø 45° bend | AL31: 2Øx2Ø tee | AM31: 4Øx4Ø coupling
B32: Name and Specifications | K32: Quantity | N32: Unit | Q32: Unit Cost | T32: Amount
B34: E. | C34: Materials | AL34: 2
C35: a. | D35: Concrete Penetrating Sealer | K35: =(E8/8)/4 -> 16.875 | N35: =IF(K35>1,"gals.","gal.") -> gals. | O35: =IF(L35>1,"gals.","gal.") -> gal. | P35: =IF(M35>1,"gals.","gal.") -> gal. | Q35: 590 | T35: =K35*Q35 -> 9956.25 | AM35: 4
C36: b. | D36: Solvent Base Acrylic Primer | K36: =E8/22 -> 24.545455 | N36: =IF(K36>1,"gals.","gal.") -> gals. | O36: =IF(L36>1,"gals.","gal.") -> gal. | P36: =IF(M36>1,"gals.","gal.") -> gal. | Q36: 950 | T36: =K36*Q36 -> 23318.182
C37: c. | D37: Patching Compound | K37: =(E8)*0.1 -> 54 | N37: =IF(K37>1,"kgs.","kg.") -> kgs. | O37: =IF(L37>1,"kgs.","kg.") -> kg. | P37: =IF(M37>1,"kgs.","kg.") -> kg. | Q37: 70 | T37: =K37*Q37 -> 3780 | AK37: =SUM(AK32:AK35) -> 0 | AL37: =SUM(AL32:AL35) -> 2 | AM37: =SUM(AM32:AM35) -> 4
C38: d. | D38: Semi Gloss Solvent Base Paint (Top Coat) | K38: =0.05*E8 -> 27 | N38: =IF(K38>1,"gals.","gal.") -> gals. | O38: =IF(L38>1,"gals.","gal.") -> gal. | P38: =IF(M38>1,"gals.","gal.") -> gal. | Q38: 910 | T38: =K38*Q38 -> 24570
C39: e. | D39: Baby Roller | K39: =0.03*E8 -> 16.2 | N39: =IF(AND(K39<1),"pc.",IF(AND(K39>1),"pcs.",IF(AND(K39=1),"pc."))) -> pcs. | Q39: 76 | T39: =K39*Q39 -> 1231.2
C40: f. | D40: 2" Paint Brush | K40: =K39 -> 16.2 | N40: =IF(AND(K40<1),"pc.",IF(AND(K40>1),"pcs.",IF(AND(K40=1),"pc."))) -> pcs. | Q40: 65 | T40: =K40*Q40 -> 1053
C41: g. | D41: 4" Paint Brush | K41: =K40 -> 16.2 | N41: =IF(AND(K41<1),"pc.",IF(AND(K41>1),"pcs.",IF(AND(K41=1),"pc."))) -> pcs. | Q41: 80 | T41: =K41*Q41 -> 1296
C42: h. | D42: Body Filler | K42: =E8/60 -> 9 | N42: gal. | Q42: 650 | T42: =K42*Q42 -> 5850
C43: i | D43: Other Consumables | T43: =0.1*SUM(T35:V42) -> 7105.4632
A46: MATERIAL | C46: Sub-Total for E | S46: P | T46: =ROUND(SUM(T35:V45),2) -> 78160.1
B47: F. | C47: Direct Cost (C+E) | T47: =T30+T46 -> 155302.96
B48: G. | C48: Overhead, Contingencies & Miscellaneous | N48: ='INPUT DATA'!C62 -> 0.05 | T48: =T47*N48 -> 7765.148
B49: H. | C49: Contractor's Profit (CP) | N49: ='INPUT DATA'!C63 -> 0.1 | T49: =T47*N49 -> 15530.296
B50: I. | C50: Value Added Tax (VAT) | N50: ='INPUT DATA'!C64 -> 0 | T50: =(T47+T48+T49)*N50 -> 0
A51: CHECKING | B51: J. | C51: Total Cost | T51: =SUM(T47:V50) -> 178598.4
A52: ADJUSTED CHECKING | B52: k. | C52: Total Unit Cost | T52: =T51/E8 -> 330.73779

Sheet 1032-Paint Metal
B1: DETAILED UNIT PRICE ANALYSIS
B3: PROJECT NAME: | E3: ='INPUT DATA'!C4 -> PROPOSED ONE STOREY TWO BED ROOM RESIDENTIAL BUILDING
B5: Item No./Description: | E5: 1032(1)c | G5: PAINTING WORKS (METAL PAINTING)
B6: Unit of Measurement: | E6: SQ.M.
B7: Output per day: | E7: =2*8*Y11 -> 16 | G7: SQ.M./DAY
B8: Quantity: | E8: ='INPUT DATA'!C37 -> 45 | G8: =E6 -> SQ.M.
B10: Designation | K10: No. Person | N10: No. of Days | Q10: Daily Rate | T10: Amount
X11: NO .OF TEAM | Y11: 1
B12: A. | C12: Labor
C13: a. | D13: Construction Foreman/Engineering Assistant | K13: 1 | N13: =E8/E7 -> 2.8125 | Q13: 800 | T13: =K13*N13*Q13 -> 2250
C14: b. | D14: Painter | K14: =2*Y11 -> 2 | N14: =N13 -> 2.8125 | Q14: 600 | T14: =K14*N14*Q14 -> 3375
C15: c. | D15: Laborer | K15: =1*Y11 -> 1 | N15: =N14 -> 2.8125 | Q15: 400 | T15: =K15*N15*Q15 -> 1125
C20: Sub-Total for A | S20: P | T20: =ROUND(SUM(T13:V18),2) -> 6750
B21: Name and Capacity | K21: No. of Units | N21: No. of Days | Q21: Daily Rate | T21: Amount
B23: B. | C23: Equipment
C24: N/A
C29: Sub-Total for B | S29: P
B30: C. | C30: Total (A+B) | T30: =T20+T29 -> 6750
B31: D. | C31: Output per day | G31: = | AK31: 2Ø 45° bend | AL31: 2Øx2Ø tee | AM31: 4Øx4Ø coupling
B32: Name and Specifications | K32: Quantity | N32: Unit | Q32: Unit Cost | T32: Amount
B34: E. | C34: Materials | AL34: 2
C35: a. | D35: Red Oxide Metal Primer | K35: =0.04*E8 -> 1.8 | N35: =IF(K35>1,"gals.","gal.") -> gals. | Q35: 550 | T35: =K35*Q35 -> 990 | AM35: 4
C36: b. | D36: Quick Dry Enamel Paint | K36: =0.1*E8 -> 4.5 | N36: =IF(K36>1,"gals.","gal.") -> gals. | Q36: 670 | T36: =K36*Q36 -> 3015
C37: c. | D37: Paint Thinner | K37: =E8*0.75 -> 33.75 | N37: gal. | Q37: 469 | T37: =K37*Q37 -> 15828.75 | AK37: =SUM(AK32:AK35) -> 0 | AL37: =SUM(AL32:AL35) -> 2 | AM37: =SUM(AM32:AM35) -> 4
C38: d. | D38: Tinting Color | K38: =E8*0.1 -> 4.5 | N38: =IF(K38>1,"pints.","pint.") -> pints. | Q38: 120 | T38: =K38*Q38 -> 540
C39: e. | D39: Consumables (5% of Material Cost) | T39: =10%*SUM(T35:V38) -> 2037.375
C46: Sub-Total for E | S46: P | T46: =ROUND(SUM(T35:V45),2) -> 22411.13
B47: F. | C47: Direct Cost (C+E) | T47: =T30+T46 -> 29161.13
B48: G. | C48: Overhead, Contingencies & Miscellaneous | N48: ='INPUT DATA'!C62 -> 0.05 | T48: =T47*N48 -> 1458.0565
B49: H. | C49: Contractor's Profit (CP) | N49: ='INPUT DATA'!C63 -> 0.1 | T49: =T47*N49 -> 2916.113
B50: I. | C50: Value Added Tax (VAT) | N50: ='INPUT DATA'!C64 -> 0 | T50: =(T47+T48+T49)*N50 -> 0
B51: J. | C51: Total Cost | T51: =SUM(T47:V50) -> 33535.3
B52: k. | C52: Total Unit Cost | T52: =T51/E8 -> 745.22888

Sheet Sliding Glass
B1: DETAILED UNIT PRICE ANALYSIS
B3: PROJECT NAME: | E3: ='INPUT DATA'!C4 -> PROPOSED ONE STOREY TWO BED ROOM RESIDENTIAL BUILDING
A5: ITEM NO. | B5: Item No./Description: | E5: SPL - ? | G5: SUPPLY AND INSTALLATION OF ANALOK TYPE SLIDING WINDOW
A6: UNIT | B6: Unit of Measurement: | E6: SQ.M.
B7: Output per day: | E7: 12 | G7: =CONCATENATE(E6,"/DAY") -> SQ.M./DAY
A8: QTY | B8: Quantity: | E8: ='INPUT DATA'!C38 -> 11.34 | G8: =E6 -> SQ.M.
B10: Designation | K10: No. Person | N10: No. of Days | Q10: Daily Rate | T10: Amount
X11: NO .OF TEAM | Y11: 1
B12: A. | C12: Labor
A13: DURATION | D13: Included in the Package
A20: LABOR | C20: Sub-Total for A | S20: P | T20: =ROUND(SUM(T13:V18),2) -> 0
B21: Name and Capacity | K21: No. of Units | N21: No. of Days | Q21: Daily Rate | T21: Amount
B23: B. | C23: Equipment
D24: Included in the Package
A29: EQUIPMENT | C29: Sub-Total for B | S29: P | T29: =ROUND(SUM(T24:V28),2) -> 0
B30: C. | C30: Total (A+B) | T30: =T20+T29 -> 0
B31: D. | C31: Output per day | G31: = | H31: =E7 -> 12 | J31: =G7 -> SQ.M./DAY
B32: Name and Specifications | K32: Quantity | N32: Unit | Q32: Unit Cost | T32: Amount
B34: E. | C34: Materials
C35: a. | D35: Aluminum Framing Analok Type -6mm. Thk. Glass | K35: =E8 -> 11.34 | N35: sq.m. | O35: =IF(L35>1,"bags","bag") -> bag | P35: =IF(M35>1,"bags","bag") -> bag | Q35: 4000 | T35: =K35*Q35 -> 45360
D37: Note: With installation
A45: MATERIAL | C45: Sub-Total for E | S45: P | T45: =ROUND(SUM(T35:V44),2) -> 45360
B46: F. | C46: Direct Cost (C+E) | T46: =T30+T45 -> 45360
B47: G. | C47: Overhead, Contingencies & Miscellaneous | N47: ='INPUT DATA'!C62 -> 0.05 | T47: =T46*N47 -> 2268
B48: H. | C48: Contractor's Profit (CP) | N48: ='INPUT DATA'!C63 -> 0.1 | T48: =T46*N48 -> 4536
B49: I. | C49: Value Added Tax (VAT) | N49: ='INPUT DATA'!C64 -> 0 | T49: =(T46+T47+T48)*N49 -> 0
A50: CHECKING | B50: J. | C50: Total Cost | T50: =SUM(T46:V49) -> 52164
A51: ADJUSTED CHECKING | B51: k. | C51: Total Unit Cost | T51: =T50/E8 -> 4600

Sheet Other item-Civil Works
B1: DETAILED UNIT PRICE ANALYSIS
B3: PROJECT NAME: | E3: ='INPUT DATA'!C4 -> PROPOSED ONE STOREY TWO BED ROOM RESIDENTIAL BUILDING
A5: ITEM NO. | B5: Item No./Description: | E5: SPL - ? | G5: (INPUT ITEM DESCRIPTION)
A6: UNIT | B6: Unit of Measurement: | E6: L.S.
B7: Output per day:
A8: QTY | B8: Quantity: | E8: ='INPUT DATA'!C39 -> 1 | G8: =E6 -> L.S.
B10: Designation | K10: No. Person | N10: No. of Days | Q10: Daily Rate | T10: Amount
X11: NO .OF TEAM | Y11: 1
B12: A. | C12: Labor
A13: DURATION | C13: a.
C14: b.
C15: c.
A20: LABOR | C20: Sub-Total for A | S20: P | T20: =ROUND(SUM(T13:V18),2) -> 0
B21: Name and Capacity | K21: No. of Units | N21: No. of Days | Q21: Daily Rate | T21: Amount
B23: B. | C23: Equipment
C24: a.
C25: b.
C26: c.
A29: EQUIPMENT | C29: Sub-Total for B | S29: P | T29: =ROUND(SUM(T24:V28),2) -> 0
B30: C. | C30: Total (A+B) | T30: =T20+T29 -> 0
B31: D. | C31: Output per day | G31: = | H31: =E7 -> 0 | J31: =G7 -> 0
B32: Name and Specifications | K32: Quantity | N32: Unit | Q32: Unit Cost | T32: Amount
B34: E. | C34: Materials
C35: a.
C36: b.
C37: c.
A45: MATERIAL | C45: Sub-Total for E | S45: P | T45: =ROUND(SUM(T35:V44),2) -> 0
B46: F. | C46: Direct Cost (C+E) | T46: =T30+T45 -> 0
B47: G. | C47: Overhead, Contingencies & Miscellaneous | N47: ='INPUT DATA'!C62 -> 0.05 | T47: =T46*N47 -> 0
B48: H. | C48: Contractor's Profit (CP) | N48: ='INPUT DATA'!C63 -> 0.1 | T48: =T46*N48 -> 0
B49: I. | C49: Value Added Tax (VAT) | N49: ='INPUT DATA'!C64 -> 0 | T49: =(T46+T47+T48)*N49 -> 0
A50: CHECKING | B50: J. | C50: Total Cost | T50: =SUM(T46:V49) -> 0
A51: ADJUSTED CHECKING | B51: k. | C51: Total Unit Cost | T51: =T50/E8 -> 0

Sheet 1001(1)a 2" -4" San PVC Pipe
B1: DETAILED UNIT PRICE ANALYSIS
B3: PROJECT NAME: | E3: ='INPUT DATA'!C4 -> PROPOSED ONE STOREY TWO BED ROOM RESIDENTIAL BUILDING
A5: ITEM NO. | B5: Item No./Description: | E5: 1001(1)a | G5: 50MM DIA - 100MM DIA SANITARY PVC PIPE, SERIES 600/1000
A6: UNIT | B6: Unit of Measurement: | E6: M.
B7: Output per day: | E7: =3*8*Y11 -> 24 | G7: M./DAY
A8: QTY | B8: Quantity: | E8: ='INPUT DATA'!C41 -> 12 | G8: =E6 -> M.
B10: Designation | K10: No. Person | N10: No. of Days | Q10: Daily Rate | T10: Amount
X11: NO .OF TEAM | Y11: 1
B12: A. | C12: Labor
A13: DURATION | C13: a. | D13: Construction Foreman/Engineering Assistant | K13: 1 | N13: =E8/E7 -> 0.5 | Q13: 800 | T13: =K13*N13*Q13 -> 400
C14: b. | D14: Skilled Laborer | K14: 1 | N14: =N13 -> 0.5 | Q14: 600 | T14: =K14*N14*Q14 -> 300
C15: c. | D15: Laborer | K15: 2 | N15: =N14 -> 0.5 | Q15: 400 | T15: =K15*N15*Q15 -> 400
A20: LABOR | C20: Sub-Total for A | S20: P | T20: =ROUND(SUM(T13:V18),2) -> 1100
B21: Name and Capacity | K21: No. of Units | N21: No. of Days | Q21: Daily Rate | T21: Amount
B23: B. | C23: Equipment
D24: Minor Tools (10% of labor Cost) | T24: =10%*T20 -> 110
Z26: DESCRIPTION | AA26: AREA
Z27: EXIST. EXTERIOR CONCRETE SURFACE 1st
Z28: EXIST. INTERIOR CONCRETE SURFACE 1st
A29: EQUIPMENT | C29: Sub-Total for B | S29: P | T29: =SUM(T24:V28) -> 110 | Z29: EXIST. EXTERIOR CONCRETE SURFACE 2nd
B30: C. | C30: Total (A+B) | T30: =T20+T29 -> 1210 | Z30: EXIST. INTERIOR CONCRETE SURFACE 2nd
B31: D. | C31: Output per day | G31: = | Z31: EXIST. EXTERIOR CONCRETE SURFACE 3rd | AK31: 2Ø 45° bend | AL31: 2Øx2Ø tee | AM31: 4Øx4Ø coupling
B32: Name and Specifications | K32: Quantity | N32: Unit | Q32: Unit Cost | T32: Amount | Z32: EXIST. INTERIOR CONCRETE SURFACE 3rd
Z33: PROP. CONCRETE SURFACE
B34: E. | C34: Materials | Z34: CEILING & INT. DRY WALL SURFACE | AL34: 2
C35: a. | D35: 100mm Sanitary PVC Pipe Series 600/1999 | K35: =E8 -> 12 | N35: m. | Q35: =450/3 -> 150 | T35: =K35*Q35 -> 1800 | Z35: METAL SURFACE | AA35: =PI()*0.3*6*#REF!+PI()*0.2*6*#REF!+PI()*0.1*6*#REF! -> #REF! | AM35: 4
C36: b. | D36: Consumables (5% of Material Cost) | T36: =10%*SUM(T35:V35) -> 180
D39: Estimator shall include the bends/elbow in the material take-off
A45: MATERIAL | C45: Sub-Total for E | S45: P | T45: =ROUND(SUM(T35:V44),2) -> 1980
B46: F. | C46: Direct Cost (C+E) | T46: =T30+T45 -> 3190
B47: G. | C47: Overhead, Contingencies & Miscellaneous | N47: ='INPUT DATA'!C62 -> 0.05 | T47: =T46*N47 -> 159.5
B48: H. | C48: Contractor's Profit (CP) | N48: ='INPUT DATA'!C63 -> 0.1 | T48: =T46*N48 -> 319
B49: I. | C49: Value Added Tax (VAT) | N49: ='INPUT DATA'!C64 -> 0 | T49: =(T46+T47+T48)*N49 -> 0
A50: CHECKING | B50: J. | C50: Total Cost | T50: =SUM(T46:V49) -> 3668.5
A51: ADJUSTED CHECKING | B51: k. | C51: Total Unit Cost | T51: =T50/E8 -> 305.70833

Sheet 1002(6) Waterline Pipes fitting
B1: DETAILED UNIT PRICE ANALYSIS
B3: PROJECT NAME: | E3: ='INPUT DATA'!C4 -> PROPOSED ONE STOREY TWO BED ROOM RESIDENTIAL BUILDING
A5: ITEM NO. | B5: Item No./Description: | E5: 1002(6) | G5: WATERLINE PIPES & FITTINGS
A6: UNIT | B6: Unit of Measurement: | E6: L.S.
B7: Output per day:
A8: QTY | B8: Quantity: | E8: ='INPUT DATA'!C42 -> 1 | G8: =E6 -> L.S.
B10: Designation | K10: No. Person | N10: No. of Days | Q10: Daily Rate | T10: Amount
X11: NO .OF TEAM | Y11: 1
B12: A. | C12: Labor
A13: DURATION | C13: a. | D13: Construction Foreman/Engineering Assistant | K13: 1 | N13: 1 | Q13: 800 | T13: =K13*N13*Q13 -> 800
C14: b. | D14: Skilled Laborer | K14: 1 | N14: =N13 -> 1 | Q14: 600 | T14: =K14*N14*Q14 -> 600
C15: c. | D15: Laborer | K15: 2 | N15: =N14 -> 1 | Q15: 400 | T15: =K15*N15*Q15 -> 800
A20: LABOR | C20: Sub-Total for A | S20: P | T20: =ROUND(SUM(T13:V18),2) -> 2200
B21: Name and Capacity | K21: No. of Units | N21: No. of Days | Q21: Daily Rate | T21: Amount
B23: B. | C23: Equipment
D24: Minor Tools (10% of labor Cost) | T24: =10%*T20 -> 220
Z26: DESCRIPTION | AA26: AREA
Z27: EXIST. EXTERIOR CONCRETE SURFACE 1st
Z28: EXIST. INTERIOR CONCRETE SURFACE 1st
A29: EQUIPMENT | C29: Sub-Total for B | S29: P | T29: =SUM(T23:V28) -> 220 | Z29: EXIST. EXTERIOR CONCRETE SURFACE 2nd
B30: C. | C30: Total (A+B) | T30: =T20+T29 -> 2420 | Z30: EXIST. INTERIOR CONCRETE SURFACE 2nd
B31: D. | C31: Output per day | G31: = | Z31: EXIST. EXTERIOR CONCRETE SURFACE 3rd | AK31: 2Ø 45° bend | AL31: 2Øx2Ø tee | AM31: 4Øx4Ø coupling
B32: Name and Specifications | K32: Quantity | N32: Unit | Q32: Unit Cost | T32: Amount | Z32: EXIST. INTERIOR CONCRETE SURFACE 3rd
Z33: PROP. CONCRETE SURFACE
B34: E. | C34: Materials | Z34: CEILING & INT. DRY WALL SURFACE | AL34: 2
C35: a. | D35: 12mm PPR Pipe | K35: 6 | N35: pc. | Q35: 380 | T35: =Q35*K35 -> 2280 | Z35: METAL SURFACE | AA35: =PI()*0.3*6*#REF!+PI()*0.2*6*#REF!+PI()*0.1*6*#REF! -> #REF! | AM35: 4
C36: b. | D36: 12mm PPR Fittins | K36: 1 | N36: lot | Q36: 500 | T36: =Q36*K36 -> 500
D40: NOTE:
D41: The estimator shall determine the needed materials and determine the duration to complete this item.
A45: MATERIAL | C45: Sub-Total for E | S45: P | T45: =ROUND(SUM(T35:V44),2) -> 2780
B46: F. | C46: Direct Cost (C+E) | T46: =T30+T45 -> 5200
B47: G. | C47: Overhead, Contingencies & Miscellaneous | N47: ='INPUT DATA'!C62 -> 0.05 | T47: =T46*N47 -> 260
B48: H. | C48: Contractor's Profit (CP) | N48: ='INPUT DATA'!C63 -> 0.1 | T48: =T46*N48 -> 520
B49: I. | C49: Value Added Tax (VAT) | N49: ='INPUT DATA'!C64 -> 0 | T49: =(T46+T47+T48)*N49 -> 0
A50: CHECKING | B50: J. | C50: Total Cost | T50: =SUM(T46:V49) -> 5980
A51: ADJUSTED CHECKING | B51: k. | C51: Total Unit Cost | T51: =T50/E8 -> 5980

Sheet 1002(5) W Closet w acc
B1: DETAILED UNIT PRICE ANALYSIS
B3: PROJECT NAME: | E3: ='INPUT DATA'!C4 -> PROPOSED ONE STOREY TWO BED ROOM RESIDENTIAL BUILDING
A5: ITEM NO. | B5: Item No./Description: | E5: 1002(5) | G5: WATER CLOSET/ URINAL W/ COMPLETE ACCESSORIES
A6: UNIT | B6: Unit of Measurement: | E6: SET
B7: Output per day: | E7: 4 | G7: SET/DAY
A8: QTY | B8: Quantity: | E8: ='INPUT DATA'!C43 -> 1 | G8: =E6 -> SET
B10: Designation | K10: No. Person | N10: No. of Days | Q10: Daily Rate | T10: Amount
B12: A. | C12: Labor
A13: DURATION | C13: a. | D13: Construction Foreman/Engineering Assistant | K13: 1 | N13: =E8/E7 -> 0.25 | Q13: 800 | T13: =K13*N13*Q13 -> 200
C14: b. | D14: Skilled Laborer | K14: 1 | N14: =N13 -> 0.25 | Q14: 600 | T14: =K14*N14*Q14 -> 150
C15: c. | D15: Laborer | K15: 1 | N15: =N14 -> 0.25 | Q15: 400 | T15: =K15*N15*Q15 -> 100
A20: LABOR | C20: Sub-Total for A | S20: P | T20: =ROUND(SUM(T13:V18),2) -> 450
B21: Name and Capacity | K21: No. of Units | N21: No. of Days | Q21: Daily Rate | T21: Amount
B23: B. | C23: Equipment
D24: Minor Tools (10% of labor Cost) | T24: =10%*T20 -> 45
A29: EQUIPMENT | C29: Sub-Total for B | S29: P | T29: =SUM(T24:V28) -> 45
B30: C. | C30: Total (A+B) | T30: =T20+T29 -> 495
B31: D. | C31: Output per day | G31: = | AK31: 2Ø 45° bend | AL31: 2Øx2Ø tee | AM31: 4Øx4Ø coupling
B32: Name and Specifications | K32: Quantity | N32: Unit | Q32: Unit Cost | T32: Amount
B34: E. | C34: Materials | AL34: 2
C35: a. | D35: Water Closet / Urinal w/ Complete Accessories | K35: =E8 -> 1 | N35: set | Q35: 6000 | T35: =Q35*K35 -> 6000 | AM35: 4
C36: b. | D36: Consumables (5% of Material Cost) | T36: =10%*SUM(T35:V35) -> 600
A45: MATERIAL | C45: Sub-Total for E | S45: P | T45: =ROUND(SUM(T35:V44),2) -> 6600
B46: F. | C46: Direct Cost (C+E) | T46: =T30+T45 -> 7095
B47: G. | C47: Overhead, Contingencies & Miscellaneous | N47: ='INPUT DATA'!C62 -> 0.05 | T47: =T46*N47 -> 354.75
B48: H. | C48: Contractor's Profit (CP) | N48: ='INPUT DATA'!C63 -> 0.1 | T48: =T46*N48 -> 709.5
B49: I. | C49: Value Added Tax (VAT) | N49: ='INPUT DATA'!C64 -> 0 | T49: =(T46+T47+T48)*N49 -> 0
A50: CHECKING | B50: J. | C50: Total Cost | T50: =SUM(T46:V49) -> 8159.25
A51: ADJUSTED CHECKING | B51: k. | C51: Total Unit Cost | T51: =T50/E8 -> 8159.25

Sheet 1002(5) Kitch SInk
B1: DETAILED UNIT PRICE ANALYSIS
B3: PROJECT NAME: | E3: ='INPUT DATA'!C4 -> PROPOSED ONE STOREY TWO BED ROOM RESIDENTIAL BUILDING
A5: ITEM NO. | B5: Item No./Description: | E5: 1002(5) | G5: KITCHEN SINK/ SCRUB/ SLOP SINK W/ COMPLETE ACCESSORIES
A6: UNIT | B6: Unit of Measurement: | E6: SET
B7: Output per day: | E7: 4 | G7: SET/DAY
A8: QTY | B8: Quantity: | E8: ='INPUT DATA'!C44 -> 1 | G8: =E6 -> SET
B10: Designation | K10: No. Person | N10: No. of Days | Q10: Daily Rate | T10: Amount
B12: A. | C12: Labor
A13: DURATION | C13: a. | D13: Construction Foreman/Engineering Assistant | K13: 1 | N13: =E8/E7 -> 0.25 | Q13: 800 | T13: =K13*N13*Q13 -> 200
C14: b. | D14: Skilled Laborer | K14: 1 | N14: =N13 -> 0.25 | Q14: 600 | T14: =K14*N14*Q14 -> 150
C15: c. | D15: Laborer | K15: 1 | N15: =N14 -> 0.25 | Q15: 400 | T15: =K15*N15*Q15 -> 100
A20: LABOR | C20: Sub-Total for A | S20: P | T20: =ROUND(SUM(T13:V18),2) -> 450
B21: Name and Capacity | K21: No. of Units | N21: No. of Days | Q21: Daily Rate | T21: Amount
B23: B. | C23: Equipment
D24: Minor Tools (10% of labor Cost) | T24: =10%*T20 -> 45
A29: EQUIPMENT | C29: Sub-Total for B | S29: P | T29: =SUM(T23:V28) -> 45
B30: C. | C30: Total (A+B) | T30: =T20+T29 -> 495
B31: D. | C31: Output per day | G31: = | AK31: 2Ø 45° bend | AL31: 2Øx2Ø tee | AM31: 4Øx4Ø coupling
B32: Name and Specifications | K32: Quantity | N32: Unit | Q32: Unit Cost | T32: Amount
B34: E. | C34: Materials | AL34: 2
C35: a. | D35: Kitchen Sink w/ Complete Accessories | K35: =E8 -> 1 | N35: set | Q35: 4500 | T35: =Q35*K35 -> 4500 | AM35: 4
C36: b. | D36: Consumables (5% of Material Cost) | T36: =10%*SUM(T35:V35) -> 450
A45: MATERIAL | C45: Sub-Total for E | S45: P | T45: =ROUND(SUM(T35:V44),2) -> 4950
B46: F. | C46: Direct Cost (C+E) | T46: =T30+T45 -> 5445
B47: G. | C47: Overhead, Contingencies & Miscellaneous | N47: ='INPUT DATA'!C62 -> 0.05 | T47: =T46*N47 -> 272.25
B48: H. | C48: Contractor's Profit (CP) | N48: ='INPUT DATA'!C63 -> 0.1 | T48: =T46*N48 -> 544.5
B49: I. | C49: Value Added Tax (VAT) | N49: ='INPUT DATA'!C64 -> 0 | T49: =(T46+T47+T48)*N49 -> 0
A50: CHECKING | B50: J. | C50: Total Cost | T50: =SUM(T46:V49) -> 6261.75
A51: ADJUSTED CHECKING | B51: k. | C51: Total Unit Cost | T51: =T50/E8 -> 6261.75

Sheet 1002(5) Counter Lavatory
B1: DETAILED UNIT PRICE ANALYSIS
B3: PROJECT NAME: | E3: ='INPUT DATA'!C4 -> PROPOSED ONE STOREY TWO BED ROOM RESIDENTIAL BUILDING
A5: ITEM NO. | B5: Item No./Description: | E5: 1002(5) | G5: WALL HANG/COUNTERTOP/ UNDER COUNTER LAVATORY W/ COMPLETE ACCESSORIES
A6: UNIT | B6: Unit of Measurement: | E6: SET
B7: Output per day: | E7: 4 | G7: SET/DAY
A8: QTY | B8: Quantity: | E8: ='INPUT DATA'!C45 -> 1 | G8: =E6 -> SET
B10: Designation | K10: No. Person | N10: No. of Days | Q10: Daily Rate | T10: Amount
B12: A. | C12: Labor
A13: DURATION | C13: a. | D13: Construction Foreman/Engineering Assistant | K13: 1 | N13: =E8/E7 -> 0.25 | Q13: 800 | T13: =K13*N13*Q13 -> 200
C14: b. | D14: Skilled Laborer | K14: 1 | N14: =N13 -> 0.25 | Q14: 600 | T14: =K14*N14*Q14 -> 150
C15: c. | D15: Laborer | K15: 1 | N15: =N14 -> 0.25 | Q15: 400 | T15: =K15*N15*Q15 -> 100
A20: LABOR | C20: Sub-Total for A | S20: P | T20: =ROUND(SUM(T13:V18),2) -> 450
B21: Name and Capacity | K21: No. of Units | N21: No. of Days | Q21: Daily Rate | T21: Amount
B23: B. | C23: Equipment
D24: Minor Tools (10% of labor Cost) | T24: =10%*T20 -> 45
A29: EQUIPMENT | C29: Sub-Total for B | S29: P | T29: =SUM(T24:V28) -> 45
B30: C. | C30: Total (A+B) | T30: =T20+T29 -> 495
B31: D. | C31: Output per day | G31: = | AK31: 2Ø 45° bend | AL31: 2Øx2Ø tee | AM31: 4Øx4Ø coupling
B32: Name and Specifications | K32: Quantity | N32: Unit | Q32: Unit Cost | T32: Amount
B34: E. | C34: Materials | AL34: 2
C35: a. | D35: Lavatory/Sinks | K35: =E8 -> 1 | N35: set | Q35: 3500 | T35: =Q35*K35 -> 3500 | AM35: 4
C36: b. | D36: Consumables (5% of Material Cost) | T36: =10%*SUM(T35:V35) -> 350
A45: MATERIAL | C45: Sub-Total for E | S45: P | T45: =ROUND(SUM(T35:V44),2) -> 3850
B46: F. | C46: Direct Cost (C+E) | T46: =T30+T45 -> 4345
B47: G. | C47: Overhead, Contingencies & Miscellaneous | N47: ='INPUT DATA'!C62 -> 0.05 | T47: =T46*N47 -> 217.25
B48: H. | C48: Contractor's Profit (CP) | N48: ='INPUT DATA'!C63 -> 0.1 | T48: =T46*N48 -> 434.5
B49: I. | C49: Value Added Tax (VAT) | N49: ='INPUT DATA'!C64 -> 0 | T49: =(T46+T47+T48)*N49 -> 0
A50: CHECKING | B50: J. | C50: Total Cost | T50: =SUM(T46:V49) -> 4996.75
A51: ADJUSTED CHECKING | B51: k. | C51: Total Unit Cost | T51: =T50/E8 -> 4996.75

Sheet 1002(5) h Floor Drain
B1: DETAILED UNIT PRICE ANALYSIS
B3: PROJECT NAME: | E3: ='INPUT DATA'!C4 -> PROPOSED ONE STOREY TWO BED ROOM RESIDENTIAL BUILDING
A5: ITEM NO. | B5: Item No./Description: | E5: 1002(5) | G5: FLOOR DRAIN PLATES (ANY SIZE)
A6: UNIT | B6: Unit of Measurement: | E6: SET
B7: Output per day: | E7: 20 | G7: SET/DAY
A8: QTY | B8: Quantity: | E8: ='INPUT DATA'!C46 -> 2 | G8: =E6 -> SET
B10: Designation | K10: No. Person | N10: No. of Days | Q10: Daily Rate | T10: Amount
B12: A. | C12: Labor
A13: DURATION | C13: a. | D13: Construction Foreman/Engineering Assistant | K13: 1 | N13: =E8/E7 -> 0.1 | Q13: 800 | T13: =K13*N13*Q13 -> 80
C14: b. | D14: Skilled Laborer | K14: 1 | N14: =N13 -> 0.1 | Q14: 600 | T14: =K14*N14*Q14 -> 60
C15: c. | D15: Laborer | K15: 1 | N15: =N14 -> 0.1 | Q15: 400 | T15: =K15*N15*Q15 -> 40
A20: LABOR | C20: Sub-Total for A | S20: P | T20: =ROUND(SUM(T13:V18),2) -> 180
B21: Name and Capacity | K21: No. of Units | N21: No. of Days | Q21: Daily Rate | T21: Amount
B23: B. | C23: Equipment
D24: Minor Tools (10% of labor Cost) | T24: =10%*T20 -> 18
A29: EQUIPMENT | C29: Sub-Total for B | S29: P | T29: =SUM(T24:V28) -> 18
B30: C. | C30: Total (A+B) | T30: =T20+T29 -> 198
B31: D. | C31: Output per day | G31: = | AK31: 2Ø 45° bend | AL31: 2Øx2Ø tee | AM31: 4Øx4Ø coupling
B32: Name and Specifications | K32: Quantity | N32: Unit | Q32: Unit Cost | T32: Amount
B34: E. | C34: Materials | AL34: 2
C35: a. | D35: Floor Drain Plate | K35: =E8 -> 2 | N35: set | Q35: 350 | T35: =Q35*K35 -> 700 | AM35: 4
C36: b. | D36: Consumables (5% of Material Cost) | T36: =10%*SUM(T35:V35) -> 70
A45: MATERIAL | C45: Sub-Total for E | S45: P | T45: =ROUND(SUM(T35:V44),2) -> 770
B46: F. | C46: Direct Cost (C+E) | T46: =T30+T45 -> 968
B47: G. | C47: Overhead, Contingencies & Miscellaneous | N47: ='INPUT DATA'!C62 -> 0.05 | T47: =T46*N47 -> 48.4
B48: H. | C48: Contractor's Profit (CP) | N48: ='INPUT DATA'!C63 -> 0.1 | T48: =T46*N48 -> 96.8
B49: I. | C49: Value Added Tax (VAT) | N49: ='INPUT DATA'!C64 -> 0 | T49: =(T46+T47+T48)*N49 -> 0
A50: CHECKING | B50: J. | C50: Total Cost | T50: =SUM(T46:V49) -> 1113.2
A51: ADJUSTED CHECKING | B51: k. | C51: Total Unit Cost | T51: =T50/E8 -> 556.6

Sheet 1002(5) Soap Holder
B1: DETAILED UNIT PRICE ANALYSIS
B3: PROJECT NAME: | E3: ='INPUT DATA'!C4 -> PROPOSED ONE STOREY TWO BED ROOM RESIDENTIAL BUILDING
A5: ITEM NO. | B5: Item No./Description: | E5: 1002(5) | G5: SOAP HOLDER /TOILET SOAP/LIQUID SOAP/TISSUE HOLDER
A6: UNIT | B6: Unit of Measurement: | E6: SET
B7: Output per day: | E7: =(1/(0.75/8)) -> 10.666667 | G7: SET/DAY
A8: QTY | B8: Quantity: | E8: ='INPUT DATA'!C47 -> 1 | G8: =E6 -> SET
B10: Designation | K10: No. Person | N10: No. of Days | Q10: Daily Rate | T10: Amount
B12: A. | C12: Labor
A13: DURATION | C13: a. | D13: Construction Foreman/Engineering Assistant | K13: 1 | N13: =E8/E7 -> 0.09375 | Q13: 800 | T13: =K13*N13*Q13 -> 75
C14: b. | D14: Skilled Laborer | K14: 1 | N14: =N13 -> 0.09375 | Q14: 600 | T14: =K14*N14*Q14 -> 56.25
C15: c. | D15: Laborer | K15: 1 | N15: =N14 -> 0.09375 | Q15: 400 | T15: =K15*N15*Q15 -> 37.5
A20: LABOR | C20: Sub-Total for A | S20: P | T20: =ROUND(SUM(T13:V18),2) -> 168.75
B21: Name and Capacity | K21: No. of Units | N21: No. of Days | Q21: Daily Rate | T21: Amount
B23: B. | C23: Equipment
D24: Minor Tools (10% of labor Cost) | T24: =10%*T20 -> 16.875
A29: EQUIPMENT | C29: Sub-Total for B | S29: P | T29: =SUM(T24:V28) -> 16.875
B30: C. | C30: Total (A+B) | T30: =T20+T29 -> 185.625
B31: D. | C31: Output per day | G31: = | AK31: 2Ø 45° bend | AL31: 2Øx2Ø tee | AM31: 4Øx4Ø coupling
B32: Name and Specifications | K32: Quantity | N32: Unit | Q32: Unit Cost | T32: Amount
B34: E. | C34: Materials | AL34: 2
C35: a. | D35: Soap Holder & Tissue Holder | K35: =E8 -> 1 | N35: set | Q35: 350 | T35: =Q35*K35 -> 350 | AM35: 4
C36: b. | D36: Consumables (5% of Material Cost) | T36: =10%*SUM(T35:V35) -> 35
A45: MATERIAL | C45: Sub-Total for E | S45: P | T45: =ROUND(SUM(T35:V44),2) -> 385
B46: F. | C46: Direct Cost (C+E) | T46: =T30+T45 -> 570.625
B47: G. | C47: Overhead, Contingencies & Miscellaneous | N47: ='INPUT DATA'!C62 -> 0.05 | T47: =T46*N47 -> 28.53125
B48: H. | C48: Contractor's Profit (CP) | N48: ='INPUT DATA'!C63 -> 0.1 | T48: =T46*N48 -> 57.0625
B49: I. | C49: Value Added Tax (VAT) | N49: ='INPUT DATA'!C64 -> 0 | T49: =(T46+T47+T48)*N49 -> 0
A50: CHECKING | B50: J. | C50: Total Cost | T50: =SUM(T46:V49) -> 656.21875
A51: ADJUSTED CHECKING | B51: k. | C51: Total Unit Cost | T51: =T50/E8 -> 656.21875

Sheet 1002(5)a Shower Head valve
B1: DETAILED UNIT PRICE ANALYSIS
B3: PROJECT NAME: | E3: ='INPUT DATA'!C4 -> PROPOSED ONE STOREY TWO BED ROOM RESIDENTIAL BUILDING
A5: ITEM NO. | B5: Item No./Description: | E5: 1002(5) | G5: SHOWER HEAD /SHOWER VALVE
A6: UNIT | B6: Unit of Measurement: | E6: SET
B7: Output per day: | E7: =(1/(1/8)) -> 8 | G7: SET/DAY
A8: QTY | B8: Quantity: | E8: ='INPUT DATA'!C47 -> 1 | G8: =E6 -> SET
B10: Designation | K10: No. Person | N10: No. of Days | Q10: Daily Rate | T10: Amount
B12: A. | C12: Labor
A13: DURATION | C13: a. | D13: Construction Foreman/Engineering Assistant | K13: 1 | N13: =E8/E7 -> 0.125 | Q13: 800 | T13: =K13*N13*Q13 -> 100
C14: b. | D14: Skilled Laborer | K14: 1 | N14: =N13 -> 0.125 | Q14: 600 | T14: =K14*N14*Q14 -> 75
C15: c. | D15: Laborer | K15: 1 | N15: =N14 -> 0.125 | Q15: 400 | T15: =K15*N15*Q15 -> 50
A20: LABOR | C20: Sub-Total for A | S20: P | T20: =ROUND(SUM(T13:V18),2) -> 225
B21: Name and Capacity | K21: No. of Units | N21: No. of Days | Q21: Daily Rate | T21: Amount
B23: B. | C23: Equipment
D24: Minor Tools (10% of labor Cost) | T24: =10%*T20 -> 22.5
A29: EQUIPMENT | C29: Sub-Total for B | S29: P
B30: C. | C30: Total (A+B) | T30: =T20+T29 -> 225
B31: D. | C31: Output per day | G31: = | AK31: 2Ø 45° bend | AL31: 2Øx2Ø tee | AM31: 4Øx4Ø coupling
B32: Name and Specifications | K32: Quantity | N32: Unit | Q32: Unit Cost | T32: Amount
B34: E. | C34: Materials | AL34: 2
C35: a. | D35: Shower Head & Valve | K35: =E8 -> 1 | N35: set | Q35: 2600 | T35: =Q35*K35 -> 2600 | AM35: 4
C36: b. | D36: Consumables (5% of Material Cost) | T36: =10%*SUM(T35:V35) -> 260
A45: MATERIAL | C45: Sub-Total for E | S45: P | T45: =ROUND(SUM(T35:V44),2) -> 2860
B46: F. | C46: Direct Cost (C+E) | T46: =T30+T45 -> 3085
B47: G. | C47: Overhead, Contingencies & Miscellaneous | N47: ='INPUT DATA'!C62 -> 0.05 | T47: =T46*N47 -> 154.25
B48: H. | C48: Contractor's Profit (CP) | N48: ='INPUT DATA'!C63 -> 0.1 | T48: =T46*N48 -> 308.5
B49: I. | C49: Value Added Tax (VAT) | N49: ='INPUT DATA'!C64 -> 0 | T49: =(T46+T47+T48)*N49 -> 0
A50: CHECKING | B50: J. | C50: Total Cost | T50: =SUM(T46:V49) -> 3547.75
A51: ADJUSTED CHECKING | B51: k. | C51: Total Unit Cost | T51: =T50/E8 -> 3547.75

Sheet 1002(5)p Facial Mirror
B1: DETAILED UNIT PRICE ANALYSIS
B3: PROJECT NAME: | E3: ='INPUT DATA'!C4 -> PROPOSED ONE STOREY TWO BED ROOM RESIDENTIAL BUILDING
A5: ITEM NO. | B5: Item No./Description: | E5: 1002(5)p | G5: FACIAL MIRROR
A6: UNIT | B6: Unit of Measurement: | E6: SQ.M.
B7: Output per day: | E7: =0.4*8 -> 3.2 | G7: SQ.M./DAY
A8: QTY | B8: Quantity: | E8: ='INPUT DATA'!C48 -> 0.5 | G8: =E6 -> SQ.M.
B10: Designation | K10: No. Person | N10: No. of Days | Q10: Daily Rate | T10: Amount
B12: A. | C12: Labor
A13: DURATION | C13: a. | D13: Construction Foreman/Engineering Assistant | K13: 1 | N13: =E8/E7 -> 0.15625 | Q13: 800 | T13: =K13*N13*Q13 -> 125
C14: b. | D14: Skilled Laborer | K14: 1 | N14: =N13 -> 0.15625 | Q14: 600 | T14: =K14*N14*Q14 -> 93.75
C15: c. | D15: Laborer | K15: 1 | N15: =N14 -> 0.15625 | Q15: 400 | T15: =K15*N15*Q15 -> 62.5
A20: LABOR | C20: Sub-Total for A | S20: P | T20: =ROUND(SUM(T13:V18),2) -> 281.25
B21: Name and Capacity | K21: No. of Units | N21: No. of Days | Q21: Daily Rate | T21: Amount
B23: B. | C23: Equipment
D24: Minor Tools (10% of labor Cost) | T24: =10%*T20 -> 28.125
A29: EQUIPMENT | C29: Sub-Total for B | S29: P | T29: =SUM(T24:V28) -> 28.125
B30: C. | C30: Total (A+B) | T30: =T20+T29 -> 309.375
B31: D. | C31: Output per day | G31: = | AK31: 2Ø 45° bend | AL31: 2Øx2Ø tee | AM31: 4Øx4Ø coupling
B32: Name and Specifications | K32: Quantity | N32: Unit | Q32: Unit Cost | T32: Amount
B34: E. | C34: Materials | AL34: 2
C35: a. | D35: Facial Mirror | K35: =E8 -> 0.5 | N35: sq.m. | Q35: 900 | T35: =Q35*K35 -> 450 | AM35: 4
C36: b. | D36: Consumables (5% of Material Cost) | T36: =10%*SUM(T35:V35) -> 45
A45: MATERIAL | C45: Sub-Total for E | S45: P | T45: =ROUND(SUM(T35:V44),2) -> 495
B46: F. | C46: Direct Cost (C+E) | T46: =T30+T45 -> 804.375
B47: G. | C47: Overhead, Contingencies & Miscellaneous | N47: ='INPUT DATA'!C62 -> 0.05 | T47: =T46*N47 -> 40.21875
B48: H. | C48: Contractor's Profit (CP) | N48: ='INPUT DATA'!C63 -> 0.1 | T48: =T46*N48 -> 80.4375
B49: I. | C49: Value Added Tax (VAT) | N49: ='INPUT DATA'!C64 -> 0 | T49: =(T46+T47+T48)*N49 -> 0
A50: CHECKING | B50: J. | C50: Total Cost | T50: =SUM(T46:V49) -> 925.03125
A51: ADJUSTED CHECKING | B51: k. | C51: Total Unit Cost | T51: =T50/E8 -> 1850.0625

Sheet Other item-Plumbing
B1: DETAILED UNIT PRICE ANALYSIS
B3: PROJECT NAME: | E3: ='INPUT DATA'!C4 -> PROPOSED ONE STOREY TWO BED ROOM RESIDENTIAL BUILDING
A5: ITEM NO. | B5: Item No./Description: | E5: SPL- ? | G5: (INPUT OTHER PLUMBING WORK ITEM THAT IS NOT FOUND IN THIS SPREADSHEET)
A6: UNIT | B6: Unit of Measurement: | E6: L.S.
B7: Output per day:
A8: QTY | B8: Quantity: | E8: ='INPUT DATA'!C49 -> 1 | G8: =E6 -> L.S.
B10: Designation | K10: No. Person | N10: No. of Days | Q10: Daily Rate | T10: Amount
B12: A. | C12: Labor
A13: DURATION | C13: a. | D13: Construction Foreman/Engineering Assistant | Q13: 800 | T13: =K13*N13*Q13 -> 0
C14: b. | D14: Skilled Laborer | Q14: 600 | T14: =K14*N14*Q14 -> 0
C15: c. | D15: Laborer | Q15: 400 | T15: =K15*N15*Q15 -> 0
A20: LABOR | C20: Sub-Total for A | S20: P | T20: =ROUND(SUM(T13:V18),2) -> 0
B21: Name and Capacity | K21: No. of Units | N21: No. of Days | Q21: Daily Rate | T21: Amount
B23: B. | C23: Equipment
D24: Minor Tools (10% of labor Cost) | T24: =10%*T20 -> 0
A29: EQUIPMENT | C29: Sub-Total for B | S29: P | T29: =SUM(T24:V28) -> 0
B30: C. | C30: Total (A+B) | T30: =T20+T29 -> 0
B31: D. | C31: Output per day | G31: = | AK31: 2Ø 45° bend | AL31: 2Øx2Ø tee | AM31: 4Øx4Ø coupling
B32: Name and Specifications | K32: Quantity | N32: Unit | Q32: Unit Cost | T32: Amount
B34: E. | C34: Materials | AL34: 2
C35: a. | AM35: 4
C36: b.
A45: MATERIAL | C45: Sub-Total for E | S45: P | T45: =ROUND(SUM(T35:V44),2) -> 0
B46: F. | C46: Direct Cost (C+E) | T46: =T30+T45 -> 0
B47: G. | C47: Overhead, Contingencies & Miscellaneous | N47: ='INPUT DATA'!C62 -> 0.05 | T47: =T46*N47 -> 0
B48: H. | C48: Contractor's Profit (CP) | N48: ='INPUT DATA'!C63 -> 0.1 | T48: =T46*N48 -> 0
B49: I. | C49: Value Added Tax (VAT) | N49: ='INPUT DATA'!C64 -> 0 | T49: =(T46+T47+T48)*N49 -> 0
A50: CHECKING | B50: J. | C50: Total Cost | T50: =SUM(T46:V49) -> 0
A51: ADJUSTED CHECKING | B51: k. | C51: Total Unit Cost | T51: =T50/E8 -> 0

Sheet 1100(1) Conduit
B1: DETAILED UNIT PRICE ANALYSIS
B3: PROJECT NAME: | E3: ='INPUT DATA'!C4 -> PROPOSED ONE STOREY TWO BED ROOM RESIDENTIAL BUILDING
A5: ITEM NO. | B5: Item No./Description: | E5: 1002(5) | G5: 15MM-25MM DIA. FLEXIBLE CONDUIT
A6: UNIT | B6: Unit of Measurement: | E6: M.
B7: Output per day: | E7: =3.534*8 -> 28.272 | G7: M./DAY
A8: QTY | B8: Quantity: | E8: ='INPUT DATA'!C51 -> 200 | G8: =E6 -> M.
B10: Designation | K10: No. Person | N10: No. of Days | Q10: Daily Rate | T10: Amount
B12: A. | C12: Labor
A13: DURATION | C13: a. | D13: Construction Foreman/Engineering Assistant | K13: 1 | N13: =E8/E7 -> 7.074137 | Q13: 800 | T13: =K13*N13*Q13 -> 5659.3096
C14: b. | D14: Skilled Laborer | K14: 1 | N14: =N13 -> 7.074137 | Q14: 600 | T14: =K14*N14*Q14 -> 4244.4822
C15: c. | D15: Laborer | K15: 1 | N15: =N14 -> 7.074137 | Q15: 400 | T15: =K15*N15*Q15 -> 2829.6548
A20: LABOR | C20: Sub-Total for A | S20: P | T20: =ROUND(SUM(T13:V18),2) -> 12733.45
B21: Name and Capacity | K21: No. of Units | N21: No. of Days | Q21: Daily Rate | T21: Amount
B23: B. | C23: Equipment
D24: Minor Tools (10% of labor Cost) | T24: =10%*T20 -> 1273.345
A29: EQUIPMENT | C29: Sub-Total for B | S29: P | T29: =SUM(T23:V28) -> 1273.345
B30: C. | C30: Total (A+B) | T30: =T20+T29 -> 14006.795
B31: D. | C31: Output per day | G31: = | AK31: 2Ø 45° bend | AL31: 2Øx2Ø tee | AM31: 4Øx4Ø coupling
B32: Name and Specifications | K32: Quantity | N32: Unit | Q32: Unit Cost | T32: Amount
B34: E. | C34: Materials | AL34: 2
C35: a. | D35: Flexible/ Rigid Conduit | K35: =E8 -> 200 | N35: m. | Q35: 15 | T35: =Q35*K35 -> 3000 | AM35: 4
C36: b. | D36: Consumables (5% of Material Cost) | T36: =10%*SUM(T35:V35) -> 300
D39: Estimator shall Include fittings in the material take-off.
A45: MATERIAL | C45: Sub-Total for E | S45: P | T45: =ROUND(SUM(T35:V44),2) -> 3300
B46: F. | C46: Direct Cost (C+E) | T46: =T30+T45 -> 17306.795
B47: G. | C47: Overhead, Contingencies & Miscellaneous | N47: ='INPUT DATA'!C62 -> 0.05 | T47: =T46*N47 -> 865.33975
B48: H. | C48: Contractor's Profit (CP) | N48: ='INPUT DATA'!C63 -> 0.1 | T48: =T46*N48 -> 1730.6795
B49: I. | C49: Value Added Tax (VAT) | N49: ='INPUT DATA'!C64 -> 0 | T49: =(T46+T47+T48)*N49 -> 0
A50: CHECKING | B50: J. | C50: Total Cost | T50: =SUM(T46:V49) -> 19902.814
A51: ADJUSTED CHECKING | B51: k. | C51: Total Unit Cost | T51: =T50/E8 -> 99.514071

Sheet 1100 Junc Utility Box
B1: DETAILED UNIT PRICE ANALYSIS
B3: PROJECT NAME: | E3: ='INPUT DATA'!C4 -> PROPOSED ONE STOREY TWO BED ROOM RESIDENTIAL BUILDING
A5: ITEM NO. | B5: Item No./Description: | E5: 1100 | G5: JUNCTION UTILITY/PULL / SQUARE BOX
A6: UNIT | B6: Unit of Measurement: | E6: PC.
B7: Output per day: | E7: =1/(0.4/8) -> 20 | G7: PC./DAY
A8: QTY | B8: Quantity: | E8: ='INPUT DATA'!C52 -> 33 | G8: =E6 -> PC.
B10: Designation | K10: No. Person | N10: No. of Days | Q10: Daily Rate | T10: Amount
B12: A. | C12: Labor
A13: DURATION | C13: a. | D13: Construction Foreman/Engineering Assistant | K13: 1 | N13: =E8/E7 -> 1.65 | Q13: 800 | T13: =K13*N13*Q13 -> 1320
C14: b. | D14: Skilled Laborer | K14: 1 | N14: =N13 -> 1.65 | Q14: 600 | T14: =K14*N14*Q14 -> 990
C15: c. | D15: Laborer | K15: 1 | N15: =N14 -> 1.65 | Q15: 400 | T15: =K15*N15*Q15 -> 660
A20: LABOR | C20: Sub-Total for A | S20: P | T20: =ROUND(SUM(T13:V18),2) -> 2970
B21: Name and Capacity | K21: No. of Units | N21: No. of Days | Q21: Daily Rate | T21: Amount
B23: B. | C23: Equipment
D24: Minor Tools (10% of labor Cost) | T24: =10%*T20 -> 297
A29: EQUIPMENT | C29: Sub-Total for B | S29: P | T29: =SUM(T23:V28) -> 297
B30: C. | C30: Total (A+B) | T30: =T20+T29 -> 3267
B31: D. | C31: Output per day | G31: = | AK31: 2Ø 45° bend | AL31: 2Øx2Ø tee | AM31: 4Øx4Ø coupling
B32: Name and Specifications | K32: Quantity | N32: Unit | Q32: Unit Cost | T32: Amount
B34: E. | C34: Materials | AL34: 2
C35: a. | D35: Junction/ Utility/ Pull/ Square Box | K35: =E8 -> 33 | N35: pc. | Q35: 45 | T35: =Q35*K35 -> 1485 | AM35: 4
C36: b. | D36: Consumables (5% of Material Cost) | T36: =10%*SUM(T35:V35) -> 148.5
A45: MATERIAL | C45: Sub-Total for E | S45: P | T45: =ROUND(SUM(T35:V44),2) -> 1633.5
B46: F. | C46: Direct Cost (C+E) | T46: =T30+T45 -> 4900.5
B47: G. | C47: Overhead, Contingencies & Miscellaneous | N47: ='INPUT DATA'!C62 -> 0.05 | T47: =T46*N47 -> 245.025
B48: H. | C48: Contractor's Profit (CP) | N48: ='INPUT DATA'!C63 -> 0.1 | T48: =T46*N48 -> 490.05
B49: I. | C49: Value Added Tax (VAT) | N49: ='INPUT DATA'!C64 -> 0 | T49: =(T46+T47+T48)*N49 -> 0
A50: CHECKING | B50: J. | C50: Total Cost | T50: =SUM(T46:V49) -> 5635.575
A51: ADJUSTED CHECKING | B51: k. | C51: Total Unit Cost | T51: =T50/E8 -> 170.775

Sheet 1101(2) 1.6-5.5 mm2 Elec Wire
B1: DETAILED UNIT PRICE ANALYSIS
B3: PROJECT NAME: | E3: ='INPUT DATA'!C4 -> PROPOSED ONE STOREY TWO BED ROOM RESIDENTIAL BUILDING
A5: ITEM NO. | B5: Item No./Description: | E5: 1101(2) | G5: 1.6MM2 - 5.5MM2 ELECTRIC WIRE (TW/THHN/TWHN2)
A6: UNIT | B6: Unit of Measurement: | E6: M.
B7: Output per day: | E7: =25*8 -> 200 | G7: M./DAY
A8: QTY | B8: Quantity: | E8: ='INPUT DATA'!C53 -> 600 | G8: =E6 -> M.
B10: Designation | K10: No. Person | N10: No. of Days | Q10: Daily Rate | T10: Amount
B12: A. | C12: Labor
A13: DURATION | C13: a. | D13: Construction Foreman/Engineering Assistant | K13: 1 | N13: =E8/E7 -> 3 | Q13: 800 | T13: =K13*N13*Q13 -> 2400
C14: b. | D14: Skilled Laborer | K14: 1 | N14: =N13 -> 3 | Q14: 600 | T14: =K14*N14*Q14 -> 1800
C15: c. | D15: Laborer | K15: 1 | N15: =N14 -> 3 | Q15: 400 | T15: =K15*N15*Q15 -> 1200
A20: LABOR | C20: Sub-Total for A | S20: P | T20: =ROUND(SUM(T13:V18),2) -> 5400
B21: Name and Capacity | K21: No. of Units | N21: No. of Days | Q21: Daily Rate | T21: Amount
B23: B. | C23: Equipment
D24: Minor Tools (10% of labor Cost) | T24: =10%*T20 -> 540
A29: EQUIPMENT | C29: Sub-Total for B | S29: P | T29: =SUM(T23:V28) -> 540
B30: C. | C30: Total (A+B) | T30: =T20+T29 -> 5940
B31: D. | C31: Output per day | G31: = | AK31: 2Ø 45° bend | AL31: 2Øx2Ø tee | AM31: 4Øx4Ø coupling
B32: Name and Specifications | K32: Quantity | N32: Unit | Q32: Unit Cost | T32: Amount
B34: E. | C34: Materials | AL34: 2
C35: a. | D35: 1.6mm2 - 5.5mm2 Electric Wire (TW/THHN/TWHN2) | K35: =E8 -> 600 | N35: m. | Q35: 29 | T35: =Q35*K35 -> 17400 | AM35: 4
C36: b. | D36: Consumables (5% of Material Cost) | T36: =10%*SUM(T35:V35) -> 1740
D40: The estimator shall breakdown the electrical wire requirements
A45: MATERIAL | C45: Sub-Total for E | S45: P | T45: =ROUND(SUM(T35:V44),2) -> 19140
B46: F. | C46: Direct Cost (C+E) | T46: =T30+T45 -> 25080
B47: G. | C47: Overhead, Contingencies & Miscellaneous | N47: ='INPUT DATA'!C62 -> 0.05 | T47: =T46*N47 -> 1254
B48: H. | C48: Contractor's Profit (CP) | N48: ='INPUT DATA'!C63 -> 0.1 | T48: =T46*N48 -> 2508
B49: I. | C49: Value Added Tax (VAT) | N49: ='INPUT DATA'!C64 -> 0 | T49: =(T46+T47+T48)*N49 -> 0
A50: CHECKING | B50: J. | C50: Total Cost | T50: =SUM(T46:V49) -> 28842
A51: ADJUSTED CHECKING | B51: k. | C51: Total Unit Cost | T51: =T50/E8 -> 48.07

Sheet 1101 Single C Outlet
B1: DETAILED UNIT PRICE ANALYSIS
B3: PROJECT NAME: | E3: ='INPUT DATA'!C4 -> PROPOSED ONE STOREY TWO BED ROOM RESIDENTIAL BUILDING
A5: ITEM NO. | B5: Item No./Description: | E5: 1101 | G5: SINGLE CONVINENCE OUTLET/ RECEPTACLE, GROUNDING TYPE/HEAVY DUTY CONVENIENCE OUTLET
A6: UNIT | B6: Unit of Measurement: | E6: SET
B7: Output per day: | E7: =(1/(0.25/8)) -> 32 | G7: SET/DAY
A8: QTY | B8: Quantity: | E8: ='INPUT DATA'!C54 -> 13 | G8: =E6 -> SET
B10: Designation | K10: No. Person | N10: No. of Days | Q10: Daily Rate | T10: Amount
B12: A. | C12: Labor
A13: DURATION | C13: a. | D13: Construction Foreman/Engineering Assistant | K13: 1 | N13: =E8/E7 -> 0.40625 | Q13: 800 | T13: =K13*N13*Q13 -> 325
C14: b. | D14: Skilled Laborer | K14: 1 | N14: =N13 -> 0.40625 | Q14: 600 | T14: =K14*N14*Q14 -> 243.75
C15: c. | D15: Laborer | K15: 1 | N15: =N14 -> 0.40625 | Q15: 400 | T15: =K15*N15*Q15 -> 162.5
A20: LABOR | C20: Sub-Total for A | S20: P | T20: =ROUND(SUM(T13:V18),2) -> 731.25
B21: Name and Capacity | K21: No. of Units | N21: No. of Days | Q21: Daily Rate | T21: Amount
B23: B. | C23: Equipment
A29: EQUIPMENT | C29: Sub-Total for B | S29: P | T29: =SUM(T23:V28) -> 0
B30: C. | C30: Total (A+B) | T30: =T20+T29 -> 731.25
B31: D. | C31: Output per day | G31: = | AK31: 2Ø 45° bend | AL31: 2Øx2Ø tee | AM31: 4Øx4Ø coupling
B32: Name and Specifications | K32: Quantity | N32: Unit | Q32: Unit Cost | T32: Amount
B34: E. | C34: Materials | AL34: 2
C35: a. | D35: Single Convenience Outlet/ or Equivalent | K35: =E8 -> 13 | N35: set | Q35: 180 | T35: =Q35*K35 -> 2340 | AM35: 4
T36: =10%*SUM(T35:V35) -> 234
A45: MATERIAL | C45: Sub-Total for E | S45: P | T45: =ROUND(SUM(T35:V44),2) -> 2574
B46: F. | C46: Direct Cost (C+E) | T46: =T30+T45 -> 3305.25
B47: G. | C47: Overhead, Contingencies & Miscellaneous | N47: ='INPUT DATA'!C62 -> 0.05 | T47: =T46*N47 -> 165.2625
B48: H. | C48: Contractor's Profit (CP) | N48: ='INPUT DATA'!C63 -> 0.1 | T48: =T46*N48 -> 330.525
B49: I. | C49: Value Added Tax (VAT) | N49: ='INPUT DATA'!C64 -> 0 | T49: =(T46+T47+T48)*N49 -> 0
A50: CHECKING | B50: J. | C50: Total Cost | T50: =SUM(T46:V49) -> 3801.0375
A51: ADJUSTED CHECKING | B51: k. | C51: Total Unit Cost | T51: =T50/E8 -> 292.3875

Sheet 1101 Duplex C Outlet
B1: DETAILED UNIT PRICE ANALYSIS
B3: PROJECT NAME: | E3: ='INPUT DATA'!C4 -> PROPOSED ONE STOREY TWO BED ROOM RESIDENTIAL BUILDING
A5: ITEM NO. | B5: Item No./Description: | E5: 1101 | G5: DUPLEX CONVINENCE OUTLET/ RECEPTACLE, GROUNDING TYPE/HEAVY DUTY CONVENIENCE OUTLET
A6: UNIT | B6: Unit of Measurement: | E6: SET
B7: Output per day: | E7: =(1/(0.3/8)) -> 26.666667 | G7: SET/DAY
A8: QTY | B8: Quantity: | E8: ='INPUT DATA'!C55 -> 10 | G8: =E6 -> SET
B10: Designation | K10: No. Person | N10: No. of Days | Q10: Daily Rate | T10: Amount
B12: A. | C12: Labor
A13: DURATION | C13: a. | D13: Construction Foreman/Engineering Assistant | K13: 1 | N13: =E8/E7 -> 0.375 | Q13: 800 | T13: =K13*N13*Q13 -> 300
C14: b. | D14: Skilled Laborer | K14: 1 | N14: =N13 -> 0.375 | Q14: 600 | T14: =K14*N14*Q14 -> 225
C15: c. | D15: Laborer | K15: 1 | N15: =N14 -> 0.375 | Q15: 400 | T15: =K15*N15*Q15 -> 150
A20: LABOR | C20: Sub-Total for A | S20: P | T20: =ROUND(SUM(T13:V18),2) -> 675
B21: Name and Capacity | K21: No. of Units | N21: No. of Days | Q21: Daily Rate | T21: Amount
B23: B. | C23: Equipment
A29: EQUIPMENT | C29: Sub-Total for B | S29: P | T29: =SUM(T23:V28) -> 0
B30: C. | C30: Total (A+B) | T30: =T20+T29 -> 675
B31: D. | C31: Output per day | G31: = | AK31: 2Ø 45° bend | AL31: 2Øx2Ø tee | AM31: 4Øx4Ø coupling
B32: Name and Specifications | K32: Quantity | N32: Unit | Q32: Unit Cost | T32: Amount
B34: E. | C34: Materials | AL34: 2
C35: a. | D35: Duplex Convenience Outlet/ or Equivalent | K35: =E8 -> 10 | N35: set | Q35: 230 | T35: =Q35*K35 -> 2300 | AM35: 4
T36: =10%*SUM(T35:V35) -> 230
A45: MATERIAL | C45: Sub-Total for E | S45: P | T45: =ROUND(SUM(T35:V44),2) -> 2530
B46: F. | C46: Direct Cost (C+E) | T46: =T30+T45 -> 3205
B47: G. | C47: Overhead, Contingencies & Miscellaneous | N47: ='INPUT DATA'!C62 -> 0.05 | T47: =T46*N47 -> 160.25
B48: H. | C48: Contractor's Profit (CP) | N48: ='INPUT DATA'!C63 -> 0.1 | T48: =T46*N48 -> 320.5
B49: I. | C49: Value Added Tax (VAT) | N49: ='INPUT DATA'!C64 -> 0 | T49: =(T46+T47+T48)*N49 -> 0
A50: CHECKING | B50: J. | C50: Total Cost | T50: =SUM(T46:V49) -> 3685.75
A51: ADJUSTED CHECKING | B51: k. | C51: Total Unit Cost | T51: =T50/E8 -> 368.575

Sheet 1102 Panel Board
B1: DETAILED UNIT PRICE ANALYSIS
B3: PROJECT NAME: | E3: ='INPUT DATA'!C4 -> PROPOSED ONE STOREY TWO BED ROOM RESIDENTIAL BUILDING
A5: ITEM NO. | B5: Item No./Description: | E5: 1102 | G5: PANEL BOARD WITH MAIN BREAKER/BRANCHES, 3 WIRES, 1 NEUTRAL, 50AMP-200AMP
A6: UNIT | B6: Unit of Measurement: | E6: SET
B7: Output per day: | E7: =(1/(5.5/8)) -> 1.4545455 | G7: SET/DAY
A8: QTY | B8: Quantity: | E8: ='INPUT DATA'!C56 -> 1 | G8: =E6 -> SET
B10: Designation | K10: No. Person | N10: No. of Days | Q10: Daily Rate | T10: Amount
B12: A. | C12: Labor
A13: DURATION | C13: a. | D13: Construction Foreman/Engineering Assistant | K13: 1 | N13: =E8/E7 -> 0.6875 | Q13: 800 | T13: =K13*N13*Q13 -> 550
C14: b. | D14: Skilled Laborer | K14: 1 | N14: =N13 -> 0.6875 | Q14: 600 | T14: =K14*N14*Q14 -> 412.5
C15: c. | D15: Laborer | K15: 2 | N15: =N14 -> 0.6875 | Q15: 400 | T15: =K15*N15*Q15 -> 550
A20: LABOR | C20: Sub-Total for A | S20: P | T20: =ROUND(SUM(T13:V18),2) -> 1512.5
B21: Name and Capacity | K21: No. of Units | N21: No. of Days | Q21: Daily Rate | T21: Amount
B23: B. | C23: Equipment
A29: EQUIPMENT | C29: Sub-Total for B | S29: P | T29: =SUM(T23:V28) -> 0
B30: C. | C30: Total (A+B) | T30: =T20+T29 -> 1512.5
B31: D. | C31: Output per day | G31: = | AK31: 2Ø 45° bend | AL31: 2Øx2Ø tee | AM31: 4Øx4Ø coupling
B32: Name and Specifications | K32: Quantity | N32: Unit | Q32: Unit Cost | T32: Amount
B34: E. | C34: Materials | AL34: 2
C35: a. | D35: Panel Board with Main Breaker and 8-Branches | K35: =E8 -> 1 | N35: set | Q35: 4000 | T35: =Q35*K35 -> 4000 | AM35: 4
C36: b. | D36: Consumables (5% of Material Cost) | T36: =10%*SUM(T35:V35) -> 400
D37: Include the Circuits Breaker needed:
C38: c. | D38: ?? Amp Circuit Breaker | K38: 1 | N38: set | Q38: 450 | T38: =Q38*K38 -> 450
C39: d. | D39: ?? Amp Circuit Breaker | K39: 2 | N39: set | Q39: 451 | T39: =Q39*K39 -> 902
C40: e. | D40: ?? Amp Circuit Breaker | K40: 2 | N40: set | Q40: 452 | T40: =Q40*K40 -> 904
A45: MATERIAL | C45: Sub-Total for E | S45: P | T45: =ROUND(SUM(T35:V44),2) -> 6656
B46: F. | C46: Direct Cost (C+E) | T46: =T30+T45 -> 8168.5
B47: G. | C47: Overhead, Contingencies & Miscellaneous | N47: ='INPUT DATA'!C62 -> 0.05 | T47: =T46*N47 -> 408.425
B48: H. | C48: Contractor's Profit (CP) | N48: ='INPUT DATA'!C63 -> 0.1 | T48: =T46*N48 -> 816.85
B49: I. | C49: Value Added Tax (VAT) | N49: ='INPUT DATA'!C64 -> 0 | T49: =(T46+T47+T48)*N49 -> 0
A50: CHECKING | B50: J. | C50: Total Cost | T50: =SUM(T46:V49) -> 9393.775
A51: ADJUSTED CHECKING | B51: k. | C51: Total Unit Cost | T51: =T50/E8 -> 9393.775

Sheet 1103(2) Lighting Fixtures
B1: DETAILED UNIT PRICE ANALYSIS
B3: PROJECT NAME: | E3: ='INPUT DATA'!C4 -> PROPOSED ONE STOREY TWO BED ROOM RESIDENTIAL BUILDING
A5: ITEM NO. | B5: Item No./Description: | E5: 1103(2) | G5: FLOURESCENT LIGHTING FIXTURE WITH BALLAST/ LIGHT EMITTING DIODE (LED) BULB, 1 BULB
A6: UNIT | B6: Unit of Measurement: | E6: SET
B7: Output per day: | E7: 8 | G7: SET/DAY
A8: QTY | B8: Quantity: | E8: ='INPUT DATA'!C57 -> 40 | G8: =E6 -> SET
B10: Designation | K10: No. Person | N10: No. of Days | Q10: Daily Rate | T10: Amount
B12: A. | C12: Labor
A13: DURATION | C13: a. | D13: Construction Foreman/Engineering Assistant | K13: 1 | N13: =E8/E7 -> 5 | Q13: 800 | T13: =K13*N13*Q13 -> 4000
C14: b. | D14: Skilled Laborer | K14: 1 | N14: =N13 -> 5 | Q14: 600 | T14: =K14*N14*Q14 -> 3000
C15: c. | D15: Laborer | K15: 1 | N15: =N14 -> 5 | Q15: 400 | T15: =K15*N15*Q15 -> 2000
A20: LABOR | C20: Sub-Total for A | S20: P | T20: =ROUND(SUM(T13:V18),2) -> 9000
B21: Name and Capacity | K21: No. of Units | N21: No. of Days | Q21: Daily Rate | T21: Amount
B23: B. | C23: Equipment
D24: Minor Tools (10% of labor Cost) | T24: =10%*T20 -> 900
A29: EQUIPMENT | C29: Sub-Total for B | S29: P | T29: =SUM(T23:V28) -> 900
B30: C. | C30: Total (A+B) | T30: =T20+T29 -> 9900
B31: D. | C31: Output per day | G31: = | AK31: 2Ø 45° bend | AL31: 2Øx2Ø tee | AM31: 4Øx4Ø coupling
B32: Name and Specifications | K32: Quantity | N32: Unit | Q32: Unit Cost | T32: Amount
B34: E. | C34: Materials | AL34: 2
C35: a. | D35: Lighting Fixture e.i. 20watts LED Surface Mounted | K35: =E8 -> 40 | N35: set | Q35: 180 | T35: =Q35*K35 -> 7200 | AM35: 4
T36: =10%*SUM(T35:V35) -> 720
A45: MATERIAL | C45: Sub-Total for E | S45: P | T45: =ROUND(SUM(T35:V44),2) -> 7920
B46: F. | C46: Direct Cost (C+E) | T46: =T30+T45 -> 17820
B47: G. | C47: Overhead, Contingencies & Miscellaneous | N47: ='INPUT DATA'!C62 -> 0.05 | T47: =T46*N47 -> 891
B48: H. | C48: Contractor's Profit (CP) | N48: ='INPUT DATA'!C63 -> 0.1 | T48: =T46*N48 -> 1782
B49: I. | C49: Value Added Tax (VAT) | N49: ='INPUT DATA'!C64 -> 0 | T49: =(T46+T47+T48)*N49 -> 0
A50: CHECKING | B50: J. | C50: Total Cost | T50: =SUM(T46:V49) -> 20493
A51: ADJUSTED CHECKING | B51: k. | C51: Total Unit Cost | T51: =T50/E8 -> 512.325

Sheet Other item-Electrical
B1: DETAILED UNIT PRICE ANALYSIS
B3: PROJECT NAME: | E3: ='INPUT DATA'!C4 -> PROPOSED ONE STOREY TWO BED ROOM RESIDENTIAL BUILDING
A5: ITEM NO. | B5: Item No./Description: | E5: SPL- ? | G5: (INPUT OTHER ELECTRICAL WORK ITEM THAT IS NOT FOUND IN THIS SPREADSHEET)
A6: UNIT | B6: Unit of Measurement: | E6: L.S.
B7: Output per day:
A8: QTY | B8: Quantity: | E8: ='INPUT DATA'!C58 -> 1 | G8: =E6 -> L.S.
B10: Designation | K10: No. Person | N10: No. of Days | Q10: Daily Rate | T10: Amount
B12: A. | C12: Labor
A13: DURATION | C13: a. | D13: Construction Foreman/Engineering Assistant | K13: 1 | Q13: 800 | T13: =K13*N13*Q13 -> 0
C14: b. | D14: Skilled Laborer | K14: 1 | Q14: 600 | T14: =K14*N14*Q14 -> 0
C15: c. | D15: Laborer | K15: 1 | Q15: 400 | T15: =K15*N15*Q15 -> 0
A20: LABOR | C20: Sub-Total for A | S20: P | T20: =ROUND(SUM(T13:V18),2) -> 0
B21: Name and Capacity | K21: No. of Units | N21: No. of Days | Q21: Daily Rate | T21: Amount
B23: B. | C23: Equipment
D24: Minor Tools (10% of labor Cost) | T24: =10%*T20 -> 0
A29: EQUIPMENT | C29: Sub-Total for B | S29: P | T29: =SUM(T23:V28) -> 0
B30: C. | C30: Total (A+B) | T30: =T20+T29 -> 0
B31: D. | C31: Output per day | G31: = | AK31: 2Ø 45° bend | AL31: 2Øx2Ø tee | AM31: 4Øx4Ø coupling
B32: Name and Specifications | K32: Quantity | N32: Unit | Q32: Unit Cost | T32: Amount
B34: E. | C34: Materials | AL34: 2
C35: a. | AM35: 4
A45: MATERIAL | C45: Sub-Total for E | S45: P | T45: =ROUND(SUM(T35:V44),2) -> 0
B46: F. | C46: Direct Cost (C+E) | T46: =T30+T45 -> 0
B47: G. | C47: Overhead, Contingencies & Miscellaneous | N47: ='INPUT DATA'!C62 -> 0.05 | T47: =T46*N47 -> 0
B48: H. | C48: Contractor's Profit (CP) | N48: ='INPUT DATA'!C63 -> 0.1 | T48: =T46*N48 -> 0
B49: I. | C49: Value Added Tax (VAT) | N49: ='INPUT DATA'!C64 -> 0 | T49: =(T46+T47+T48)*N49 -> 0
A50: CHECKING | B50: J. | C50: Total Cost | T50: =SUM(T46:V49) -> 0
A51: ADJUSTED CHECKING | B51: k. | C51: Total Unit Cost | T51: =T50/E8 -> 0
